Workbook

Sheet FINAL
B2: # | C2: Segment · play | D2: Staples path (exact L3/L4) | E2: Score | F2: Primary 1 | G2: Primary 2 | H2: Secondary 1 | I2: Secondary 2 | J2: The story for the room | K2: Commercial moment | L2: Fast-start
B3: 1 | C3: =INDEX('Path Scorecard'!$Q$5:$Q$80,MATCH("CL166388",'Path Scorecard'!$H$5:$H$80,0))&" · "&INDEX('Path Scorecard'!$AC$5:$AC$80,MATCH("CL166388",'Path Scorecard'!$H$5:$H$80,0)) -> Hero · EXTEND | D3: Office Supplies > Calendars & Planners > Planners & Personal Organizers | E3: =INDEX('Path Scorecard'!$Z$5:$Z$80,MATCH("CL166388",'Path Scorecard'!$H$5:$H$80,0)) -> 95 | F3: =INDEX('Path Scorecard'!$AE$5:$AE$80,MATCH("CL166388",'Path Scorecard'!$H$5:$H$80,0)) -> Amazon | G3: =INDEX('Path Scorecard'!$AF$5:$AF$80,MATCH("CL166388",'Path Scorecard'!$H$5:$H$80,0)) -> Target | H3: =INDEX('Path Scorecard'!$AG$5:$AG$80,MATCH("CL166388",'Path Scorecard'!$H$5:$H$80,0)) -> Erin Condren | I3: =INDEX('Path Scorecard'!$AH$5:$AH$80,MATCH("CL166388",'Path Scorecard'!$H$5:$H$80,0)) -> Michaels | J3: Staples launched Sincerely Jules for Blue Sky in Jun-2026. This shows the next step beyond one influencer line. | K3: Jan-2027 New Year planning; Jul-Aug 2027 academic planners. | L3: =INDEX('Path Scorecard'!$AD$5:$AD$80,MATCH("CL166388",'Path Scorecard'!$H$5:$H$80,0)) -> Yes
B4: 2 | C4: =INDEX('Path Scorecard'!$Q$5:$Q$80,MATCH("CL140991",'Path Scorecard'!$H$5:$H$80,0))&" · "&INDEX('Path Scorecard'!$AC$5:$AC$80,MATCH("CL140991",'Path Scorecard'!$H$5:$H$80,0)) -> Hero · EXTEND | D4: Office Supplies > Desk Organizers & Accessories > Desk Organizers | E4: =INDEX('Path Scorecard'!$Z$5:$Z$80,MATCH("CL140991",'Path Scorecard'!$H$5:$H$80,0)) -> 91 | F4: =INDEX('Path Scorecard'!$AE$5:$AE$80,MATCH("CL140991",'Path Scorecard'!$H$5:$H$80,0)) -> Target | G4: =INDEX('Path Scorecard'!$AF$5:$AF$80,MATCH("CL140991",'Path Scorecard'!$H$5:$H$80,0)) -> Amazon | H4: =INDEX('Path Scorecard'!$AG$5:$AG$80,MATCH("CL140991",'Path Scorecard'!$H$5:$H$80,0)) -> Grovemade | I4: =INDEX('Path Scorecard'!$AH$5:$AH$80,MATCH("CL140991",'Path Scorecard'!$H$5:$H$80,0)) -> The Container Store | J4: Desk organization is a header-nav Staples staple and a low-ticket attach to every paper and pen basket. | K4: January 'get organized' season; BTS desk & dorm refresh. | L4: =INDEX('Path Scorecard'!$AD$5:$AD$80,MATCH("CL140991",'Path Scorecard'!$H$5:$H$80,0))
B5: 3 | C5: =INDEX('Path Scorecard'!$Q$5:$Q$80,MATCH("CL142745",'Path Scorecard'!$H$5:$H$80,0))&" · "&INDEX('Path Scorecard'!$AC$5:$AC$80,MATCH("CL142745",'Path Scorecard'!$H$5:$H$80,0)) -> Hero · EXTEND | D5: Bags, Backpacks & Luggage > Backpacks & Laptop Bags > Backpacks | E5: =INDEX('Path Scorecard'!$Z$5:$Z$80,MATCH("CL142745",'Path Scorecard'!$H$5:$H$80,0)) -> 86 | F5: =INDEX('Path Scorecard'!$AE$5:$AE$80,MATCH("CL142745",'Path Scorecard'!$H$5:$H$80,0)) -> Amazon | G5: =INDEX('Path Scorecard'!$AF$5:$AF$80,MATCH("CL142745",'Path Scorecard'!$H$5:$H$80,0)) -> Target | H5: =INDEX('Path Scorecard'!$AG$5:$AG$80,MATCH("CL142745",'Path Scorecard'!$H$5:$H$80,0)) -> Bellroy | I5: =INDEX('Path Scorecard'!$AH$5:$AH$80,MATCH("CL142745",'Path Scorecard'!$H$5:$H$80,0)) -> Urban Outfitters | J5: JanSport now sells on Target Plus, the curated-marketplace peer Pat can point to. | K5: BTS-2027. | L5: =INDEX('Path Scorecard'!$AD$5:$AD$80,MATCH("CL142745",'Path Scorecard'!$H$5:$H$80,0)) -> Yes
B6: 4 | C6: =INDEX('Path Scorecard'!$Q$5:$Q$80,MATCH("CL210795",'Path Scorecard'!$H$5:$H$80,0))&" · "&INDEX('Path Scorecard'!$AC$5:$AC$80,MATCH("CL210795",'Path Scorecard'!$H$5:$H$80,0)) -> Hero · EXTEND | D6: Furniture > Desks > Office Desks | E6: =INDEX('Path Scorecard'!$Z$5:$Z$80,MATCH("CL210795",'Path Scorecard'!$H$5:$H$80,0)) -> 81 | F6: =INDEX('Path Scorecard'!$AE$5:$AE$80,MATCH("CL210795",'Path Scorecard'!$H$5:$H$80,0)) -> Wayfair | G6: =INDEX('Path Scorecard'!$AF$5:$AF$80,MATCH("CL210795",'Path Scorecard'!$H$5:$H$80,0)) -> Amazon | H6: =INDEX('Path Scorecard'!$AG$5:$AG$80,MATCH("CL210795",'Path Scorecard'!$H$5:$H$80,0)) -> Design Within Reach | I6: =INDEX('Path Scorecard'!$AH$5:$AH$80,MATCH("CL210795",'Path Scorecard'!$H$5:$H$80,0)) -> West Elm | J6: Second half of the White Chair story. | K6: Q1 office refresh. | L6: =INDEX('Path Scorecard'!$AD$5:$AD$80,MATCH("CL210795",'Path Scorecard'!$H$5:$H$80,0)) -> Yes
B7: 5 | C7: =INDEX('Path Scorecard'!$Q$5:$Q$80,MATCH("CL354650",'Path Scorecard'!$H$5:$H$80,0))&" · "&INDEX('Path Scorecard'!$AC$5:$AC$80,MATCH("CL354650",'Path Scorecard'!$H$5:$H$80,0)) -> Probable Hero · BUILD | D7: Coffee, Water & Snacks > Water & Beverages > Water Bottles, Tumblers & Travel Mugs | E7: =INDEX('Path Scorecard'!$Z$5:$Z$80,MATCH("CL354650",'Path Scorecard'!$H$5:$H$80,0)) -> 91 | F7: =INDEX('Path Scorecard'!$AE$5:$AE$80,MATCH("CL354650",'Path Scorecard'!$H$5:$H$80,0)) -> Dick's Sporting Goods | G7: =INDEX('Path Scorecard'!$AF$5:$AF$80,MATCH("CL354650",'Path Scorecard'!$H$5:$H$80,0)) -> Target | H7: =INDEX('Path Scorecard'!$AG$5:$AG$80,MATCH("CL354650",'Path Scorecard'!$H$5:$H$80,0)) -> Scheels | I7: =INDEX('Path Scorecard'!$AH$5:$AH$80,MATCH("CL354650",'Path Scorecard'!$H$5:$H$80,0)) -> YETI | J7: Everyone in the room knows the Stanley / Owala craze. | K7: BTS-2027 (Jul-Sep); Q4 gifting; January hydration resolutions. | L7: =INDEX('Path Scorecard'!$AD$5:$AD$80,MATCH("CL354650",'Path Scorecard'!$H$5:$H$80,0)) -> Yes
B8: 6 | C8: =INDEX('Path Scorecard'!$Q$5:$Q$80,MATCH("CL70203",'Path Scorecard'!$H$5:$H$80,0))&" · "&INDEX('Path Scorecard'!$AC$5:$AC$80,MATCH("CL70203",'Path Scorecard'!$H$5:$H$80,0)) -> Probable Hero · BUILD | D8: Furniture > Chairs & Seating > Accent & Waiting Room Chairs | E8: =INDEX('Path Scorecard'!$Z$5:$Z$80,MATCH("CL70203",'Path Scorecard'!$H$5:$H$80,0)) -> 89 | F8: =INDEX('Path Scorecard'!$AE$5:$AE$80,MATCH("CL70203",'Path Scorecard'!$H$5:$H$80,0)) -> Wayfair | G8: =INDEX('Path Scorecard'!$AF$5:$AF$80,MATCH("CL70203",'Path Scorecard'!$H$5:$H$80,0)) -> Amazon | H8: =INDEX('Path Scorecard'!$AG$5:$AG$80,MATCH("CL70203",'Path Scorecard'!$H$5:$H$80,0)) -> Article | I8: =INDEX('Path Scorecard'!$AH$5:$AH$80,MATCH("CL70203",'Path Scorecard'!$H$5:$H$80,0)) -> West Elm | J8: Pat's own example: the thesis in one picture. | K8: Q1-2027 office refresh and return-to-office budgets. | L8: =INDEX('Path Scorecard'!$AD$5:$AD$80,MATCH("CL70203",'Path Scorecard'!$H$5:$H$80,0)) -> Yes
B9: 7 | C9: =INDEX('Path Scorecard'!$Q$5:$Q$80,MATCH("CL167867",'Path Scorecard'!$H$5:$H$80,0))&" · "&INDEX('Path Scorecard'!$AC$5:$AC$80,MATCH("CL167867",'Path Scorecard'!$H$5:$H$80,0)) -> Probable Hero · BUILD | D9: Furniture > Lamps & Lighting > Desk Lamps | E9: =INDEX('Path Scorecard'!$Z$5:$Z$80,MATCH("CL167867",'Path Scorecard'!$H$5:$H$80,0)) -> 86 | F9: =INDEX('Path Scorecard'!$AE$5:$AE$80,MATCH("CL167867",'Path Scorecard'!$H$5:$H$80,0)) -> Wayfair | G9: =INDEX('Path Scorecard'!$AF$5:$AF$80,MATCH("CL167867",'Path Scorecard'!$H$5:$H$80,0)) -> Amazon | H9: =INDEX('Path Scorecard'!$AG$5:$AG$80,MATCH("CL167867",'Path Scorecard'!$H$5:$H$80,0)) -> Lamps Plus | I9: =INDEX('Path Scorecard'!$AH$5:$AH$80,MATCH("CL167867",'Path Scorecard'!$H$5:$H$80,0)) -> Urban Outfitters | J9: 2026 home-office trend reports all name better lighting and warm materials. | K9: Q1-2027 home-office refresh; BTS dorm. | L9: =INDEX('Path Scorecard'!$AD$5:$AD$80,MATCH("CL167867",'Path Scorecard'!$H$5:$H$80,0)) -> Yes
B10: 8 | C10: Probable Hero · BUILD | D10: Bags, Backpacks & Luggage > Totes & Handbags > Lunch Bags & Boxes | E10: 86 | F10: Amazon | G10: Target | H10: Bentgo | I10: Pottery Barn Kids | J10: BTS is Pat's named seasonal anchor and lunch is on every parent's list. | K10: BTS-2027; January 'bring lunch to the office' resolutions. | L10: Yes
B11: 9 | C11: Non-Hero · EXPLORE | D11: Furniture > Decor > Clocks & Timers | E11: 77 | F11: Wayfair | G11: Amazon | H11: Schoolhouse | I11: Anthropologie | J11: Every office wall has one. | K11: Q1 office refresh.
B12: 10 | C12: Non-Hero · EXPLORE | D12: Office Supplies > Desk Organizers & Accessories > Desk Pads | E12: 76 | F12: Amazon | G12: Wayfair | H12: Grovemade | I12: Orbitkey | J12: Wayfair even has a Desk Pads node. | K12: Q1.
B13: 11 | C13: Non-Hero · EXPLORE | D13: Coffee, Water & Snacks > Coffee, Coffee Makers & Supplies > Coffee Organizers & Dispensers | E13: 72 | F13: Amazon | G13: Wayfair | H13: Williams Sonoma | I13: Crate & Barrel | J13: Every office has a coffee corner. | K13: Q1-2027 breakroom refresh; holiday hosting.
B14: 12 | C14: Non-Hero · EXPLORE | D14: Furniture > Cubicle & Panel Systems > Office Partitions & Dividers | E14: 67 | F14: Wayfair | G14: Amazon | H14: Felt Right | I14: Anthropologie | J14: 'Broken-plan' offices and home work corners. | K14: Q1-2027 office fit-outs; WFH corners.

Sheet Executive Summary
A1: Staples Marketplace PoC: the Top 20 L3/L4 shelves, and who to benchmark them against
A2: v3, prepared 29-Sep-2026 for Sai (LatentView). Paths are exact nodes from the Staples navigation tree (snapshot 21-Sep-2026).
A4: • | B4: Recommendation: 20 L3/L4 shelves: 7 Hero, 7 Probable Hero and 6 Non-Hero. Each is benchmarked against 4 competitors: 2 primaries (broad retailers that measure the gap) and 2 secondaries (enthusiast / design specialists outside Staples' scope that show the 'super-extension', like Scheels and Michaels in Ben's examples).
A5: • | B5: Hero = Staples' own top categories (EXTEND with style variants; PROTECT where variants would copy 1P). Probable Hero = the market's top categories where Staples is not yet a destination (BUILD). Non-Hero = neither (EXPLORE: a low-risk test where sellers hold the stock). Full rules and 1-5 anchors are in 'Hero Criteria'.
A6: • | B6: How the 20 are chosen: 4 hard gates, then the Hero segment, then an 8-criterion path score. The best shelves inside each segment fill the quota. Quotas, cut-offs and weights are editable, and everything recalculates.
A7: • | B7: Secondaries double as a recruitment list: 9 of the Top-20 secondary picks are D2C brands that could list on Staples Marketplace themselves (Bellroy, Bentgo, Erin Condren, Fellow, Felt Right, Grovemade, Keychron, Orbitkey, YETI).
A8: • | B8: 8 Top-20 shelves already have Staples SKUs in hand ('Fast-start'); the rest need a Staples leaf scrape first.
A9: • | B9: Caveats: no internal Staples sales or margin data, so 'Hero' uses external proxies (swap in Staples' own sales rank when Pat shares it). Competitor depth is scored from desk research (retailer sites blocked live counts); confirm it when listings are collected.
A11: Top 20 (grouped by segment; everything in this table is live)
A12: # | B12: Segment · play | C12: Staples path (exact L3/L4) | D12: Score | E12: Primary 1 | F12: Primary 2 | G12: Secondary 1 | H12: Secondary 2 | I12: The story for the room | J12: Commercial moment | K12: Fast-start
A13: 1 | B13: =INDEX('Path Scorecard'!$Q$5:$Q$80,MATCH("CL166388",'Path Scorecard'!$H$5:$H$80,0))&" · "&INDEX('Path Scorecard'!$AC$5:$AC$80,MATCH("CL166388",'Path Scorecard'!$H$5:$H$80,0)) -> Hero · EXTEND | C13: Office Supplies > Calendars & Planners > Planners & Personal Organizers | D13: =INDEX('Path Scorecard'!$Z$5:$Z$80,MATCH("CL166388",'Path Scorecard'!$H$5:$H$80,0)) -> 95 | E13: =INDEX('Path Scorecard'!$AE$5:$AE$80,MATCH("CL166388",'Path Scorecard'!$H$5:$H$80,0)) -> Amazon | F13: =INDEX('Path Scorecard'!$AF$5:$AF$80,MATCH("CL166388",'Path Scorecard'!$H$5:$H$80,0)) -> Target | G13: =INDEX('Path Scorecard'!$AG$5:$AG$80,MATCH("CL166388",'Path Scorecard'!$H$5:$H$80,0)) -> Erin Condren | H13: =INDEX('Path Scorecard'!$AH$5:$AH$80,MATCH("CL166388",'Path Scorecard'!$H$5:$H$80,0)) -> Michaels | I13: Staples launched Sincerely Jules for Blue Sky in Jun-2026. This shows the next step beyond one influencer line. | J13: Jan-2027 New Year planning; Jul-Aug 2027 academic planners. | K13: =INDEX('Path Scorecard'!$AD$5:$AD$80,MATCH("CL166388",'Path Scorecard'!$H$5:$H$80,0)) -> Yes
A14: 2 | B14: =INDEX('Path Scorecard'!$Q$5:$Q$80,MATCH("CL140991",'Path Scorecard'!$H$5:$H$80,0))&" · "&INDEX('Path Scorecard'!$AC$5:$AC$80,MATCH("CL140991",'Path Scorecard'!$H$5:$H$80,0)) -> Hero · EXTEND | C14: Office Supplies > Desk Organizers & Accessories > Desk Organizers | D14: =INDEX('Path Scorecard'!$Z$5:$Z$80,MATCH("CL140991",'Path Scorecard'!$H$5:$H$80,0)) -> 91 | E14: =INDEX('Path Scorecard'!$AE$5:$AE$80,MATCH("CL140991",'Path Scorecard'!$H$5:$H$80,0)) -> Target | F14: =INDEX('Path Scorecard'!$AF$5:$AF$80,MATCH("CL140991",'Path Scorecard'!$H$5:$H$80,0)) -> Amazon | G14: =INDEX('Path Scorecard'!$AG$5:$AG$80,MATCH("CL140991",'Path Scorecard'!$H$5:$H$80,0)) -> Grovemade | H14: =INDEX('Path Scorecard'!$AH$5:$AH$80,MATCH("CL140991",'Path Scorecard'!$H$5:$H$80,0)) -> The Container Store | I14: Desk organization is a header-nav Staples staple and a low-ticket attach to every paper and pen basket. | J14: January 'get organized' season; BTS desk & dorm refresh. | K14: =INDEX('Path Scorecard'!$AD$5:$AD$80,MATCH("CL140991",'Path Scorecard'!$H$5:$H$80,0))
A15: 3 | B15: =INDEX('Path Scorecard'!$Q$5:$Q$80,MATCH("CL219245",'Path Scorecard'!$H$5:$H$80,0))&" · "&INDEX('Path Scorecard'!$AC$5:$AC$80,MATCH("CL219245",'Path Scorecard'!$H$5:$H$80,0)) -> Hero · EXTEND | C15: School Supplies > Teacher Supplies > Classroom Decorations > Decorative Accents & Board Sets | D15: =INDEX('Path Scorecard'!$Z$5:$Z$80,MATCH("CL219245",'Path Scorecard'!$H$5:$H$80,0)) -> 86 | E15: =INDEX('Path Scorecard'!$AE$5:$AE$80,MATCH("CL219245",'Path Scorecard'!$H$5:$H$80,0)) -> Amazon | F15: =INDEX('Path Scorecard'!$AF$5:$AF$80,MATCH("CL219245",'Path Scorecard'!$H$5:$H$80,0)) -> Walmart | G15: =INDEX('Path Scorecard'!$AG$5:$AG$80,MATCH("CL219245",'Path Scorecard'!$H$5:$H$80,0)) -> Etsy | H15: =INDEX('Path Scorecard'!$AH$5:$AH$80,MATCH("CL219245",'Path Scorecard'!$H$5:$H$80,0)) -> Oriental Trading | I15: Teachers are a Staples loyalty segment (teacher coupon, teacher lists). | J15: BTS-2027 classroom set-up (Jul-Aug); Teacher Appreciation Week (May). | K15: =INDEX('Path Scorecard'!$AD$5:$AD$80,MATCH("CL219245",'Path Scorecard'!$H$5:$H$80,0))
A16: 4 | B16: =INDEX('Path Scorecard'!$Q$5:$Q$80,MATCH("CL142745",'Path Scorecard'!$H$5:$H$80,0))&" · "&INDEX('Path Scorecard'!$AC$5:$AC$80,MATCH("CL142745",'Path Scorecard'!$H$5:$H$80,0)) -> Hero · EXTEND | C16: Bags, Backpacks & Luggage > Backpacks & Laptop Bags > Backpacks | D16: =INDEX('Path Scorecard'!$Z$5:$Z$80,MATCH("CL142745",'Path Scorecard'!$H$5:$H$80,0)) -> 86 | E16: =INDEX('Path Scorecard'!$AE$5:$AE$80,MATCH("CL142745",'Path Scorecard'!$H$5:$H$80,0)) -> Amazon | F16: =INDEX('Path Scorecard'!$AF$5:$AF$80,MATCH("CL142745",'Path Scorecard'!$H$5:$H$80,0)) -> Target | G16: =INDEX('Path Scorecard'!$AG$5:$AG$80,MATCH("CL142745",'Path Scorecard'!$H$5:$H$80,0)) -> Bellroy | H16: =INDEX('Path Scorecard'!$AH$5:$AH$80,MATCH("CL142745",'Path Scorecard'!$H$5:$H$80,0)) -> Urban Outfitters | I16: JanSport now sells on Target Plus, the curated-marketplace peer Pat can point to. | J16: BTS-2027. | K16: =INDEX('Path Scorecard'!$AD$5:$AD$80,MATCH("CL142745",'Path Scorecard'!$H$5:$H$80,0)) -> Yes
A17: 5 | B17: =INDEX('Path Scorecard'!$Q$5:$Q$80,MATCH("CL210795",'Path Scorecard'!$H$5:$H$80,0))&" · "&INDEX('Path Scorecard'!$AC$5:$AC$80,MATCH("CL210795",'Path Scorecard'!$H$5:$H$80,0)) -> Hero · EXTEND | C17: Furniture > Desks > Office Desks | D17: =INDEX('Path Scorecard'!$Z$5:$Z$80,MATCH("CL210795",'Path Scorecard'!$H$5:$H$80,0)) -> 81 | E17: =INDEX('Path Scorecard'!$AE$5:$AE$80,MATCH("CL210795",'Path Scorecard'!$H$5:$H$80,0)) -> Wayfair | F17: =INDEX('Path Scorecard'!$AF$5:$AF$80,MATCH("CL210795",'Path Scorecard'!$H$5:$H$80,0)) -> Amazon | G17: =INDEX('Path Scorecard'!$AG$5:$AG$80,MATCH("CL210795",'Path Scorecard'!$H$5:$H$80,0)) -> Design Within Reach | H17: =INDEX('Path Scorecard'!$AH$5:$AH$80,MATCH("CL210795",'Path Scorecard'!$H$5:$H$80,0)) -> West Elm | I17: Second half of the White Chair story. | J17: Q1 office refresh. | K17: =INDEX('Path Scorecard'!$AD$5:$AD$80,MATCH("CL210795",'Path Scorecard'!$H$5:$H$80,0)) -> Yes
A18: 6 | B18: =INDEX('Path Scorecard'!$Q$5:$Q$80,MATCH("CL142403",'Path Scorecard'!$H$5:$H$80,0))&" · "&INDEX('Path Scorecard'!$AC$5:$AC$80,MATCH("CL142403",'Path Scorecard'!$H$5:$H$80,0)) -> Hero · EXTEND | C18: Furniture > Boards & Easels > Bulletin Boards | D18: =INDEX('Path Scorecard'!$Z$5:$Z$80,MATCH("CL142403",'Path Scorecard'!$H$5:$H$80,0)) -> 77 | E18: =INDEX('Path Scorecard'!$AE$5:$AE$80,MATCH("CL142403",'Path Scorecard'!$H$5:$H$80,0)) -> Amazon | F18: =INDEX('Path Scorecard'!$AF$5:$AF$80,MATCH("CL142403",'Path Scorecard'!$H$5:$H$80,0)) -> Wayfair | G18: =INDEX('Path Scorecard'!$AG$5:$AG$80,MATCH("CL142403",'Path Scorecard'!$H$5:$H$80,0)) -> Etsy | H18: =INDEX('Path Scorecard'!$AH$5:$AH$80,MATCH("CL142403",'Path Scorecard'!$H$5:$H$80,0)) -> Pottery Barn Teen | I18: Letter boards are an office & classroom staple. | J18: BTS dorm; Jan planning. | K18: =INDEX('Path Scorecard'!$AD$5:$AD$80,MATCH("CL142403",'Path Scorecard'!$H$5:$H$80,0))
A19: 7 | B19: =INDEX('Path Scorecard'!$Q$5:$Q$80,MATCH("CL215783",'Path Scorecard'!$H$5:$H$80,0))&" · "&INDEX('Path Scorecard'!$AC$5:$AC$80,MATCH("CL215783",'Path Scorecard'!$H$5:$H$80,0)) -> Hero · EXTEND | C19: Computers & Accessories > Computer Accessories & Peripherals > Computer Keyboards | D19: =INDEX('Path Scorecard'!$Z$5:$Z$80,MATCH("CL215783",'Path Scorecard'!$H$5:$H$80,0)) -> 75 | E19: =INDEX('Path Scorecard'!$AE$5:$AE$80,MATCH("CL215783",'Path Scorecard'!$H$5:$H$80,0)) -> Amazon | F19: =INDEX('Path Scorecard'!$AF$5:$AF$80,MATCH("CL215783",'Path Scorecard'!$H$5:$H$80,0)) -> Best Buy | G19: =INDEX('Path Scorecard'!$AG$5:$AG$80,MATCH("CL215783",'Path Scorecard'!$H$5:$H$80,0)) -> Keychron | H19: =INDEX('Path Scorecard'!$AH$5:$AH$80,MATCH("CL215783",'Path Scorecard'!$H$5:$H$80,0)) -> Drop | I19: Shows the colour gap inside a brand Staples already sells. | J19: BTS; holiday. | K19: =INDEX('Path Scorecard'!$AD$5:$AD$80,MATCH("CL215783",'Path Scorecard'!$H$5:$H$80,0))
A20: 8 | B20: =INDEX('Path Scorecard'!$Q$5:$Q$80,MATCH("CL354650",'Path Scorecard'!$H$5:$H$80,0))&" · "&INDEX('Path Scorecard'!$AC$5:$AC$80,MATCH("CL354650",'Path Scorecard'!$H$5:$H$80,0)) -> Probable Hero · BUILD | C20: Coffee, Water & Snacks > Water & Beverages > Water Bottles, Tumblers & Travel Mugs | D20: =INDEX('Path Scorecard'!$Z$5:$Z$80,MATCH("CL354650",'Path Scorecard'!$H$5:$H$80,0)) -> 91 | E20: =INDEX('Path Scorecard'!$AE$5:$AE$80,MATCH("CL354650",'Path Scorecard'!$H$5:$H$80,0)) -> Dick's Sporting Goods | F20: =INDEX('Path Scorecard'!$AF$5:$AF$80,MATCH("CL354650",'Path Scorecard'!$H$5:$H$80,0)) -> Target | G20: =INDEX('Path Scorecard'!$AG$5:$AG$80,MATCH("CL354650",'Path Scorecard'!$H$5:$H$80,0)) -> Scheels | H20: =INDEX('Path Scorecard'!$AH$5:$AH$80,MATCH("CL354650",'Path Scorecard'!$H$5:$H$80,0)) -> YETI | I20: Everyone in the room knows the Stanley / Owala craze. | J20: BTS-2027 (Jul-Sep); Q4 gifting; January hydration resolutions. | K20: =INDEX('Path Scorecard'!$AD$5:$AD$80,MATCH("CL354650",'Path Scorecard'!$H$5:$H$80,0)) -> Yes
A21: 9 | B21: =INDEX('Path Scorecard'!$Q$5:$Q$80,MATCH("CL70203",'Path Scorecard'!$H$5:$H$80,0))&" · "&INDEX('Path Scorecard'!$AC$5:$AC$80,MATCH("CL70203",'Path Scorecard'!$H$5:$H$80,0)) -> Probable Hero · BUILD | C21: Furniture > Chairs & Seating > Accent & Waiting Room Chairs | D21: =INDEX('Path Scorecard'!$Z$5:$Z$80,MATCH("CL70203",'Path Scorecard'!$H$5:$H$80,0)) -> 89 | E21: =INDEX('Path Scorecard'!$AE$5:$AE$80,MATCH("CL70203",'Path Scorecard'!$H$5:$H$80,0)) -> Wayfair | F21: =INDEX('Path Scorecard'!$AF$5:$AF$80,MATCH("CL70203",'Path Scorecard'!$H$5:$H$80,0)) -> Amazon | G21: =INDEX('Path Scorecard'!$AG$5:$AG$80,MATCH("CL70203",'Path Scorecard'!$H$5:$H$80,0)) -> Article | H21: =INDEX('Path Scorecard'!$AH$5:$AH$80,MATCH("CL70203",'Path Scorecard'!$H$5:$H$80,0)) -> West Elm | I21: Pat's own example: the thesis in one picture. | J21: Q1-2027 office refresh and return-to-office budgets. | K21: =INDEX('Path Scorecard'!$AD$5:$AD$80,MATCH("CL70203",'Path Scorecard'!$H$5:$H$80,0)) -> Yes
A22: 10 | B22: =INDEX('Path Scorecard'!$Q$5:$Q$80,MATCH("CL167867",'Path Scorecard'!$H$5:$H$80,0))&" · "&INDEX('Path Scorecard'!$AC$5:$AC$80,MATCH("CL167867",'Path Scorecard'!$H$5:$H$80,0)) -> Probable Hero · BUILD | C22: Furniture > Lamps & Lighting > Desk Lamps | D22: =INDEX('Path Scorecard'!$Z$5:$Z$80,MATCH("CL167867",'Path Scorecard'!$H$5:$H$80,0)) -> 86 | E22: =INDEX('Path Scorecard'!$AE$5:$AE$80,MATCH("CL167867",'Path Scorecard'!$H$5:$H$80,0)) -> Wayfair | F22: =INDEX('Path Scorecard'!$AF$5:$AF$80,MATCH("CL167867",'Path Scorecard'!$H$5:$H$80,0)) -> Amazon | G22: =INDEX('Path Scorecard'!$AG$5:$AG$80,MATCH("CL167867",'Path Scorecard'!$H$5:$H$80,0)) -> Lamps Plus | H22: =INDEX('Path Scorecard'!$AH$5:$AH$80,MATCH("CL167867",'Path Scorecard'!$H$5:$H$80,0)) -> Urban Outfitters | I22: 2026 home-office trend reports all name better lighting and warm materials. | J22: Q1-2027 home-office refresh; BTS dorm. | K22: =INDEX('Path Scorecard'!$AD$5:$AD$80,MATCH("CL167867",'Path Scorecard'!$H$5:$H$80,0)) -> Yes
A23: 11 | B23: =INDEX('Path Scorecard'!$Q$5:$Q$80,MATCH("CL141253",'Path Scorecard'!$H$5:$H$80,0))&" · "&INDEX('Path Scorecard'!$AC$5:$AC$80,MATCH("CL141253",'Path Scorecard'!$H$5:$H$80,0)) -> Probable Hero · BUILD | C23: Office Supplies > Writing Supplies & Instruments > Pencil Accessories > Pencil Cases & Pouches | D23: =INDEX('Path Scorecard'!$Z$5:$Z$80,MATCH("CL141253",'Path Scorecard'!$H$5:$H$80,0)) -> 86 | E23: =INDEX('Path Scorecard'!$AE$5:$AE$80,MATCH("CL141253",'Path Scorecard'!$H$5:$H$80,0)) -> Amazon | F23: =INDEX('Path Scorecard'!$AF$5:$AF$80,MATCH("CL141253",'Path Scorecard'!$H$5:$H$80,0)) -> Target | G23: =INDEX('Path Scorecard'!$AG$5:$AG$80,MATCH("CL141253",'Path Scorecard'!$H$5:$H$80,0)) -> JetPens | H23: =INDEX('Path Scorecard'!$AH$5:$AH$80,MATCH("CL141253",'Path Scorecard'!$H$5:$H$80,0)) -> Kinokuniya | I23: Staples' Recess Club / Jellygram exclusives (BTS 2026) already prove the demand. | J23: BTS-2027 (Jul-Sep). | K23: =INDEX('Path Scorecard'!$AD$5:$AD$80,MATCH("CL141253",'Path Scorecard'!$H$5:$H$80,0))
A24: 12 | B24: =INDEX('Path Scorecard'!$Q$5:$Q$80,MATCH("CL165124",'Path Scorecard'!$H$5:$H$80,0))&" · "&INDEX('Path Scorecard'!$AC$5:$AC$80,MATCH("CL165124",'Path Scorecard'!$H$5:$H$80,0)) -> Probable Hero · BUILD | C24: Bags, Backpacks & Luggage > Totes & Handbags > Lunch Bags & Boxes | D24: =INDEX('Path Scorecard'!$Z$5:$Z$80,MATCH("CL165124",'Path Scorecard'!$H$5:$H$80,0)) -> 86 | E24: =INDEX('Path Scorecard'!$AE$5:$AE$80,MATCH("CL165124",'Path Scorecard'!$H$5:$H$80,0)) -> Amazon | F24: =INDEX('Path Scorecard'!$AF$5:$AF$80,MATCH("CL165124",'Path Scorecard'!$H$5:$H$80,0)) -> Target | G24: =INDEX('Path Scorecard'!$AG$5:$AG$80,MATCH("CL165124",'Path Scorecard'!$H$5:$H$80,0)) -> Bentgo | H24: =INDEX('Path Scorecard'!$AH$5:$AH$80,MATCH("CL165124",'Path Scorecard'!$H$5:$H$80,0)) -> Pottery Barn Kids | I24: BTS is Pat's named seasonal anchor and lunch is on every parent's list. | J24: BTS-2027; January 'bring lunch to the office' resolutions. | K24: =INDEX('Path Scorecard'!$AD$5:$AD$80,MATCH("CL165124",'Path Scorecard'!$H$5:$H$80,0)) -> Yes
A25: 13 | B25: =INDEX('Path Scorecard'!$Q$5:$Q$80,MATCH("CL354705",'Path Scorecard'!$H$5:$H$80,0))&" · "&INDEX('Path Scorecard'!$AC$5:$AC$80,MATCH("CL354705",'Path Scorecard'!$H$5:$H$80,0)) -> Probable Hero · BUILD | C25: Office Supplies > Storage & Organization > Storage Baskets | D25: =INDEX('Path Scorecard'!$Z$5:$Z$80,MATCH("CL354705",'Path Scorecard'!$H$5:$H$80,0)) -> 85 | E25: =INDEX('Path Scorecard'!$AE$5:$AE$80,MATCH("CL354705",'Path Scorecard'!$H$5:$H$80,0)) -> Wayfair | F25: =INDEX('Path Scorecard'!$AF$5:$AF$80,MATCH("CL354705",'Path Scorecard'!$H$5:$H$80,0)) -> Target | G25: =INDEX('Path Scorecard'!$AG$5:$AG$80,MATCH("CL354705",'Path Scorecard'!$H$5:$H$80,0)) -> The Container Store | H25: =INDEX('Path Scorecard'!$AH$5:$AH$80,MATCH("CL354705",'Path Scorecard'!$H$5:$H$80,0)) -> Pottery Barn | I25: Organization is a January ritual every retailer promotes. | J25: January 'get organized' season. | K25: =INDEX('Path Scorecard'!$AD$5:$AD$80,MATCH("CL354705",'Path Scorecard'!$H$5:$H$80,0))
A26: 14 | B26: =INDEX('Path Scorecard'!$Q$5:$Q$80,MATCH("CL219256",'Path Scorecard'!$H$5:$H$80,0))&" · "&INDEX('Path Scorecard'!$AC$5:$AC$80,MATCH("CL219256",'Path Scorecard'!$H$5:$H$80,0)) -> Probable Hero · BUILD | C26: Bags, Backpacks & Luggage > Backpacks & Laptop Bags > Laptop Sleeves & Cases | D26: =INDEX('Path Scorecard'!$Z$5:$Z$80,MATCH("CL219256",'Path Scorecard'!$H$5:$H$80,0)) -> 83 | E26: =INDEX('Path Scorecard'!$AE$5:$AE$80,MATCH("CL219256",'Path Scorecard'!$H$5:$H$80,0)) -> Amazon | F26: =INDEX('Path Scorecard'!$AF$5:$AF$80,MATCH("CL219256",'Path Scorecard'!$H$5:$H$80,0)) -> Target | G26: =INDEX('Path Scorecard'!$AG$5:$AG$80,MATCH("CL219256",'Path Scorecard'!$H$5:$H$80,0)) -> Bellroy | H26: =INDEX('Path Scorecard'!$AH$5:$AH$80,MATCH("CL219256",'Path Scorecard'!$H$5:$H$80,0)) -> Urban Outfitters | I26: Directly serves Pat's '1-2 extra items per checkout'. | J26: BTS; laptop-attach all year. | K26: =INDEX('Path Scorecard'!$AD$5:$AD$80,MATCH("CL219256",'Path Scorecard'!$H$5:$H$80,0)) -> Yes
A27: 15 | B27: =INDEX('Path Scorecard'!$Q$5:$Q$80,MATCH("CL161533",'Path Scorecard'!$H$5:$H$80,0))&" · "&INDEX('Path Scorecard'!$AC$5:$AC$80,MATCH("CL161533",'Path Scorecard'!$H$5:$H$80,0)) -> Non-Hero · EXPLORE | C27: Furniture > Decor > Clocks & Timers | D27: =INDEX('Path Scorecard'!$Z$5:$Z$80,MATCH("CL161533",'Path Scorecard'!$H$5:$H$80,0)) -> 77 | E27: =INDEX('Path Scorecard'!$AE$5:$AE$80,MATCH("CL161533",'Path Scorecard'!$H$5:$H$80,0)) -> Wayfair | F27: =INDEX('Path Scorecard'!$AF$5:$AF$80,MATCH("CL161533",'Path Scorecard'!$H$5:$H$80,0)) -> Amazon | G27: =INDEX('Path Scorecard'!$AG$5:$AG$80,MATCH("CL161533",'Path Scorecard'!$H$5:$H$80,0)) -> Schoolhouse | H27: =INDEX('Path Scorecard'!$AH$5:$AH$80,MATCH("CL161533",'Path Scorecard'!$H$5:$H$80,0)) -> Anthropologie | I27: Every office wall has one. | J27: Q1 office refresh. | K27: =INDEX('Path Scorecard'!$AD$5:$AD$80,MATCH("CL161533",'Path Scorecard'!$H$5:$H$80,0))
A28: 16 | B28: =INDEX('Path Scorecard'!$Q$5:$Q$80,MATCH("CL140589",'Path Scorecard'!$H$5:$H$80,0))&" · "&INDEX('Path Scorecard'!$AC$5:$AC$80,MATCH("CL140589",'Path Scorecard'!$H$5:$H$80,0)) -> Non-Hero · EXPLORE | C28: Office Supplies > Desk Organizers & Accessories > Desk Pads | D28: =INDEX('Path Scorecard'!$Z$5:$Z$80,MATCH("CL140589",'Path Scorecard'!$H$5:$H$80,0)) -> 76 | E28: =INDEX('Path Scorecard'!$AE$5:$AE$80,MATCH("CL140589",'Path Scorecard'!$H$5:$H$80,0)) -> Amazon | F28: =INDEX('Path Scorecard'!$AF$5:$AF$80,MATCH("CL140589",'Path Scorecard'!$H$5:$H$80,0)) -> Wayfair | G28: =INDEX('Path Scorecard'!$AG$5:$AG$80,MATCH("CL140589",'Path Scorecard'!$H$5:$H$80,0)) -> Grovemade | H28: =INDEX('Path Scorecard'!$AH$5:$AH$80,MATCH("CL140589",'Path Scorecard'!$H$5:$H$80,0)) -> Orbitkey | I28: Wayfair even has a Desk Pads node. | J28: Q1. | K28: =INDEX('Path Scorecard'!$AD$5:$AD$80,MATCH("CL140589",'Path Scorecard'!$H$5:$H$80,0))
A29: 17 | B29: =INDEX('Path Scorecard'!$Q$5:$Q$80,MATCH("CL214775",'Path Scorecard'!$H$5:$H$80,0))&" · "&INDEX('Path Scorecard'!$AC$5:$AC$80,MATCH("CL214775",'Path Scorecard'!$H$5:$H$80,0)) -> Non-Hero · EXPLORE | C29: Coffee, Water & Snacks > Coffee, Coffee Makers & Supplies > Coffee Organizers & Dispensers | D29: =INDEX('Path Scorecard'!$Z$5:$Z$80,MATCH("CL214775",'Path Scorecard'!$H$5:$H$80,0)) -> 72 | E29: =INDEX('Path Scorecard'!$AE$5:$AE$80,MATCH("CL214775",'Path Scorecard'!$H$5:$H$80,0)) -> Amazon | F29: =INDEX('Path Scorecard'!$AF$5:$AF$80,MATCH("CL214775",'Path Scorecard'!$H$5:$H$80,0)) -> Wayfair | G29: =INDEX('Path Scorecard'!$AG$5:$AG$80,MATCH("CL214775",'Path Scorecard'!$H$5:$H$80,0)) -> Williams Sonoma | H29: =INDEX('Path Scorecard'!$AH$5:$AH$80,MATCH("CL214775",'Path Scorecard'!$H$5:$H$80,0)) -> Crate & Barrel | I29: Every office has a coffee corner. | J29: Q1-2027 breakroom refresh; holiday hosting. | K29: =INDEX('Path Scorecard'!$AD$5:$AD$80,MATCH("CL214775",'Path Scorecard'!$H$5:$H$80,0))
A30: 18 | B30: =INDEX('Path Scorecard'!$Q$5:$Q$80,MATCH("CL166381",'Path Scorecard'!$H$5:$H$80,0))&" · "&INDEX('Path Scorecard'!$AC$5:$AC$80,MATCH("CL166381",'Path Scorecard'!$H$5:$H$80,0)) -> Non-Hero · EXPLORE | C30: Furniture > Cubicle & Panel Systems > Desktop Privacy Panels | D30: =INDEX('Path Scorecard'!$Z$5:$Z$80,MATCH("CL166381",'Path Scorecard'!$H$5:$H$80,0)) -> 69 | E30: =INDEX('Path Scorecard'!$AE$5:$AE$80,MATCH("CL166381",'Path Scorecard'!$H$5:$H$80,0)) -> Amazon | F30: =INDEX('Path Scorecard'!$AF$5:$AF$80,MATCH("CL166381",'Path Scorecard'!$H$5:$H$80,0)) -> Wayfair | G30: =INDEX('Path Scorecard'!$AG$5:$AG$80,MATCH("CL166381",'Path Scorecard'!$H$5:$H$80,0)) -> Felt Right | H30: =INDEX('Path Scorecard'!$AH$5:$AH$80,MATCH("CL166381",'Path Scorecard'!$H$5:$H$80,0)) -> Etsy | I30: Open-plan noise is every office manager's complaint. | J30: Q1-2027 return-to-office fit-outs. | K30: =INDEX('Path Scorecard'!$AD$5:$AD$80,MATCH("CL166381",'Path Scorecard'!$H$5:$H$80,0))
A31: 19 | B31: =INDEX('Path Scorecard'!$Q$5:$Q$80,MATCH("CL70600",'Path Scorecard'!$H$5:$H$80,0))&" · "&INDEX('Path Scorecard'!$AC$5:$AC$80,MATCH("CL70600",'Path Scorecard'!$H$5:$H$80,0)) -> Non-Hero · EXPLORE | C31: Furniture > Cubicle & Panel Systems > Office Partitions & Dividers | D31: =INDEX('Path Scorecard'!$Z$5:$Z$80,MATCH("CL70600",'Path Scorecard'!$H$5:$H$80,0)) -> 67 | E31: =INDEX('Path Scorecard'!$AE$5:$AE$80,MATCH("CL70600",'Path Scorecard'!$H$5:$H$80,0)) -> Wayfair | F31: =INDEX('Path Scorecard'!$AF$5:$AF$80,MATCH("CL70600",'Path Scorecard'!$H$5:$H$80,0)) -> Amazon | G31: =INDEX('Path Scorecard'!$AG$5:$AG$80,MATCH("CL70600",'Path Scorecard'!$H$5:$H$80,0)) -> Felt Right | H31: =INDEX('Path Scorecard'!$AH$5:$AH$80,MATCH("CL70600",'Path Scorecard'!$H$5:$H$80,0)) -> Anthropologie | I31: 'Broken-plan' offices and home work corners. | J31: Q1-2027 office fit-outs; WFH corners. | K31: =INDEX('Path Scorecard'!$AD$5:$AD$80,MATCH("CL70600",'Path Scorecard'!$H$5:$H$80,0))
A32: 20 | B32: =INDEX('Path Scorecard'!$Q$5:$Q$80,MATCH("CL142180",'Path Scorecard'!$H$5:$H$80,0))&" · "&INDEX('Path Scorecard'!$AC$5:$AC$80,MATCH("CL142180",'Path Scorecard'!$H$5:$H$80,0)) -> Non-Hero · EXPLORE | C32: Coffee, Water & Snacks > Coffee, Coffee Makers & Supplies > Carafes, Kettles & Decanters | D32: =INDEX('Path Scorecard'!$Z$5:$Z$80,MATCH("CL142180",'Path Scorecard'!$H$5:$H$80,0)) -> 67 | E32: =INDEX('Path Scorecard'!$AE$5:$AE$80,MATCH("CL142180",'Path Scorecard'!$H$5:$H$80,0)) -> Amazon | F32: =INDEX('Path Scorecard'!$AF$5:$AF$80,MATCH("CL142180",'Path Scorecard'!$H$5:$H$80,0)) -> Target | G32: =INDEX('Path Scorecard'!$AG$5:$AG$80,MATCH("CL142180",'Path Scorecard'!$H$5:$H$80,0)) -> Fellow | H32: =INDEX('Path Scorecard'!$AH$5:$AH$80,MATCH("CL142180",'Path Scorecard'!$H$5:$H$80,0)) -> Williams Sonoma | I32: Coffee culture at the office. | J32: Q4 gifting; Q1 breakroom refresh. | K32: =INDEX('Path Scorecard'!$AD$5:$AD$80,MATCH("CL142180",'Path Scorecard'!$H$5:$H$80,0))
B33: Top-20 mix (live) | C33: =COUNTIFS('Path Scorecard'!$AB$5:$AB$80,"Recommended",'Path Scorecard'!$Q$5:$Q$80,"Hero")&" Hero · "&COUNTIFS('Path Scorecard'!$AB$5:$AB$80,"Recommended",'Path Scorecard'!$Q$5:$Q$80,"Probable Hero")&" Probable Hero · "&COUNTIFS('Path Scorecard'!$AB$5:$AB$80,"Recommended",'Path Scorecard'!$Q$5:$Q$80,"Non-Hero")&" Non-Hero = "&COUNTIFS('Path Scorecard'!$AB$5:$AB$80,"Recommended")&" shelves" -> 7 Hero · 7 Probable Hero · 6 Non-Hero = 20 shelves
A35: What changed
A36: • | B36: v3 vs v2: the recommendation is now a Top 20 with every segment represented (7 / 7 / 6). Non-Hero shelves are no longer capped; their play is EXPLORE (a low-risk marketplace test). Six Non-Hero shelves enter: Clocks, Desk Pads, Coffee Organizers, Desktop Privacy Panels, Office Partitions and Kettles.
A37: • | B37: v3 vs v2: four competitors per shelf (2 primary + 2 secondary) with separate, documented criteria ('Competitor Criteria'). Scheels and Michaels, your original picks, are kept as secondaries where they score best (Water Bottles; Planners). For Backpacks, Bellroy and Urban Outfitters edge Scheels on adjacency, so Scheels stays an alternate.
A38: • | B38: v3 vs v2: dedicated 'Hero Criteria' sheet with plain-English definitions, the decision rule, 1-5 scoring anchors for every factor, quotas and worked plays.
A39: • | B39: v3 vs v2: 9 new candidate shelves researched (incl. Ben's Scheels examples: yard games, recovery tools, hydration mixes). Outdoor Games is a Non-Hero reserve; the rest are backlog.
A40: • | B40: Versus your initial 9-item list: kept and drilled down Chairs & Seating, Desks, Lamps, Hydration and Planning. Parked Rugs and Labels (no L3/L4 below them), reframed Labels & Packaging to small-business packaging, and refocused Fitness to 'active workstation'. See 'Your List Review'.
A42: Suggested sequencing
A43: 1. | B43: Wave 1a (Staples data in hand): Planners, Backpacks, Office desks, Water bottles, Accent chairs, Desk lamps, Lunch, Laptop sleeves.
A44: 2. | B44: Wave 1b (needs a Staples leaf scrape): Desk organizers, Classroom decor, Bulletin boards, Keyboards, Pencil cases, Storage baskets, Clocks, Desk pads, Coffee organizers, Privacy panels, Partitions, Kettles.
A45: 3. | B45: Keep Office Chairs as a control shelf (Hero, PROTECT): it shows the safety gate correctly rejecting look-alikes of core 1P chairs.
A46: 4. | B46: Collect primaries at scale for the gap maths; sample secondaries by hand as a style / upside lens. Ask Pat for a Staples sales / margin rank to replace the Hero proxies.
A48: How to read this workbook
B49: Top 20 Recommendations | C49: The 20 shelves (+ 9 reserves) with segment, play, 4 competitors, the super-extension, archetypes, 1P watch-outs and moments.
B50: Segment Map | C50: One picture: every shelf placed as Hero, Probable Hero or Non-Hero.
B51: Hero Criteria | C51: Segment definitions, the decision rule, 1-5 anchors, cut-offs and quotas (editable).
B52: Competitor Criteria | C52: Primary (K1-K5) and secondary (E1-E5) competitor criteria, pools and weights (editable).
B53: Your List Review | C53: Verdict on each of the 9 initial items, their segment mix, and exact L3/L4 drill-downs.
B54: Selection Criteria | C54: Gates and the 8 path-score criteria (editable).
B55: Path Scorecard | C55: All 76 candidate shelves with gates, segment, score, rank, status, play and 4 competitors (formulas).
B56: Hero Segmentation | C56: The two indices behind each segment, plus an L2 roll-up.
B57: Primary / Secondary Competitor Fit | C57: Competitor scores per shelf; ranks 1-2 are the picks.
B58: Competitor Profiles | C58: Every competitor: pool, evidence, scores, where it is used, cautions.
B59: Parked & Excluded / Evidence & Sources / Staples Tree Extract | C59: What was dropped and why; every fact with its source; all terminal Staples nodes.
B61: Legend | C61: Blue text on yellow = editable input. Segments: blue Hero, orange Probable Hero, grey Non-Hero. Status: green Recommended, amber Reserve, grey Backlog, light blue Protect, red Parked.

Sheet Top 20 Recommendations
A1: Top 20 L3/L4 recommendations: 7 Hero · 7 Probable Hero · 6 Non-Hero, each with 4 competitors
A2: Segment, rank, status, play, score and all four competitors are live lookups. Primary = broad retailer (measures the gap); Secondary = enthusiast / design specialist (the super-extension).
A4: # | B4: Hero segment | C4: Rank in segment | D4: Status (live) | E4: Marketplace play | F4: Path score | G4: Staples path (exact) | H4: Level | I4: Category ID | J4: Staples items | K4: SKUs in hand | L4: Fast-start | M4: Primary 1 | N4: Primary 2 | O4: Secondary 1 (enthusiast) | P4: Secondary 2 (enthusiast) | Q4: What the secondaries show (super-extension) | R4: Why this path | S4: Archetypes we expect to find (hypotheses) | T4: 1P watch-out (cannibalisation) | U4: Commercial moment | V4: Why the room will relate | W4: Where to look on the primaries | X4: Staples URL
A5: 1 | B5: =INDEX('Path Scorecard'!$Q$5:$Q$80,MATCH($I5,'Path Scorecard'!$H$5:$H$80,0)) -> Hero | C5: =INDEX('Path Scorecard'!$AA$5:$AA$80,MATCH($I5,'Path Scorecard'!$H$5:$H$80,0)) -> 1 | D5: =INDEX('Path Scorecard'!$AB$5:$AB$80,MATCH($I5,'Path Scorecard'!$H$5:$H$80,0)) -> Recommended | E5: =INDEX('Path Scorecard'!$AC$5:$AC$80,MATCH($I5,'Path Scorecard'!$H$5:$H$80,0)) -> EXTEND | F5: =INDEX('Path Scorecard'!$Z$5:$Z$80,MATCH($I5,'Path Scorecard'!$H$5:$H$80,0)) -> 95 | G5: Office Supplies > Calendars & Planners > Planners & Personal Organizers | H5: 3 | I5: CL166388 | J5: 1037 | K5: 1016 | L5: =INDEX('Path Scorecard'!$AD$5:$AD$80,MATCH($I5,'Path Scorecard'!$H$5:$H$80,0)) -> Yes | M5: =INDEX('Path Scorecard'!$AE$5:$AE$80,MATCH($I5,'Path Scorecard'!$H$5:$H$80,0)) -> Amazon | N5: =INDEX('Path Scorecard'!$AF$5:$AF$80,MATCH($I5,'Path Scorecard'!$H$5:$H$80,0)) -> Target | O5: =INDEX('Path Scorecard'!$AG$5:$AG$80,MATCH($I5,'Path Scorecard'!$H$5:$H$80,0)) -> Erin Condren | P5: =INDEX('Path Scorecard'!$AH$5:$AH$80,MATCH($I5,'Path Scorecard'!$H$5:$H$80,0)) -> Michaels | Q5: Erin Condren and Michaels show the enthusiast planner system: customisable LifePlanners, disc-bound Happy Planner, stickers and accessories sold as an ecosystem. | R5: Staples' deepest stationery shelf (1,037 items) is dated-planner led (Blue Sky, At-A-Glance). Enthusiast formats (disc-bound, undated, sticker-ready, wellness) live at Michaels and Amazon. | S5: Disc-bound customisable planners; undated goal & wellness planners; pastel/floral teacher & student planners; vegan-leather premium planners ($30-60). | T5: Dated 12-month planners incl. the Sincerely Jules exclusive: add other formats, not look-alikes. | U5: Jan-2027 New Year planning; Jul-Aug 2027 academic planners. | V5: Staples launched Sincerely Jules for Blue Sky in Jun-2026. This shows the next step beyond one influencer line. | W5: Amazon: Planners, Refills & Covers (breadth + recruitable sellers). Michaels: Papercraft > Planners (The Happy Planner + companion accessories); near-tie with Amazon. | X5: https://www.staples.com/Planners-Personal-Organizers/cat_CL166388
A6: 2 | B6: =INDEX('Path Scorecard'!$Q$5:$Q$80,MATCH($I6,'Path Scorecard'!$H$5:$H$80,0)) -> Hero | C6: =INDEX('Path Scorecard'!$AA$5:$AA$80,MATCH($I6,'Path Scorecard'!$H$5:$H$80,0)) -> 2 | D6: =INDEX('Path Scorecard'!$AB$5:$AB$80,MATCH($I6,'Path Scorecard'!$H$5:$H$80,0)) -> Recommended | E6: =INDEX('Path Scorecard'!$AC$5:$AC$80,MATCH($I6,'Path Scorecard'!$H$5:$H$80,0)) -> EXTEND | F6: =INDEX('Path Scorecard'!$Z$5:$Z$80,MATCH($I6,'Path Scorecard'!$H$5:$H$80,0)) -> 91 | G6: Office Supplies > Desk Organizers & Accessories > Desk Organizers | H6: 3 | I6: CL140991 | J6: 342 | K6: 0 | L6: =INDEX('Path Scorecard'!$AD$5:$AD$80,MATCH($I6,'Path Scorecard'!$H$5:$H$80,0)) | M6: =INDEX('Path Scorecard'!$AE$5:$AE$80,MATCH($I6,'Path Scorecard'!$H$5:$H$80,0)) -> Target | N6: =INDEX('Path Scorecard'!$AF$5:$AF$80,MATCH($I6,'Path Scorecard'!$H$5:$H$80,0)) -> Amazon | O6: =INDEX('Path Scorecard'!$AG$5:$AG$80,MATCH($I6,'Path Scorecard'!$H$5:$H$80,0)) -> Grovemade | P6: =INDEX('Path Scorecard'!$AH$5:$AH$80,MATCH($I6,'Path Scorecard'!$H$5:$H$80,0)) -> The Container Store | Q6: Grovemade shows the premium end (walnut, cork, modular desk systems); The Container Store shows coordinated acrylic / marble collections. | R6: Staples' 342 organizers are mostly black mesh and utility. Target (Brightroom) and Container Store sell coordinated desk collections in acrylic, bamboo, marble, linen and pastel. | S6: Clear acrylic modular sets; warm-wood / bamboo sets; pastel & neutral 'aesthetic desk' collections; turntable caddies. | T6: Black mesh sets (Staples brand, Officemate). | U6: January 'get organized' season; BTS desk & dorm refresh. | V6: Desk organization is a header-nav Staples staple and a low-ticket attach to every paper and pen basket. | W6: Target: Brightroom desk organization + Target Plus brands. Amazon: Desk Organizers. Container Store: Office > Desktop Collections (style benchmark). | X6: https://www.staples.com/Desk-Organizers/cat_CL140991
A7: 3 | B7: =INDEX('Path Scorecard'!$Q$5:$Q$80,MATCH($I7,'Path Scorecard'!$H$5:$H$80,0)) -> Hero | C7: =INDEX('Path Scorecard'!$AA$5:$AA$80,MATCH($I7,'Path Scorecard'!$H$5:$H$80,0)) -> 3 | D7: =INDEX('Path Scorecard'!$AB$5:$AB$80,MATCH($I7,'Path Scorecard'!$H$5:$H$80,0)) -> Recommended | E7: =INDEX('Path Scorecard'!$AC$5:$AC$80,MATCH($I7,'Path Scorecard'!$H$5:$H$80,0)) -> EXTEND | F7: =INDEX('Path Scorecard'!$Z$5:$Z$80,MATCH($I7,'Path Scorecard'!$H$5:$H$80,0)) -> 86 | G7: School Supplies > Teacher Supplies > Classroom Decorations > Decorative Accents & Board Sets | H7: 4 | I7: CL219245 | J7: 607 | K7: 0 | L7: =INDEX('Path Scorecard'!$AD$5:$AD$80,MATCH($I7,'Path Scorecard'!$H$5:$H$80,0)) | M7: =INDEX('Path Scorecard'!$AE$5:$AE$80,MATCH($I7,'Path Scorecard'!$H$5:$H$80,0)) -> Amazon | N7: =INDEX('Path Scorecard'!$AF$5:$AF$80,MATCH($I7,'Path Scorecard'!$H$5:$H$80,0)) -> Walmart | O7: =INDEX('Path Scorecard'!$AG$5:$AG$80,MATCH($I7,'Path Scorecard'!$H$5:$H$80,0)) -> Etsy | P7: =INDEX('Path Scorecard'!$AH$5:$AH$80,MATCH($I7,'Path Scorecard'!$H$5:$H$80,0)) -> Oriental Trading | Q7: Etsy shows handmade theme sets (boho, calm); Oriental Trading shows complete themed classroom kits. | R7: 607 Staples items. Teachers self-fund about $895 a year and buy decor as coordinated themes (boho, calm, pastel). | S7: Boho / neutral theme sets; calm-corner & SEL decor; pastel bulletin-board kits; plant & nature themes. | T7: Existing bulletin-board sets: compare theme coverage, not SKU swaps. | U7: BTS-2027 classroom set-up (Jul-Aug); Teacher Appreciation Week (May). | V7: Teachers are a Staples loyalty segment (teacher coupon, teacher lists). | W7: Amazon: Classroom Decorations. Oriental Trading: Teaching Supplies > Classroom Decorations. Michaels: Teacher Supplies. | X7: https://www.staples.com/Decorative-Accents-Board-Sets/cat_CL219245
A8: 4 | B8: =INDEX('Path Scorecard'!$Q$5:$Q$80,MATCH($I8,'Path Scorecard'!$H$5:$H$80,0)) -> Hero | C8: =INDEX('Path Scorecard'!$AA$5:$AA$80,MATCH($I8,'Path Scorecard'!$H$5:$H$80,0)) -> 4 | D8: =INDEX('Path Scorecard'!$AB$5:$AB$80,MATCH($I8,'Path Scorecard'!$H$5:$H$80,0)) -> Recommended | E8: =INDEX('Path Scorecard'!$AC$5:$AC$80,MATCH($I8,'Path Scorecard'!$H$5:$H$80,0)) -> EXTEND | F8: =INDEX('Path Scorecard'!$Z$5:$Z$80,MATCH($I8,'Path Scorecard'!$H$5:$H$80,0)) -> 86 | G8: Bags, Backpacks & Luggage > Backpacks & Laptop Bags > Backpacks | H8: 3 | I8: CL142745 | J8: 585 | K8: 542 | L8: =INDEX('Path Scorecard'!$AD$5:$AD$80,MATCH($I8,'Path Scorecard'!$H$5:$H$80,0)) -> Yes | M8: =INDEX('Path Scorecard'!$AE$5:$AE$80,MATCH($I8,'Path Scorecard'!$H$5:$H$80,0)) -> Amazon | N8: =INDEX('Path Scorecard'!$AF$5:$AF$80,MATCH($I8,'Path Scorecard'!$H$5:$H$80,0)) -> Target | O8: =INDEX('Path Scorecard'!$AG$5:$AG$80,MATCH($I8,'Path Scorecard'!$H$5:$H$80,0)) -> Bellroy | P8: =INDEX('Path Scorecard'!$AH$5:$AH$80,MATCH($I8,'Path Scorecard'!$H$5:$H$80,0)) -> Urban Outfitters | Q8: Bellroy shows premium commuter design; Urban Outfitters shows fashion-led styles (mini packs, corduroy). Scheels and REI (alternates) show technical packs. | R8: 585 Staples items, laptop & commuter led. 85% of parents bought a backpack for BTS; lifestyle backpacks grew 3% in 2025 (Circana). | S8: Corduroy / soft-aesthetic backpacks; Scandinavian-minimal daypacks; mini backpacks; personalisable patch & pin packs. | T8: Laptop backpacks (SwissGear, Targus): watch cannibalisation here. | U8: BTS-2027. | V8: JanSport now sells on Target Plus, the curated-marketplace peer Pat can point to. | W8: Amazon: Backpacks. Target: Backpacks (incl. JanSport on Target Plus). | X8: https://www.staples.com/Backpacks/cat_CL142745
A9: 5 | B9: =INDEX('Path Scorecard'!$Q$5:$Q$80,MATCH($I9,'Path Scorecard'!$H$5:$H$80,0)) -> Hero | C9: =INDEX('Path Scorecard'!$AA$5:$AA$80,MATCH($I9,'Path Scorecard'!$H$5:$H$80,0)) -> 5 | D9: =INDEX('Path Scorecard'!$AB$5:$AB$80,MATCH($I9,'Path Scorecard'!$H$5:$H$80,0)) -> Recommended | E9: =INDEX('Path Scorecard'!$AC$5:$AC$80,MATCH($I9,'Path Scorecard'!$H$5:$H$80,0)) -> EXTEND | F9: =INDEX('Path Scorecard'!$Z$5:$Z$80,MATCH($I9,'Path Scorecard'!$H$5:$H$80,0)) -> 81 | G9: Furniture > Desks > Office Desks | H9: 3 | I9: CL210795 | J9: 1501 | K9: 1265 | L9: =INDEX('Path Scorecard'!$AD$5:$AD$80,MATCH($I9,'Path Scorecard'!$H$5:$H$80,0)) -> Yes | M9: =INDEX('Path Scorecard'!$AE$5:$AE$80,MATCH($I9,'Path Scorecard'!$H$5:$H$80,0)) -> Wayfair | N9: =INDEX('Path Scorecard'!$AF$5:$AF$80,MATCH($I9,'Path Scorecard'!$H$5:$H$80,0)) -> Amazon | O9: =INDEX('Path Scorecard'!$AG$5:$AG$80,MATCH($I9,'Path Scorecard'!$H$5:$H$80,0)) -> Design Within Reach | P9: =INDEX('Path Scorecard'!$AH$5:$AH$80,MATCH($I9,'Path Scorecard'!$H$5:$H$80,0)) -> West Elm | Q9: Design Within Reach shows iconic design desks (Herman Miller); West Elm shows mid-century home-office desks. | R9: 1,501 Staples items. Pilot Computer-desk split: 3 recommended archetypes (1 Strong). Split by Staples' own type facet. | S9: Fluted / curved-edge writing desks; cane & rattan desks; small-space floating desks; warm-wood Scandinavian desks. | T9: Laminate computer desks (Bush, Sauder, Union & Scale). | U9: Q1 office refresh. | V9: Second half of the White Chair story. | W9: Wayfair: Office Furniture > Desks + Small Space Offices. Amazon: Home Office Desks. | X9: https://www.staples.com/Office-Desks/cat_CL210795
A10: 6 | B10: =INDEX('Path Scorecard'!$Q$5:$Q$80,MATCH($I10,'Path Scorecard'!$H$5:$H$80,0)) -> Hero | C10: =INDEX('Path Scorecard'!$AA$5:$AA$80,MATCH($I10,'Path Scorecard'!$H$5:$H$80,0)) -> 6 | D10: =INDEX('Path Scorecard'!$AB$5:$AB$80,MATCH($I10,'Path Scorecard'!$H$5:$H$80,0)) -> Recommended | E10: =INDEX('Path Scorecard'!$AC$5:$AC$80,MATCH($I10,'Path Scorecard'!$H$5:$H$80,0)) -> EXTEND | F10: =INDEX('Path Scorecard'!$Z$5:$Z$80,MATCH($I10,'Path Scorecard'!$H$5:$H$80,0)) -> 77 | G10: Furniture > Boards & Easels > Bulletin Boards | H10: 3 | I10: CL142403 | J10: 284 | K10: 0 | L10: =INDEX('Path Scorecard'!$AD$5:$AD$80,MATCH($I10,'Path Scorecard'!$H$5:$H$80,0)) | M10: =INDEX('Path Scorecard'!$AE$5:$AE$80,MATCH($I10,'Path Scorecard'!$H$5:$H$80,0)) -> Amazon | N10: =INDEX('Path Scorecard'!$AF$5:$AF$80,MATCH($I10,'Path Scorecard'!$H$5:$H$80,0)) -> Wayfair | O10: =INDEX('Path Scorecard'!$AG$5:$AG$80,MATCH($I10,'Path Scorecard'!$H$5:$H$80,0)) -> Etsy | P10: =INDEX('Path Scorecard'!$AH$5:$AH$80,MATCH($I10,'Path Scorecard'!$H$5:$H$80,0)) -> Pottery Barn Teen | Q10: Etsy shows letter boards and custom felt boards; Pottery Barn Teen shows scalloped, fabric and statement pinboards. | R10: 284 Staples items, cork & utility led. | S10: Fabric memo boards; felt letter boards; pinnable felt tiles; framed & acrylic boards. | T10: Cork boards (Quartet, U Brands). | U10: BTS dorm; Jan planning. | V10: Letter boards are an office & classroom staple. | W10: Amazon: memo & letter boards. Wayfair: Office Organization > Memo Boards. | X10: https://www.staples.com/Bulletin-Boards/cat_CL142403
A11: 7 | B11: =INDEX('Path Scorecard'!$Q$5:$Q$80,MATCH($I11,'Path Scorecard'!$H$5:$H$80,0)) -> Hero | C11: =INDEX('Path Scorecard'!$AA$5:$AA$80,MATCH($I11,'Path Scorecard'!$H$5:$H$80,0)) -> 7 | D11: =INDEX('Path Scorecard'!$AB$5:$AB$80,MATCH($I11,'Path Scorecard'!$H$5:$H$80,0)) -> Recommended | E11: =INDEX('Path Scorecard'!$AC$5:$AC$80,MATCH($I11,'Path Scorecard'!$H$5:$H$80,0)) -> EXTEND | F11: =INDEX('Path Scorecard'!$Z$5:$Z$80,MATCH($I11,'Path Scorecard'!$H$5:$H$80,0)) -> 75 | G11: Computers & Accessories > Computer Accessories & Peripherals > Computer Keyboards | H11: 3 | I11: CL215783 | J11: 374 | K11: 0 | L11: =INDEX('Path Scorecard'!$AD$5:$AD$80,MATCH($I11,'Path Scorecard'!$H$5:$H$80,0)) | M11: =INDEX('Path Scorecard'!$AE$5:$AE$80,MATCH($I11,'Path Scorecard'!$H$5:$H$80,0)) -> Amazon | N11: =INDEX('Path Scorecard'!$AF$5:$AF$80,MATCH($I11,'Path Scorecard'!$H$5:$H$80,0)) -> Best Buy | O11: =INDEX('Path Scorecard'!$AG$5:$AG$80,MATCH($I11,'Path Scorecard'!$H$5:$H$80,0)) -> Keychron | P11: =INDEX('Path Scorecard'!$AH$5:$AH$80,MATCH($I11,'Path Scorecard'!$H$5:$H$80,0)) -> Drop | Q11: Keychron and Drop show the enthusiast keyboard world: retro layouts, custom keycaps, hot-swap switches. | R11: 374 Staples items. Typewriter-style and pastel keyboards went mainstream (Logitech POP). | S11: Retro round-key keyboards; pastel compact 75% boards; colour-matched keyboard + mouse sets. | T11: Logitech / Microsoft business keyboards: core 1P, watch CRS. | U11: BTS; holiday. | V11: Shows the colour gap inside a brand Staples already sells. | W11: Amazon: Keyboards. Best Buy: Keyboards (colour filter). | X11: https://www.staples.com/Computer-Keyboards/cat_CL215783
A12: 8 | B12: =INDEX('Path Scorecard'!$Q$5:$Q$80,MATCH($I12,'Path Scorecard'!$H$5:$H$80,0)) -> Probable Hero | C12: =INDEX('Path Scorecard'!$AA$5:$AA$80,MATCH($I12,'Path Scorecard'!$H$5:$H$80,0)) -> 1 | D12: =INDEX('Path Scorecard'!$AB$5:$AB$80,MATCH($I12,'Path Scorecard'!$H$5:$H$80,0)) -> Recommended | E12: =INDEX('Path Scorecard'!$AC$5:$AC$80,MATCH($I12,'Path Scorecard'!$H$5:$H$80,0)) -> BUILD | F12: =INDEX('Path Scorecard'!$Z$5:$Z$80,MATCH($I12,'Path Scorecard'!$H$5:$H$80,0)) -> 91 | G12: Coffee, Water & Snacks > Water & Beverages > Water Bottles, Tumblers & Travel Mugs | H12: 3 | I12: CL354650 | J12: 463 | K12: 462 | L12: =INDEX('Path Scorecard'!$AD$5:$AD$80,MATCH($I12,'Path Scorecard'!$H$5:$H$80,0)) -> Yes | M12: =INDEX('Path Scorecard'!$AE$5:$AE$80,MATCH($I12,'Path Scorecard'!$H$5:$H$80,0)) -> Dick's Sporting Goods | N12: =INDEX('Path Scorecard'!$AF$5:$AF$80,MATCH($I12,'Path Scorecard'!$H$5:$H$80,0)) -> Target | O12: =INDEX('Path Scorecard'!$AG$5:$AG$80,MATCH($I12,'Path Scorecard'!$H$5:$H$80,0)) -> Scheels | P12: =INDEX('Path Scorecard'!$AH$5:$AH$80,MATCH($I12,'Path Scorecard'!$H$5:$H$80,0)) -> YETI | Q12: Scheels shows wall-to-wall colourways, lids and accessories; YETI shows customisation and premium colour drops. | R12: Staples carries 463 desk-use items. Specialists sell full colourways, lids, sizes and accessories from Owala, Stanley, YETI, HydroJug and BruMate. | S12: Sip/chug hybrid bottles; 40 oz handle tumblers in seasonal colourways; kids' 12-16 oz school bottles; lids, boots & straw accessories. | T12: Stanley / Hydro Flask SKUs Staples already sells: gap is colourway & size, not the same SKU. | U12: BTS-2027 (Jul-Sep); Q4 gifting; January hydration resolutions. | V12: Everyone in the room knows the Stanley / Owala craze. | W12: Dick's: Drinkware / Sport Water Bottles. Target: water bottles & tumblers incl. exclusive colourways. | X12: https://www.staples.com/Water-Bottles-Tumblers-Travel-Mugs/cat_CL354650
A13: 9 | B13: =INDEX('Path Scorecard'!$Q$5:$Q$80,MATCH($I13,'Path Scorecard'!$H$5:$H$80,0)) -> Probable Hero | C13: =INDEX('Path Scorecard'!$AA$5:$AA$80,MATCH($I13,'Path Scorecard'!$H$5:$H$80,0)) -> 2 | D13: =INDEX('Path Scorecard'!$AB$5:$AB$80,MATCH($I13,'Path Scorecard'!$H$5:$H$80,0)) -> Recommended | E13: =INDEX('Path Scorecard'!$AC$5:$AC$80,MATCH($I13,'Path Scorecard'!$H$5:$H$80,0)) -> BUILD | F13: =INDEX('Path Scorecard'!$Z$5:$Z$80,MATCH($I13,'Path Scorecard'!$H$5:$H$80,0)) -> 89 | G13: Furniture > Chairs & Seating > Accent & Waiting Room Chairs | H13: 3 | I13: CL70203 | J13: 229 | K13: 199 | L13: =INDEX('Path Scorecard'!$AD$5:$AD$80,MATCH($I13,'Path Scorecard'!$H$5:$H$80,0)) -> Yes | M13: =INDEX('Path Scorecard'!$AE$5:$AE$80,MATCH($I13,'Path Scorecard'!$H$5:$H$80,0)) -> Wayfair | N13: =INDEX('Path Scorecard'!$AF$5:$AF$80,MATCH($I13,'Path Scorecard'!$H$5:$H$80,0)) -> Amazon | O13: =INDEX('Path Scorecard'!$AG$5:$AG$80,MATCH($I13,'Path Scorecard'!$H$5:$H$80,0)) -> Article | P13: =INDEX('Path Scorecard'!$AH$5:$AH$80,MATCH($I13,'Path Scorecard'!$H$5:$H$80,0)) -> West Elm | Q13: Article and West Elm show the design-led mid-century / boucle end at $300-600. | R13: The original 'White Chair' shelf. Pilot (Sep-2026): 5 recommended archetypes, 2 Strong; 94% high-confidence mapping. | S13: Boucle / curved barrel chairs; cream & sage upholstered side chairs with wood legs; rattan & cane lounge chairs; $150-350 design tier. | T13: Black vinyl / fabric guest & reception chairs (Flash, Boss, HON). | U13: Q1-2027 office refresh and return-to-office budgets. | V13: Pat's own example: the thesis in one picture. | W13: Wayfair: Living Room > Accent Chairs and Professional > Office Seating > Accent Chairs. Amazon: Accent Chairs. | X13: https://www.staples.com/Accent-Waiting-Room-Chairs/cat_CL70203
A14: 10 | B14: =INDEX('Path Scorecard'!$Q$5:$Q$80,MATCH($I14,'Path Scorecard'!$H$5:$H$80,0)) -> Probable Hero | C14: =INDEX('Path Scorecard'!$AA$5:$AA$80,MATCH($I14,'Path Scorecard'!$H$5:$H$80,0)) -> 3 | D14: =INDEX('Path Scorecard'!$AB$5:$AB$80,MATCH($I14,'Path Scorecard'!$H$5:$H$80,0)) -> Recommended | E14: =INDEX('Path Scorecard'!$AC$5:$AC$80,MATCH($I14,'Path Scorecard'!$H$5:$H$80,0)) -> BUILD | F14: =INDEX('Path Scorecard'!$Z$5:$Z$80,MATCH($I14,'Path Scorecard'!$H$5:$H$80,0)) -> 86 | G14: Furniture > Lamps & Lighting > Desk Lamps | H14: 3 | I14: CL167867 | J14: 210 | K14: 195 | L14: =INDEX('Path Scorecard'!$AD$5:$AD$80,MATCH($I14,'Path Scorecard'!$H$5:$H$80,0)) -> Yes | M14: =INDEX('Path Scorecard'!$AE$5:$AE$80,MATCH($I14,'Path Scorecard'!$H$5:$H$80,0)) -> Wayfair | N14: =INDEX('Path Scorecard'!$AF$5:$AF$80,MATCH($I14,'Path Scorecard'!$H$5:$H$80,0)) -> Amazon | O14: =INDEX('Path Scorecard'!$AG$5:$AG$80,MATCH($I14,'Path Scorecard'!$H$5:$H$80,0)) -> Lamps Plus | P14: =INDEX('Path Scorecard'!$AH$5:$AH$80,MATCH($I14,'Path Scorecard'!$H$5:$H$80,0)) -> Urban Outfitters | Q14: Lamps Plus shows specialist depth (90,000+ designs); Urban Outfitters shows trend lamps (mushroom, pleated). | R14: 210 Staples items, mostly LED task lamps. Wayfair sells mushroom, pleated, rechargeable and sculptural lamps that sit between task light and decor. | S14: Mushroom / dome lamps; pleated-shade & ceramic-base lamps; rechargeable cordless lamps; brass & warm-wood architect lamps. | T14: LED task lamps with USB ports: Staples' core. | U14: Q1-2027 home-office refresh; BTS dorm. | V14: 2026 home-office trend reports all name better lighting and warm materials. | W14: Wayfair: Lighting > Table & Floor Lamps > Desk Lamps (+ Teen Desk Lamps). Amazon: Desk Lamps. | X14: https://www.staples.com/Desk-Lamps/cat_CL167867
A15: 11 | B15: =INDEX('Path Scorecard'!$Q$5:$Q$80,MATCH($I15,'Path Scorecard'!$H$5:$H$80,0)) -> Probable Hero | C15: =INDEX('Path Scorecard'!$AA$5:$AA$80,MATCH($I15,'Path Scorecard'!$H$5:$H$80,0)) -> 4 | D15: =INDEX('Path Scorecard'!$AB$5:$AB$80,MATCH($I15,'Path Scorecard'!$H$5:$H$80,0)) -> Recommended | E15: =INDEX('Path Scorecard'!$AC$5:$AC$80,MATCH($I15,'Path Scorecard'!$H$5:$H$80,0)) -> BUILD | F15: =INDEX('Path Scorecard'!$Z$5:$Z$80,MATCH($I15,'Path Scorecard'!$H$5:$H$80,0)) -> 86 | G15: Office Supplies > Writing Supplies & Instruments > Pencil Accessories > Pencil Cases & Pouches | H15: 4 | I15: CL141253 | J15: 107 | K15: 0 | L15: =INDEX('Path Scorecard'!$AD$5:$AD$80,MATCH($I15,'Path Scorecard'!$H$5:$H$80,0)) | M15: =INDEX('Path Scorecard'!$AE$5:$AE$80,MATCH($I15,'Path Scorecard'!$H$5:$H$80,0)) -> Amazon | N15: =INDEX('Path Scorecard'!$AF$5:$AF$80,MATCH($I15,'Path Scorecard'!$H$5:$H$80,0)) -> Target | O15: =INDEX('Path Scorecard'!$AG$5:$AG$80,MATCH($I15,'Path Scorecard'!$H$5:$H$80,0)) -> JetPens | P15: =INDEX('Path Scorecard'!$AH$5:$AH$80,MATCH($I15,'Path Scorecard'!$H$5:$H$80,0)) -> Kinokuniya | Q15: JetPens and Kinokuniya show Japanese stationery culture: stand-up pouches, multi-compartment cases, character collabs. | R15: 107 Staples items. The pencil pouch is the first 'aesthetic' purchase in the BTS basket, at under $20. | S15: Large-capacity multi-layer pouches (Japanese style); clear / jelly pouches; corduroy & quilted pouches; kawaii & character cases. | T15: Staples' own Recess Club pouches: extend beyond them, don't duplicate. | U15: BTS-2027 (Jul-Sep). | V15: Staples' Recess Club / Jellygram exclusives (BTS 2026) already prove the demand. | W15: Amazon: Pencil Cases. Target: pencil cases & pouches. JetPens: Pencil Cases (style benchmark). | X15: https://www.staples.com/Pencil-Cases-Pouches/cat_CL141253
A16: 12 | B16: =INDEX('Path Scorecard'!$Q$5:$Q$80,MATCH($I16,'Path Scorecard'!$H$5:$H$80,0)) -> Probable Hero | C16: =INDEX('Path Scorecard'!$AA$5:$AA$80,MATCH($I16,'Path Scorecard'!$H$5:$H$80,0)) -> 5 | D16: =INDEX('Path Scorecard'!$AB$5:$AB$80,MATCH($I16,'Path Scorecard'!$H$5:$H$80,0)) -> Recommended | E16: =INDEX('Path Scorecard'!$AC$5:$AC$80,MATCH($I16,'Path Scorecard'!$H$5:$H$80,0)) -> BUILD | F16: =INDEX('Path Scorecard'!$Z$5:$Z$80,MATCH($I16,'Path Scorecard'!$H$5:$H$80,0)) -> 86 | G16: Bags, Backpacks & Luggage > Totes & Handbags > Lunch Bags & Boxes | H16: 3 | I16: CL165124 | J16: 404 | K16: 406 | L16: =INDEX('Path Scorecard'!$AD$5:$AD$80,MATCH($I16,'Path Scorecard'!$H$5:$H$80,0)) -> Yes | M16: =INDEX('Path Scorecard'!$AE$5:$AE$80,MATCH($I16,'Path Scorecard'!$H$5:$H$80,0)) -> Amazon | N16: =INDEX('Path Scorecard'!$AF$5:$AF$80,MATCH($I16,'Path Scorecard'!$H$5:$H$80,0)) -> Target | O16: =INDEX('Path Scorecard'!$AG$5:$AG$80,MATCH($I16,'Path Scorecard'!$H$5:$H$80,0)) -> Bentgo | P16: =INDEX('Path Scorecard'!$AH$5:$AH$80,MATCH($I16,'Path Scorecard'!$H$5:$H$80,0)) -> Pottery Barn Kids | Q16: Bentgo shows the bento system for kids and adults; Pottery Barn Kids shows personalised, coordinated lunch bundles. | R16: 404 Staples items. Bento compartments, stainless and leak-proof designs lead BTS and work-lunch search. | S16: Bento compartment boxes (kids & adult); neutral / vegan-leather insulated lunch totes; stainless & glass meal-prep sets. | T16: Basic insulated lunch bags Staples already stocks. | U16: BTS-2027; January 'bring lunch to the office' resolutions. | V16: BTS is Pat's named seasonal anchor and lunch is on every parent's list. | W16: Amazon: Lunch Boxes & Bags. Target: lunch boxes & bags (Bentgo, Stasher, owned brands). | X16: https://www.staples.com/Lunch-Bags-Boxes/cat_CL165124
... A24: 20 | B24: =INDEX('Path Scorecard'!$Q$5:$Q$80,MATCH($I24,'Path Scorecard'!$H$5:$H$80,0)) -> Non-Hero | C24: =INDEX('Path Scorecard'!$AA$5:$AA$80,MATCH($I24,'Path Scorecard'!$H$5:$H$80,0)) -> 6 | D24: =INDEX('Path Scorecard'!$AB$5:$AB$80,MATCH($I24,'Path Scorecard'!$H$5:$H$80,0)) -> Recommended | E24: =INDEX('Path Scorecard'!$AC$5:$AC$80,MATCH($I24,'Path Scorecard'!$H$5:$H$80,0)) -> EXPLORE | F24: =INDEX('Path Scorecard'!$Z$5:$Z$80,MATCH($I24,'Path Scorecard'!$H$5:$H$80,0)) -> 67 | G24: Coffee, Water & Snacks > Coffee, Coffee Makers & Supplies > Carafes, Kettles & Decanters | H24: 3 | I24: CL142180 | J24: 55 | K24: 0 | L24: =INDEX('Path Scorecard'!$AD$5:$AD$80,MATCH($I24,'Path Scorecard'!$H$5:$H$80,0)) | M24: =INDEX('Path Scorecard'!$AE$5:$AE$80,MATCH($I24,'Path Scorecard'!$H$5:$H$80,0)) -> Amazon | N24: =INDEX('Path Scorecard'!$AF$5:$AF$80,MATCH($I24,'Path Scorecard'!$H$5:$H$80,0)) -> Target | O24: =INDEX('Path Scorecard'!$AG$5:$AG$80,MATCH($I24,'Path Scorecard'!$H$5:$H$80,0)) -> Fellow | P24: =INDEX('Path Scorecard'!$AH$5:$AH$80,MATCH($I24,'Path Scorecard'!$H$5:$H$80,0)) -> Williams Sonoma | Q24: Fellow and Williams Sonoma show the design / coffee-enthusiast kettle. | R24: 55 Staples items of carafes, kettles & decanters. The gooseneck, temperature-control kettle (Fellow Stagg) is a design object in coffee culture. | S24: Matte-black gooseneck kettles with temperature control; retro enamel kettles; glass tea kettles. | T24: Basic electric kettles and airpots (moderate 1P). | U24: Q4 gifting; Q1 breakroom refresh. | V24: Coffee culture at the office. | W24: Amazon / Target: electric kettles. Fellow: Stagg range. Williams Sonoma: kettles. | X24: https://www.staples.com/Carafes-Kettles-Decanters/cat_CL142180
A26: Reserves: the next 3 shelves per segment (swap-ins)
A27: R1 | B27: =INDEX('Path Scorecard'!$Q$5:$Q$80,MATCH($I27,'Path Scorecard'!$H$5:$H$80,0)) -> Hero | C27: =INDEX('Path Scorecard'!$AA$5:$AA$80,MATCH($I27,'Path Scorecard'!$H$5:$H$80,0)) -> 8 | D27: =INDEX('Path Scorecard'!$AB$5:$AB$80,MATCH($I27,'Path Scorecard'!$H$5:$H$80,0)) -> Reserve | E27: =INDEX('Path Scorecard'!$AC$5:$AC$80,MATCH($I27,'Path Scorecard'!$H$5:$H$80,0)) -> EXTEND | F27: =INDEX('Path Scorecard'!$Z$5:$Z$80,MATCH($I27,'Path Scorecard'!$H$5:$H$80,0)) -> 74 | G27: Office Supplies > Calendars & Planners > Calendars | H27: 3 | I27: CL166389 | J27: 1234 | K27: 0 | L27: =INDEX('Path Scorecard'!$AD$5:$AD$80,MATCH($I27,'Path Scorecard'!$H$5:$H$80,0)) | M27: =INDEX('Path Scorecard'!$AE$5:$AE$80,MATCH($I27,'Path Scorecard'!$H$5:$H$80,0)) -> Amazon | N27: =INDEX('Path Scorecard'!$AF$5:$AF$80,MATCH($I27,'Path Scorecard'!$H$5:$H$80,0)) -> Target | O27: =INDEX('Path Scorecard'!$AG$5:$AG$80,MATCH($I27,'Path Scorecard'!$H$5:$H$80,0)) -> Erin Condren | P27: =INDEX('Path Scorecard'!$AH$5:$AH$80,MATCH($I27,'Path Scorecard'!$H$5:$H$80,0)) -> Etsy | Q27: Erin Condren and Etsy show design and personalised calendars. | R27: 1,234 Staples items of dated wall & desk calendars. | S27: Art & photography wall calendars; acrylic reusable calendars; minimalist desk calendars. | T27: At-A-Glance / Blue Sky dated calendars: core 1P. | U27: Q4-2026 / Jan-2027 dated-goods peak. | V27: Calendar season lines up with Q1 planning. | W27: Amazon: wall calendars. Target. | X27: https://www.staples.com/Calendars/cat_CL166389
A28: R2 | B28: =INDEX('Path Scorecard'!$Q$5:$Q$80,MATCH($I28,'Path Scorecard'!$H$5:$H$80,0)) -> Hero | C28: =INDEX('Path Scorecard'!$AA$5:$AA$80,MATCH($I28,'Path Scorecard'!$H$5:$H$80,0)) -> 9 | D28: =INDEX('Path Scorecard'!$AB$5:$AB$80,MATCH($I28,'Path Scorecard'!$H$5:$H$80,0)) -> Reserve | E28: =INDEX('Path Scorecard'!$AC$5:$AC$80,MATCH($I28,'Path Scorecard'!$H$5:$H$80,0)) -> EXTEND | F28: =INDEX('Path Scorecard'!$Z$5:$Z$80,MATCH($I28,'Path Scorecard'!$H$5:$H$80,0)) -> 73 | G28: Office Supplies > Label Makers & Tapes > Label Makers | H28: 3 | I28: CL90400 | J28: 148 | K28: 103 | L28: =INDEX('Path Scorecard'!$AD$5:$AD$80,MATCH($I28,'Path Scorecard'!$H$5:$H$80,0)) | M28: =INDEX('Path Scorecard'!$AE$5:$AE$80,MATCH($I28,'Path Scorecard'!$H$5:$H$80,0)) -> Amazon | N28: =INDEX('Path Scorecard'!$AF$5:$AF$80,MATCH($I28,'Path Scorecard'!$H$5:$H$80,0)) -> Walmart | O28: =INDEX('Path Scorecard'!$AG$5:$AG$80,MATCH($I28,'Path Scorecard'!$H$5:$H$80,0)) -> Michaels | P28: =INDEX('Path Scorecard'!$AH$5:$AH$80,MATCH($I28,'Path Scorecard'!$H$5:$H$80,0)) -> The Container Store | Q28: Michaels (Cricut) and The Container Store show the organising / crafting use of label makers. | R28: 148 Staples items (Brother, DYMO). Mini Bluetooth thermal printers went viral for home, classroom and seller labelling. | S28: Pastel mini Bluetooth label printers; sticker printers for small sellers; 4x6 shipping-label printers. | T28: Brother P-touch / DYMO LabelManager: core 1P, check CRS. | U28: January organize; BTS teachers. | V28: Your 'Labels & Packaging' idea, made specific. | W28: Amazon: Label Makers. Michaels: Cricut Joy / craft machines. | X28: https://www.staples.com/Label-Makers/cat_CL90400
A29: R3 | B29: =INDEX('Path Scorecard'!$Q$5:$Q$80,MATCH($I29,'Path Scorecard'!$H$5:$H$80,0)) -> Hero | C29: =INDEX('Path Scorecard'!$AA$5:$AA$80,MATCH($I29,'Path Scorecard'!$H$5:$H$80,0)) -> 9 | D29: =INDEX('Path Scorecard'!$AB$5:$AB$80,MATCH($I29,'Path Scorecard'!$H$5:$H$80,0)) -> Reserve | E29: =INDEX('Path Scorecard'!$AC$5:$AC$80,MATCH($I29,'Path Scorecard'!$H$5:$H$80,0)) -> EXTEND | F29: =INDEX('Path Scorecard'!$Z$5:$Z$80,MATCH($I29,'Path Scorecard'!$H$5:$H$80,0)) -> 73 | G29: Shipping, Packing & Mailing Supplies > Mailing Supplies > Mailers | H29: 3 | I29: CL142648 | J29: 396 | K29: 387 | L29: =INDEX('Path Scorecard'!$AD$5:$AD$80,MATCH($I29,'Path Scorecard'!$H$5:$H$80,0)) | M29: =INDEX('Path Scorecard'!$AE$5:$AE$80,MATCH($I29,'Path Scorecard'!$H$5:$H$80,0)) -> Amazon | N29: =INDEX('Path Scorecard'!$AF$5:$AF$80,MATCH($I29,'Path Scorecard'!$H$5:$H$80,0)) -> Uline | O29: =INDEX('Path Scorecard'!$AG$5:$AG$80,MATCH($I29,'Path Scorecard'!$H$5:$H$80,0)) -> noissue | P29: =INDEX('Path Scorecard'!$AH$5:$AH$80,MATCH($I29,'Path Scorecard'!$H$5:$H$80,0)) -> Packhelp | Q29: noissue and Packhelp show custom-branded, eco packaging with low minimums. | R29: 396 Staples items of utility mailers. | S29: Coloured & printed poly mailers; recycled / compostable mailers; coloured padded kraft. | T29: Staples-brand & Scotch bubble mailers: core 1P. | U29: Q4 small-business shipping peak. | V29: Small-business unboxing trend. | W29: Amazon: poly mailers. Uline: coloured poly mailers. | X29: https://www.staples.com/Mailers/cat_CL142648
A30: R4 | B30: =INDEX('Path Scorecard'!$Q$5:$Q$80,MATCH($I30,'Path Scorecard'!$H$5:$H$80,0)) -> Probable Hero | C30: =INDEX('Path Scorecard'!$AA$5:$AA$80,MATCH($I30,'Path Scorecard'!$H$5:$H$80,0)) -> 8 | D30: =INDEX('Path Scorecard'!$AB$5:$AB$80,MATCH($I30,'Path Scorecard'!$H$5:$H$80,0)) -> Reserve | E30: =INDEX('Path Scorecard'!$AC$5:$AC$80,MATCH($I30,'Path Scorecard'!$H$5:$H$80,0)) -> BUILD | F30: =INDEX('Path Scorecard'!$Z$5:$Z$80,MATCH($I30,'Path Scorecard'!$H$5:$H$80,0)) -> 82 | G30: Bags, Backpacks & Luggage > Briefcases & Padfolios > Totes & Handbags | H30: 3 | I30: CL160451 | J30: 173 | K30: 166 | L30: =INDEX('Path Scorecard'!$AD$5:$AD$80,MATCH($I30,'Path Scorecard'!$H$5:$H$80,0)) | M30: =INDEX('Path Scorecard'!$AE$5:$AE$80,MATCH($I30,'Path Scorecard'!$H$5:$H$80,0)) -> Amazon | N30: =INDEX('Path Scorecard'!$AF$5:$AF$80,MATCH($I30,'Path Scorecard'!$H$5:$H$80,0)) -> Target | O30: =INDEX('Path Scorecard'!$AG$5:$AG$80,MATCH($I30,'Path Scorecard'!$H$5:$H$80,0)) -> Bellroy | P30: =INDEX('Path Scorecard'!$AH$5:$AH$80,MATCH($I30,'Path Scorecard'!$H$5:$H$80,0)) -> Nordstrom | Q30: Bellroy and Nordstrom show premium work totes. | R30: 173 Staples items. The work tote is the lifestyle version of the briefcase. | S30: Structured work totes with laptop sleeve; neoprene totes; vegan-leather commuter totes. | T30: Briefcases & padfolios (Samsonite, Solo). | U30: Q1 return-to-office; graduation gifting. | V30: The 'White Chair' of bags. | W30: Amazon: work totes. Target: tote bags. | X30: https://www.staples.com/Totes-Handbags/cat_CL160451
A31: R5 | B31: =INDEX('Path Scorecard'!$Q$5:$Q$80,MATCH($I31,'Path Scorecard'!$H$5:$H$80,0)) -> Probable Hero | C31: =INDEX('Path Scorecard'!$AA$5:$AA$80,MATCH($I31,'Path Scorecard'!$H$5:$H$80,0)) -> 9 | D31: =INDEX('Path Scorecard'!$AB$5:$AB$80,MATCH($I31,'Path Scorecard'!$H$5:$H$80,0)) -> Reserve | E31: =INDEX('Path Scorecard'!$AC$5:$AC$80,MATCH($I31,'Path Scorecard'!$H$5:$H$80,0)) -> BUILD | F31: =INDEX('Path Scorecard'!$Z$5:$Z$80,MATCH($I31,'Path Scorecard'!$H$5:$H$80,0)) -> 80 | G31: Office Supplies > Notebooks & Notepads > Journals & Diaries | H31: 3 | I31: CL166390 | J31: 253 | K31: 0 | L31: =INDEX('Path Scorecard'!$AD$5:$AD$80,MATCH($I31,'Path Scorecard'!$H$5:$H$80,0)) | M31: =INDEX('Path Scorecard'!$AE$5:$AE$80,MATCH($I31,'Path Scorecard'!$H$5:$H$80,0)) -> Amazon | N31: =INDEX('Path Scorecard'!$AF$5:$AF$80,MATCH($I31,'Path Scorecard'!$H$5:$H$80,0)) -> Target | O31: =INDEX('Path Scorecard'!$AG$5:$AG$80,MATCH($I31,'Path Scorecard'!$H$5:$H$80,0)) -> JetPens | P31: =INDEX('Path Scorecard'!$AH$5:$AH$80,MATCH($I31,'Path Scorecard'!$H$5:$H$80,0)) -> Kinokuniya | Q31: JetPens and Kinokuniya show premium Japanese journals (Hobonichi, Traveler's). | R31: 253 Staples items. Journaling is a Gen-Z wellness habit. | S31: Dotted-grid bullet journals; linen & leather-look hardcovers; guided gratitude / wellness journals. | T31: Notebooks Staples already sells. | U31: Jan-2027. | V31: Pairs with the planner story. | W31: Amazon: Journals. Michaels: Papercraft journals. | X31: https://www.staples.com/Journals-Diaries/cat_CL166390
A32: R6 | B32: =INDEX('Path Scorecard'!$Q$5:$Q$80,MATCH($I32,'Path Scorecard'!$H$5:$H$80,0)) -> Probable Hero | C32: =INDEX('Path Scorecard'!$AA$5:$AA$80,MATCH($I32,'Path Scorecard'!$H$5:$H$80,0)) -> 10 | D32: =INDEX('Path Scorecard'!$AB$5:$AB$80,MATCH($I32,'Path Scorecard'!$H$5:$H$80,0)) -> Reserve | E32: =INDEX('Path Scorecard'!$AC$5:$AC$80,MATCH($I32,'Path Scorecard'!$H$5:$H$80,0)) -> BUILD | F32: =INDEX('Path Scorecard'!$Z$5:$Z$80,MATCH($I32,'Path Scorecard'!$H$5:$H$80,0)) -> 80 | G32: Furniture > Decor > Artificial Plants & Flowers > Artificial Plants | H32: 4 | I32: CL355087 | J32: 203 | K32: 0 | L32: =INDEX('Path Scorecard'!$AD$5:$AD$80,MATCH($I32,'Path Scorecard'!$H$5:$H$80,0)) | M32: =INDEX('Path Scorecard'!$AE$5:$AE$80,MATCH($I32,'Path Scorecard'!$H$5:$H$80,0)) -> Wayfair | N32: =INDEX('Path Scorecard'!$AF$5:$AF$80,MATCH($I32,'Path Scorecard'!$H$5:$H$80,0)) -> Amazon | O32: =INDEX('Path Scorecard'!$AG$5:$AG$80,MATCH($I32,'Path Scorecard'!$H$5:$H$80,0)) -> Michaels | P32: =INDEX('Path Scorecard'!$AH$5:$AH$80,MATCH($I32,'Path Scorecard'!$H$5:$H$80,0)) -> Anthropologie | Q32: Michaels (floral) and Anthropologie show premium faux botanicals. | R32: 203 Staples items. Plants are the most-used desk personalisation in 2026 home-office trend reports. | S32: Trailing pothos / ivy; small potted succulents in ceramic; olive & fiddle-leaf floor trees; plant + planter sets. | T32: Seasonal faux trees & wreaths. | U32: Q1 office refresh; spring. | V32: Biophilic, 'resimercial' offices are the return-to-office default. | W32: Wayfair: Flowers & Plants > Faux Plants / Faux Trees. Michaels: Floral. | X32: https://www.staples.com/Artificial-Plants/cat_CL355087
A33: R7 | B33: =INDEX('Path Scorecard'!$Q$5:$Q$80,MATCH($I33,'Path Scorecard'!$H$5:$H$80,0)) -> Non-Hero | C33: =INDEX('Path Scorecard'!$AA$5:$AA$80,MATCH($I33,'Path Scorecard'!$H$5:$H$80,0)) -> 7 | D33: =INDEX('Path Scorecard'!$AB$5:$AB$80,MATCH($I33,'Path Scorecard'!$H$5:$H$80,0)) -> Reserve | E33: =INDEX('Path Scorecard'!$AC$5:$AC$80,MATCH($I33,'Path Scorecard'!$H$5:$H$80,0)) -> EXPLORE | F33: =INDEX('Path Scorecard'!$Z$5:$Z$80,MATCH($I33,'Path Scorecard'!$H$5:$H$80,0)) -> 67 | G33: Furniture > Decor > Essential Oils & Diffusers | H33: 3 | I33: CL354884 | J33: 46 | K33: 0 | L33: =INDEX('Path Scorecard'!$AD$5:$AD$80,MATCH($I33,'Path Scorecard'!$H$5:$H$80,0)) | M33: =INDEX('Path Scorecard'!$AE$5:$AE$80,MATCH($I33,'Path Scorecard'!$H$5:$H$80,0)) -> Target | N33: =INDEX('Path Scorecard'!$AF$5:$AF$80,MATCH($I33,'Path Scorecard'!$H$5:$H$80,0)) -> Amazon | O33: =INDEX('Path Scorecard'!$AG$5:$AG$80,MATCH($I33,'Path Scorecard'!$H$5:$H$80,0)) -> Vitruvi | P33: =INDEX('Path Scorecard'!$AH$5:$AH$80,MATCH($I33,'Path Scorecard'!$H$5:$H$80,0)) -> Anthropologie | Q33: Vitruvi and Anthropologie show diffusers as decor objects. | R33: 46 Staples items. Wellness decor for desks and reception areas. | S33: Porcelain / stone ultrasonic diffusers; USB desk diffusers; reed diffusers. | T33: None material. | U33: Q1 wellness resolutions; holiday gifting. | V33: Wellness at work. | W33: Amazon / Target. Vitruvi: diffusers. Anthropologie: home fragrance. | X33: https://www.staples.com/Oils-Diffusers/cat_CL354884
A34: R8 | B34: =INDEX('Path Scorecard'!$Q$5:$Q$80,MATCH($I34,'Path Scorecard'!$H$5:$H$80,0)) -> Non-Hero | C34: =INDEX('Path Scorecard'!$AA$5:$AA$80,MATCH($I34,'Path Scorecard'!$H$5:$H$80,0)) -> 8 | D34: =INDEX('Path Scorecard'!$AB$5:$AB$80,MATCH($I34,'Path Scorecard'!$H$5:$H$80,0)) -> Reserve | E34: =INDEX('Path Scorecard'!$AC$5:$AC$80,MATCH($I34,'Path Scorecard'!$H$5:$H$80,0)) -> EXPLORE | F34: =INDEX('Path Scorecard'!$Z$5:$Z$80,MATCH($I34,'Path Scorecard'!$H$5:$H$80,0)) -> 66 | G34: School Supplies > Teacher Supplies > Physical Education & Recreation > Outdoor Games | H34: 4 | I34: CL353835 | J34: 78 | K34: 0 | L34: =INDEX('Path Scorecard'!$AD$5:$AD$80,MATCH($I34,'Path Scorecard'!$H$5:$H$80,0)) | M34: =INDEX('Path Scorecard'!$AE$5:$AE$80,MATCH($I34,'Path Scorecard'!$H$5:$H$80,0)) -> Amazon | N34: =INDEX('Path Scorecard'!$AF$5:$AF$80,MATCH($I34,'Path Scorecard'!$H$5:$H$80,0)) -> Dick's Sporting Goods | O34: =INDEX('Path Scorecard'!$AG$5:$AG$80,MATCH($I34,'Path Scorecard'!$H$5:$H$80,0)) -> Scheels | P34: =INDEX('Path Scorecard'!$AH$5:$AH$80,MATCH($I34,'Path Scorecard'!$H$5:$H$80,0)) -> Etsy | Q34: Scheels shows premium cornhole, Spikeball and giant games; Etsy shows custom boards. | R34: 78 Staples items of PE-style outdoor games. Scheels sells premium cornhole, Spikeball and giant yard games (one of Ben's examples). | S34: Tournament-grade cornhole boards; Spikeball / roundnet sets; giant yard games; pickleball sets. | T34: Classroom PE games (low risk). | U34: Summer company picnics (May-Aug 2027). | V34: Corporate picnics and team events. | W34: Amazon / Walmart. Scheels: Yard Games, Cornhole Boards. Etsy: custom cornhole. | X34: https://www.staples.com/Outdoor-Games/cat_CL353835
A35: R9 | B35: =INDEX('Path Scorecard'!$Q$5:$Q$80,MATCH($I35,'Path Scorecard'!$H$5:$H$80,0)) -> Non-Hero | C35: =INDEX('Path Scorecard'!$AA$5:$AA$80,MATCH($I35,'Path Scorecard'!$H$5:$H$80,0)) -> 9 | D35: =INDEX('Path Scorecard'!$AB$5:$AB$80,MATCH($I35,'Path Scorecard'!$H$5:$H$80,0)) -> Reserve | E35: =INDEX('Path Scorecard'!$AC$5:$AC$80,MATCH($I35,'Path Scorecard'!$H$5:$H$80,0)) -> EXPLORE | F35: =INDEX('Path Scorecard'!$Z$5:$Z$80,MATCH($I35,'Path Scorecard'!$H$5:$H$80,0)) -> 64 | G35: Furniture > Home & Office Tables > Accent & Coffee Tables | H35: 3 | I35: CL161009 | J35: 203 | K35: 0 | L35: =INDEX('Path Scorecard'!$AD$5:$AD$80,MATCH($I35,'Path Scorecard'!$H$5:$H$80,0)) | M35: =INDEX('Path Scorecard'!$AE$5:$AE$80,MATCH($I35,'Path Scorecard'!$H$5:$H$80,0)) -> Wayfair | N35: =INDEX('Path Scorecard'!$AF$5:$AF$80,MATCH($I35,'Path Scorecard'!$H$5:$H$80,0)) -> Amazon | O35: =INDEX('Path Scorecard'!$AG$5:$AG$80,MATCH($I35,'Path Scorecard'!$H$5:$H$80,0)) -> Article | P35: =INDEX('Path Scorecard'!$AH$5:$AH$80,MATCH($I35,'Path Scorecard'!$H$5:$H$80,0)) -> West Elm | Q35: Article and West Elm show design accent tables. | R35: 203 Staples items for reception areas. | S35: Travertine / marble side tables; rattan & mango-wood accent tables; nesting tables. | T35: Laminate reception tables. | U35: Q1 office refresh. | V35: Reception makeovers. | W35: Wayfair / Amazon. Article, West Elm, CB2. | X35: https://www.staples.com/Accent-Coffee-Tables/cat_CL161009

Sheet Segment Map
A1: Segment map: Staples strength vs market attractiveness
A2: Picture = snapshot at default inputs (labelled). The Excel chart further down is live: it moves when you edit inputs or cut-offs.
B49: How to read it: right of the dashed line = Hero (Staples is already strong); top-left = Probable Hero (the market loves it, Staples is not yet a destination); bottom-left = Non-Hero.
B50: Plays: Hero = EXTEND (style extensions only) or PROTECT (keep the marketplace out, e.g. Office Chairs, Pens); Probable Hero = BUILD (fill the gap with sellers); Non-Hero = EXPLORE (low-risk test, sellers hold the stock).
B51: The Top 20 takes the best 7 Hero, 7 Probable Hero and 6 Non-Hero shelves by path score, so every segment is represented.

Sheet Hero Criteria
A1: Hero segmentation criteria: Hero, Probable Hero, Non-Hero
A2: How every L3/L4 shelf is placed in a segment, how each segment is played, and how many of each go into the Top 20. Yellow cells are editable.
A4: 1. What the three segments mean
A5: Segment | B5: In plain words | C5: The question it answers | D5: Play | E5: What Staples Marketplace does
A6: Hero | B6: Staples' own top categories: where Staples already has depth, visibility, investment and shopper trust. (Proxy for 'top by sales / profit / assortment', built from external data.) | C6: Is Staples already known for this? | D6: EXTEND (or PROTECT) | E6: Add design / lifestyle extensions of what Staples already sells well. Keep the marketplace out where variants would copy 1P best-sellers (PROTECT).
A7: Probable Hero | B7: The market's top categories where Staples is not (yet) a destination: room for improvement. | C7: Does the market love it while Staples is still thin? | D7: BUILD | E7: Fill the depth gap fast with marketplace sellers recruited from the competitors' brands. The biggest commission upside.
A8: Non-Hero | B8: Neither a Staples strength nor a market favourite today. | C8: Is it a low-risk experiment worth a small test? | D8: EXPLORE | E8: Test a small, curated range through sellers: no inventory and no 1P risk. Keep the winners, drop the rest.
A10: 2. The decision rule (applied in this order)
A11: Step 1 | B11: Compute two scores for every L3/L4 shelf: the Staples Strength Index (SSI, section 3) and the Market Attractiveness Index (MAI, section 4), each 0-100.
A12: Step 2 | B12: If SSI >= the Hero cut-off, the shelf is a HERO. Inside Hero: if the shelf's 1P-protection score (C3 on the Path Scorecard) <= the Protect cut-off, the play is PROTECT (control shelf); otherwise EXTEND.
A13: Step 3 | B13: Otherwise, if MAI >= the Probable Hero cut-off, the shelf is a PROBABLE HERO (play BUILD).
A14: Step 4 | B14: Otherwise the shelf is a NON-HERO (play EXPLORE).
A15: Step 5 | B15: Rank the shelves inside each segment by path score ('Selection Criteria') and take the quota per segment (section 5) = the Top 20. The next shelves are reserves.
A17: 3. Staples Strength Index (SSI): is it already a Staples hero?
A18: Code | B18: Component | C18: What it measures | D18: Weight | E18: Score 1 | F18: Score 2 | G18: Score 3 | H18: Score 4 | I18: Score 5 | J18: How it is scored
A19: S1 | B19: Assortment depth | C19: Staples items on the leaf (the only 'size' signal available without sales data) | D19: 30 | E19: < 75 items | F19: 75-199 | G19: 200-499 | H19: 500-999 | I19: >= 1,000 | J19: Computed from the tree (bands in section 5)
A20: S2 | B20: Shelf visibility | C20: Is the shelf's L1 in Staples' header navigation? | D20: 15 | E20: - | F20: L1 not in header nav | G20: - | H20: - | I20: L1 in header nav | J20: Computed from the tree ('Summary by L1')
A21: S3 | B21: Merchandising investment | C21: Exclusives, collaborations, own brands, BTS / seasonal feature slots | D21: 25 | E21: No visible investment; generic range | F21: Occasional promos only | G21: Seasonal features or some own brand | H21: Own brand or an exclusive line + feature slots | I21: Exclusive collabs + own brand + hero campaigns (e.g. Sincerely Jules planners) | J21: Analyst: Staples press releases & site
A22: S4 | B22: Shopper association | C22: Would a shopper think of Staples first for this? | D22: 30 | E22: Nobody thinks of Staples for this | F22: Occasional convenience buy | G22: One of several options | H22: Staples is a usual stop | I22: Staples is the default destination | J22: Analyst judgement
C23: Total weight | D23: =SUM(D19:D22) -> 100 | E23: Index = sum(score x weight) / (5 x total weight) x 100
A25: 4. Market Attractiveness Index (MAI): is it a market hero?
A26: Code | B26: Component | C26: What it measures | D26: Weight | E26: Score 1 | F26: Score 2 | G26: Score 3 | H26: Score 4 | I26: Score 5 | J26: How it is scored
A27: M1 | B27: Demand momentum | C27: Growth and trend signals | D27: 35 | E27: Declining | F27: Flat | G27: Steady growth | H27: Clear growth / trending on social | I27: Viral or double-digit growth (e.g. Owala, Stanley) | J27: Analyst: Circana, trade press, social
A28: M2 | B28: Competitor destination strength | C28: Do competitors run it as a department with specialist depth? | D28: 25 | E28: No competitor features it | F28: One competitor | G28: A few mass retailers carry decent depth | H28: Mass + a specialist run it as a department | I28: Several specialists and mass leaders treat it as a destination | J28: Analyst: competitor site structure
A29: M3 | B29: Category size & purchase frequency | C29: How big the category is and how often it is bought | D29: 25 | E29: Niche, rare purchase | F29: Small or infrequent | G29: Mid-sized, yearly | H29: Large or several times a year | I29: Very large and frequent | J29: Analyst
A30: M4 | B30: Occasion strength | C30: Seasonal peak in the planning window | D30: 15 | E30: No moment | F30: Weak | G30: Some seasonality | H30: Clear Q1 or BTS peak | I30: Peaks in both Q1-2027 and BTS-2027 | J30: Same as C7 on the Path Scorecard
C31: Total weight | D31: =SUM(D27:D30) -> 100 | E31: Index = sum(score x weight) / (5 x total weight) x 100
A33: 5. Cut-offs, quotas and settings
A34: Code | B34: Setting | C34: Value | D34: Note
A35: H | B35: Hero cut-off (SSI >=) | C35: 65 | D35: Checked first: a strong Staples shelf is a Hero whatever the market does.
A36: P | B36: Probable Hero cut-off (MAI >=) | C36: 65 | D36: Applied to shelves that are not Heroes.
A37: PR | B37: Protect cut-off (Hero with C3 <=) | C37: 2 | D37: Hero shelves where design variants would substitute 1P: keep the marketplace out.
A38: QH | B38: Top-20 quota: Hero | C38: 7 | D38: Brief: 20 shelves, at least 6 per segment.
A39: QP | B39: Top-20 quota: Probable Hero | C39: 7
A40: QN | B40: Top-20 quota: Non-Hero | C40: 6
A41: RS | B41: Reserves per segment | C41: 3 | D41: Swap-ins if a Top-20 shelf is dropped.
A42: B5 | B42: S1 band: items >= this scores 5 | C42: 1000
A43: B4 | B43: S1 band: scores 4 | C43: 500
A44: B3 | B44: S1 band: scores 3 | C44: 200
A45: B2 | B45: S1 band: scores 2 (else 1) | C45: 75
A46: NY | B46: S2 score if the L1 is in the header nav | C46: 5
A47: NN | B47: S2 score if not | C47: 2
B48: Top-20 check (live) | C48: =SUM(C38:C40) -> 20 | D48: =IF(AND(MIN(C38:C40)>=6,SUM(C38:C40)=20),"OK: 20 shelves, at least 6 per segment","Check: the brief asks for 20 shelves with at least 6 per segment") -> OK: 20 shelves, at least 6 per segment
A50: 6. Marketplace plays
A51: Segment | B51: Play | C51: When | D51: What Staples Marketplace does
A52: Hero | B52: EXTEND | C52: Staples is strong and 1P risk is manageable (C3 above the Protect cut-off). | D52: Add style / lifestyle extensions of the hero only (the 'White Chair' move); strict cannibalisation gate; invite brands Staples already buys first.
A53: Hero | B53: PROTECT | C53: Staples is strong and design variants would substitute 1P (C3 at or below the Protect cut-off). | D53: Keep the marketplace out; use as a control shelf that shows the safety gate working.
A54: Probable Hero | B54: BUILD | C54: The market treats it as a top category but Staples is not (yet) a destination. | D54: Fill the depth gap quickly with marketplace sellers recruited from the primary competitor's brands: the biggest commission upside.
A55: Non-Hero | B55: EXPLORE | C55: Neither a Staples strength nor a market favourite. | D55: Low-risk test through the marketplace: no 1P to protect and sellers hold the inventory. Keep the winners, drop the rest.

Sheet Competitor Criteria
A1: Competitor criteria: 2 primary + 2 secondary competitors per shelf
A2: Primary = broad retailers that measure the gap. Secondary = enthusiast / design specialists outside Staples' scope that show the 'super-extension'. Yellow cells are editable.
A4: 1. Why four competitors, in two roles
A5: • | B5: PRIMARY (2 per shelf): broad retailers and marketplaces that sell to the same shopper at scale. They measure the gap (archetypes, price tiers, colourways Staples lacks) and feed the share-based gap maths. Chosen with K1-K5 from the primary pool.
A6: • | B6: SECONDARY (2 per shelf): enthusiast or design specialists outside Staples' normal competitive set, like Scheels and Michaels in Ben's examples. They show the 'super-extension': how far the category stretches in depth, premium tier and aesthetics. Chosen with E1-E5 from the secondary pool.
A7: • | B7: Secondaries are a style / upside lens, not a share baseline. Many are D2C brands (Erin Condren, Grovemade, Keychron, Bellroy, Felt Right, Fellow, Bentgo, YETI, noissue) that could list on Staples Marketplace themselves: a ready seller-recruitment list.
A9: 2. Primary competitor criteria (K1-K5)
A10: Code | B10: Criterion | C10: What it measures | D10: Scores 5 when | E10: Scores 1 when | F10: Weight
A11: K1 | B11: Assortment depth on this shelf | C11: Breadth of the competitor's range on the mapped node | D11: Several times Staples' range, many sub-types | E11: Similar or smaller than Staples | F11: 30
A12: K2 | B12: Aesthetic & lifestyle range | C12: Variety of styles, colourways, materials and price tiers | D12: Destination for design-led choice | E12: Utility only | F12: 25
A13: K3 | B13: Shopper overlap with Staples | C13: Same home-office, student, teacher or small-business shopper | D13: Same shopper and mission | E13: Different shopper | F13: 15
A14: K4 | B14: Seller recruitability | C14: Can the brands / suppliers behind the range be invited onto Staples Marketplace? | D14: Multi-brand 3P or drop-ship suppliers | E14: Mostly own / private label | F14: 15
A15: K5 | B15: Data accessibility | C15: Can the team collect listing-level data at PoC speed? (tested 29-Sep-2026) | D15: Already scraped or official API | E15: Bot-blocked, needs a paid proxy | F15: 15
E16: Total weight | F16: =SUM(F11:F15) -> 100
A18: 3. Secondary competitor criteria (E1-E5): the 'super-extension' lens
A19: Code | B19: Criterion | C19: What it measures | D19: Scores 5 when | E19: Scores 1 when | F19: Weight
A20: E1 | B20: Enthusiast depth | C20: How far beyond Staples the specialist's range goes (technical, premium, hobby-grade sub-types) | D20: Enthusiast destination: many sub-types, premium tiers, accessories | E20: Similar to Staples | F20: 25
A21: E2 | B21: Aesthetic authority | C21: Does it set the look: design-led, trend-setting, curated? | D21: A trend-setter the shopper follows | E21: Generic look | F21: 25
A22: E3 | B22: Distance from Staples' scope | C22: Is it outside Staples' normal competitive set (not an office-supply or mass retailer)? | D22: Clearly outside (specialist, D2C, lifestyle) | E22: A direct Staples competitor | F22: 15
A23: E4 | B23: Adjacency relevance | C23: Would the extension still make sense to a Staples shopper? (guards against off-brand picks) | D23: Obvious next step for the Staples shopper | E23: Unrelated hobby or luxury | F23: 20
A24: E5 | B24: Seller / brand transferability | C24: Could its brands, or the brand itself if D2C, list on Staples Marketplace? | D24: D2C brand or multi-brand seller base | E24: Only own / private label | F24: 15
E25: Total weight | F25: =SUM(F20:F24) -> 100
A28: 4. Competitor pools
A29: Pool | B29: Members | C29: Rule
A30: Primary | B30: Wayfair, Amazon, Target, Walmart, Best Buy, Dick's Sporting Goods, Uline | C30: Same shopper, broad assortment, data at scale. Office Depot is excluded: its range mirrors Staples', so it shows little gap.
A31: Secondary | B31: Anthropologie, Article, Bellroy, Bentgo, CB2, Crate & Barrel, Design Within Reach, Drop, Erin Condren, Etsy, Fellow, Felt Right, Grovemade, JetPens, Keychron, Kinokuniya, Lamps Plus, Michaels, Micro Center, Nordstrom, Orbitkey, Oriental Trading, Packhelp, Paper Source, Pottery Barn, Pottery Barn Kids, Pottery Barn Teen, REI, Really Good Stuff, Scheels, Schoolhouse, The Container Store, Urban Outfitters, Vitruvi, West Elm, Williams Sonoma, YETI, noissue | C31: Enthusiast, design or D2C specialists that are not direct Staples competitors. Dick's is primary (national mass sporting); Scheels and REI are secondary (enthusiast).
A33: 5. How the four are picked
A34: 1. | B34: For every Top-20 and reserve shelf, 3 plausible primaries and 2-4 plausible secondaries are scored 1-5 on the shelf-specific criteria (K1-K3; E1, E2, E4). The competitor-level criteria (K4, K5; E3, E5) are fixed per competitor ('Competitor Profiles').
A35: 2. | B35: Primary 1 and 2 = the two highest primary fit scores ('Primary Competitor Fit'). Secondary 1 and 2 = the two highest secondary fit scores ('Secondary Competitor Fit'). Ties are broken by depth (K1 / E1).
A36: 3. | B36: Everything is live: change a weight here or a score in the fit sheets and the picks update across the workbook.
A37: 4. | B37: Scores are analyst judgement from desk research ('Evidence & Sources'). Confirm depth when listings are collected; secondaries can be sampled manually because they are a style lens, not a share baseline.

Sheet Your List Review
A1: Review of the initial 9-item list: verdicts, segment mix and exact L3/L4 drill-downs
A2: Table 1 = verdict per item; column I shows most L2s mix Hero, Probable Hero and Non-Hero shelves (why segmenting at L2 misleads). Table 2 = the drill-down paths with live segment, status and competitors.
A4: # | B4: Your item | C4: Your competitor | D4: Exact Staples node(s) | E4: Verdict | F4: What the research says | G4: Competitor view (v3: 2 primary + 2 secondary) | H4: Headline competitors | I4: Segment mix of its L3/L4 paths (live)
A5: 1 | B5: Chairs & Seating | C5: Wayfair | D5: Furniture > Chairs & Seating | E5: KEEP: strongest furniture item | F5: Core-adjacent furniture with 14 leaves. The pilot proved the method here (Accent & Waiting Room, Benches, Bar Stools). The 2026 'resimercial' return-to-office trend supports design-led seating. | G5: Wayfair is right as Primary 1, with Amazon as Primary 2 (seller pool, value tier). Secondaries: Article + West Elm (design-led accent chairs). | H5: P: Wayfair + Amazon | S: Article + West Elm | I5: ="Hero "&COUNTIFS('Hero Segmentation'!$C$5:$C$80,"1. Chairs & Seating",'Hero Segmentation'!$Q$5:$Q$80,"Hero",'Hero Segmentation'!$S$5:$S$80,"<>Parked (gate)")&CHAR(10)&"Probable Hero "&COUNTIFS('Hero Segmentation'!$C$5:$C$80,"1. Chairs & Seating",'Hero Segmentation'!$Q$5:$Q$80,"Probable Hero",'Hero Segmentation'!$S$5:$S$80,"<>Parked (gate)")&CHAR(10)&"Non-Hero "&COUNTIFS('Hero Segmentation'!$C$5:$C$80,"1. Chairs & Seating",'Hero Segmentation'!$Q$5:$Q$80,"Non-Hero",'Hero Segmentation'!$S$5:$S$80,"<>Parked (gate)")&CHAR(10)&"Parked "&COUNTIFS('Hero Segmentation'!$C$5:$C$80,"1. Chairs & Seating",'Hero Segmentation'!$S$5:$S$80,"Parked (gate)") -> Hero 1 Probable Hero 5 Non-Hero 2 Parked 0
A6: 2 | B6: Desks | C6: Wayfair | D6: Furniture > Desks | E6: KEEP, narrow to Office Desks | F6: Office Desks is the real shelf (1,501 items), split by Staples' own type facet. Sit & Stand is spec-led, so design gaps are smaller and it is a PROTECT shelf. | G6: Wayfair + Amazon as primaries; Design Within Reach + West Elm as secondaries. | H6: P: Wayfair + Amazon | S: DWR + West Elm | I6: ="Hero "&COUNTIFS('Hero Segmentation'!$C$5:$C$80,"2. Desks",'Hero Segmentation'!$Q$5:$Q$80,"Hero",'Hero Segmentation'!$S$5:$S$80,"<>Parked (gate)")&CHAR(10)&"Probable Hero "&COUNTIFS('Hero Segmentation'!$C$5:$C$80,"2. Desks",'Hero Segmentation'!$Q$5:$Q$80,"Probable Hero",'Hero Segmentation'!$S$5:$S$80,"<>Parked (gate)")&CHAR(10)&"Non-Hero "&COUNTIFS('Hero Segmentation'!$C$5:$C$80,"2. Desks",'Hero Segmentation'!$Q$5:$Q$80,"Non-Hero",'Hero Segmentation'!$S$5:$S$80,"<>Parked (gate)")&CHAR(10)&"Parked "&COUNTIFS('Hero Segmentation'!$C$5:$C$80,"2. Desks",'Hero Segmentation'!$S$5:$S$80,"Parked (gate)") -> Hero 2 Probable Hero 0 Non-Hero 1 Parked 0
A7: 3 | B7: Lamps & Lighting | C7: Wayfair | D7: Furniture > Lamps & Lighting | E7: KEEP (Desk Lamps) | F7: The purest aesthetic category in the core catalogue; Staples SKUs already in hand. | G7: Wayfair + Amazon as primaries; Lamps Plus (specialist depth) + Urban Outfitters (trend lamps) as secondaries. | H7: P: Wayfair + Amazon | S: Lamps Plus + Urban Outfitters | I7: ="Hero "&COUNTIFS('Hero Segmentation'!$C$5:$C$80,"3. Lamps & Lighting",'Hero Segmentation'!$Q$5:$Q$80,"Hero",'Hero Segmentation'!$S$5:$S$80,"<>Parked (gate)")&CHAR(10)&"Probable Hero "&COUNTIFS('Hero Segmentation'!$C$5:$C$80,"3. Lamps & Lighting",'Hero Segmentation'!$Q$5:$Q$80,"Probable Hero",'Hero Segmentation'!$S$5:$S$80,"<>Parked (gate)")&CHAR(10)&"Non-Hero "&COUNTIFS('Hero Segmentation'!$C$5:$C$80,"3. Lamps & Lighting",'Hero Segmentation'!$Q$5:$Q$80,"Non-Hero",'Hero Segmentation'!$S$5:$S$80,"<>Parked (gate)")&CHAR(10)&"Parked "&COUNTIFS('Hero Segmentation'!$C$5:$C$80,"3. Lamps & Lighting",'Hero Segmentation'!$S$5:$S$80,"Parked (gate)") -> Hero 0 Probable Hero 3 Non-Hero 0 Parked 0
A8: 4 | B8: Rugs | C8: Wayfair | D8: Decor > Rugs (L2 leaf, no L3/L4 under it) | E8: PARK: fails the granularity gate | F8: There is nothing to drill into: 'Decor > Rugs' is a single L2 leaf of 804 items. Rugs are also residential decor, the weakest link to Staples' work and school mission. | G8: For a decor story at L3/L4, use Storage Baskets (Top 20) or Faux Plants (reserve). | H8: n/a (parked) | I8: ="Hero "&COUNTIFS('Hero Segmentation'!$C$5:$C$80,"4. Rugs",'Hero Segmentation'!$Q$5:$Q$80,"Hero",'Hero Segmentation'!$S$5:$S$80,"<>Parked (gate)")&CHAR(10)&"Probable Hero "&COUNTIFS('Hero Segmentation'!$C$5:$C$80,"4. Rugs",'Hero Segmentation'!$Q$5:$Q$80,"Probable Hero",'Hero Segmentation'!$S$5:$S$80,"<>Parked (gate)")&CHAR(10)&"Non-Hero "&COUNTIFS('Hero Segmentation'!$C$5:$C$80,"4. Rugs",'Hero Segmentation'!$Q$5:$Q$80,"Non-Hero",'Hero Segmentation'!$S$5:$S$80,"<>Parked (gate)")&CHAR(10)&"Parked "&COUNTIFS('Hero Segmentation'!$C$5:$C$80,"4. Rugs",'Hero Segmentation'!$S$5:$S$80,"Parked (gate)") -> Hero 0 Probable Hero 0 Non-Hero 0 Parked 1
A9: 5 | B9: Fitness Equipment | C9: Amazon | D9: Fitness > Fitness Equipment > Fitness Machines > Fitness Machines (the only leaf) | E9: REFOCUS as 'active workstation' (backlog) | F9: Fitness is not a Staples destination: one leaf, 43 items, not in the header nav. Defensible only as under-desk walking pads and desk bikes next to sit-stand desks. A Probable Hero, but a low path score. | G9: If run: Amazon + Dick's as primaries; Scheels as the enthusiast secondary (recovery and training gear). | H9: Backlog | I9: ="Hero "&COUNTIFS('Hero Segmentation'!$C$5:$C$80,"5. Fitness Equipment",'Hero Segmentation'!$Q$5:$Q$80,"Hero",'Hero Segmentation'!$S$5:$S$80,"<>Parked (gate)")&CHAR(10)&"Probable Hero "&COUNTIFS('Hero Segmentation'!$C$5:$C$80,"5. Fitness Equipment",'Hero Segmentation'!$Q$5:$Q$80,"Probable Hero",'Hero Segmentation'!$S$5:$S$80,"<>Parked (gate)")&CHAR(10)&"Non-Hero "&COUNTIFS('Hero Segmentation'!$C$5:$C$80,"5. Fitness Equipment",'Hero Segmentation'!$Q$5:$Q$80,"Non-Hero",'Hero Segmentation'!$S$5:$S$80,"<>Parked (gate)")&CHAR(10)&"Parked "&COUNTIFS('Hero Segmentation'!$C$5:$C$80,"5. Fitness Equipment",'Hero Segmentation'!$S$5:$S$80,"Parked (gate)") -> Hero 0 Probable Hero 1 Non-Hero 0 Parked 0
A10: 6 | B10: Backpacks & Bags | C10: Scheels | D10: Bags, Backpacks & Luggage > Backpacks & Laptop Bags (+ Totes & Handbags, Briefcases & Padfolios) | E10: KEEP, re-cast Scheels as a secondary | F10: Strong BTS anchor (85% of parents buy a backpack, Circana). Scheels is exactly the enthusiast lens, but its depth is technical / hunting packs, so for backpacks Bellroy and Urban Outfitters score higher on adjacency. | G10: Primaries: Amazon + Target. Secondaries: Bellroy (premium commuter) + Urban Outfitters (fashion). Scheels and REI stay as technical-pack alternates. | H10: P: Amazon + Target | S: Bellroy + Urban Outfitters | I10: ="Hero "&COUNTIFS('Hero Segmentation'!$C$5:$C$80,"6. Backpacks & Bags",'Hero Segmentation'!$Q$5:$Q$80,"Hero",'Hero Segmentation'!$S$5:$S$80,"<>Parked (gate)")&CHAR(10)&"Probable Hero "&COUNTIFS('Hero Segmentation'!$C$5:$C$80,"6. Backpacks & Bags",'Hero Segmentation'!$Q$5:$Q$80,"Probable Hero",'Hero Segmentation'!$S$5:$S$80,"<>Parked (gate)")&CHAR(10)&"Non-Hero "&COUNTIFS('Hero Segmentation'!$C$5:$C$80,"6. Backpacks & Bags",'Hero Segmentation'!$Q$5:$Q$80,"Non-Hero",'Hero Segmentation'!$S$5:$S$80,"<>Parked (gate)")&CHAR(10)&"Parked "&COUNTIFS('Hero Segmentation'!$C$5:$C$80,"6. Backpacks & Bags",'Hero Segmentation'!$S$5:$S$80,"Parked (gate)") -> Hero 1 Probable Hero 3 Non-Hero 0 Parked 1
A11: 7 | B11: Hydration & Drinkware | C11: Scheels | D11: Coffee, Water & Snacks > Water & Beverages > Water Bottles, Tumblers & Travel Mugs | E11: KEEP: #1 Probable Hero | F11: The Staples node is an L3 under Coffee, Water & Snacks. 463 items, already in the sample. The kitchen 'Drinkware & Glassware' leaf has only 15 items and fails the baseline gate. | G11: Primaries: Dick's + Target. Scheels is kept, now as Secondary 1 (wall-to-wall colourways), with YETI (customisation). | H11: P: Dick's + Target | S: Scheels + YETI | I11: ="Hero "&COUNTIFS('Hero Segmentation'!$C$5:$C$80,"7. Hydration & Drinkware",'Hero Segmentation'!$Q$5:$Q$80,"Hero",'Hero Segmentation'!$S$5:$S$80,"<>Parked (gate)")&CHAR(10)&"Probable Hero "&COUNTIFS('Hero Segmentation'!$C$5:$C$80,"7. Hydration & Drinkware",'Hero Segmentation'!$Q$5:$Q$80,"Probable Hero",'Hero Segmentation'!$S$5:$S$80,"<>Parked (gate)")&CHAR(10)&"Non-Hero "&COUNTIFS('Hero Segmentation'!$C$5:$C$80,"7. Hydration & Drinkware",'Hero Segmentation'!$Q$5:$Q$80,"Non-Hero",'Hero Segmentation'!$S$5:$S$80,"<>Parked (gate)")&CHAR(10)&"Parked "&COUNTIFS('Hero Segmentation'!$C$5:$C$80,"7. Hydration & Drinkware",'Hero Segmentation'!$S$5:$S$80,"Parked (gate)") -> Hero 0 Probable Hero 1 Non-Hero 0 Parked 1
A12: 8 | B12: Labels & Packaging Accessories | C12: Michaels | D12: Office Supplies > Labels (L2 leaf) · Party Supplies > Wrapping Supplies · Retail Store Supplies > Retail Packaging | E12: REFRAME | F12: 'Labels' is an L2 leaf of 11,493 commodity labels (a Hero to protect). Gift wrap and gift bags overlap the Party City partner assortment on Staples.com (Apr-2026). Label Makers and Mailers are Hero reserves. | G12: Mailers: P Amazon + Uline, S noissue + Packhelp (custom branded packaging). Label Makers: P Amazon + Walmart, S Michaels (Cricut) + Container Store. | H12: Reserves: see Table 2 | I12: ="Hero "&COUNTIFS('Hero Segmentation'!$C$5:$C$80,"8. Labels & Packaging Accessories",'Hero Segmentation'!$Q$5:$Q$80,"Hero",'Hero Segmentation'!$S$5:$S$80,"<>Parked (gate)")&CHAR(10)&"Probable Hero "&COUNTIFS('Hero Segmentation'!$C$5:$C$80,"8. Labels & Packaging Accessories",'Hero Segmentation'!$Q$5:$Q$80,"Probable Hero",'Hero Segmentation'!$S$5:$S$80,"<>Parked (gate)")&CHAR(10)&"Non-Hero "&COUNTIFS('Hero Segmentation'!$C$5:$C$80,"8. Labels & Packaging Accessories",'Hero Segmentation'!$Q$5:$Q$80,"Non-Hero",'Hero Segmentation'!$S$5:$S$80,"<>Parked (gate)")&CHAR(10)&"Parked "&COUNTIFS('Hero Segmentation'!$C$5:$C$80,"8. Labels & Packaging Accessories",'Hero Segmentation'!$S$5:$S$80,"Parked (gate)") -> Hero 2 Probable Hero 1 Non-Hero 0 Parked 3
A13: 9 | B13: Planning & Craft Organization | C13: Michaels | D13: Office Supplies > Calendars & Planners · Arts & Crafts > Scrapbooking / Crafting · Office Supplies > Storage & Organization | E13: KEEP, split in two | F13: Two shopper missions in one bucket. Planning is the #1 Hero (Michaels' Happy Planner ecosystem vs Staples' dated planners). Organization works better as Desk Organizers (Hero) and Storage Baskets (Probable Hero). | G13: Planners: P Amazon + Target, S Erin Condren + Michaels (your pick, kept). Organization: P Target + Amazon / Wayfair, S Grovemade + Container Store. | H13: P: Amazon + Target | S: Erin Condren + Michaels | I13: ="Hero "&COUNTIFS('Hero Segmentation'!$C$5:$C$80,"9. Planning & Craft Organization",'Hero Segmentation'!$Q$5:$Q$80,"Hero",'Hero Segmentation'!$S$5:$S$80,"<>Parked (gate)")&CHAR(10)&"Probable Hero "&COUNTIFS('Hero Segmentation'!$C$5:$C$80,"9. Planning & Craft Organization",'Hero Segmentation'!$Q$5:$Q$80,"Probable Hero",'Hero Segmentation'!$S$5:$S$80,"<>Parked (gate)")&CHAR(10)&"Non-Hero "&COUNTIFS('Hero Segmentation'!$C$5:$C$80,"9. Planning & Craft Organization",'Hero Segmentation'!$Q$5:$Q$80,"Non-Hero",'Hero Segmentation'!$S$5:$S$80,"<>Parked (gate)")&CHAR(10)&"Parked "&COUNTIFS('Hero Segmentation'!$C$5:$C$80,"9. Planning & Craft Organization",'Hero Segmentation'!$S$5:$S$80,"Parked (gate)") -> Hero 3 Probable Hero 3 Non-Hero 1 Parked 0
A15: Table 2. Drill-down L3/L4 paths for each item (exact nav-tree paths; segment, status and competitors are live)
A16: # | B16: Path ID | C16: Staples path (exact) | D16: Level | E16: Category ID | F16: Staples items | G16: Hero segment | H16: Marketplace play | I16: Status | J16: Path score | K16: Primary 1 / Primary 2 | L16: Secondary 1 / Secondary 2 | M16: Role in PoC
A17: 1 | B17: P04 | C17: Furniture > Chairs & Seating > Accent & Waiting Room Chairs | D17: 3 | E17: CL70203 | F17: 229 | G17: =INDEX('Path Scorecard'!$Q$5:$Q$80,MATCH($E17,'Path Scorecard'!$H$5:$H$80,0)) -> Probable Hero | H17: =INDEX('Path Scorecard'!$AC$5:$AC$80,MATCH($E17,'Path Scorecard'!$H$5:$H$80,0)) -> BUILD | I17: =INDEX('Path Scorecard'!$AB$5:$AB$80,MATCH($E17,'Path Scorecard'!$H$5:$H$80,0)) -> Recommended | J17: =INDEX('Path Scorecard'!$Z$5:$Z$80,MATCH($E17,'Path Scorecard'!$H$5:$H$80,0)) -> 89 | K17: =INDEX('Path Scorecard'!$AE$5:$AE$80,MATCH($E17,'Path Scorecard'!$H$5:$H$80,0))&" / "&INDEX('Path Scorecard'!$AF$5:$AF$80,MATCH($E17,'Path Scorecard'!$H$5:$H$80,0)) -> Wayfair / Amazon | L17: =INDEX('Path Scorecard'!$AG$5:$AG$80,MATCH($E17,'Path Scorecard'!$H$5:$H$80,0))&" / "&INDEX('Path Scorecard'!$AH$5:$AH$80,MATCH($E17,'Path Scorecard'!$H$5:$H$80,0)) -> Article / West Elm | M17: Top 20
A18: 1 | B18: P25 | C18: Furniture > Chairs & Seating > Sofas & Benches > Benches & Beam Seating | D18: 4 | E18: CL163750 | F18: 49 | G18: =INDEX('Path Scorecard'!$Q$5:$Q$80,MATCH($E18,'Path Scorecard'!$H$5:$H$80,0)) -> Probable Hero | H18: =INDEX('Path Scorecard'!$AC$5:$AC$80,MATCH($E18,'Path Scorecard'!$H$5:$H$80,0)) -> BUILD | I18: =INDEX('Path Scorecard'!$AB$5:$AB$80,MATCH($E18,'Path Scorecard'!$H$5:$H$80,0)) -> Backlog | J18: =INDEX('Path Scorecard'!$Z$5:$Z$80,MATCH($E18,'Path Scorecard'!$H$5:$H$80,0)) -> 75 | K18: =INDEX('Path Scorecard'!$AE$5:$AE$80,MATCH($E18,'Path Scorecard'!$H$5:$H$80,0))&" / "&INDEX('Path Scorecard'!$AF$5:$AF$80,MATCH($E18,'Path Scorecard'!$H$5:$H$80,0)) -> - / - | L18: =INDEX('Path Scorecard'!$AG$5:$AG$80,MATCH($E18,'Path Scorecard'!$H$5:$H$80,0))&" / "&INDEX('Path Scorecard'!$AH$5:$AH$80,MATCH($E18,'Path Scorecard'!$H$5:$H$80,0)) -> - / - | M18: Backlog
A19: 1 | B19: P30 | C19: Furniture > Chairs & Seating > Stools & Ottomans > Counter & Bar Stools | D19: 4 | E19: CL166182 | F19: 617 | G19: =INDEX('Path Scorecard'!$Q$5:$Q$80,MATCH($E19,'Path Scorecard'!$H$5:$H$80,0)) -> Probable Hero | H19: =INDEX('Path Scorecard'!$AC$5:$AC$80,MATCH($E19,'Path Scorecard'!$H$5:$H$80,0)) -> BUILD | I19: =INDEX('Path Scorecard'!$AB$5:$AB$80,MATCH($E19,'Path Scorecard'!$H$5:$H$80,0)) -> Backlog | J19: =INDEX('Path Scorecard'!$Z$5:$Z$80,MATCH($E19,'Path Scorecard'!$H$5:$H$80,0)) -> 73 | K19: =INDEX('Path Scorecard'!$AE$5:$AE$80,MATCH($E19,'Path Scorecard'!$H$5:$H$80,0))&" / "&INDEX('Path Scorecard'!$AF$5:$AF$80,MATCH($E19,'Path Scorecard'!$H$5:$H$80,0)) -> - / - | L19: =INDEX('Path Scorecard'!$AG$5:$AG$80,MATCH($E19,'Path Scorecard'!$H$5:$H$80,0))&" / "&INDEX('Path Scorecard'!$AH$5:$AH$80,MATCH($E19,'Path Scorecard'!$H$5:$H$80,0)) -> - / - | M19: Backlog
A20: 1 | B20: P28 | C20: Furniture > Chairs & Seating > Breakroom & Dining Chairs | D20: 3 | E20: CL166181 | F20: 75 | G20: =INDEX('Path Scorecard'!$Q$5:$Q$80,MATCH($E20,'Path Scorecard'!$H$5:$H$80,0)) -> Probable Hero | H20: =INDEX('Path Scorecard'!$AC$5:$AC$80,MATCH($E20,'Path Scorecard'!$H$5:$H$80,0)) -> BUILD | I20: =INDEX('Path Scorecard'!$AB$5:$AB$80,MATCH($E20,'Path Scorecard'!$H$5:$H$80,0)) -> Backlog | J20: =INDEX('Path Scorecard'!$Z$5:$Z$80,MATCH($E20,'Path Scorecard'!$H$5:$H$80,0)) -> 74 | K20: =INDEX('Path Scorecard'!$AE$5:$AE$80,MATCH($E20,'Path Scorecard'!$H$5:$H$80,0))&" / "&INDEX('Path Scorecard'!$AF$5:$AF$80,MATCH($E20,'Path Scorecard'!$H$5:$H$80,0)) -> - / - | L20: =INDEX('Path Scorecard'!$AG$5:$AG$80,MATCH($E20,'Path Scorecard'!$H$5:$H$80,0))&" / "&INDEX('Path Scorecard'!$AH$5:$AH$80,MATCH($E20,'Path Scorecard'!$H$5:$H$80,0)) -> - / - | M20: Backlog
A21: 1 | B21: P38 | C21: Furniture > Chairs & Seating > Stools & Ottomans > Ottomans | D21: 4 | E21: CL161807 | F21: 64 | G21: =INDEX('Path Scorecard'!$Q$5:$Q$80,MATCH($E21,'Path Scorecard'!$H$5:$H$80,0)) -> Probable Hero | H21: =INDEX('Path Scorecard'!$AC$5:$AC$80,MATCH($E21,'Path Scorecard'!$H$5:$H$80,0)) -> BUILD | I21: =INDEX('Path Scorecard'!$AB$5:$AB$80,MATCH($E21,'Path Scorecard'!$H$5:$H$80,0)) -> Backlog | J21: =INDEX('Path Scorecard'!$Z$5:$Z$80,MATCH($E21,'Path Scorecard'!$H$5:$H$80,0)) -> 69 | K21: =INDEX('Path Scorecard'!$AE$5:$AE$80,MATCH($E21,'Path Scorecard'!$H$5:$H$80,0))&" / "&INDEX('Path Scorecard'!$AF$5:$AF$80,MATCH($E21,'Path Scorecard'!$H$5:$H$80,0)) -> Wayfair / Amazon | L21: =INDEX('Path Scorecard'!$AG$5:$AG$80,MATCH($E21,'Path Scorecard'!$H$5:$H$80,0))&" / "&INDEX('Path Scorecard'!$AH$5:$AH$80,MATCH($E21,'Path Scorecard'!$H$5:$H$80,0)) -> - / - | M21: Backlog
A22: 1 | B22: P54 | C22: Furniture > Chairs & Seating > Office Chairs | D22: 3 | E22: CL166253 | F22: 1008 | G22: =INDEX('Path Scorecard'!$Q$5:$Q$80,MATCH($E22,'Path Scorecard'!$H$5:$H$80,0)) -> Hero | H22: =INDEX('Path Scorecard'!$AC$5:$AC$80,MATCH($E22,'Path Scorecard'!$H$5:$H$80,0)) -> PROTECT | I22: =INDEX('Path Scorecard'!$AB$5:$AB$80,MATCH($E22,'Path Scorecard'!$H$5:$H$80,0)) -> Protect (control) | J22: =INDEX('Path Scorecard'!$Z$5:$Z$80,MATCH($E22,'Path Scorecard'!$H$5:$H$80,0)) -> 65 | K22: =INDEX('Path Scorecard'!$AE$5:$AE$80,MATCH($E22,'Path Scorecard'!$H$5:$H$80,0))&" / "&INDEX('Path Scorecard'!$AF$5:$AF$80,MATCH($E22,'Path Scorecard'!$H$5:$H$80,0)) -> Wayfair / Amazon (control shelf) | L22: =INDEX('Path Scorecard'!$AG$5:$AG$80,MATCH($E22,'Path Scorecard'!$H$5:$H$80,0))&" / "&INDEX('Path Scorecard'!$AH$5:$AH$80,MATCH($E22,'Path Scorecard'!$H$5:$H$80,0)) -> - / - | M22: Control shelf (Hero, PROTECT): shows the safety gate rejecting core-1P look-alikes
A23: 1 | B23: P63 | C23: Furniture > Chairs & Seating > Kids Seating | D23: 3 | E23: CL210316 | F23: 147 | G23: =INDEX('Path Scorecard'!$Q$5:$Q$80,MATCH($E23,'Path Scorecard'!$H$5:$H$80,0)) -> Non-Hero | H23: =INDEX('Path Scorecard'!$AC$5:$AC$80,MATCH($E23,'Path Scorecard'!$H$5:$H$80,0)) -> EXPLORE | I23: =INDEX('Path Scorecard'!$AB$5:$AB$80,MATCH($E23,'Path Scorecard'!$H$5:$H$80,0)) -> Backlog | J23: =INDEX('Path Scorecard'!$Z$5:$Z$80,MATCH($E23,'Path Scorecard'!$H$5:$H$80,0)) -> 59 | K23: =INDEX('Path Scorecard'!$AE$5:$AE$80,MATCH($E23,'Path Scorecard'!$H$5:$H$80,0))&" / "&INDEX('Path Scorecard'!$AF$5:$AF$80,MATCH($E23,'Path Scorecard'!$H$5:$H$80,0)) -> Wayfair / Target | L23: =INDEX('Path Scorecard'!$AG$5:$AG$80,MATCH($E23,'Path Scorecard'!$H$5:$H$80,0))&" / "&INDEX('Path Scorecard'!$AH$5:$AH$80,MATCH($E23,'Path Scorecard'!$H$5:$H$80,0)) -> - / - | M23: Backlog
A24: 1 | B24: P67 | C24: Furniture > Chairs & Seating > Gaming Chairs | D24: 3 | E24: CL210317 | F24: 87 | G24: =INDEX('Path Scorecard'!$Q$5:$Q$80,MATCH($E24,'Path Scorecard'!$H$5:$H$80,0)) -> Non-Hero | H24: =INDEX('Path Scorecard'!$AC$5:$AC$80,MATCH($E24,'Path Scorecard'!$H$5:$H$80,0)) -> EXPLORE | I24: =INDEX('Path Scorecard'!$AB$5:$AB$80,MATCH($E24,'Path Scorecard'!$H$5:$H$80,0)) -> Backlog | J24: =INDEX('Path Scorecard'!$Z$5:$Z$80,MATCH($E24,'Path Scorecard'!$H$5:$H$80,0)) -> 50 | K24: =INDEX('Path Scorecard'!$AE$5:$AE$80,MATCH($E24,'Path Scorecard'!$H$5:$H$80,0))&" / "&INDEX('Path Scorecard'!$AF$5:$AF$80,MATCH($E24,'Path Scorecard'!$H$5:$H$80,0)) -> Best Buy / Amazon | L24: =INDEX('Path Scorecard'!$AG$5:$AG$80,MATCH($E24,'Path Scorecard'!$H$5:$H$80,0))&" / "&INDEX('Path Scorecard'!$AH$5:$AH$80,MATCH($E24,'Path Scorecard'!$H$5:$H$80,0)) -> - / - | M24: Backlog
A25: 2 | B25: P13 | C25: Furniture > Desks > Office Desks | D25: 3 | E25: CL210795 | F25: 1501 | G25: =INDEX('Path Scorecard'!$Q$5:$Q$80,MATCH($E25,'Path Scorecard'!$H$5:$H$80,0)) -> Hero | H25: =INDEX('Path Scorecard'!$AC$5:$AC$80,MATCH($E25,'Path Scorecard'!$H$5:$H$80,0)) -> EXTEND | I25: =INDEX('Path Scorecard'!$AB$5:$AB$80,MATCH($E25,'Path Scorecard'!$H$5:$H$80,0)) -> Recommended | J25: =INDEX('Path Scorecard'!$Z$5:$Z$80,MATCH($E25,'Path Scorecard'!$H$5:$H$80,0)) -> 81 | K25: =INDEX('Path Scorecard'!$AE$5:$AE$80,MATCH($E25,'Path Scorecard'!$H$5:$H$80,0))&" / "&INDEX('Path Scorecard'!$AF$5:$AF$80,MATCH($E25,'Path Scorecard'!$H$5:$H$80,0)) -> Wayfair / Amazon | L25: =INDEX('Path Scorecard'!$AG$5:$AG$80,MATCH($E25,'Path Scorecard'!$H$5:$H$80,0))&" / "&INDEX('Path Scorecard'!$AH$5:$AH$80,MATCH($E25,'Path Scorecard'!$H$5:$H$80,0)) -> Design Within Reach / West Elm | M25: Top 20
A26: 2 | B26: P50 | C26: Furniture > Desks > Sit & Stand Desks | D26: 3 | E26: CL215523 | F26: 576 | G26: =INDEX('Path Scorecard'!$Q$5:$Q$80,MATCH($E26,'Path Scorecard'!$H$5:$H$80,0)) -> Hero | H26: =INDEX('Path Scorecard'!$AC$5:$AC$80,MATCH($E26,'Path Scorecard'!$H$5:$H$80,0)) -> PROTECT | I26: =INDEX('Path Scorecard'!$AB$5:$AB$80,MATCH($E26,'Path Scorecard'!$H$5:$H$80,0)) -> Protect (control) | J26: =INDEX('Path Scorecard'!$Z$5:$Z$80,MATCH($E26,'Path Scorecard'!$H$5:$H$80,0)) -> 66 | K26: =INDEX('Path Scorecard'!$AE$5:$AE$80,MATCH($E26,'Path Scorecard'!$H$5:$H$80,0))&" / "&INDEX('Path Scorecard'!$AF$5:$AF$80,MATCH($E26,'Path Scorecard'!$H$5:$H$80,0)) -> Amazon / Wayfair | L26: =INDEX('Path Scorecard'!$AG$5:$AG$80,MATCH($E26,'Path Scorecard'!$H$5:$H$80,0))&" / "&INDEX('Path Scorecard'!$AH$5:$AH$80,MATCH($E26,'Path Scorecard'!$H$5:$H$80,0)) -> - / - | M26: Control shelf (PROTECT)
A27: 2 | B27: P66 | C27: Furniture > Desks > Desk Components & Hutches > Hutches | D27: 4 | E27: CL353865 | F27: 77 | G27: =INDEX('Path Scorecard'!$Q$5:$Q$80,MATCH($E27,'Path Scorecard'!$H$5:$H$80,0)) -> Non-Hero | H27: =INDEX('Path Scorecard'!$AC$5:$AC$80,MATCH($E27,'Path Scorecard'!$H$5:$H$80,0)) -> EXPLORE | I27: =INDEX('Path Scorecard'!$AB$5:$AB$80,MATCH($E27,'Path Scorecard'!$H$5:$H$80,0)) -> Backlog | J27: =INDEX('Path Scorecard'!$Z$5:$Z$80,MATCH($E27,'Path Scorecard'!$H$5:$H$80,0)) -> 52 | K27: =INDEX('Path Scorecard'!$AE$5:$AE$80,MATCH($E27,'Path Scorecard'!$H$5:$H$80,0))&" / "&INDEX('Path Scorecard'!$AF$5:$AF$80,MATCH($E27,'Path Scorecard'!$H$5:$H$80,0)) -> Wayfair / Amazon | L27: =INDEX('Path Scorecard'!$AG$5:$AG$80,MATCH($E27,'Path Scorecard'!$H$5:$H$80,0))&" / "&INDEX('Path Scorecard'!$AH$5:$AH$80,MATCH($E27,'Path Scorecard'!$H$5:$H$80,0)) -> - / - | M27: Backlog
A28: 3 | B28: P05 | C28: Furniture > Lamps & Lighting > Desk Lamps | D28: 3 | E28: CL167867 | F28: 210 | G28: =INDEX('Path Scorecard'!$Q$5:$Q$80,MATCH($E28,'Path Scorecard'!$H$5:$H$80,0)) -> Probable Hero | H28: =INDEX('Path Scorecard'!$AC$5:$AC$80,MATCH($E28,'Path Scorecard'!$H$5:$H$80,0)) -> BUILD | I28: =INDEX('Path Scorecard'!$AB$5:$AB$80,MATCH($E28,'Path Scorecard'!$H$5:$H$80,0)) -> Recommended | J28: =INDEX('Path Scorecard'!$Z$5:$Z$80,MATCH($E28,'Path Scorecard'!$H$5:$H$80,0)) -> 86 | K28: =INDEX('Path Scorecard'!$AE$5:$AE$80,MATCH($E28,'Path Scorecard'!$H$5:$H$80,0))&" / "&INDEX('Path Scorecard'!$AF$5:$AF$80,MATCH($E28,'Path Scorecard'!$H$5:$H$80,0)) -> Wayfair / Amazon | L28: =INDEX('Path Scorecard'!$AG$5:$AG$80,MATCH($E28,'Path Scorecard'!$H$5:$H$80,0))&" / "&INDEX('Path Scorecard'!$AH$5:$AH$80,MATCH($E28,'Path Scorecard'!$H$5:$H$80,0)) -> Lamps Plus / Urban Outfitters | M28: Top 20
... A53: 9 | B53: P34 | C53: Office Supplies > Storage & Organization > Storage Bins | D53: 3 | E53: CL354710 | F53: 660 | G53: =INDEX('Path Scorecard'!$Q$5:$Q$80,MATCH($E53,'Path Scorecard'!$H$5:$H$80,0)) -> Hero | H53: =INDEX('Path Scorecard'!$AC$5:$AC$80,MATCH($E53,'Path Scorecard'!$H$5:$H$80,0)) -> EXTEND | I53: =INDEX('Path Scorecard'!$AB$5:$AB$80,MATCH($E53,'Path Scorecard'!$H$5:$H$80,0)) -> Backlog | J53: =INDEX('Path Scorecard'!$Z$5:$Z$80,MATCH($E53,'Path Scorecard'!$H$5:$H$80,0)) -> 72 | K53: =INDEX('Path Scorecard'!$AE$5:$AE$80,MATCH($E53,'Path Scorecard'!$H$5:$H$80,0))&" / "&INDEX('Path Scorecard'!$AF$5:$AF$80,MATCH($E53,'Path Scorecard'!$H$5:$H$80,0)) -> - / - | L53: =INDEX('Path Scorecard'!$AG$5:$AG$80,MATCH($E53,'Path Scorecard'!$H$5:$H$80,0))&" / "&INDEX('Path Scorecard'!$AH$5:$AH$80,MATCH($E53,'Path Scorecard'!$H$5:$H$80,0)) -> - / - | M53: Backlog

Sheet Selection Criteria
A1: Path selection: gates and the 8 path-score criteria
A2: Yellow cells with blue text are editable. Hero segmentation lives in 'Hero Criteria'; competitor criteria in 'Competitor Criteria'.
A4: A. Hard gates: a path must pass all four to be considered
A5: Code | B5: Gate | C5: Rule | D5: Why it matters
A6: G1 | B6: Granularity | C6: The node is an L3 or L4 in the Staples navigation tree (Level 3 or 4). | D6: L2 is too coarse: the gap must be readable on one shelf.
A7: G2 | B7: Brand authority | C7: The node sits on a Staples work / school / small-business mission (not mis-shelved or leisure). | D7: Pat: build momentum 'without straying too far from Staples' brand authority'.
A8: G3 | B8: Staples baseline | C8: Staples lists at least the minimum item count (section C). | D8: Needs a nearest-Staples-family comparison and a share baseline.
A9: G4 | B9: No partner conflict | C9: No Staples strategic partner already owns the assortment on Staples.com. | D9: Party City (Apr-2026) now supplies party decor, gift bags and wrap.
A11: B. Path-score criteria: each scored 1-5, weighted score scaled to 0-100 (ranks shelves inside each segment)
A12: Code | B12: Criterion | C12: What it measures | D12: Scores 5 when | E12: Scores 1 when | F12: Weight
A13: C1 | B13: Design & lifestyle variance ('White Chair' test) | C13: Do shoppers choose on colour, material, style or 'vibe' rather than spec? | D13: Style drives the choice; many aesthetic archetypes exist | E13: Pure spec / commodity | F13: 20
A14: C2 | B14: Competitor depth advantage | C14: How much wider the best competitor's assortment is on this shelf | D14: Best competitor is several times wider, with archetypes Staples lacks | E14: Parity with Staples | F14: 15
A15: C3 | B15: 1P protection (low cannibalisation) | C15: Can design variants be added without substituting Staples' core best-sellers? | D15: Design variants clearly distinct from the 1P core | E15: Direct substitute of core 1P | F15: 15
A16: C4 | B16: Core-adjacency & shopper mission | C16: Same work, school or small-business mission as Staples' core | D16: Sits on the core Staples mission | E16: Residential or leisure mission | F16: 15
A17: C5 | B17: Basket attach & quick-win economics | C17: Parcel-shippable, lower ticket, attaches to core baskets (Pat: +1-2 items per checkout) | D17: Under ~$50, parcel, frequent attach | E17: Oversize freight, considered purchase | F17: 10
A18: C6 | B18: Business familiarity & story | C18: Would the Staples room recognise it instantly (header nav, Staples' own moves, visible trend)? | D18: Header-nav shelf + Staples' own recent move or a famous trend | E18: Obscure shelf | F18: 10
A19: C7 | B19: Commercial moment | C19: Peaks in the Q1-2027 window or BTS-2027 (Pat's seasonal anchor) | D19: Peaks in Jan-Mar or Jul-Sep 2027 | E19: No clear moment | F19: 5
A20: C8 | B20: Data readiness | C20: Staples SKUs already in hand + competitor already scraped or reachable | D20: Both sides in hand / reachable | E20: Neither side available | F20: 10
E21: Total weight | F21: =SUM(F13:F20) -> 100
A23: C. Thresholds
A24: Code | B24: Parameter | C24: Value | D24: Note
A25: G3 | B25: Minimum Staples items on the leaf | C25: 20 | D25: Feeds gate G3.
A26: FS | B26: Fast-start: min Staples SKUs already in the sample | C26: 100 | D26: Top-20 shelves above this can start without a new Staples scrape.
A28: D. How the Top 20 is chosen
A29: 1. | B29: Gates (section A) remove shelves that are not true L3/L4, are off-mission, too thin, or in a partner's space.
A30: 2. | B30: Each remaining shelf gets a Hero segment and a marketplace play ('Hero Criteria').
A31: 3. | B31: Each shelf gets a path score, 0-100, from the 8 criteria above.
A32: 4. | B32: Inside each segment, shelves are ranked by path score (ties: C4 core-adjacency, then C1 design variance). PROTECT shelves are left out: they are control shelves.
A33: 5. | B33: The top 7 Hero + 7 Probable Hero + 6 Non-Hero become the Top 20 (quotas editable in 'Hero Criteria', minimum 6 each); the next 3 per segment are reserves.
A34: 6. | B34: Each Top-20 and reserve shelf gets 2 primary + 2 secondary competitors ('Competitor Criteria').

Sheet Path Scorecard
A1: Path scorecard: every candidate Staples L3/L4 path
A2: Blue cells are analyst inputs. Gates, segment, score, rank in segment, status, play and competitors are formulas. Sort or filter freely; IDs are stable.
A4: Path ID | B4: Staples path (exact, from nav tree) | C4: L1 | D4: L2 | E4: L3 | F4: L4 | G4: Level | H4: Category ID | I4: Staples items (site) | J4: Staples SKUs in hand (sample) | K4: Link to your list | L4: G1 Granularity | M4: G2 Brand authority | N4: G3 Baseline | O4: G4 No partner conflict | P4: All gates | Q4: Hero segment | R4: C1 Design variance | S4: C2 Comp. depth | T4: C3 1P protection | U4: C4 Core-adjacency | V4: C5 Basket attach | W4: C6 Familiarity | X4: C7 Moment | Y4: C8 Data readiness | Z4: Path score (0-100) | AA4: Rank in segment | AB4: Status | AC4: Marketplace play | AD4: Fast-start | AE4: Primary 1 | AF4: Primary 2 | AG4: Secondary 1 | AH4: Secondary 2 | AI4: Rationale / gate note | AJ4: Rank key (helper)
A5: P01 | B5: Office Supplies > Calendars & Planners > Planners & Personal Organizers | C5: Office Supplies | D5: Calendars & Planners | E5: Planners & Personal Organizers | G5: 3 | H5: CL166388 | I5: 1037 | J5: 1016 | K5: 9. Planning & Craft Organization | L5: =IF(OR(G5=3,G5=4),"Pass","Fail") -> Pass | M5: Pass | N5: =IF(I5>='Selection Criteria'!$C$25,"Pass","Fail") -> Pass | O5: Pass | P5: =IF(AND(L5="Pass",M5="Pass",N5="Pass",O5="Pass"),"Pass","Fail") -> Pass | Q5: =INDEX('Hero Segmentation'!$Q$5:$Q$80,MATCH($A5,'Hero Segmentation'!$A$5:$A$80,0)) -> Hero | R5: 5 | S5: 5 | T5: 4 | U5: 5 | V5: 5 | W5: 5 | X5: 5 | Y5: 4 | Z5: =IF(P5="Pass",(R5*'Selection Criteria'!$F$13+S5*'Selection Criteria'!$F$14+T5*'Selection Criteria'!$F$15+U5*'Selection Criteria'!$F$16+V5*'Selection Criteria'!$F$17+W5*'Selection Criteria'!$F$18+X5*'Selection Criteria'!$F$19+Y5*'Selection Criteria'!$F$20)/(5*'Selection Criteria'!$F$21)*100,"-") -> 95 | AA5: =IF(AJ5<0,"-",COUNTIFS($Q$5:$Q$80,Q5,$AJ$5:$AJ$80,">"&AJ5)+1) -> 1 | AB5: =IF(P5<>"Pass","Parked (gate)",IF(AC5="PROTECT","Protect (control)",IF(AA5<=IF(Q5="Hero",'Hero Criteria'!$C$38,IF(Q5="Probable Hero",'Hero Criteria'!$C$39,'Hero Criteria'!$C$40)),"Recommended",IF(AA5<=IF(Q5="Hero",'Hero Criteria'!$C$38,IF(Q5="Probable Hero",'Hero Criteria'!$C$39,'Hero Criteria'!$C$40))+'Hero Criteria'!$C$41,"Reserve","Backlog")))) -> Recommended | AC5: =INDEX('Hero Segmentation'!$R$5:$R$80,MATCH($A5,'Hero Segmentation'!$A$5:$A$80,0)) -> EXTEND | AD5: =IF(AND(AB5="Recommended",J5>='Selection Criteria'!$C$26),"Yes","") -> Yes | AE5: =IFERROR(INDEX('Primary Competitor Fit'!$D$5:$D$91,MATCH($A5&"|Primary 1",'Primary Competitor Fit'!$M$5:$M$91,0)),"-") -> Amazon | AF5: =IFERROR(INDEX('Primary Competitor Fit'!$D$5:$D$91,MATCH($A5&"|Primary 2",'Primary Competitor Fit'!$M$5:$M$91,0)),"-") -> Target | AG5: =IFERROR(INDEX('Secondary Competitor Fit'!$D$5:$D$98,MATCH($A5&"|Secondary 1",'Secondary Competitor Fit'!$M$5:$M$98,0)),"-") -> Erin Condren | AH5: =IFERROR(INDEX('Secondary Competitor Fit'!$D$5:$D$98,MATCH($A5&"|Secondary 2",'Secondary Competitor Fit'!$M$5:$M$98,0)),"-") -> Michaels | AI5: Deep Staples shelf (1,037) and Staples' own Sincerely Jules move; enthusiast formats missing. | AJ5: =IF(AND(P5="Pass",AC5<>"PROTECT"),Z5+U5/100+R5/1000,-1) -> 95.055
A6: P02 | B6: Office Supplies > Desk Organizers & Accessories > Desk Organizers | C6: Office Supplies | D6: Desk Organizers & Accessories | E6: Desk Organizers | G6: 3 | H6: CL140991 | I6: 342 | J6: 0 | K6: New | L6: =IF(OR(G6=3,G6=4),"Pass","Fail") -> Pass | M6: Pass | N6: =IF(I6>='Selection Criteria'!$C$25,"Pass","Fail") -> Pass | O6: Pass | P6: =IF(AND(L6="Pass",M6="Pass",N6="Pass",O6="Pass"),"Pass","Fail") -> Pass | Q6: =INDEX('Hero Segmentation'!$Q$5:$Q$80,MATCH($A6,'Hero Segmentation'!$A$5:$A$80,0)) -> Hero | R6: 5 | S6: 5 | T6: 4 | U6: 5 | V6: 5 | W6: 5 | X6: 5 | Y6: 2 | Z6: =IF(P6="Pass",(R6*'Selection Criteria'!$F$13+S6*'Selection Criteria'!$F$14+T6*'Selection Criteria'!$F$15+U6*'Selection Criteria'!$F$16+V6*'Selection Criteria'!$F$17+W6*'Selection Criteria'!$F$18+X6*'Selection Criteria'!$F$19+Y6*'Selection Criteria'!$F$20)/(5*'Selection Criteria'!$F$21)*100,"-") -> 91 | AA6: =IF(AJ6<0,"-",COUNTIFS($Q$5:$Q$80,Q6,$AJ$5:$AJ$80,">"&AJ6)+1) -> 2 | AB6: =IF(P6<>"Pass","Parked (gate)",IF(AC6="PROTECT","Protect (control)",IF(AA6<=IF(Q6="Hero",'Hero Criteria'!$C$38,IF(Q6="Probable Hero",'Hero Criteria'!$C$39,'Hero Criteria'!$C$40)),"Recommended",IF(AA6<=IF(Q6="Hero",'Hero Criteria'!$C$38,IF(Q6="Probable Hero",'Hero Criteria'!$C$39,'Hero Criteria'!$C$40))+'Hero Criteria'!$C$41,"Reserve","Backlog")))) -> Recommended | AC6: =INDEX('Hero Segmentation'!$R$5:$R$80,MATCH($A6,'Hero Segmentation'!$A$5:$A$80,0)) -> EXTEND | AD6: =IF(AND(AB6="Recommended",J6>='Selection Criteria'!$C$26),"Yes","") | AE6: =IFERROR(INDEX('Primary Competitor Fit'!$D$5:$D$91,MATCH($A6&"|Primary 1",'Primary Competitor Fit'!$M$5:$M$91,0)),"-") -> Target | AF6: =IFERROR(INDEX('Primary Competitor Fit'!$D$5:$D$91,MATCH($A6&"|Primary 2",'Primary Competitor Fit'!$M$5:$M$91,0)),"-") -> Amazon | AG6: =IFERROR(INDEX('Secondary Competitor Fit'!$D$5:$D$98,MATCH($A6&"|Secondary 1",'Secondary Competitor Fit'!$M$5:$M$98,0)),"-") -> Grovemade | AH6: =IFERROR(INDEX('Secondary Competitor Fit'!$D$5:$D$98,MATCH($A6&"|Secondary 2",'Secondary Competitor Fit'!$M$5:$M$98,0)),"-") -> The Container Store | AI6: Header-nav core, low ticket, coordinated design collections at Target/Container Store. | AJ6: =IF(AND(P6="Pass",AC6<>"PROTECT"),Z6+U6/100+R6/1000,-1) -> 91.055
A7: P03 | B7: Coffee, Water & Snacks > Water & Beverages > Water Bottles, Tumblers & Travel Mugs | C7: Coffee, Water & Snacks | D7: Water & Beverages | E7: Water Bottles, Tumblers & Travel Mugs | G7: 3 | H7: CL354650 | I7: 463 | J7: 462 | K7: 7. Hydration & Drinkware | L7: =IF(OR(G7=3,G7=4),"Pass","Fail") -> Pass | M7: Pass | N7: =IF(I7>='Selection Criteria'!$C$25,"Pass","Fail") -> Pass | O7: Pass | P7: =IF(AND(L7="Pass",M7="Pass",N7="Pass",O7="Pass"),"Pass","Fail") -> Pass | Q7: =INDEX('Hero Segmentation'!$Q$5:$Q$80,MATCH($A7,'Hero Segmentation'!$A$5:$A$80,0)) -> Probable Hero | R7: 5 | S7: 5 | T7: 4 | U7: 4 | V7: 5 | W7: 5 | X7: 4 | Y7: 4 | Z7: =IF(P7="Pass",(R7*'Selection Criteria'!$F$13+S7*'Selection Criteria'!$F$14+T7*'Selection Criteria'!$F$15+U7*'Selection Criteria'!$F$16+V7*'Selection Criteria'!$F$17+W7*'Selection Criteria'!$F$18+X7*'Selection Criteria'!$F$19+Y7*'Selection Criteria'!$F$20)/(5*'Selection Criteria'!$F$21)*100,"-") -> 91 | AA7: =IF(AJ7<0,"-",COUNTIFS($Q$5:$Q$80,Q7,$AJ$5:$AJ$80,">"&AJ7)+1) -> 1 | AB7: =IF(P7<>"Pass","Parked (gate)",IF(AC7="PROTECT","Protect (control)",IF(AA7<=IF(Q7="Hero",'Hero Criteria'!$C$38,IF(Q7="Probable Hero",'Hero Criteria'!$C$39,'Hero Criteria'!$C$40)),"Recommended",IF(AA7<=IF(Q7="Hero",'Hero Criteria'!$C$38,IF(Q7="Probable Hero",'Hero Criteria'!$C$39,'Hero Criteria'!$C$40))+'Hero Criteria'!$C$41,"Reserve","Backlog")))) -> Recommended | AC7: =INDEX('Hero Segmentation'!$R$5:$R$80,MATCH($A7,'Hero Segmentation'!$A$5:$A$80,0)) -> BUILD | AD7: =IF(AND(AB7="Recommended",J7>='Selection Criteria'!$C$26),"Yes","") -> Yes | AE7: =IFERROR(INDEX('Primary Competitor Fit'!$D$5:$D$91,MATCH($A7&"|Primary 1",'Primary Competitor Fit'!$M$5:$M$91,0)),"-") -> Dick's Sporting Goods | AF7: =IFERROR(INDEX('Primary Competitor Fit'!$D$5:$D$91,MATCH($A7&"|Primary 2",'Primary Competitor Fit'!$M$5:$M$91,0)),"-") -> Target | AG7: =IFERROR(INDEX('Secondary Competitor Fit'!$D$5:$D$98,MATCH($A7&"|Secondary 1",'Secondary Competitor Fit'!$M$5:$M$98,0)),"-") -> Scheels | AH7: =IFERROR(INDEX('Secondary Competitor Fit'!$D$5:$D$98,MATCH($A7&"|Secondary 2",'Secondary Competitor Fit'!$M$5:$M$98,0)),"-") -> YETI | AI7: Owala/Stanley colourway gap; data in hand; everyone relates. | AJ7: =IF(AND(P7="Pass",AC7<>"PROTECT"),Z7+U7/100+R7/1000,-1) -> 91.045
A8: P04 | B8: Furniture > Chairs & Seating > Accent & Waiting Room Chairs | C8: Furniture | D8: Chairs & Seating | E8: Accent & Waiting Room Chairs | G8: 3 | H8: CL70203 | I8: 229 | J8: 199 | K8: 1. Chairs & Seating | L8: =IF(OR(G8=3,G8=4),"Pass","Fail") -> Pass | M8: Pass | N8: =IF(I8>='Selection Criteria'!$C$25,"Pass","Fail") -> Pass | O8: Pass | P8: =IF(AND(L8="Pass",M8="Pass",N8="Pass",O8="Pass"),"Pass","Fail") -> Pass | Q8: =INDEX('Hero Segmentation'!$Q$5:$Q$80,MATCH($A8,'Hero Segmentation'!$A$5:$A$80,0)) -> Probable Hero | R8: 5 | S8: 5 | T8: 5 | U8: 4 | V8: 2 | W8: 5 | X8: 3 | Y8: 5 | Z8: =IF(P8="Pass",(R8*'Selection Criteria'!$F$13+S8*'Selection Criteria'!$F$14+T8*'Selection Criteria'!$F$15+U8*'Selection Criteria'!$F$16+V8*'Selection Criteria'!$F$17+W8*'Selection Criteria'!$F$18+X8*'Selection Criteria'!$F$19+Y8*'Selection Criteria'!$F$20)/(5*'Selection Criteria'!$F$21)*100,"-") -> 89 | AA8: =IF(AJ8<0,"-",COUNTIFS($Q$5:$Q$80,Q8,$AJ$5:$AJ$80,">"&AJ8)+1) -> 2 | AB8: =IF(P8<>"Pass","Parked (gate)",IF(AC8="PROTECT","Protect (control)",IF(AA8<=IF(Q8="Hero",'Hero Criteria'!$C$38,IF(Q8="Probable Hero",'Hero Criteria'!$C$39,'Hero Criteria'!$C$40)),"Recommended",IF(AA8<=IF(Q8="Hero",'Hero Criteria'!$C$38,IF(Q8="Probable Hero",'Hero Criteria'!$C$39,'Hero Criteria'!$C$40))+'Hero Criteria'!$C$41,"Reserve","Backlog")))) -> Recommended | AC8: =INDEX('Hero Segmentation'!$R$5:$R$80,MATCH($A8,'Hero Segmentation'!$A$5:$A$80,0)) -> BUILD | AD8: =IF(AND(AB8="Recommended",J8>='Selection Criteria'!$C$26),"Yes","") -> Yes | AE8: =IFERROR(INDEX('Primary Competitor Fit'!$D$5:$D$91,MATCH($A8&"|Primary 1",'Primary Competitor Fit'!$M$5:$M$91,0)),"-") -> Wayfair | AF8: =IFERROR(INDEX('Primary Competitor Fit'!$D$5:$D$91,MATCH($A8&"|Primary 2",'Primary Competitor Fit'!$M$5:$M$91,0)),"-") -> Amazon | AG8: =IFERROR(INDEX('Secondary Competitor Fit'!$D$5:$D$98,MATCH($A8&"|Secondary 1",'Secondary Competitor Fit'!$M$5:$M$98,0)),"-") -> Article | AH8: =IFERROR(INDEX('Secondary Competitor Fit'!$D$5:$D$98,MATCH($A8&"|Secondary 2",'Secondary Competitor Fit'!$M$5:$M$98,0)),"-") -> West Elm | AI8: Pat's own 'White Chair' shelf; pilot: 5 recs, 2 Strong, 94% confident mapping. | AJ8: =IF(AND(P8="Pass",AC8<>"PROTECT"),Z8+U8/100+R8/1000,-1) -> 89.045
A9: P05 | B9: Furniture > Lamps & Lighting > Desk Lamps | C9: Furniture | D9: Lamps & Lighting | E9: Desk Lamps | G9: 3 | H9: CL167867 | I9: 210 | J9: 195 | K9: 3. Lamps & Lighting | L9: =IF(OR(G9=3,G9=4),"Pass","Fail") -> Pass | M9: Pass | N9: =IF(I9>='Selection Criteria'!$C$25,"Pass","Fail") -> Pass | O9: Pass | P9: =IF(AND(L9="Pass",M9="Pass",N9="Pass",O9="Pass"),"Pass","Fail") -> Pass | Q9: =INDEX('Hero Segmentation'!$Q$5:$Q$80,MATCH($A9,'Hero Segmentation'!$A$5:$A$80,0)) -> Probable Hero | R9: 5 | S9: 4 | T9: 4 | U9: 5 | V9: 4 | W9: 4 | X9: 3 | Y9: 4 | Z9: =IF(P9="Pass",(R9*'Selection Criteria'!$F$13+S9*'Selection Criteria'!$F$14+T9*'Selection Criteria'!$F$15+U9*'Selection Criteria'!$F$16+V9*'Selection Criteria'!$F$17+W9*'Selection Criteria'!$F$18+X9*'Selection Criteria'!$F$19+Y9*'Selection Criteria'!$F$20)/(5*'Selection Criteria'!$F$21)*100,"-") -> 86 | AA9: =IF(AJ9<0,"-",COUNTIFS($Q$5:$Q$80,Q9,$AJ$5:$AJ$80,">"&AJ9)+1) -> 3 | AB9: =IF(P9<>"Pass","Parked (gate)",IF(AC9="PROTECT","Protect (control)",IF(AA9<=IF(Q9="Hero",'Hero Criteria'!$C$38,IF(Q9="Probable Hero",'Hero Criteria'!$C$39,'Hero Criteria'!$C$40)),"Recommended",IF(AA9<=IF(Q9="Hero",'Hero Criteria'!$C$38,IF(Q9="Probable Hero",'Hero Criteria'!$C$39,'Hero Criteria'!$C$40))+'Hero Criteria'!$C$41,"Reserve","Backlog")))) -> Recommended | AC9: =INDEX('Hero Segmentation'!$R$5:$R$80,MATCH($A9,'Hero Segmentation'!$A$5:$A$80,0)) -> BUILD | AD9: =IF(AND(AB9="Recommended",J9>='Selection Criteria'!$C$26),"Yes","") -> Yes | AE9: =IFERROR(INDEX('Primary Competitor Fit'!$D$5:$D$91,MATCH($A9&"|Primary 1",'Primary Competitor Fit'!$M$5:$M$91,0)),"-") -> Wayfair | AF9: =IFERROR(INDEX('Primary Competitor Fit'!$D$5:$D$91,MATCH($A9&"|Primary 2",'Primary Competitor Fit'!$M$5:$M$91,0)),"-") -> Amazon | AG9: =IFERROR(INDEX('Secondary Competitor Fit'!$D$5:$D$98,MATCH($A9&"|Secondary 1",'Secondary Competitor Fit'!$M$5:$M$98,0)),"-") -> Lamps Plus | AH9: =IFERROR(INDEX('Secondary Competitor Fit'!$D$5:$D$98,MATCH($A9&"|Secondary 2",'Secondary Competitor Fit'!$M$5:$M$98,0)),"-") -> Urban Outfitters | AI9: Aesthetic lighting on the work desk; Staples SKUs in hand. | AJ9: =IF(AND(P9="Pass",AC9<>"PROTECT"),Z9+U9/100+R9/1000,-1) -> 86.055
A10: P06 | B10: Office Supplies > Writing Supplies & Instruments > Pencil Accessories > Pencil Cases & Pouches | C10: Office Supplies | D10: Writing Supplies & Instruments | E10: Pencil Accessories | F10: Pencil Cases & Pouches | G10: 4 | H10: CL141253 | I10: 107 | J10: 0 | K10: New | L10: =IF(OR(G10=3,G10=4),"Pass","Fail") -> Pass | M10: Pass | N10: =IF(I10>='Selection Criteria'!$C$25,"Pass","Fail") -> Pass | O10: Pass | P10: =IF(AND(L10="Pass",M10="Pass",N10="Pass",O10="Pass"),"Pass","Fail") -> Pass | Q10: =INDEX('Hero Segmentation'!$Q$5:$Q$80,MATCH($A10,'Hero Segmentation'!$A$5:$A$80,0)) -> Probable Hero | R10: 5 | S10: 4 | T10: 5 | U10: 4 | V10: 5 | W10: 4 | X10: 5 | Y10: 2 | Z10: =IF(P10="Pass",(R10*'Selection Criteria'!$F$13+S10*'Selection Criteria'!$F$14+T10*'Selection Criteria'!$F$15+U10*'Selection Criteria'!$F$16+V10*'Selection Criteria'!$F$17+W10*'Selection Criteria'!$F$18+X10*'Selection Criteria'!$F$19+Y10*'Selection Criteria'!$F$20)/(5*'Selection Criteria'!$F$21)*100,"-") -> 86 | AA10: =IF(AJ10<0,"-",COUNTIFS($Q$5:$Q$80,Q10,$AJ$5:$AJ$80,">"&AJ10)+1) -> 4 | AB10: =IF(P10<>"Pass","Parked (gate)",IF(AC10="PROTECT","Protect (control)",IF(AA10<=IF(Q10="Hero",'Hero Criteria'!$C$38,IF(Q10="Probable Hero",'Hero Criteria'!$C$39,'Hero Criteria'!$C$40)),"Recommended",IF(AA10<=IF(Q10="Hero",'Hero Criteria'!$C$38,IF(Q10="Probable Hero",'Hero Criteria'!$C$39,'Hero Criteria'!$C$40))+'Hero Criteria'!$C$41,"Reserve","Backlog")))) -> Recommended | AC10: =INDEX('Hero Segmentation'!$R$5:$R$80,MATCH($A10,'Hero Segmentation'!$A$5:$A$80,0)) -> BUILD | AD10: =IF(AND(AB10="Recommended",J10>='Selection Criteria'!$C$26),"Yes","") | AE10: =IFERROR(INDEX('Primary Competitor Fit'!$D$5:$D$91,MATCH($A10&"|Primary 1",'Primary Competitor Fit'!$M$5:$M$91,0)),"-") -> Amazon | AF10: =IFERROR(INDEX('Primary Competitor Fit'!$D$5:$D$91,MATCH($A10&"|Primary 2",'Primary Competitor Fit'!$M$5:$M$91,0)),"-") -> Target | AG10: =IFERROR(INDEX('Secondary Competitor Fit'!$D$5:$D$98,MATCH($A10&"|Secondary 1",'Secondary Competitor Fit'!$M$5:$M$98,0)),"-") -> JetPens | AH10: =IFERROR(INDEX('Secondary Competitor Fit'!$D$5:$D$98,MATCH($A10&"|Secondary 2",'Secondary Competitor Fit'!$M$5:$M$98,0)),"-") -> Kinokuniya | AI10: First 'aesthetic' item in the BTS basket; Staples' Recess Club proves demand. | AJ10: =IF(AND(P10="Pass",AC10<>"PROTECT"),Z10+U10/100+R10/1000,-1) -> 86.045
A11: P07 | B11: Bags, Backpacks & Luggage > Backpacks & Laptop Bags > Backpacks | C11: Bags, Backpacks & Luggage | D11: Backpacks & Laptop Bags | E11: Backpacks | G11: 3 | H11: CL142745 | I11: 585 | J11: 542 | K11: 6. Backpacks & Bags | L11: =IF(OR(G11=3,G11=4),"Pass","Fail") -> Pass | M11: Pass | N11: =IF(I11>='Selection Criteria'!$C$25,"Pass","Fail") -> Pass | O11: Pass | P11: =IF(AND(L11="Pass",M11="Pass",N11="Pass",O11="Pass"),"Pass","Fail") -> Pass | Q11: =INDEX('Hero Segmentation'!$Q$5:$Q$80,MATCH($A11,'Hero Segmentation'!$A$5:$A$80,0)) -> Hero | R11: 4 | S11: 5 | T11: 3 | U11: 5 | V11: 4 | W11: 5 | X11: 5 | Y11: 4 | Z11: =IF(P11="Pass",(R11*'Selection Criteria'!$F$13+S11*'Selection Criteria'!$F$14+T11*'Selection Criteria'!$F$15+U11*'Selection Criteria'!$F$16+V11*'Selection Criteria'!$F$17+W11*'Selection Criteria'!$F$18+X11*'Selection Criteria'!$F$19+Y11*'Selection Criteria'!$F$20)/(5*'Selection Criteria'!$F$21)*100,"-") -> 86 | AA11: =IF(AJ11<0,"-",COUNTIFS($Q$5:$Q$80,Q11,$AJ$5:$AJ$80,">"&AJ11)+1) -> 4 | AB11: =IF(P11<>"Pass","Parked (gate)",IF(AC11="PROTECT","Protect (control)",IF(AA11<=IF(Q11="Hero",'Hero Criteria'!$C$38,IF(Q11="Probable Hero",'Hero Criteria'!$C$39,'Hero Criteria'!$C$40)),"Recommended",IF(AA11<=IF(Q11="Hero",'Hero Criteria'!$C$38,IF(Q11="Probable Hero",'Hero Criteria'!$C$39,'Hero Criteria'!$C$40))+'Hero Criteria'!$C$41,"Reserve","Backlog")))) -> Recommended | AC11: =INDEX('Hero Segmentation'!$R$5:$R$80,MATCH($A11,'Hero Segmentation'!$A$5:$A$80,0)) -> EXTEND | AD11: =IF(AND(AB11="Recommended",J11>='Selection Criteria'!$C$26),"Yes","") -> Yes | AE11: =IFERROR(INDEX('Primary Competitor Fit'!$D$5:$D$91,MATCH($A11&"|Primary 1",'Primary Competitor Fit'!$M$5:$M$91,0)),"-") -> Amazon | AF11: =IFERROR(INDEX('Primary Competitor Fit'!$D$5:$D$91,MATCH($A11&"|Primary 2",'Primary Competitor Fit'!$M$5:$M$91,0)),"-") -> Target | AG11: =IFERROR(INDEX('Secondary Competitor Fit'!$D$5:$D$98,MATCH($A11&"|Secondary 1",'Secondary Competitor Fit'!$M$5:$M$98,0)),"-") -> Bellroy | AH11: =IFERROR(INDEX('Secondary Competitor Fit'!$D$5:$D$98,MATCH($A11&"|Secondary 2",'Secondary Competitor Fit'!$M$5:$M$98,0)),"-") -> Urban Outfitters | AI11: BTS anchor (85% of parents buy one); laptop packs are core 1P. | AJ11: =IF(AND(P11="Pass",AC11<>"PROTECT"),Z11+U11/100+R11/1000,-1) -> 86.054
A12: P08 | B12: Bags, Backpacks & Luggage > Totes & Handbags > Lunch Bags & Boxes | C12: Bags, Backpacks & Luggage | D12: Totes & Handbags | E12: Lunch Bags & Boxes | G12: 3 | H12: CL165124 | I12: 404 | J12: 406 | K12: 6. Backpacks & Bags | L12: =IF(OR(G12=3,G12=4),"Pass","Fail") -> Pass | M12: Pass | N12: =IF(I12>='Selection Criteria'!$C$25,"Pass","Fail") -> Pass | O12: Pass | P12: =IF(AND(L12="Pass",M12="Pass",N12="Pass",O12="Pass"),"Pass","Fail") -> Pass | Q12: =INDEX('Hero Segmentation'!$Q$5:$Q$80,MATCH($A12,'Hero Segmentation'!$A$5:$A$80,0)) -> Probable Hero | R12: 4 | S12: 5 | T12: 4 | U12: 4 | V12: 5 | W12: 4 | X12: 5 | Y12: 4 | Z12: =IF(P12="Pass",(R12*'Selection Criteria'!$F$13+S12*'Selection Criteria'!$F$14+T12*'Selection Criteria'!$F$15+U12*'Selection Criteria'!$F$16+V12*'Selection Criteria'!$F$17+W12*'Selection Criteria'!$F$18+X12*'Selection Criteria'!$F$19+Y12*'Selection Criteria'!$F$20)/(5*'Selection Criteria'!$F$21)*100,"-") -> 86 | AA12: =IF(AJ12<0,"-",COUNTIFS($Q$5:$Q$80,Q12,$AJ$5:$AJ$80,">"&AJ12)+1) -> 5 | AB12: =IF(P12<>"Pass","Parked (gate)",IF(AC12="PROTECT","Protect (control)",IF(AA12<=IF(Q12="Hero",'Hero Criteria'!$C$38,IF(Q12="Probable Hero",'Hero Criteria'!$C$39,'Hero Criteria'!$C$40)),"Recommended",IF(AA12<=IF(Q12="Hero",'Hero Criteria'!$C$38,IF(Q12="Probable Hero",'Hero Criteria'!$C$39,'Hero Criteria'!$C$40))+'Hero Criteria'!$C$41,"Reserve","Backlog")))) -> Recommended | AC12: =INDEX('Hero Segmentation'!$R$5:$R$80,MATCH($A12,'Hero Segmentation'!$A$5:$A$80,0)) -> BUILD | AD12: =IF(AND(AB12="Recommended",J12>='Selection Criteria'!$C$26),"Yes","") -> Yes | AE12: =IFERROR(INDEX('Primary Competitor Fit'!$D$5:$D$91,MATCH($A12&"|Primary 1",'Primary Competitor Fit'!$M$5:$M$91,0)),"-") -> Amazon | AF12: =IFERROR(INDEX('Primary Competitor Fit'!$D$5:$D$91,MATCH($A12&"|Primary 2",'Primary Competitor Fit'!$M$5:$M$91,0)),"-") -> Target | AG12: =IFERROR(INDEX('Secondary Competitor Fit'!$D$5:$D$98,MATCH($A12&"|Secondary 1",'Secondary Competitor Fit'!$M$5:$M$98,0)),"-") -> Bentgo | AH12: =IFERROR(INDEX('Secondary Competitor Fit'!$D$5:$D$98,MATCH($A12&"|Secondary 2",'Secondary Competitor Fit'!$M$5:$M$98,0)),"-") -> Pottery Barn Kids | AI12: Bento/leak-proof designs lead BTS & work-lunch; data in hand. | AJ12: =IF(AND(P12="Pass",AC12<>"PROTECT"),Z12+U12/100+R12/1000,-1) -> 86.044
A13: P09 | B13: School Supplies > Teacher Supplies > Classroom Decorations > Decorative Accents & Board Sets | C13: School Supplies | D13: Teacher Supplies | E13: Classroom Decorations | F13: Decorative Accents & Board Sets | G13: 4 | H13: CL219245 | I13: 607 | J13: 0 | K13: New | L13: =IF(OR(G13=3,G13=4),"Pass","Fail") -> Pass | M13: Pass | N13: =IF(I13>='Selection Criteria'!$C$25,"Pass","Fail") -> Pass | O13: Pass | P13: =IF(AND(L13="Pass",M13="Pass",N13="Pass",O13="Pass"),"Pass","Fail") -> Pass | Q13: =INDEX('Hero Segmentation'!$Q$5:$Q$80,MATCH($A13,'Hero Segmentation'!$A$5:$A$80,0)) -> Hero | R13: 5 | S13: 4 | T13: 4 | U13: 5 | V13: 5 | W13: 4 | X13: 5 | Y13: 2 | Z13: =IF(P13="Pass",(R13*'Selection Criteria'!$F$13+S13*'Selection Criteria'!$F$14+T13*'Selection Criteria'!$F$15+U13*'Selection Criteria'!$F$16+V13*'Selection Criteria'!$F$17+W13*'Selection Criteria'!$F$18+X13*'Selection Criteria'!$F$19+Y13*'Selection Criteria'!$F$20)/(5*'Selection Criteria'!$F$21)*100,"-") -> 86 | AA13: =IF(AJ13<0,"-",COUNTIFS($Q$5:$Q$80,Q13,$AJ$5:$AJ$80,">"&AJ13)+1) -> 3 | AB13: =IF(P13<>"Pass","Parked (gate)",IF(AC13="PROTECT","Protect (control)",IF(AA13<=IF(Q13="Hero",'Hero Criteria'!$C$38,IF(Q13="Probable Hero",'Hero Criteria'!$C$39,'Hero Criteria'!$C$40)),"Recommended",IF(AA13<=IF(Q13="Hero",'Hero Criteria'!$C$38,IF(Q13="Probable Hero",'Hero Criteria'!$C$39,'Hero Criteria'!$C$40))+'Hero Criteria'!$C$41,"Reserve","Backlog")))) -> Recommended | AC13: =INDEX('Hero Segmentation'!$R$5:$R$80,MATCH($A13,'Hero Segmentation'!$A$5:$A$80,0)) -> EXTEND | AD13: =IF(AND(AB13="Recommended",J13>='Selection Criteria'!$C$26),"Yes","") | AE13: =IFERROR(INDEX('Primary Competitor Fit'!$D$5:$D$91,MATCH($A13&"|Primary 1",'Primary Competitor Fit'!$M$5:$M$91,0)),"-") -> Amazon | AF13: =IFERROR(INDEX('Primary Competitor Fit'!$D$5:$D$91,MATCH($A13&"|Primary 2",'Primary Competitor Fit'!$M$5:$M$91,0)),"-") -> Walmart | AG13: =IFERROR(INDEX('Secondary Competitor Fit'!$D$5:$D$98,MATCH($A13&"|Secondary 1",'Secondary Competitor Fit'!$M$5:$M$98,0)),"-") -> Etsy | AH13: =IFERROR(INDEX('Secondary Competitor Fit'!$D$5:$D$98,MATCH($A13&"|Secondary 2",'Secondary Competitor Fit'!$M$5:$M$98,0)),"-") -> Oriental Trading | AI13: Teachers self-fund ~$895/yr and buy themed sets: Pat's BTS anchor. | AJ13: =IF(AND(P13="Pass",AC13<>"PROTECT"),Z13+U13/100+R13/1000,-1) -> 86.055
A14: P10 | B14: Office Supplies > Storage & Organization > Storage Baskets | C14: Office Supplies | D14: Storage & Organization | E14: Storage Baskets | G14: 3 | H14: CL354705 | I14: 95 | J14: 0 | K14: New | L14: =IF(OR(G14=3,G14=4),"Pass","Fail") -> Pass | M14: Pass | N14: =IF(I14>='Selection Criteria'!$C$25,"Pass","Fail") -> Pass | O14: Pass | P14: =IF(AND(L14="Pass",M14="Pass",N14="Pass",O14="Pass"),"Pass","Fail") -> Pass | Q14: =INDEX('Hero Segmentation'!$Q$5:$Q$80,MATCH($A14,'Hero Segmentation'!$A$5:$A$80,0)) -> Probable Hero | R14: 5 | S14: 5 | T14: 5 | U14: 4 | V14: 4 | W14: 3 | X14: 5 | Y14: 2 | Z14: =IF(P14="Pass",(R14*'Selection Criteria'!$F$13+S14*'Selection Criteria'!$F$14+T14*'Selection Criteria'!$F$15+U14*'Selection Criteria'!$F$16+V14*'Selection Criteria'!$F$17+W14*'Selection Criteria'!$F$18+X14*'Selection Criteria'!$F$19+Y14*'Selection Criteria'!$F$20)/(5*'Selection Criteria'!$F$21)*100,"-") -> 85 | AA14: =IF(AJ14<0,"-",COUNTIFS($Q$5:$Q$80,Q14,$AJ$5:$AJ$80,">"&AJ14)+1) -> 6 | AB14: =IF(P14<>"Pass","Parked (gate)",IF(AC14="PROTECT","Protect (control)",IF(AA14<=IF(Q14="Hero",'Hero Criteria'!$C$38,IF(Q14="Probable Hero",'Hero Criteria'!$C$39,'Hero Criteria'!$C$40)),"Recommended",IF(AA14<=IF(Q14="Hero",'Hero Criteria'!$C$38,IF(Q14="Probable Hero",'Hero Criteria'!$C$39,'Hero Criteria'!$C$40))+'Hero Criteria'!$C$41,"Reserve","Backlog")))) -> Recommended | AC14: =INDEX('Hero Segmentation'!$R$5:$R$80,MATCH($A14,'Hero Segmentation'!$A$5:$A$80,0)) -> BUILD | AD14: =IF(AND(AB14="Recommended",J14>='Selection Criteria'!$C$26),"Yes","") | AE14: =IFERROR(INDEX('Primary Competitor Fit'!$D$5:$D$91,MATCH($A14&"|Primary 1",'Primary Competitor Fit'!$M$5:$M$91,0)),"-") -> Wayfair | AF14: =IFERROR(INDEX('Primary Competitor Fit'!$D$5:$D$91,MATCH($A14&"|Primary 2",'Primary Competitor Fit'!$M$5:$M$91,0)),"-") -> Target | AG14: =IFERROR(INDEX('Secondary Competitor Fit'!$D$5:$D$98,MATCH($A14&"|Secondary 1",'Secondary Competitor Fit'!$M$5:$M$98,0)),"-") -> The Container Store | AH14: =IFERROR(INDEX('Secondary Competitor Fit'!$D$5:$D$98,MATCH($A14&"|Secondary 2",'Secondary Competitor Fit'!$M$5:$M$98,0)),"-") -> Pottery Barn | AI14: 95 items vs Wayfair's Woven/Decorative/Fabric basket nodes; style-led storage. | AJ14: =IF(AND(P14="Pass",AC14<>"PROTECT"),Z14+U14/100+R14/1000,-1) -> 85.045
A15: P11 | B15: Bags, Backpacks & Luggage > Backpacks & Laptop Bags > Laptop Sleeves & Cases | C15: Bags, Backpacks & Luggage | D15: Backpacks & Laptop Bags | E15: Laptop Sleeves & Cases | G15: 3 | H15: CL219256 | I15: 300 | J15: 265 | K15: 6. Backpacks & Bags | L15: =IF(OR(G15=3,G15=4),"Pass","Fail") -> Pass | M15: Pass | N15: =IF(I15>='Selection Criteria'!$C$25,"Pass","Fail") -> Pass | O15: Pass | P15: =IF(AND(L15="Pass",M15="Pass",N15="Pass",O15="Pass"),"Pass","Fail") -> Pass | Q15: =INDEX('Hero Segmentation'!$Q$5:$Q$80,MATCH($A15,'Hero Segmentation'!$A$5:$A$80,0)) -> Probable Hero | R15: 4 | S15: 4 | T15: 4 | U15: 5 | V15: 5 | W15: 3 | X15: 4 | Y15: 4 | Z15: =IF(P15="Pass",(R15*'Selection Criteria'!$F$13+S15*'Selection Criteria'!$F$14+T15*'Selection Criteria'!$F$15+U15*'Selection Criteria'!$F$16+V15*'Selection Criteria'!$F$17+W15*'Selection Criteria'!$F$18+X15*'Selection Criteria'!$F$19+Y15*'Selection Criteria'!$F$20)/(5*'Selection Criteria'!$F$21)*100,"-") -> 83 | AA15: =IF(AJ15<0,"-",COUNTIFS($Q$5:$Q$80,Q15,$AJ$5:$AJ$80,">"&AJ15)+1) -> 7 | AB15: =IF(P15<>"Pass","Parked (gate)",IF(AC15="PROTECT","Protect (control)",IF(AA15<=IF(Q15="Hero",'Hero Criteria'!$C$38,IF(Q15="Probable Hero",'Hero Criteria'!$C$39,'Hero Criteria'!$C$40)),"Recommended",IF(AA15<=IF(Q15="Hero",'Hero Criteria'!$C$38,IF(Q15="Probable Hero",'Hero Criteria'!$C$39,'Hero Criteria'!$C$40))+'Hero Criteria'!$C$41,"Reserve","Backlog")))) -> Recommended | AC15: =INDEX('Hero Segmentation'!$R$5:$R$80,MATCH($A15,'Hero Segmentation'!$A$5:$A$80,0)) -> BUILD | AD15: =IF(AND(AB15="Recommended",J15>='Selection Criteria'!$C$26),"Yes","") -> Yes | AE15: =IFERROR(INDEX('Primary Competitor Fit'!$D$5:$D$91,MATCH($A15&"|Primary 1",'Primary Competitor Fit'!$M$5:$M$91,0)),"-") -> Amazon | AF15: =IFERROR(INDEX('Primary Competitor Fit'!$D$5:$D$91,MATCH($A15&"|Primary 2",'Primary Competitor Fit'!$M$5:$M$91,0)),"-") -> Target | AG15: =IFERROR(INDEX('Secondary Competitor Fit'!$D$5:$D$98,MATCH($A15&"|Secondary 1",'Secondary Competitor Fit'!$M$5:$M$98,0)),"-") -> Bellroy | AH15: =IFERROR(INDEX('Secondary Competitor Fit'!$D$5:$D$98,MATCH($A15&"|Secondary 2",'Secondary Competitor Fit'!$M$5:$M$98,0)),"-") -> Urban Outfitters | AI15: Low-ticket attach to every laptop sale. | AJ15: =IF(AND(P15="Pass",AC15<>"PROTECT"),Z15+U15/100+R15/1000,-1) -> 83.054
A16: P12 | B16: Bags, Backpacks & Luggage > Briefcases & Padfolios > Totes & Handbags | C16: Bags, Backpacks & Luggage | D16: Briefcases & Padfolios | E16: Totes & Handbags | G16: 3 | H16: CL160451 | I16: 173 | J16: 166 | K16: 6. Backpacks & Bags | L16: =IF(OR(G16=3,G16=4),"Pass","Fail") -> Pass | M16: Pass | N16: =IF(I16>='Selection Criteria'!$C$25,"Pass","Fail") -> Pass | O16: Pass | P16: =IF(AND(L16="Pass",M16="Pass",N16="Pass",O16="Pass"),"Pass","Fail") -> Pass | Q16: =INDEX('Hero Segmentation'!$Q$5:$Q$80,MATCH($A16,'Hero Segmentation'!$A$5:$A$80,0)) -> Probable Hero | R16: 5 | S16: 5 | T16: 4 | U16: 4 | V16: 3 | W16: 3 | X16: 3 | Y16: 4 | Z16: =IF(P16="Pass",(R16*'Selection Criteria'!$F$13+S16*'Selection Criteria'!$F$14+T16*'Selection Criteria'!$F$15+U16*'Selection Criteria'!$F$16+V16*'Selection Criteria'!$F$17+W16*'Selection Criteria'!$F$18+X16*'Selection Criteria'!$F$19+Y16*'Selection Criteria'!$F$20)/(5*'Selection Criteria'!$F$21)*100,"-") -> 82 | AA16: =IF(AJ16<0,"-",COUNTIFS($Q$5:$Q$80,Q16,$AJ$5:$AJ$80,">"&AJ16)+1) -> 8 | AB16: =IF(P16<>"Pass","Parked (gate)",IF(AC16="PROTECT","Protect (control)",IF(AA16<=IF(Q16="Hero",'Hero Criteria'!$C$38,IF(Q16="Probable Hero",'Hero Criteria'!$C$39,'Hero Criteria'!$C$40)),"Recommended",IF(AA16<=IF(Q16="Hero",'Hero Criteria'!$C$38,IF(Q16="Probable Hero",'Hero Criteria'!$C$39,'Hero Criteria'!$C$40))+'Hero Criteria'!$C$41,"Reserve","Backlog")))) -> Reserve | AC16: =INDEX('Hero Segmentation'!$R$5:$R$80,MATCH($A16,'Hero Segmentation'!$A$5:$A$80,0)) -> BUILD | AD16: =IF(AND(AB16="Recommended",J16>='Selection Criteria'!$C$26),"Yes","") | AE16: =IFERROR(INDEX('Primary Competitor Fit'!$D$5:$D$91,MATCH($A16&"|Primary 1",'Primary Competitor Fit'!$M$5:$M$91,0)),"-") -> Amazon | AF16: =IFERROR(INDEX('Primary Competitor Fit'!$D$5:$D$91,MATCH($A16&"|Primary 2",'Primary Competitor Fit'!$M$5:$M$91,0)),"-") -> Target | AG16: =IFERROR(INDEX('Secondary Competitor Fit'!$D$5:$D$98,MATCH($A16&"|Secondary 1",'Secondary Competitor Fit'!$M$5:$M$98,0)),"-") -> Bellroy | AH16: =IFERROR(INDEX('Secondary Competitor Fit'!$D$5:$D$98,MATCH($A16&"|Secondary 2",'Secondary Competitor Fit'!$M$5:$M$98,0)),"-") -> Nordstrom | AI16: Lifestyle version of the briefcase. | AJ16: =IF(AND(P16="Pass",AC16<>"PROTECT"),Z16+U16/100+R16/1000,-1) -> 82.045
A17: P13 | B17: Furniture > Desks > Office Desks | C17: Furniture | D17: Desks | E17: Office Desks | G17: 3 | H17: CL210795 | I17: 1501 | J17: 1265 | K17: 2. Desks | L17: =IF(OR(G17=3,G17=4),"Pass","Fail") -> Pass | M17: Pass | N17: =IF(I17>='Selection Criteria'!$C$25,"Pass","Fail") -> Pass | O17: Pass | P17: =IF(AND(L17="Pass",M17="Pass",N17="Pass",O17="Pass"),"Pass","Fail") -> Pass | Q17: =INDEX('Hero Segmentation'!$Q$5:$Q$80,MATCH($A17,'Hero Segmentation'!$A$5:$A$80,0)) -> Hero | R17: 4 | S17: 5 | T17: 3 | U17: 5 | V17: 1 | W17: 5 | X17: 4 | Y17: 5 | Z17: =IF(P17="Pass",(R17*'Selection Criteria'!$F$13+S17*'Selection Criteria'!$F$14+T17*'Selection Criteria'!$F$15+U17*'Selection Criteria'!$F$16+V17*'Selection Criteria'!$F$17+W17*'Selection Criteria'!$F$18+X17*'Selection Criteria'!$F$19+Y17*'Selection Criteria'!$F$20)/(5*'Selection Criteria'!$F$21)*100,"-") -> 81 | AA17: =IF(AJ17<0,"-",COUNTIFS($Q$5:$Q$80,Q17,$AJ$5:$AJ$80,">"&AJ17)+1) -> 5 | AB17: =IF(P17<>"Pass","Parked (gate)",IF(AC17="PROTECT","Protect (control)",IF(AA17<=IF(Q17="Hero",'Hero Criteria'!$C$38,IF(Q17="Probable Hero",'Hero Criteria'!$C$39,'Hero Criteria'!$C$40)),"Recommended",IF(AA17<=IF(Q17="Hero",'Hero Criteria'!$C$38,IF(Q17="Probable Hero",'Hero Criteria'!$C$39,'Hero Criteria'!$C$40))+'Hero Criteria'!$C$41,"Reserve","Backlog")))) -> Recommended | AC17: =INDEX('Hero Segmentation'!$R$5:$R$80,MATCH($A17,'Hero Segmentation'!$A$5:$A$80,0)) -> EXTEND | AD17: =IF(AND(AB17="Recommended",J17>='Selection Criteria'!$C$26),"Yes","") -> Yes | AE17: =IFERROR(INDEX('Primary Competitor Fit'!$D$5:$D$91,MATCH($A17&"|Primary 1",'Primary Competitor Fit'!$M$5:$M$91,0)),"-") -> Wayfair | AF17: =IFERROR(INDEX('Primary Competitor Fit'!$D$5:$D$91,MATCH($A17&"|Primary 2",'Primary Competitor Fit'!$M$5:$M$91,0)),"-") -> Amazon | AG17: =IFERROR(INDEX('Secondary Competitor Fit'!$D$5:$D$98,MATCH($A17&"|Secondary 1",'Secondary Competitor Fit'!$M$5:$M$98,0)),"-") -> Design Within Reach | AH17: =IFERROR(INDEX('Secondary Competitor Fit'!$D$5:$D$98,MATCH($A17&"|Secondary 2",'Secondary Competitor Fit'!$M$5:$M$98,0)),"-") -> West Elm | AI17: 1,501 items; pilot Computer split: 3 recs (1 Strong). Split by Staples' own type facet. | AJ17: =IF(AND(P17="Pass",AC17<>"PROTECT"),Z17+U17/100+R17/1000,-1) -> 81.054
A18: P14 | B18: Office Supplies > Notebooks & Notepads > Journals & Diaries | C18: Office Supplies | D18: Notebooks & Notepads | E18: Journals & Diaries | G18: 3 | H18: CL166390 | I18: 253 | J18: 0 | K18: 9. Planning & Craft Organization | L18: =IF(OR(G18=3,G18=4),"Pass","Fail") -> Pass | M18: Pass | N18: =IF(I18>='Selection Criteria'!$C$25,"Pass","Fail") -> Pass | O18: Pass | P18: =IF(AND(L18="Pass",M18="Pass",N18="Pass",O18="Pass"),"Pass","Fail") -> Pass | Q18: =INDEX('Hero Segmentation'!$Q$5:$Q$80,MATCH($A18,'Hero Segmentation'!$A$5:$A$80,0)) -> Probable Hero | R18: 5 | S18: 4 | T18: 4 | U18: 4 | V18: 5 | W18: 3 | X18: 4 | Y18: 2 | Z18: =IF(P18="Pass",(R18*'Selection Criteria'!$F$13+S18*'Selection Criteria'!$F$14+T18*'Selection Criteria'!$F$15+U18*'Selection Criteria'!$F$16+V18*'Selection Criteria'!$F$17+W18*'Selection Criteria'!$F$18+X18*'Selection Criteria'!$F$19+Y18*'Selection Criteria'!$F$20)/(5*'Selection Criteria'!$F$21)*100,"-") -> 80 | AA18: =IF(AJ18<0,"-",COUNTIFS($Q$5:$Q$80,Q18,$AJ$5:$AJ$80,">"&AJ18)+1) -> 9 | AB18: =IF(P18<>"Pass","Parked (gate)",IF(AC18="PROTECT","Protect (control)",IF(AA18<=IF(Q18="Hero",'Hero Criteria'!$C$38,IF(Q18="Probable Hero",'Hero Criteria'!$C$39,'Hero Criteria'!$C$40)),"Recommended",IF(AA18<=IF(Q18="Hero",'Hero Criteria'!$C$38,IF(Q18="Probable Hero",'Hero Criteria'!$C$39,'Hero Criteria'!$C$40))+'Hero Criteria'!$C$41,"Reserve","Backlog")))) -> Reserve | AC18: =INDEX('Hero Segmentation'!$R$5:$R$80,MATCH($A18,'Hero Segmentation'!$A$5:$A$80,0)) -> BUILD | AD18: =IF(AND(AB18="Recommended",J18>='Selection Criteria'!$C$26),"Yes","") | AE18: =IFERROR(INDEX('Primary Competitor Fit'!$D$5:$D$91,MATCH($A18&"|Primary 1",'Primary Competitor Fit'!$M$5:$M$91,0)),"-") -> Amazon | AF18: =IFERROR(INDEX('Primary Competitor Fit'!$D$5:$D$91,MATCH($A18&"|Primary 2",'Primary Competitor Fit'!$M$5:$M$91,0)),"-") -> Target | AG18: =IFERROR(INDEX('Secondary Competitor Fit'!$D$5:$D$98,MATCH($A18&"|Secondary 1",'Secondary Competitor Fit'!$M$5:$M$98,0)),"-") -> JetPens | AH18: =IFERROR(INDEX('Secondary Competitor Fit'!$D$5:$D$98,MATCH($A18&"|Secondary 2",'Secondary Competitor Fit'!$M$5:$M$98,0)),"-") -> Kinokuniya | AI18: Gen-Z journaling habit; pairs with planners. | AJ18: =IF(AND(P18="Pass",AC18<>"PROTECT"),Z18+U18/100+R18/1000,-1) -> 80.045
A19: P15 | B19: Furniture > Decor > Artificial Plants & Flowers > Artificial Plants | C19: Furniture | D19: Decor | E19: Artificial Plants & Flowers | F19: Artificial Plants | G19: 4 | H19: CL355087 | I19: 203 | J19: 0 | K19: New | L19: =IF(OR(G19=3,G19=4),"Pass","Fail") -> Pass | M19: Pass | N19: =IF(I19>='Selection Criteria'!$C$25,"Pass","Fail") -> Pass | O19: Pass | P19: =IF(AND(L19="Pass",M19="Pass",N19="Pass",O19="Pass"),"Pass","Fail") -> Pass | Q19: =INDEX('Hero Segmentation'!$Q$5:$Q$80,MATCH($A19,'Hero Segmentation'!$A$5:$A$80,0)) -> Probable Hero | R19: 5 | S19: 5 | T19: 5 | U19: 3 | V19: 4 | W19: 3 | X19: 3 | Y19: 2 | Z19: =IF(P19="Pass",(R19*'Selection Criteria'!$F$13+S19*'Selection Criteria'!$F$14+T19*'Selection Criteria'!$F$15+U19*'Selection Criteria'!$F$16+V19*'Selection Criteria'!$F$17+W19*'Selection Criteria'!$F$18+X19*'Selection Criteria'!$F$19+Y19*'Selection Criteria'!$F$20)/(5*'Selection Criteria'!$F$21)*100,"-") -> 80 | AA19: =IF(AJ19<0,"-",COUNTIFS($Q$5:$Q$80,Q19,$AJ$5:$AJ$80,">"&AJ19)+1) -> 10 | AB19: =IF(P19<>"Pass","Parked (gate)",IF(AC19="PROTECT","Protect (control)",IF(AA19<=IF(Q19="Hero",'Hero Criteria'!$C$38,IF(Q19="Probable Hero",'Hero Criteria'!$C$39,'Hero Criteria'!$C$40)),"Recommended",IF(AA19<=IF(Q19="Hero",'Hero Criteria'!$C$38,IF(Q19="Probable Hero",'Hero Criteria'!$C$39,'Hero Criteria'!$C$40))+'Hero Criteria'!$C$41,"Reserve","Backlog")))) -> Reserve | AC19: =INDEX('Hero Segmentation'!$R$5:$R$80,MATCH($A19,'Hero Segmentation'!$A$5:$A$80,0)) -> BUILD | AD19: =IF(AND(AB19="Recommended",J19>='Selection Criteria'!$C$26),"Yes","") | AE19: =IFERROR(INDEX('Primary Competitor Fit'!$D$5:$D$91,MATCH($A19&"|Primary 1",'Primary Competitor Fit'!$M$5:$M$91,0)),"-") -> Wayfair | AF19: =IFERROR(INDEX('Primary Competitor Fit'!$D$5:$D$91,MATCH($A19&"|Primary 2",'Primary Competitor Fit'!$M$5:$M$91,0)),"-") -> Amazon | AG19: =IFERROR(INDEX('Secondary Competitor Fit'!$D$5:$D$98,MATCH($A19&"|Secondary 1",'Secondary Competitor Fit'!$M$5:$M$98,0)),"-") -> Michaels | AH19: =IFERROR(INDEX('Secondary Competitor Fit'!$D$5:$D$98,MATCH($A19&"|Secondary 2",'Secondary Competitor Fit'!$M$5:$M$98,0)),"-") -> Anthropologie | AI19: Biophilic / resimercial office default. | AJ19: =IF(AND(P19="Pass",AC19<>"PROTECT"),Z19+U19/100+R19/1000,-1) -> 80.035
A20: P16 | B20: Office Supplies > Tape, Fasteners & Adhesives > Tape > Arts & Crafts Tape | C20: Office Supplies | D20: Tape, Fasteners & Adhesives | E20: Tape | F20: Arts & Crafts Tape | G20: 4 | H20: CL215702 | I20: 32 | J20: 0 | K20: 9. Planning & Craft Organization | L20: =IF(OR(G20=3,G20=4),"Pass","Fail") -> Pass | M20: Pass | N20: =IF(I20>='Selection Criteria'!$C$25,"Pass","Fail") -> Pass | O20: Pass | P20: =IF(AND(L20="Pass",M20="Pass",N20="Pass",O20="Pass"),"Pass","Fail") -> Pass | Q20: =INDEX('Hero Segmentation'!$Q$5:$Q$80,MATCH($A20,'Hero Segmentation'!$A$5:$A$80,0)) -> Probable Hero | R20: 5 | S20: 5 | T20: 5 | U20: 3 | V20: 5 | W20: 2 | X20: 3 | Y20: 1 | Z20: =IF(P20="Pass",(R20*'Selection Criteria'!$F$13+S20*'Selection Criteria'!$F$14+T20*'Selection Criteria'!$F$15+U20*'Selection Criteria'!$F$16+V20*'Selection Criteria'!$F$17+W20*'Selection Criteria'!$F$18+X20*'Selection Criteria'!$F$19+Y20*'Selection Criteria'!$F$20)/(5*'Selection Criteria'!$F$21)*100,"-") -> 78 | AA20: =IF(AJ20<0,"-",COUNTIFS($Q$5:$Q$80,Q20,$AJ$5:$AJ$80,">"&AJ20)+1) -> 12 | AB20: =IF(P20<>"Pass","Parked (gate)",IF(AC20="PROTECT","Protect (control)",IF(AA20<=IF(Q20="Hero",'Hero Criteria'!$C$38,IF(Q20="Probable Hero",'Hero Criteria'!$C$39,'Hero Criteria'!$C$40)),"Recommended",IF(AA20<=IF(Q20="Hero",'Hero Criteria'!$C$38,IF(Q20="Probable Hero",'Hero Criteria'!$C$39,'Hero Criteria'!$C$40))+'Hero Criteria'!$C$41,"Reserve","Backlog")))) -> Backlog | AC20: =INDEX('Hero Segmentation'!$R$5:$R$80,MATCH($A20,'Hero Segmentation'!$A$5:$A$80,0)) -> BUILD | AD20: =IF(AND(AB20="Recommended",J20>='Selection Criteria'!$C$26),"Yes","") | AE20: =IFERROR(INDEX('Primary Competitor Fit'!$D$5:$D$91,MATCH($A20&"|Primary 1",'Primary Competitor Fit'!$M$5:$M$91,0)),"-") -> - | AF20: =IFERROR(INDEX('Primary Competitor Fit'!$D$5:$D$91,MATCH($A20&"|Primary 2",'Primary Competitor Fit'!$M$5:$M$91,0)),"-") -> - | AG20: =IFERROR(INDEX('Secondary Competitor Fit'!$D$5:$D$98,MATCH($A20&"|Secondary 1",'Secondary Competitor Fit'!$M$5:$M$98,0)),"-") -> - | AH20: =IFERROR(INDEX('Secondary Competitor Fit'!$D$5:$D$98,MATCH($A20&"|Secondary 2",'Secondary Competitor Fit'!$M$5:$M$98,0)),"-") -> - | AI20: Only 32 Staples items: near-pure whitespace, tiny ticket. | AJ20: =IF(AND(P20="Pass",AC20<>"PROTECT"),Z20+U20/100+R20/1000,-1) -> 78.035
A21: P17 | B21: Arts & Crafts > Scrapbooking > Stickers & Embellishments | C21: Arts & Crafts | D21: Scrapbooking | E21: Stickers & Embellishments | G21: 3 | H21: CL167442 | I21: 166 | J21: 0 | K21: 9. Planning & Craft Organization | L21: =IF(OR(G21=3,G21=4),"Pass","Fail") -> Pass | M21: Pass | N21: =IF(I21>='Selection Criteria'!$C$25,"Pass","Fail") -> Pass | O21: Pass | P21: =IF(AND(L21="Pass",M21="Pass",N21="Pass",O21="Pass"),"Pass","Fail") -> Pass | Q21: =INDEX('Hero Segmentation'!$Q$5:$Q$80,MATCH($A21,'Hero Segmentation'!$A$5:$A$80,0)) -> Probable Hero | R21: 5 | S21: 5 | T21: 5 | U21: 3 | V21: 5 | W21: 2 | X21: 3 | Y21: 1 | Z21: =IF(P21="Pass",(R21*'Selection Criteria'!$F$13+S21*'Selection Criteria'!$F$14+T21*'Selection Criteria'!$F$15+U21*'Selection Criteria'!$F$16+V21*'Selection Criteria'!$F$17+W21*'Selection Criteria'!$F$18+X21*'Selection Criteria'!$F$19+Y21*'Selection Criteria'!$F$20)/(5*'Selection Criteria'!$F$21)*100,"-") -> 78 | AA21: =IF(AJ21<0,"-",COUNTIFS($Q$5:$Q$80,Q21,$AJ$5:$AJ$80,">"&AJ21)+1) -> 12 | AB21: =IF(P21<>"Pass","Parked (gate)",IF(AC21="PROTECT","Protect (control)",IF(AA21<=IF(Q21="Hero",'Hero Criteria'!$C$38,IF(Q21="Probable Hero",'Hero Criteria'!$C$39,'Hero Criteria'!$C$40)),"Recommended",IF(AA21<=IF(Q21="Hero",'Hero Criteria'!$C$38,IF(Q21="Probable Hero",'Hero Criteria'!$C$39,'Hero Criteria'!$C$40))+'Hero Criteria'!$C$41,"Reserve","Backlog")))) -> Backlog | AC21: =INDEX('Hero Segmentation'!$R$5:$R$80,MATCH($A21,'Hero Segmentation'!$A$5:$A$80,0)) -> BUILD | AD21: =IF(AND(AB21="Recommended",J21>='Selection Criteria'!$C$26),"Yes","") | AE21: =IFERROR(INDEX('Primary Competitor Fit'!$D$5:$D$91,MATCH($A21&"|Primary 1",'Primary Competitor Fit'!$M$5:$M$91,0)),"-") -> - | AF21: =IFERROR(INDEX('Primary Competitor Fit'!$D$5:$D$91,MATCH($A21&"|Primary 2",'Primary Competitor Fit'!$M$5:$M$91,0)),"-") -> - | AG21: =IFERROR(INDEX('Secondary Competitor Fit'!$D$5:$D$98,MATCH($A21&"|Secondary 1",'Secondary Competitor Fit'!$M$5:$M$98,0)),"-") -> - | AH21: =IFERROR(INDEX('Secondary Competitor Fit'!$D$5:$D$98,MATCH($A21&"|Secondary 2",'Secondary Competitor Fit'!$M$5:$M$98,0)),"-") -> - | AI21: Planner-companion consumable = repeat commission. | AJ21: =IF(AND(P21="Pass",AC21<>"PROTECT"),Z21+U21/100+R21/1000,-1) -> 78.035
A22: P18 | B22: Computers & Accessories > Computer Accessories & Peripherals > Mouse Pads & Wrist Rests | C22: Computers & Accessories | D22: Computer Accessories & Peripherals | E22: Mouse Pads & Wrist Rests | G22: 3 | H22: CL141474 | I22: 318 | J22: 0 | K22: New | L22: =IF(OR(G22=3,G22=4),"Pass","Fail") -> Pass | M22: Pass | N22: =IF(I22>='Selection Criteria'!$C$25,"Pass","Fail") -> Pass | O22: Pass | P22: =IF(AND(L22="Pass",M22="Pass",N22="Pass",O22="Pass"),"Pass","Fail") -> Pass | Q22: =INDEX('Hero Segmentation'!$Q$5:$Q$80,MATCH($A22,'Hero Segmentation'!$A$5:$A$80,0)) -> Probable Hero | R22: 4 | S22: 4 | T22: 4 | U22: 5 | V22: 5 | W22: 3 | X22: 3 | Y22: 2 | Z22: =IF(P22="Pass",(R22*'Selection Criteria'!$F$13+S22*'Selection Criteria'!$F$14+T22*'Selection Criteria'!$F$15+U22*'Selection Criteria'!$F$16+V22*'Selection Criteria'!$F$17+W22*'Selection Criteria'!$F$18+X22*'Selection Criteria'!$F$19+Y22*'Selection Criteria'!$F$20)/(5*'Selection Criteria'!$F$21)*100,"-") -> 78 | AA22: =IF(AJ22<0,"-",COUNTIFS($Q$5:$Q$80,Q22,$AJ$5:$AJ$80,">"&AJ22)+1) -> 11 | AB22: =IF(P22<>"Pass","Parked (gate)",IF(AC22="PROTECT","Protect (control)",IF(AA22<=IF(Q22="Hero",'Hero Criteria'!$C$38,IF(Q22="Probable Hero",'Hero Criteria'!$C$39,'Hero Criteria'!$C$40)),"Recommended",IF(AA22<=IF(Q22="Hero",'Hero Criteria'!$C$38,IF(Q22="Probable Hero",'Hero Criteria'!$C$39,'Hero Criteria'!$C$40))+'Hero Criteria'!$C$41,"Reserve","Backlog")))) -> Backlog | AC22: =INDEX('Hero Segmentation'!$R$5:$R$80,MATCH($A22,'Hero Segmentation'!$A$5:$A$80,0)) -> BUILD | AD22: =IF(AND(AB22="Recommended",J22>='Selection Criteria'!$C$26),"Yes","") | AE22: =IFERROR(INDEX('Primary Competitor Fit'!$D$5:$D$91,MATCH($A22&"|Primary 1",'Primary Competitor Fit'!$M$5:$M$91,0)),"-") -> - | AF22: =IFERROR(INDEX('Primary Competitor Fit'!$D$5:$D$91,MATCH($A22&"|Primary 2",'Primary Competitor Fit'!$M$5:$M$91,0)),"-") -> - | AG22: =IFERROR(INDEX('Secondary Competitor Fit'!$D$5:$D$98,MATCH($A22&"|Secondary 1",'Secondary Competitor Fit'!$M$5:$M$98,0)),"-") -> - | AH22: =IFERROR(INDEX('Secondary Competitor Fit'!$D$5:$D$98,MATCH($A22&"|Secondary 2",'Secondary Competitor Fit'!$M$5:$M$98,0)),"-") -> - | AI22: Desk mat is now a decor object; gel wrist rests are core. | AJ22: =IF(AND(P22="Pass",AC22<>"PROTECT"),Z22+U22/100+R22/1000,-1) -> 78.054
A23: P19 | B23: Furniture > Boards & Easels > Bulletin Boards | C23: Furniture | D23: Boards & Easels | E23: Bulletin Boards | G23: 3 | H23: CL142403 | I23: 284 | J23: 0 | K23: New | L23: =IF(OR(G23=3,G23=4),"Pass","Fail") -> Pass | M23: Pass | N23: =IF(I23>='Selection Criteria'!$C$25,"Pass","Fail") -> Pass | O23: Pass | P23: =IF(AND(L23="Pass",M23="Pass",N23="Pass",O23="Pass"),"Pass","Fail") -> Pass | Q23: =INDEX('Hero Segmentation'!$Q$5:$Q$80,MATCH($A23,'Hero Segmentation'!$A$5:$A$80,0)) -> Hero | R23: 4 | S23: 4 | T23: 4 | U23: 5 | V23: 4 | W23: 3 | X23: 4 | Y23: 2 | Z23: =IF(P23="Pass",(R23*'Selection Criteria'!$F$13+S23*'Selection Criteria'!$F$14+T23*'Selection Criteria'!$F$15+U23*'Selection Criteria'!$F$16+V23*'Selection Criteria'!$F$17+W23*'Selection Criteria'!$F$18+X23*'Selection Criteria'!$F$19+Y23*'Selection Criteria'!$F$20)/(5*'Selection Criteria'!$F$21)*100,"-") -> 77 | AA23: =IF(AJ23<0,"-",COUNTIFS($Q$5:$Q$80,Q23,$AJ$5:$AJ$80,">"&AJ23)+1) -> 6 | AB23: =IF(P23<>"Pass","Parked (gate)",IF(AC23="PROTECT","Protect (control)",IF(AA23<=IF(Q23="Hero",'Hero Criteria'!$C$38,IF(Q23="Probable Hero",'Hero Criteria'!$C$39,'Hero Criteria'!$C$40)),"Recommended",IF(AA23<=IF(Q23="Hero",'Hero Criteria'!$C$38,IF(Q23="Probable Hero",'Hero Criteria'!$C$39,'Hero Criteria'!$C$40))+'Hero Criteria'!$C$41,"Reserve","Backlog")))) -> Recommended | AC23: =INDEX('Hero Segmentation'!$R$5:$R$80,MATCH($A23,'Hero Segmentation'!$A$5:$A$80,0)) -> EXTEND | AD23: =IF(AND(AB23="Recommended",J23>='Selection Criteria'!$C$26),"Yes","") | AE23: =IFERROR(INDEX('Primary Competitor Fit'!$D$5:$D$91,MATCH($A23&"|Primary 1",'Primary Competitor Fit'!$M$5:$M$91,0)),"-") -> Amazon | AF23: =IFERROR(INDEX('Primary Competitor Fit'!$D$5:$D$91,MATCH($A23&"|Primary 2",'Primary Competitor Fit'!$M$5:$M$91,0)),"-") -> Wayfair | AG23: =IFERROR(INDEX('Secondary Competitor Fit'!$D$5:$D$98,MATCH($A23&"|Secondary 1",'Secondary Competitor Fit'!$M$5:$M$98,0)),"-") -> Etsy | AH23: =IFERROR(INDEX('Secondary Competitor Fit'!$D$5:$D$98,MATCH($A23&"|Secondary 2",'Secondary Competitor Fit'!$M$5:$M$98,0)),"-") -> Pottery Barn Teen | AI23: Letter/felt/fabric memo boards vs cork utility. | AJ23: =IF(AND(P23="Pass",AC23<>"PROTECT"),Z23+U23/100+R23/1000,-1) -> 77.054
A24: P20 | B24: Furniture > Decor > Clocks & Timers | C24: Furniture | D24: Decor | E24: Clocks & Timers | G24: 3 | H24: CL161533 | I24: 229 | J24: 0 | K24: New | L24: =IF(OR(G24=3,G24=4),"Pass","Fail") -> Pass | M24: Pass | N24: =IF(I24>='Selection Criteria'!$C$25,"Pass","Fail") -> Pass | O24: Pass | P24: =IF(AND(L24="Pass",M24="Pass",N24="Pass",O24="Pass"),"Pass","Fail") -> Pass | Q24: =INDEX('Hero Segmentation'!$Q$5:$Q$80,MATCH($A24,'Hero Segmentation'!$A$5:$A$80,0)) -> Non-Hero | R24: 5 | S24: 5 | T24: 4 | U24: 4 | V24: 4 | W24: 2 | X24: 2 | Y24: 2 | Z24: =IF(P24="Pass",(R24*'Selection Criteria'!$F$13+S24*'Selection Criteria'!$F$14+T24*'Selection Criteria'!$F$15+U24*'Selection Criteria'!$F$16+V24*'Selection Criteria'!$F$17+W24*'Selection Criteria'!$F$18+X24*'Selection Criteria'!$F$19+Y24*'Selection Criteria'!$F$20)/(5*'Selection Criteria'!$F$21)*100,"-") -> 77 | AA24: =IF(AJ24<0,"-",COUNTIFS($Q$5:$Q$80,Q24,$AJ$5:$AJ$80,">"&AJ24)+1) -> 1 | AB24: =IF(P24<>"Pass","Parked (gate)",IF(AC24="PROTECT","Protect (control)",IF(AA24<=IF(Q24="Hero",'Hero Criteria'!$C$38,IF(Q24="Probable Hero",'Hero Criteria'!$C$39,'Hero Criteria'!$C$40)),"Recommended",IF(AA24<=IF(Q24="Hero",'Hero Criteria'!$C$38,IF(Q24="Probable Hero",'Hero Criteria'!$C$39,'Hero Criteria'!$C$40))+'Hero Criteria'!$C$41,"Reserve","Backlog")))) -> Recommended | AC24: =INDEX('Hero Segmentation'!$R$5:$R$80,MATCH($A24,'Hero Segmentation'!$A$5:$A$80,0)) -> EXPLORE | AD24: =IF(AND(AB24="Recommended",J24>='Selection Criteria'!$C$26),"Yes","") | AE24: =IFERROR(INDEX('Primary Competitor Fit'!$D$5:$D$91,MATCH($A24&"|Primary 1",'Primary Competitor Fit'!$M$5:$M$91,0)),"-") -> Wayfair | AF24: =IFERROR(INDEX('Primary Competitor Fit'!$D$5:$D$91,MATCH($A24&"|Primary 2",'Primary Competitor Fit'!$M$5:$M$91,0)),"-") -> Amazon | AG24: =IFERROR(INDEX('Secondary Competitor Fit'!$D$5:$D$98,MATCH($A24&"|Secondary 1",'Secondary Competitor Fit'!$M$5:$M$98,0)),"-") -> Schoolhouse | AH24: =IFERROR(INDEX('Secondary Competitor Fit'!$D$5:$D$98,MATCH($A24&"|Secondary 2",'Secondary Competitor Fit'!$M$5:$M$98,0)),"-") -> Anthropologie | AI24: Wayfair runs a whole Clocks department. | AJ24: =IF(AND(P24="Pass",AC24<>"PROTECT"),Z24+U24/100+R24/1000,-1) -> 77.045
A25: P21 | B25: Furniture > Decor > Picture Frames & Photo Albums | C25: Furniture | D25: Decor | E25: Picture Frames & Photo Albums | G25: 3 | H25: CL161523 | I25: 435 | J25: 0 | K25: New | L25: =IF(OR(G25=3,G25=4),"Pass","Fail") -> Pass | M25: Pass | N25: =IF(I25>='Selection Criteria'!$C$25,"Pass","Fail") -> Pass | O25: Pass | P25: =IF(AND(L25="Pass",M25="Pass",N25="Pass",O25="Pass"),"Pass","Fail") -> Pass | Q25: =INDEX('Hero Segmentation'!$Q$5:$Q$80,MATCH($A25,'Hero Segmentation'!$A$5:$A$80,0)) -> Probable Hero | R25: 5 | S25: 5 | T25: 4 | U25: 3 | V25: 4 | W25: 3 | X25: 3 | Y25: 2 | Z25: =IF(P25="Pass",(R25*'Selection Criteria'!$F$13+S25*'Selection Criteria'!$F$14+T25*'Selection Criteria'!$F$15+U25*'Selection Criteria'!$F$16+V25*'Selection Criteria'!$F$17+W25*'Selection Criteria'!$F$18+X25*'Selection Criteria'!$F$19+Y25*'Selection Criteria'!$F$20)/(5*'Selection Criteria'!$F$21)*100,"-") -> 77 | AA25: =IF(AJ25<0,"-",COUNTIFS($Q$5:$Q$80,Q25,$AJ$5:$AJ$80,">"&AJ25)+1) -> 15 | AB25: =IF(P25<>"Pass","Parked (gate)",IF(AC25="PROTECT","Protect (control)",IF(AA25<=IF(Q25="Hero",'Hero Criteria'!$C$38,IF(Q25="Probable Hero",'Hero Criteria'!$C$39,'Hero Criteria'!$C$40)),"Recommended",IF(AA25<=IF(Q25="Hero",'Hero Criteria'!$C$38,IF(Q25="Probable Hero",'Hero Criteria'!$C$39,'Hero Criteria'!$C$40))+'Hero Criteria'!$C$41,"Reserve","Backlog")))) -> Backlog | AC25: =INDEX('Hero Segmentation'!$R$5:$R$80,MATCH($A25,'Hero Segmentation'!$A$5:$A$80,0)) -> BUILD | AD25: =IF(AND(AB25="Recommended",J25>='Selection Criteria'!$C$26),"Yes","") | AE25: =IFERROR(INDEX('Primary Competitor Fit'!$D$5:$D$91,MATCH($A25&"|Primary 1",'Primary Competitor Fit'!$M$5:$M$91,0)),"-") -> - | AF25: =IFERROR(INDEX('Primary Competitor Fit'!$D$5:$D$91,MATCH($A25&"|Primary 2",'Primary Competitor Fit'!$M$5:$M$91,0)),"-") -> - | AG25: =IFERROR(INDEX('Secondary Competitor Fit'!$D$5:$D$98,MATCH($A25&"|Secondary 1",'Secondary Competitor Fit'!$M$5:$M$98,0)),"-") -> - | AH25: =IFERROR(INDEX('Secondary Competitor Fit'!$D$5:$D$98,MATCH($A25&"|Secondary 2",'Secondary Competitor Fit'!$M$5:$M$98,0)),"-") -> - | AI25: Examples doc already names Michaels on framing. | AJ25: =IF(AND(P25="Pass",AC25<>"PROTECT"),Z25+U25/100+R25/1000,-1) -> 77.035
A26: P22 | B26: Retail Store Supplies > Retail Packaging > Retail Boxes & Bags | C26: Retail Store Supplies | D26: Retail Packaging | E26: Retail Boxes & Bags | G26: 3 | H26: CL167951 | I26: 99 | J26: 98 | K26: 8. Labels & Packaging Accessories | L26: =IF(OR(G26=3,G26=4),"Pass","Fail") -> Pass | M26: Pass | N26: =IF(I26>='Selection Criteria'!$C$25,"Pass","Fail") -> Pass | O26: Pass | P26: =IF(AND(L26="Pass",M26="Pass",N26="Pass",O26="Pass"),"Pass","Fail") -> Pass | Q26: =INDEX('Hero Segmentation'!$Q$5:$Q$80,MATCH($A26,'Hero Segmentation'!$A$5:$A$80,0)) -> Probable Hero | R26: 4 | S26: 4 | T26: 4 | U26: 4 | V26: 4 | W26: 3 | X26: 3 | Y26: 4 | Z26: =IF(P26="Pass",(R26*'Selection Criteria'!$F$13+S26*'Selection Criteria'!$F$14+T26*'Selection Criteria'!$F$15+U26*'Selection Criteria'!$F$16+V26*'Selection Criteria'!$F$17+W26*'Selection Criteria'!$F$18+X26*'Selection Criteria'!$F$19+Y26*'Selection Criteria'!$F$20)/(5*'Selection Criteria'!$F$21)*100,"-") -> 77 | AA26: =IF(AJ26<0,"-",COUNTIFS($Q$5:$Q$80,Q26,$AJ$5:$AJ$80,">"&AJ26)+1) -> 14 | AB26: =IF(P26<>"Pass","Parked (gate)",IF(AC26="PROTECT","Protect (control)",IF(AA26<=IF(Q26="Hero",'Hero Criteria'!$C$38,IF(Q26="Probable Hero",'Hero Criteria'!$C$39,'Hero Criteria'!$C$40)),"Recommended",IF(AA26<=IF(Q26="Hero",'Hero Criteria'!$C$38,IF(Q26="Probable Hero",'Hero Criteria'!$C$39,'Hero Criteria'!$C$40))+'Hero Criteria'!$C$41,"Reserve","Backlog")))) -> Backlog | AC26: =INDEX('Hero Segmentation'!$R$5:$R$80,MATCH($A26,'Hero Segmentation'!$A$5:$A$80,0)) -> BUILD | AD26: =IF(AND(AB26="Recommended",J26>='Selection Criteria'!$C$26),"Yes","") | AE26: =IFERROR(INDEX('Primary Competitor Fit'!$D$5:$D$91,MATCH($A26&"|Primary 1",'Primary Competitor Fit'!$M$5:$M$91,0)),"-") -> - | AF26: =IFERROR(INDEX('Primary Competitor Fit'!$D$5:$D$91,MATCH($A26&"|Primary 2",'Primary Competitor Fit'!$M$5:$M$91,0)),"-") -> - | AG26: =IFERROR(INDEX('Secondary Competitor Fit'!$D$5:$D$98,MATCH($A26&"|Secondary 1",'Secondary Competitor Fit'!$M$5:$M$98,0)),"-") -> - | AH26: =IFERROR(INDEX('Secondary Competitor Fit'!$D$5:$D$98,MATCH($A26&"|Secondary 2",'Secondary Competitor Fit'!$M$5:$M$98,0)),"-") -> - | AI26: Boutique packaging for small sellers: Staples' core SMB customer. | AJ26: =IF(AND(P26="Pass",AC26<>"PROTECT"),Z26+U26/100+R26/1000,-1) -> 77.044
A27: P23 | B27: Office Supplies > Desk Organizers & Accessories > Desk Pads | C27: Office Supplies | D27: Desk Organizers & Accessories | E27: Desk Pads | G27: 3 | H27: CL140589 | I27: 82 | J27: 0 | K27: New | L27: =IF(OR(G27=3,G27=4),"Pass","Fail") -> Pass | M27: Pass | N27: =IF(I27>='Selection Criteria'!$C$25,"Pass","Fail") -> Pass | O27: Pass | P27: =IF(AND(L27="Pass",M27="Pass",N27="Pass",O27="Pass"),"Pass","Fail") -> Pass | Q27: =INDEX('Hero Segmentation'!$Q$5:$Q$80,MATCH($A27,'Hero Segmentation'!$A$5:$A$80,0)) -> Non-Hero | R27: 4 | S27: 4 | T27: 4 | U27: 5 | V27: 4 | W27: 3 | X27: 3 | Y27: 2 | Z27: =IF(P27="Pass",(R27*'Selection Criteria'!$F$13+S27*'Selection Criteria'!$F$14+T27*'Selection Criteria'!$F$15+U27*'Selection Criteria'!$F$16+V27*'Selection Criteria'!$F$17+W27*'Selection Criteria'!$F$18+X27*'Selection Criteria'!$F$19+Y27*'Selection Criteria'!$F$20)/(5*'Selection Criteria'!$F$21)*100,"-") -> 76 | AA27: =IF(AJ27<0,"-",COUNTIFS($Q$5:$Q$80,Q27,$AJ$5:$AJ$80,">"&AJ27)+1) -> 2 | AB27: =IF(P27<>"Pass","Parked (gate)",IF(AC27="PROTECT","Protect (control)",IF(AA27<=IF(Q27="Hero",'Hero Criteria'!$C$38,IF(Q27="Probable Hero",'Hero Criteria'!$C$39,'Hero Criteria'!$C$40)),"Recommended",IF(AA27<=IF(Q27="Hero",'Hero Criteria'!$C$38,IF(Q27="Probable Hero",'Hero Criteria'!$C$39,'Hero Criteria'!$C$40))+'Hero Criteria'!$C$41,"Reserve","Backlog")))) -> Recommended | AC27: =INDEX('Hero Segmentation'!$R$5:$R$80,MATCH($A27,'Hero Segmentation'!$A$5:$A$80,0)) -> EXPLORE | AD27: =IF(AND(AB27="Recommended",J27>='Selection Criteria'!$C$26),"Yes","") | AE27: =IFERROR(INDEX('Primary Competitor Fit'!$D$5:$D$91,MATCH($A27&"|Primary 1",'Primary Competitor Fit'!$M$5:$M$91,0)),"-") -> Amazon | AF27: =IFERROR(INDEX('Primary Competitor Fit'!$D$5:$D$91,MATCH($A27&"|Primary 2",'Primary Competitor Fit'!$M$5:$M$91,0)),"-") -> Wayfair | AG27: =IFERROR(INDEX('Secondary Competitor Fit'!$D$5:$D$98,MATCH($A27&"|Secondary 1",'Secondary Competitor Fit'!$M$5:$M$98,0)),"-") -> Grovemade | AH27: =IFERROR(INDEX('Secondary Competitor Fit'!$D$5:$D$98,MATCH($A27&"|Secondary 2",'Secondary Competitor Fit'!$M$5:$M$98,0)),"-") -> Orbitkey | AI27: Leather/felt desk pads; Wayfair has a Desk Pads node. | AJ27: =IF(AND(P27="Pass",AC27<>"PROTECT"),Z27+U27/100+R27/1000,-1) -> 76.054
A28: P24 | B28: Computers & Accessories > Computer Accessories & Peripherals > Laptop Accessories > Laptop Stands & Lap Desks | C28: Computers & Accessories | D28: Computer Accessories & Peripherals | E28: Laptop Accessories | F28: Laptop Stands & Lap Desks | G28: 4 | H28: CL165071 | I28: 205 | J28: 0 | K28: New | L28: =IF(OR(G28=3,G28=4),"Pass","Fail") -> Pass | M28: Pass | N28: =IF(I28>='Selection Criteria'!$C$25,"Pass","Fail") -> Pass | O28: Pass | P28: =IF(AND(L28="Pass",M28="Pass",N28="Pass",O28="Pass"),"Pass","Fail") -> Pass | Q28: =INDEX('Hero Segmentation'!$Q$5:$Q$80,MATCH($A28,'Hero Segmentation'!$A$5:$A$80,0)) -> Probable Hero | R28: 4 | S28: 4 | T28: 4 | U28: 5 | V28: 4 | W28: 3 | X28: 3 | Y28: 2 | Z28: =IF(P28="Pass",(R28*'Selection Criteria'!$F$13+S28*'Selection Criteria'!$F$14+T28*'Selection Criteria'!$F$15+U28*'Selection Criteria'!$F$16+V28*'Selection Criteria'!$F$17+W28*'Selection Criteria'!$F$18+X28*'Selection Criteria'!$F$19+Y28*'Selection Criteria'!$F$20)/(5*'Selection Criteria'!$F$21)*100,"-") -> 76 | AA28: =IF(AJ28<0,"-",COUNTIFS($Q$5:$Q$80,Q28,$AJ$5:$AJ$80,">"&AJ28)+1) -> 16 | AB28: =IF(P28<>"Pass","Parked (gate)",IF(AC28="PROTECT","Protect (control)",IF(AA28<=IF(Q28="Hero",'Hero Criteria'!$C$38,IF(Q28="Probable Hero",'Hero Criteria'!$C$39,'Hero Criteria'!$C$40)),"Recommended",IF(AA28<=IF(Q28="Hero",'Hero Criteria'!$C$38,IF(Q28="Probable Hero",'Hero Criteria'!$C$39,'Hero Criteria'!$C$40))+'Hero Criteria'!$C$41,"Reserve","Backlog")))) -> Backlog | AC28: =INDEX('Hero Segmentation'!$R$5:$R$80,MATCH($A28,'Hero Segmentation'!$A$5:$A$80,0)) -> BUILD | AD28: =IF(AND(AB28="Recommended",J28>='Selection Criteria'!$C$26),"Yes","") | AE28: =IFERROR(INDEX('Primary Competitor Fit'!$D$5:$D$91,MATCH($A28&"|Primary 1",'Primary Competitor Fit'!$M$5:$M$91,0)),"-") -> - | AF28: =IFERROR(INDEX('Primary Competitor Fit'!$D$5:$D$91,MATCH($A28&"|Primary 2",'Primary Competitor Fit'!$M$5:$M$91,0)),"-") -> - | AG28: =IFERROR(INDEX('Secondary Competitor Fit'!$D$5:$D$98,MATCH($A28&"|Secondary 1",'Secondary Competitor Fit'!$M$5:$M$98,0)),"-") -> - | AH28: =IFERROR(INDEX('Secondary Competitor Fit'!$D$5:$D$98,MATCH($A28&"|Secondary 2",'Secondary Competitor Fit'!$M$5:$M$98,0)),"-") -> - | AI28: Wood/aluminium stands are desk-setup objects. | AJ28: =IF(AND(P28="Pass",AC28<>"PROTECT"),Z28+U28/100+R28/1000,-1) -> 76.054
A29: P25 | B29: Furniture > Chairs & Seating > Sofas & Benches > Benches & Beam Seating | C29: Furniture | D29: Chairs & Seating | E29: Sofas & Benches | F29: Benches & Beam Seating | G29: 4 | H29: CL163750 | I29: 49 | J29: 40 | K29: 1. Chairs & Seating | L29: =IF(OR(G29=3,G29=4),"Pass","Fail") -> Pass | M29: Pass | N29: =IF(I29>='Selection Criteria'!$C$25,"Pass","Fail") -> Pass | O29: Pass | P29: =IF(AND(L29="Pass",M29="Pass",N29="Pass",O29="Pass"),"Pass","Fail") -> Pass | Q29: =INDEX('Hero Segmentation'!$Q$5:$Q$80,MATCH($A29,'Hero Segmentation'!$A$5:$A$80,0)) -> Probable Hero | R29: 4 | S29: 5 | T29: 4 | U29: 4 | V29: 1 | W29: 3 | X29: 2 | Y29: 5 | Z29: =IF(P29="Pass",(R29*'Selection Criteria'!$F$13+S29*'Selection Criteria'!$F$14+T29*'Selection Criteria'!$F$15+U29*'Selection Criteria'!$F$16+V29*'Selection Criteria'!$F$17+W29*'Selection Criteria'!$F$18+X29*'Selection Criteria'!$F$19+Y29*'Selection Criteria'!$F$20)/(5*'Selection Criteria'!$F$21)*100,"-") -> 75 | AA29: =IF(AJ29<0,"-",COUNTIFS($Q$5:$Q$80,Q29,$AJ$5:$AJ$80,">"&AJ29)+1) -> 17 | AB29: =IF(P29<>"Pass","Parked (gate)",IF(AC29="PROTECT","Protect (control)",IF(AA29<=IF(Q29="Hero",'Hero Criteria'!$C$38,IF(Q29="Probable Hero",'Hero Criteria'!$C$39,'Hero Criteria'!$C$40)),"Recommended",IF(AA29<=IF(Q29="Hero",'Hero Criteria'!$C$38,IF(Q29="Probable Hero",'Hero Criteria'!$C$39,'Hero Criteria'!$C$40))+'Hero Criteria'!$C$41,"Reserve","Backlog")))) -> Backlog | AC29: =INDEX('Hero Segmentation'!$R$5:$R$80,MATCH($A29,'Hero Segmentation'!$A$5:$A$80,0)) -> BUILD | AD29: =IF(AND(AB29="Recommended",J29>='Selection Criteria'!$C$26),"Yes","") | AE29: =IFERROR(INDEX('Primary Competitor Fit'!$D$5:$D$91,MATCH($A29&"|Primary 1",'Primary Competitor Fit'!$M$5:$M$91,0)),"-") -> - | AF29: =IFERROR(INDEX('Primary Competitor Fit'!$D$5:$D$91,MATCH($A29&"|Primary 2",'Primary Competitor Fit'!$M$5:$M$91,0)),"-") -> - | AG29: =IFERROR(INDEX('Secondary Competitor Fit'!$D$5:$D$98,MATCH($A29&"|Secondary 1",'Secondary Competitor Fit'!$M$5:$M$98,0)),"-") -> - | AH29: =IFERROR(INDEX('Secondary Competitor Fit'!$D$5:$D$98,MATCH($A29&"|Secondary 2",'Secondary Competitor Fit'!$M$5:$M$98,0)),"-") -> - | AI29: Pilot: 2 Strong recs; thin Staples baseline (49); oversize freight. | AJ29: =IF(AND(P29="Pass",AC29<>"PROTECT"),Z29+U29/100+R29/1000,-1) -> 75.044
A30: P26 | B30: Furniture > Lamps & Lighting > Table Lamps | C30: Furniture | D30: Lamps & Lighting | E30: Table Lamps | G30: 3 | H30: CL216712 | I30: 211 | J30: 129 | K30: 3. Lamps & Lighting | L30: =IF(OR(G30=3,G30=4),"Pass","Fail") -> Pass | M30: Pass | N30: =IF(I30>='Selection Criteria'!$C$25,"Pass","Fail") -> Pass | O30: Pass | P30: =IF(AND(L30="Pass",M30="Pass",N30="Pass",O30="Pass"),"Pass","Fail") -> Pass | Q30: =INDEX('Hero Segmentation'!$Q$5:$Q$80,MATCH($A30,'Hero Segmentation'!$A$5:$A$80,0)) -> Probable Hero | R30: 5 | S30: 4 | T30: 4 | U30: 3 | V30: 3 | W30: 3 | X30: 2 | Y30: 4 | Z30: =IF(P30="Pass",(R30*'Selection Criteria'!$F$13+S30*'Selection Criteria'!$F$14+T30*'Selection Criteria'!$F$15+U30*'Selection Criteria'!$F$16+V30*'Selection Criteria'!$F$17+W30*'Selection Criteria'!$F$18+X30*'Selection Criteria'!$F$19+Y30*'Selection Criteria'!$F$20)/(5*'Selection Criteria'!$F$21)*100,"-") -> 75 | AA30: =IF(AJ30<0,"-",COUNTIFS($Q$5:$Q$80,Q30,$AJ$5:$AJ$80,">"&AJ30)+1) -> 18 | AB30: =IF(P30<>"Pass","Parked (gate)",IF(AC30="PROTECT","Protect (control)",IF(AA30<=IF(Q30="Hero",'Hero Criteria'!$C$38,IF(Q30="Probable Hero",'Hero Criteria'!$C$39,'Hero Criteria'!$C$40)),"Recommended",IF(AA30<=IF(Q30="Hero",'Hero Criteria'!$C$38,IF(Q30="Probable Hero",'Hero Criteria'!$C$39,'Hero Criteria'!$C$40))+'Hero Criteria'!$C$41,"Reserve","Backlog")))) -> Backlog | AC30: =INDEX('Hero Segmentation'!$R$5:$R$80,MATCH($A30,'Hero Segmentation'!$A$5:$A$80,0)) -> BUILD | AD30: =IF(AND(AB30="Recommended",J30>='Selection Criteria'!$C$26),"Yes","") | AE30: =IFERROR(INDEX('Primary Competitor Fit'!$D$5:$D$91,MATCH($A30&"|Primary 1",'Primary Competitor Fit'!$M$5:$M$91,0)),"-") -> - | AF30: =IFERROR(INDEX('Primary Competitor Fit'!$D$5:$D$91,MATCH($A30&"|Primary 2",'Primary Competitor Fit'!$M$5:$M$91,0)),"-") -> - | AG30: =IFERROR(INDEX('Secondary Competitor Fit'!$D$5:$D$98,MATCH($A30&"|Secondary 1",'Secondary Competitor Fit'!$M$5:$M$98,0)),"-") -> - | AH30: =IFERROR(INDEX('Secondary Competitor Fit'!$D$5:$D$98,MATCH($A30&"|Secondary 2",'Secondary Competitor Fit'!$M$5:$M$98,0)),"-") -> - | AI30: Reception / home-office decor lighting. | AJ30: =IF(AND(P30="Pass",AC30<>"PROTECT"),Z30+U30/100+R30/1000,-1) -> 75.035
A31: P27 | B31: Computers & Accessories > Computer Accessories & Peripherals > Computer Keyboards | C31: Computers & Accessories | D31: Computer Accessories & Peripherals | E31: Computer Keyboards | G31: 3 | H31: CL215783 | I31: 374 | J31: 0 | K31: New | L31: =IF(OR(G31=3,G31=4),"Pass","Fail") -> Pass | M31: Pass | N31: =IF(I31>='Selection Criteria'!$C$25,"Pass","Fail") -> Pass | O31: Pass | P31: =IF(AND(L31="Pass",M31="Pass",N31="Pass",O31="Pass"),"Pass","Fail") -> Pass | Q31: =INDEX('Hero Segmentation'!$Q$5:$Q$80,MATCH($A31,'Hero Segmentation'!$A$5:$A$80,0)) -> Hero | R31: 4 | S31: 4 | T31: 3 | U31: 5 | V31: 4 | W31: 4 | X31: 3 | Y31: 2 | Z31: =IF(P31="Pass",(R31*'Selection Criteria'!$F$13+S31*'Selection Criteria'!$F$14+T31*'Selection Criteria'!$F$15+U31*'Selection Criteria'!$F$16+V31*'Selection Criteria'!$F$17+W31*'Selection Criteria'!$F$18+X31*'Selection Criteria'!$F$19+Y31*'Selection Criteria'!$F$20)/(5*'Selection Criteria'!$F$21)*100,"-") -> 75 | AA31: =IF(AJ31<0,"-",COUNTIFS($Q$5:$Q$80,Q31,$AJ$5:$AJ$80,">"&AJ31)+1) -> 7 | AB31: =IF(P31<>"Pass","Parked (gate)",IF(AC31="PROTECT","Protect (control)",IF(AA31<=IF(Q31="Hero",'Hero Criteria'!$C$38,IF(Q31="Probable Hero",'Hero Criteria'!$C$39,'Hero Criteria'!$C$40)),"Recommended",IF(AA31<=IF(Q31="Hero",'Hero Criteria'!$C$38,IF(Q31="Probable Hero",'Hero Criteria'!$C$39,'Hero Criteria'!$C$40))+'Hero Criteria'!$C$41,"Reserve","Backlog")))) -> Recommended | AC31: =INDEX('Hero Segmentation'!$R$5:$R$80,MATCH($A31,'Hero Segmentation'!$A$5:$A$80,0)) -> EXTEND | AD31: =IF(AND(AB31="Recommended",J31>='Selection Criteria'!$C$26),"Yes","") | AE31: =IFERROR(INDEX('Primary Competitor Fit'!$D$5:$D$91,MATCH($A31&"|Primary 1",'Primary Competitor Fit'!$M$5:$M$91,0)),"-") -> Amazon | AF31: =IFERROR(INDEX('Primary Competitor Fit'!$D$5:$D$91,MATCH($A31&"|Primary 2",'Primary Competitor Fit'!$M$5:$M$91,0)),"-") -> Best Buy | AG31: =IFERROR(INDEX('Secondary Competitor Fit'!$D$5:$D$98,MATCH($A31&"|Secondary 1",'Secondary Competitor Fit'!$M$5:$M$98,0)),"-") -> Keychron | AH31: =IFERROR(INDEX('Secondary Competitor Fit'!$D$5:$D$98,MATCH($A31&"|Secondary 2",'Secondary Competitor Fit'!$M$5:$M$98,0)),"-") -> Drop | AI31: Typewriter/pastel keyboards mainstream (Logitech POP); business keyboards are core. | AJ31: =IF(AND(P31="Pass",AC31<>"PROTECT"),Z31+U31/100+R31/1000,-1) -> 75.054
A32: P28 | B32: Furniture > Chairs & Seating > Breakroom & Dining Chairs | C32: Furniture | D32: Chairs & Seating | E32: Breakroom & Dining Chairs | G32: 3 | H32: CL166181 | I32: 75 | J32: 40 | K32: 1. Chairs & Seating | L32: =IF(OR(G32=3,G32=4),"Pass","Fail") -> Pass | M32: Pass | N32: =IF(I32>='Selection Criteria'!$C$25,"Pass","Fail") -> Pass | O32: Pass | P32: =IF(AND(L32="Pass",M32="Pass",N32="Pass",O32="Pass"),"Pass","Fail") -> Pass | Q32: =INDEX('Hero Segmentation'!$Q$5:$Q$80,MATCH($A32,'Hero Segmentation'!$A$5:$A$80,0)) -> Probable Hero | R32: 4 | S32: 5 | T32: 3 | U32: 4 | V32: 2 | W32: 3 | X32: 2 | Y32: 5 | Z32: =IF(P32="Pass",(R32*'Selection Criteria'!$F$13+S32*'Selection Criteria'!$F$14+T32*'Selection Criteria'!$F$15+U32*'Selection Criteria'!$F$16+V32*'Selection Criteria'!$F$17+W32*'Selection Criteria'!$F$18+X32*'Selection Criteria'!$F$19+Y32*'Selection Criteria'!$F$20)/(5*'Selection Criteria'!$F$21)*100,"-") -> 74 | AA32: =IF(AJ32<0,"-",COUNTIFS($Q$5:$Q$80,Q32,$AJ$5:$AJ$80,">"&AJ32)+1) -> 19 | AB32: =IF(P32<>"Pass","Parked (gate)",IF(AC32="PROTECT","Protect (control)",IF(AA32<=IF(Q32="Hero",'Hero Criteria'!$C$38,IF(Q32="Probable Hero",'Hero Criteria'!$C$39,'Hero Criteria'!$C$40)),"Recommended",IF(AA32<=IF(Q32="Hero",'Hero Criteria'!$C$38,IF(Q32="Probable Hero",'Hero Criteria'!$C$39,'Hero Criteria'!$C$40))+'Hero Criteria'!$C$41,"Reserve","Backlog")))) -> Backlog | AC32: =INDEX('Hero Segmentation'!$R$5:$R$80,MATCH($A32,'Hero Segmentation'!$A$5:$A$80,0)) -> BUILD | AD32: =IF(AND(AB32="Recommended",J32>='Selection Criteria'!$C$26),"Yes","") | AE32: =IFERROR(INDEX('Primary Competitor Fit'!$D$5:$D$91,MATCH($A32&"|Primary 1",'Primary Competitor Fit'!$M$5:$M$91,0)),"-") -> - | AF32: =IFERROR(INDEX('Primary Competitor Fit'!$D$5:$D$91,MATCH($A32&"|Primary 2",'Primary Competitor Fit'!$M$5:$M$91,0)),"-") -> - | AG32: =IFERROR(INDEX('Secondary Competitor Fit'!$D$5:$D$98,MATCH($A32&"|Secondary 1",'Secondary Competitor Fit'!$M$5:$M$98,0)),"-") -> - | AH32: =IFERROR(INDEX('Secondary Competitor Fit'!$D$5:$D$98,MATCH($A32&"|Secondary 2",'Secondary Competitor Fit'!$M$5:$M$98,0)),"-") -> - | AI32: Pilot: 5 recs but methods disagree (rho 0.08); RTO breakroom story. | AJ32: =IF(AND(P32="Pass",AC32<>"PROTECT"),Z32+U32/100+R32/1000,-1) -> 74.044
A33: P29 | B33: Office Supplies > Calendars & Planners > Calendars | C33: Office Supplies | D33: Calendars & Planners | E33: Calendars | G33: 3 | H33: CL166389 | I33: 1234 | J33: 0 | K33: 9. Planning & Craft Organization | L33: =IF(OR(G33=3,G33=4),"Pass","Fail") -> Pass | M33: Pass | N33: =IF(I33>='Selection Criteria'!$C$25,"Pass","Fail") -> Pass | O33: Pass | P33: =IF(AND(L33="Pass",M33="Pass",N33="Pass",O33="Pass"),"Pass","Fail") -> Pass | Q33: =INDEX('Hero Segmentation'!$Q$5:$Q$80,MATCH($A33,'Hero Segmentation'!$A$5:$A$80,0)) -> Hero | R33: 4 | S33: 3 | T33: 3 | U33: 5 | V33: 5 | W33: 3 | X33: 5 | Y33: 2 | Z33: =IF(P33="Pass",(R33*'Selection Criteria'!$F$13+S33*'Selection Criteria'!$F$14+T33*'Selection Criteria'!$F$15+U33*'Selection Criteria'!$F$16+V33*'Selection Criteria'!$F$17+W33*'Selection Criteria'!$F$18+X33*'Selection Criteria'!$F$19+Y33*'Selection Criteria'!$F$20)/(5*'Selection Criteria'!$F$21)*100,"-") -> 74 | AA33: =IF(AJ33<0,"-",COUNTIFS($Q$5:$Q$80,Q33,$AJ$5:$AJ$80,">"&AJ33)+1) -> 8 | AB33: =IF(P33<>"Pass","Parked (gate)",IF(AC33="PROTECT","Protect (control)",IF(AA33<=IF(Q33="Hero",'Hero Criteria'!$C$38,IF(Q33="Probable Hero",'Hero Criteria'!$C$39,'Hero Criteria'!$C$40)),"Recommended",IF(AA33<=IF(Q33="Hero",'Hero Criteria'!$C$38,IF(Q33="Probable Hero",'Hero Criteria'!$C$39,'Hero Criteria'!$C$40))+'Hero Criteria'!$C$41,"Reserve","Backlog")))) -> Reserve | AC33: =INDEX('Hero Segmentation'!$R$5:$R$80,MATCH($A33,'Hero Segmentation'!$A$5:$A$80,0)) -> EXTEND | AD33: =IF(AND(AB33="Recommended",J33>='Selection Criteria'!$C$26),"Yes","") | AE33: =IFERROR(INDEX('Primary Competitor Fit'!$D$5:$D$91,MATCH($A33&"|Primary 1",'Primary Competitor Fit'!$M$5:$M$91,0)),"-") -> Amazon | AF33: =IFERROR(INDEX('Primary Competitor Fit'!$D$5:$D$91,MATCH($A33&"|Primary 2",'Primary Competitor Fit'!$M$5:$M$91,0)),"-") -> Target | AG33: =IFERROR(INDEX('Secondary Competitor Fit'!$D$5:$D$98,MATCH($A33&"|Secondary 1",'Secondary Competitor Fit'!$M$5:$M$98,0)),"-") -> Erin Condren | AH33: =IFERROR(INDEX('Secondary Competitor Fit'!$D$5:$D$98,MATCH($A33&"|Secondary 2",'Secondary Competitor Fit'!$M$5:$M$98,0)),"-") -> Etsy | AI33: Dated goods are core 1P; design calendars are the adjacency. | AJ33: =IF(AND(P33="Pass",AC33<>"PROTECT"),Z33+U33/100+R33/1000,-1) -> 74.054
A34: P30 | B34: Furniture > Chairs & Seating > Stools & Ottomans > Counter & Bar Stools | C34: Furniture | D34: Chairs & Seating | E34: Stools & Ottomans | F34: Counter & Bar Stools | G34: 4 | H34: CL166182 | I34: 617 | J34: 601 | K34: 1. Chairs & Seating | L34: =IF(OR(G34=3,G34=4),"Pass","Fail") -> Pass | M34: Pass | N34: =IF(I34>='Selection Criteria'!$C$25,"Pass","Fail") -> Pass | O34: Pass | P34: =IF(AND(L34="Pass",M34="Pass",N34="Pass",O34="Pass"),"Pass","Fail") -> Pass | Q34: =INDEX('Hero Segmentation'!$Q$5:$Q$80,MATCH($A34,'Hero Segmentation'!$A$5:$A$80,0)) -> Probable Hero | R34: 4 | S34: 4 | T34: 4 | U34: 3 | V34: 2 | W34: 4 | X34: 2 | Y34: 5 | Z34: =IF(P34="Pass",(R34*'Selection Criteria'!$F$13+S34*'Selection Criteria'!$F$14+T34*'Selection Criteria'!$F$15+U34*'Selection Criteria'!$F$16+V34*'Selection Criteria'!$F$17+W34*'Selection Criteria'!$F$18+X34*'Selection Criteria'!$F$19+Y34*'Selection Criteria'!$F$20)/(5*'Selection Criteria'!$F$21)*100,"-") -> 73 | AA34: =IF(AJ34<0,"-",COUNTIFS($Q$5:$Q$80,Q34,$AJ$5:$AJ$80,">"&AJ34)+1) -> 21 | AB34: =IF(P34<>"Pass","Parked (gate)",IF(AC34="PROTECT","Protect (control)",IF(AA34<=IF(Q34="Hero",'Hero Criteria'!$C$38,IF(Q34="Probable Hero",'Hero Criteria'!$C$39,'Hero Criteria'!$C$40)),"Recommended",IF(AA34<=IF(Q34="Hero",'Hero Criteria'!$C$38,IF(Q34="Probable Hero",'Hero Criteria'!$C$39,'Hero Criteria'!$C$40))+'Hero Criteria'!$C$41,"Reserve","Backlog")))) -> Backlog | AC34: =INDEX('Hero Segmentation'!$R$5:$R$80,MATCH($A34,'Hero Segmentation'!$A$5:$A$80,0)) -> BUILD | AD34: =IF(AND(AB34="Recommended",J34>='Selection Criteria'!$C$26),"Yes","") | AE34: =IFERROR(INDEX('Primary Competitor Fit'!$D$5:$D$91,MATCH($A34&"|Primary 1",'Primary Competitor Fit'!$M$5:$M$91,0)),"-") -> - | AF34: =IFERROR(INDEX('Primary Competitor Fit'!$D$5:$D$91,MATCH($A34&"|Primary 2",'Primary Competitor Fit'!$M$5:$M$91,0)),"-") -> - | AG34: =IFERROR(INDEX('Secondary Competitor Fit'!$D$5:$D$98,MATCH($A34&"|Secondary 1",'Secondary Competitor Fit'!$M$5:$M$98,0)),"-") -> - | AH34: =IFERROR(INDEX('Secondary Competitor Fit'!$D$5:$D$98,MATCH($A34&"|Secondary 2",'Secondary Competitor Fit'!$M$5:$M$98,0)),"-") -> - | AI34: Pilot: best method agreement (rho 0.73 on bar-height split); café/breakroom, not the core work mission. | AJ34: =IF(AND(P34="Pass",AC34<>"PROTECT"),Z34+U34/100+R34/1000,-1) -> 73.034
A35: P31 | B35: Furniture > Lamps & Lighting > Floor Lamps | C35: Furniture | D35: Lamps & Lighting | E35: Floor Lamps | G35: 3 | H35: CL216710 | I35: 132 | J35: 120 | K35: 3. Lamps & Lighting | L35: =IF(OR(G35=3,G35=4),"Pass","Fail") -> Pass | M35: Pass | N35: =IF(I35>='Selection Criteria'!$C$25,"Pass","Fail") -> Pass | O35: Pass | P35: =IF(AND(L35="Pass",M35="Pass",N35="Pass",O35="Pass"),"Pass","Fail") -> Pass | Q35: =INDEX('Hero Segmentation'!$Q$5:$Q$80,MATCH($A35,'Hero Segmentation'!$A$5:$A$80,0)) -> Probable Hero | R35: 5 | S35: 4 | T35: 4 | U35: 3 | V35: 2 | W35: 3 | X35: 2 | Y35: 4 | Z35: =IF(P35="Pass",(R35*'Selection Criteria'!$F$13+S35*'Selection Criteria'!$F$14+T35*'Selection Criteria'!$F$15+U35*'Selection Criteria'!$F$16+V35*'Selection Criteria'!$F$17+W35*'Selection Criteria'!$F$18+X35*'Selection Criteria'!$F$19+Y35*'Selection Criteria'!$F$20)/(5*'Selection Criteria'!$F$21)*100,"-") -> 73 | AA35: =IF(AJ35<0,"-",COUNTIFS($Q$5:$Q$80,Q35,$AJ$5:$AJ$80,">"&AJ35)+1) -> 20 | AB35: =IF(P35<>"Pass","Parked (gate)",IF(AC35="PROTECT","Protect (control)",IF(AA35<=IF(Q35="Hero",'Hero Criteria'!$C$38,IF(Q35="Probable Hero",'Hero Criteria'!$C$39,'Hero Criteria'!$C$40)),"Recommended",IF(AA35<=IF(Q35="Hero",'Hero Criteria'!$C$38,IF(Q35="Probable Hero",'Hero Criteria'!$C$39,'Hero Criteria'!$C$40))+'Hero Criteria'!$C$41,"Reserve","Backlog")))) -> Backlog | AC35: =INDEX('Hero Segmentation'!$R$5:$R$80,MATCH($A35,'Hero Segmentation'!$A$5:$A$80,0)) -> BUILD | AD35: =IF(AND(AB35="Recommended",J35>='Selection Criteria'!$C$26),"Yes","") | AE35: =IFERROR(INDEX('Primary Competitor Fit'!$D$5:$D$91,MATCH($A35&"|Primary 1",'Primary Competitor Fit'!$M$5:$M$91,0)),"-") -> - | AF35: =IFERROR(INDEX('Primary Competitor Fit'!$D$5:$D$91,MATCH($A35&"|Primary 2",'Primary Competitor Fit'!$M$5:$M$91,0)),"-") -> - | AG35: =IFERROR(INDEX('Secondary Competitor Fit'!$D$5:$D$98,MATCH($A35&"|Secondary 1",'Secondary Competitor Fit'!$M$5:$M$98,0)),"-") -> - | AH35: =IFERROR(INDEX('Secondary Competitor Fit'!$D$5:$D$98,MATCH($A35&"|Secondary 2",'Secondary Competitor Fit'!$M$5:$M$98,0)),"-") -> - | AI35: Strong design variance; living-room leaning. | AJ35: =IF(AND(P35="Pass",AC35<>"PROTECT"),Z35+U35/100+R35/1000,-1) -> 73.035
A36: P32 | B36: Office Supplies > Label Makers & Tapes > Label Makers | C36: Office Supplies | D36: Label Makers & Tapes | E36: Label Makers | G36: 3 | H36: CL90400 | I36: 148 | J36: 103 | K36: 8. Labels & Packaging Accessories | L36: =IF(OR(G36=3,G36=4),"Pass","Fail") -> Pass | M36: Pass | N36: =IF(I36>='Selection Criteria'!$C$25,"Pass","Fail") -> Pass | O36: Pass | P36: =IF(AND(L36="Pass",M36="Pass",N36="Pass",O36="Pass"),"Pass","Fail") -> Pass | Q36: =INDEX('Hero Segmentation'!$Q$5:$Q$80,MATCH($A36,'Hero Segmentation'!$A$5:$A$80,0)) -> Hero | R36: 3 | S36: 4 | T36: 3 | U36: 5 | V36: 4 | W36: 3 | X36: 3 | Y36: 4 | Z36: =IF(P36="Pass",(R36*'Selection Criteria'!$F$13+S36*'Selection Criteria'!$F$14+T36*'Selection Criteria'!$F$15+U36*'Selection Criteria'!$F$16+V36*'Selection Criteria'!$F$17+W36*'Selection Criteria'!$F$18+X36*'Selection Criteria'!$F$19+Y36*'Selection Criteria'!$F$20)/(5*'Selection Criteria'!$F$21)*100,"-") -> 73 | AA36: =IF(AJ36<0,"-",COUNTIFS($Q$5:$Q$80,Q36,$AJ$5:$AJ$80,">"&AJ36)+1) -> 9 | AB36: =IF(P36<>"Pass","Parked (gate)",IF(AC36="PROTECT","Protect (control)",IF(AA36<=IF(Q36="Hero",'Hero Criteria'!$C$38,IF(Q36="Probable Hero",'Hero Criteria'!$C$39,'Hero Criteria'!$C$40)),"Recommended",IF(AA36<=IF(Q36="Hero",'Hero Criteria'!$C$38,IF(Q36="Probable Hero",'Hero Criteria'!$C$39,'Hero Criteria'!$C$40))+'Hero Criteria'!$C$41,"Reserve","Backlog")))) -> Reserve | AC36: =INDEX('Hero Segmentation'!$R$5:$R$80,MATCH($A36,'Hero Segmentation'!$A$5:$A$80,0)) -> EXTEND | AD36: =IF(AND(AB36="Recommended",J36>='Selection Criteria'!$C$26),"Yes","") | AE36: =IFERROR(INDEX('Primary Competitor Fit'!$D$5:$D$91,MATCH($A36&"|Primary 1",'Primary Competitor Fit'!$M$5:$M$91,0)),"-") -> Amazon | AF36: =IFERROR(INDEX('Primary Competitor Fit'!$D$5:$D$91,MATCH($A36&"|Primary 2",'Primary Competitor Fit'!$M$5:$M$91,0)),"-") -> Walmart | AG36: =IFERROR(INDEX('Secondary Competitor Fit'!$D$5:$D$98,MATCH($A36&"|Secondary 1",'Secondary Competitor Fit'!$M$5:$M$98,0)),"-") -> Michaels | AH36: =IFERROR(INDEX('Secondary Competitor Fit'!$D$5:$D$98,MATCH($A36&"|Secondary 2",'Secondary Competitor Fit'!$M$5:$M$98,0)),"-") -> The Container Store | AI36: Mini thermal label printers went viral; Brother/DYMO are core 1P. | AJ36: =IF(AND(P36="Pass",AC36<>"PROTECT"),Z36+U36/100+R36/1000,-1) -> 73.053
A37: P33 | B37: Shipping, Packing & Mailing Supplies > Mailing Supplies > Mailers | C37: Shipping, Packing & Mailing Supplies | D37: Mailing Supplies | E37: Mailers | G37: 3 | H37: CL142648 | I37: 396 | J37: 387 | K37: 8. Labels & Packaging Accessories | L37: =IF(OR(G37=3,G37=4),"Pass","Fail") -> Pass | M37: Pass | N37: =IF(I37>='Selection Criteria'!$C$25,"Pass","Fail") -> Pass | O37: Pass | P37: =IF(AND(L37="Pass",M37="Pass",N37="Pass",O37="Pass"),"Pass","Fail") -> Pass | Q37: =INDEX('Hero Segmentation'!$Q$5:$Q$80,MATCH($A37,'Hero Segmentation'!$A$5:$A$80,0)) -> Hero | R37: 3 | S37: 4 | T37: 3 | U37: 5 | V37: 4 | W37: 3 | X37: 3 | Y37: 4 | Z37: =IF(P37="Pass",(R37*'Selection Criteria'!$F$13+S37*'Selection Criteria'!$F$14+T37*'Selection Criteria'!$F$15+U37*'Selection Criteria'!$F$16+V37*'Selection Criteria'!$F$17+W37*'Selection Criteria'!$F$18+X37*'Selection Criteria'!$F$19+Y37*'Selection Criteria'!$F$20)/(5*'Selection Criteria'!$F$21)*100,"-") -> 73 | AA37: =IF(AJ37<0,"-",COUNTIFS($Q$5:$Q$80,Q37,$AJ$5:$AJ$80,">"&AJ37)+1) -> 9 | AB37: =IF(P37<>"Pass","Parked (gate)",IF(AC37="PROTECT","Protect (control)",IF(AA37<=IF(Q37="Hero",'Hero Criteria'!$C$38,IF(Q37="Probable Hero",'Hero Criteria'!$C$39,'Hero Criteria'!$C$40)),"Recommended",IF(AA37<=IF(Q37="Hero",'Hero Criteria'!$C$38,IF(Q37="Probable Hero",'Hero Criteria'!$C$39,'Hero Criteria'!$C$40))+'Hero Criteria'!$C$41,"Reserve","Backlog")))) -> Reserve | AC37: =INDEX('Hero Segmentation'!$R$5:$R$80,MATCH($A37,'Hero Segmentation'!$A$5:$A$80,0)) -> EXTEND | AD37: =IF(AND(AB37="Recommended",J37>='Selection Criteria'!$C$26),"Yes","") | AE37: =IFERROR(INDEX('Primary Competitor Fit'!$D$5:$D$91,MATCH($A37&"|Primary 1",'Primary Competitor Fit'!$M$5:$M$91,0)),"-") -> Amazon | AF37: =IFERROR(INDEX('Primary Competitor Fit'!$D$5:$D$91,MATCH($A37&"|Primary 2",'Primary Competitor Fit'!$M$5:$M$91,0)),"-") -> Uline | AG37: =IFERROR(INDEX('Secondary Competitor Fit'!$D$5:$D$98,MATCH($A37&"|Secondary 1",'Secondary Competitor Fit'!$M$5:$M$98,0)),"-") -> noissue | AH37: =IFERROR(INDEX('Secondary Competitor Fit'!$D$5:$D$98,MATCH($A37&"|Secondary 2",'Secondary Competitor Fit'!$M$5:$M$98,0)),"-") -> Packhelp | AI37: Coloured/printed/recycled mailers; utility mailers are core 1P. | AJ37: =IF(AND(P37="Pass",AC37<>"PROTECT"),Z37+U37/100+R37/1000,-1) -> 73.053
A38: P34 | B38: Office Supplies > Storage & Organization > Storage Bins | C38: Office Supplies | D38: Storage & Organization | E38: Storage Bins | G38: 3 | H38: CL354710 | I38: 660 | J38: 0 | K38: 9. Planning & Craft Organization | L38: =IF(OR(G38=3,G38=4),"Pass","Fail") -> Pass | M38: Pass | N38: =IF(I38>='Selection Criteria'!$C$25,"Pass","Fail") -> Pass | O38: Pass | P38: =IF(AND(L38="Pass",M38="Pass",N38="Pass",O38="Pass"),"Pass","Fail") -> Pass | Q38: =INDEX('Hero Segmentation'!$Q$5:$Q$80,MATCH($A38,'Hero Segmentation'!$A$5:$A$80,0)) -> Hero | R38: 4 | S38: 4 | T38: 3 | U38: 4 | V38: 4 | W38: 3 | X38: 5 | Y38: 2 | Z38: =IF(P38="Pass",(R38*'Selection Criteria'!$F$13+S38*'Selection Criteria'!$F$14+T38*'Selection Criteria'!$F$15+U38*'Selection Criteria'!$F$16+V38*'Selection Criteria'!$F$17+W38*'Selection Criteria'!$F$18+X38*'Selection Criteria'!$F$19+Y38*'Selection Criteria'!$F$20)/(5*'Selection Criteria'!$F$21)*100,"-") -> 72 | AA38: =IF(AJ38<0,"-",COUNTIFS($Q$5:$Q$80,Q38,$AJ$5:$AJ$80,">"&AJ38)+1) -> 11 | AB38: =IF(P38<>"Pass","Parked (gate)",IF(AC38="PROTECT","Protect (control)",IF(AA38<=IF(Q38="Hero",'Hero Criteria'!$C$38,IF(Q38="Probable Hero",'Hero Criteria'!$C$39,'Hero Criteria'!$C$40)),"Recommended",IF(AA38<=IF(Q38="Hero",'Hero Criteria'!$C$38,IF(Q38="Probable Hero",'Hero Criteria'!$C$39,'Hero Criteria'!$C$40))+'Hero Criteria'!$C$41,"Reserve","Backlog")))) -> Backlog | AC38: =INDEX('Hero Segmentation'!$R$5:$R$80,MATCH($A38,'Hero Segmentation'!$A$5:$A$80,0)) -> EXTEND | AD38: =IF(AND(AB38="Recommended",J38>='Selection Criteria'!$C$26),"Yes","") | AE38: =IFERROR(INDEX('Primary Competitor Fit'!$D$5:$D$91,MATCH($A38&"|Primary 1",'Primary Competitor Fit'!$M$5:$M$91,0)),"-") -> - | AF38: =IFERROR(INDEX('Primary Competitor Fit'!$D$5:$D$91,MATCH($A38&"|Primary 2",'Primary Competitor Fit'!$M$5:$M$91,0)),"-") -> - | AG38: =IFERROR(INDEX('Secondary Competitor Fit'!$D$5:$D$98,MATCH($A38&"|Secondary 1",'Secondary Competitor Fit'!$M$5:$M$98,0)),"-") -> - | AH38: =IFERROR(INDEX('Secondary Competitor Fit'!$D$5:$D$98,MATCH($A38&"|Secondary 2",'Secondary Competitor Fit'!$M$5:$M$98,0)),"-") -> - | AI38: Plastic utility bins are core; fabric/acrylic are the adjacency. | AJ38: =IF(AND(P38="Pass",AC38<>"PROTECT"),Z38+U38/100+R38/1000,-1) -> 72.044
A39: P35 | B39: Furniture > Boards & Easels > Calendar & In-Out Boards | C39: Furniture | D39: Boards & Easels | E39: Calendar & In-Out Boards | G39: 3 | H39: CL142105 | I39: 63 | J39: 0 | K39: New | L39: =IF(OR(G39=3,G39=4),"Pass","Fail") -> Pass | M39: Pass | N39: =IF(I39>='Selection Criteria'!$C$25,"Pass","Fail") -> Pass | O39: Pass | P39: =IF(AND(L39="Pass",M39="Pass",N39="Pass",O39="Pass"),"Pass","Fail") -> Pass | Q39: =INDEX('Hero Segmentation'!$Q$5:$Q$80,MATCH($A39,'Hero Segmentation'!$A$5:$A$80,0)) -> Probable Hero | R39: 4 | S39: 3 | T39: 4 | U39: 5 | V39: 4 | W39: 2 | X39: 4 | Y39: 2 | Z39: =IF(P39="Pass",(R39*'Selection Criteria'!$F$13+S39*'Selection Criteria'!$F$14+T39*'Selection Criteria'!$F$15+U39*'Selection Criteria'!$F$16+V39*'Selection Criteria'!$F$17+W39*'Selection Criteria'!$F$18+X39*'Selection Criteria'!$F$19+Y39*'Selection Criteria'!$F$20)/(5*'Selection Criteria'!$F$21)*100,"-") -> 72 | AA39: =IF(AJ39<0,"-",COUNTIFS($Q$5:$Q$80,Q39,$AJ$5:$AJ$80,">"&AJ39)+1) -> 22 | AB39: =IF(P39<>"Pass","Parked (gate)",IF(AC39="PROTECT","Protect (control)",IF(AA39<=IF(Q39="Hero",'Hero Criteria'!$C$38,IF(Q39="Probable Hero",'Hero Criteria'!$C$39,'Hero Criteria'!$C$40)),"Recommended",IF(AA39<=IF(Q39="Hero",'Hero Criteria'!$C$38,IF(Q39="Probable Hero",'Hero Criteria'!$C$39,'Hero Criteria'!$C$40))+'Hero Criteria'!$C$41,"Reserve","Backlog")))) -> Backlog | AC39: =INDEX('Hero Segmentation'!$R$5:$R$80,MATCH($A39,'Hero Segmentation'!$A$5:$A$80,0)) -> BUILD | AD39: =IF(AND(AB39="Recommended",J39>='Selection Criteria'!$C$26),"Yes","") | AE39: =IFERROR(INDEX('Primary Competitor Fit'!$D$5:$D$91,MATCH($A39&"|Primary 1",'Primary Competitor Fit'!$M$5:$M$91,0)),"-") -> - | AF39: =IFERROR(INDEX('Primary Competitor Fit'!$D$5:$D$91,MATCH($A39&"|Primary 2",'Primary Competitor Fit'!$M$5:$M$91,0)),"-") -> - | AG39: =IFERROR(INDEX('Secondary Competitor Fit'!$D$5:$D$98,MATCH($A39&"|Secondary 1",'Secondary Competitor Fit'!$M$5:$M$98,0)),"-") -> - | AH39: =IFERROR(INDEX('Secondary Competitor Fit'!$D$5:$D$98,MATCH($A39&"|Secondary 2",'Secondary Competitor Fit'!$M$5:$M$98,0)),"-") -> - | AI39: Acrylic/glass calendars; pairs with planners. | AJ39: =IF(AND(P39="Pass",AC39<>"PROTECT"),Z39+U39/100+R39/1000,-1) -> 72.054
A40: P36 | B40: Coffee, Water & Snacks > Coffee, Coffee Makers & Supplies > Coffee Organizers & Dispensers | C40: Coffee, Water & Snacks | D40: Coffee, Coffee Makers & Supplies | E40: Coffee Organizers & Dispensers | G40: 3 | H40: CL214775 | I40: 50 | J40: 0 | K40: New | L40: =IF(OR(G40=3,G40=4),"Pass","Fail") -> Pass | M40: Pass | N40: =IF(I40>='Selection Criteria'!$C$25,"Pass","Fail") -> Pass | O40: Pass | P40: =IF(AND(L40="Pass",M40="Pass",N40="Pass",O40="Pass"),"Pass","Fail") -> Pass | Q40: =INDEX('Hero Segmentation'!$Q$5:$Q$80,MATCH($A40,'Hero Segmentation'!$A$5:$A$80,0)) -> Non-Hero | R40: 4 | S40: 4 | T40: 4 | U40: 4 | V40: 5 | W40: 2 | X40: 2 | Y40: 2 | Z40: =IF(P40="Pass",(R40*'Selection Criteria'!$F$13+S40*'Selection Criteria'!$F$14+T40*'Selection Criteria'!$F$15+U40*'Selection Criteria'!$F$16+V40*'Selection Criteria'!$F$17+W40*'Selection Criteria'!$F$18+X40*'Selection Criteria'!$F$19+Y40*'Selection Criteria'!$F$20)/(5*'Selection Criteria'!$F$21)*100,"-") -> 72 | AA40: =IF(AJ40<0,"-",COUNTIFS($Q$5:$Q$80,Q40,$AJ$5:$AJ$80,">"&AJ40)+1) -> 3 | AB40: =IF(P40<>"Pass","Parked (gate)",IF(AC40="PROTECT","Protect (control)",IF(AA40<=IF(Q40="Hero",'Hero Criteria'!$C$38,IF(Q40="Probable Hero",'Hero Criteria'!$C$39,'Hero Criteria'!$C$40)),"Recommended",IF(AA40<=IF(Q40="Hero",'Hero Criteria'!$C$38,IF(Q40="Probable Hero",'Hero Criteria'!$C$39,'Hero Criteria'!$C$40))+'Hero Criteria'!$C$41,"Reserve","Backlog")))) -> Recommended | AC40: =INDEX('Hero Segmentation'!$R$5:$R$80,MATCH($A40,'Hero Segmentation'!$A$5:$A$80,0)) -> EXPLORE | AD40: =IF(AND(AB40="Recommended",J40>='Selection Criteria'!$C$26),"Yes","") | AE40: =IFERROR(INDEX('Primary Competitor Fit'!$D$5:$D$91,MATCH($A40&"|Primary 1",'Primary Competitor Fit'!$M$5:$M$91,0)),"Amazon") -> Amazon | AF40: =IFERROR(INDEX('Primary Competitor Fit'!$D$5:$D$91,MATCH($A40&"|Primary 2",'Primary Competitor Fit'!$M$5:$M$91,0)),"Target") -> Wayfair | AG40: =IFERROR(INDEX('Secondary Competitor Fit'!$D$5:$D$98,MATCH($A40&"|Secondary 1",'Secondary Competitor Fit'!$M$5:$M$98,0)),"-") -> Williams Sonoma | AH40: =IFERROR(INDEX('Secondary Competitor Fit'!$D$5:$D$98,MATCH($A40&"|Secondary 2",'Secondary Competitor Fit'!$M$5:$M$98,0)),"-") -> Crate & Barrel | AI40: Breakroom coffee station: design-led pod drawers and coffee-bar sets vs utility carousels. | AJ40: =IF(AND(P40="Pass",AC40<>"PROTECT"),Z40+U40/100+R40/1000,-1) -> 72.044
