Workbook

Sheet Executive Summary
A1: Staples Marketplace PoC: which L3/L4 shelves to analyse, and against whom
A2: v2, prepared 29-Sep-2026 for Sai (LatentView). Paths are exact nodes from the Staples navigation tree (snapshot 21-Sep-2026).
A4: • | B4: Recommendation: run the PoC on 10 Tier-1 L3/L4 shelves across 5 Staples L1s, benchmarked against 6 competitors. A further 23 Tier-2 shelves are ready as swap-ins.
A5: • | B5: Two lenses, one answer. Lens 1, Hero segmentation: is the shelf a Staples Hero (its own strength), a Probable Hero (a market favourite where Staples is not yet a destination) or a Non-Hero? Lens 2, a path score: 8 criteria led by Pat's 'White Chair' test, competitor depth and 1P protection.
A6: • | B6: Tier 1 mixes both growth stories: 4 Heroes to EXTEND with style variants and 6 Probable Heroes to BUILD with marketplace sellers. Non-Heroes are capped at Tier 3, and Heroes where variants would substitute 1P (Office Chairs, Pens) are marked PROTECT.
A7: • | B7: Every shelf first passed four hard gates: a true L3/L4 in the Staples tree, on Staples' work / school / small-business mission, 20+ Staples items as a baseline, and no clash with a Staples partner (Party City now supplies party décor and gift wrap on Staples.com).
A8: • | B8: Six Tier-1 shelves already have Staples SKUs in hand ('Fast-start'). Competitors are picked per shelf; Amazon wins most secondaries because its sellers are the ones Staples can actually recruit.
A9: • | B9: Caveats: no internal Staples sales or margin data exists, so 'Hero' uses external proxies (depth, header-nav visibility, merchandising investment, shopper association); swap in Staples' own sales rank when Pat shares it. Competitor depth is scored from desk research; confirm it when the listings are collected.
A11: Tier 1: PoC wave 1
A12: # | B12: Staples path (exact L3/L4) | C12: Score | D12: Level | E12: Hero segment · play | F12: Primary competitor | G12: Secondary competitor | H12: The story for the room | I12: Commercial moment | J12: Fast-start
A13: 1 | B13: Office Supplies > Calendars & Planners > Planners & Personal Organizers | C13: =INDEX('Path Scorecard'!$Z$5:$Z$71,MATCH("CL166388",'Path Scorecard'!$H$5:$H$71,0)) -> 95 | D13: L3 | E13: =INDEX('Path Scorecard'!$Q$5:$Q$71,MATCH("CL166388",'Path Scorecard'!$H$5:$H$71,0))&" · "&INDEX('Path Scorecard'!$AC$5:$AC$71,MATCH("CL166388",'Path Scorecard'!$H$5:$H$71,0)) -> Hero · EXTEND | F13: =INDEX('Path Scorecard'!$AE$5:$AE$71,MATCH("CL166388",'Path Scorecard'!$H$5:$H$71,0)) -> Amazon | G13: =INDEX('Path Scorecard'!$AF$5:$AF$71,MATCH("CL166388",'Path Scorecard'!$H$5:$H$71,0)) -> Michaels | H13: Staples launched Sincerely Jules for Blue Sky in Jun-2026. This shows the next step beyond one influencer line. | I13: Jan-2027 New Year planning; Jul-Aug 2027 academic planners. | J13: =INDEX('Path Scorecard'!$AD$5:$AD$71,MATCH("CL166388",'Path Scorecard'!$H$5:$H$71,0)) -> Yes
A14: 2 | B14: Office Supplies > Desk Organizers & Accessories > Desk Organizers | C14: =INDEX('Path Scorecard'!$Z$5:$Z$71,MATCH("CL140991",'Path Scorecard'!$H$5:$H$71,0)) -> 91 | D14: L3 | E14: =INDEX('Path Scorecard'!$Q$5:$Q$71,MATCH("CL140991",'Path Scorecard'!$H$5:$H$71,0))&" · "&INDEX('Path Scorecard'!$AC$5:$AC$71,MATCH("CL140991",'Path Scorecard'!$H$5:$H$71,0)) -> Hero · EXTEND | F14: =INDEX('Path Scorecard'!$AE$5:$AE$71,MATCH("CL140991",'Path Scorecard'!$H$5:$H$71,0)) -> Target | G14: =INDEX('Path Scorecard'!$AF$5:$AF$71,MATCH("CL140991",'Path Scorecard'!$H$5:$H$71,0)) -> Amazon | H14: Desk organization is a header-nav Staples staple and a low-ticket attach to every paper and pen basket. | I14: January 'get organized' season; BTS desk & dorm refresh. | J14: =INDEX('Path Scorecard'!$AD$5:$AD$71,MATCH("CL140991",'Path Scorecard'!$H$5:$H$71,0))
A15: 3 | B15: Coffee, Water & Snacks > Water & Beverages > Water Bottles, Tumblers & Travel Mugs | C15: =INDEX('Path Scorecard'!$Z$5:$Z$71,MATCH("CL354650",'Path Scorecard'!$H$5:$H$71,0)) -> 91 | D15: L3 | E15: =INDEX('Path Scorecard'!$Q$5:$Q$71,MATCH("CL354650",'Path Scorecard'!$H$5:$H$71,0))&" · "&INDEX('Path Scorecard'!$AC$5:$AC$71,MATCH("CL354650",'Path Scorecard'!$H$5:$H$71,0)) -> Probable Hero · BUILD | F15: =INDEX('Path Scorecard'!$AE$5:$AE$71,MATCH("CL354650",'Path Scorecard'!$H$5:$H$71,0)) -> Dick's Sporting Goods | G15: =INDEX('Path Scorecard'!$AF$5:$AF$71,MATCH("CL354650",'Path Scorecard'!$H$5:$H$71,0)) -> Target | H15: Everyone in the room knows the Stanley / Owala craze. | I15: BTS-2027 (Jul-Sep); Q4 gifting; January hydration resolutions. | J15: =INDEX('Path Scorecard'!$AD$5:$AD$71,MATCH("CL354650",'Path Scorecard'!$H$5:$H$71,0)) -> Yes
A16: 4 | B16: Furniture > Chairs & Seating > Accent & Waiting Room Chairs | C16: =INDEX('Path Scorecard'!$Z$5:$Z$71,MATCH("CL70203",'Path Scorecard'!$H$5:$H$71,0)) -> 89 | D16: L3 | E16: =INDEX('Path Scorecard'!$Q$5:$Q$71,MATCH("CL70203",'Path Scorecard'!$H$5:$H$71,0))&" · "&INDEX('Path Scorecard'!$AC$5:$AC$71,MATCH("CL70203",'Path Scorecard'!$H$5:$H$71,0)) -> Probable Hero · BUILD | F16: =INDEX('Path Scorecard'!$AE$5:$AE$71,MATCH("CL70203",'Path Scorecard'!$H$5:$H$71,0)) -> Wayfair | G16: =INDEX('Path Scorecard'!$AF$5:$AF$71,MATCH("CL70203",'Path Scorecard'!$H$5:$H$71,0)) -> Amazon | H16: Pat's own example: the thesis in one picture. | I16: Q1-2027 office refresh and return-to-office budgets. | J16: =INDEX('Path Scorecard'!$AD$5:$AD$71,MATCH("CL70203",'Path Scorecard'!$H$5:$H$71,0)) -> Yes
A17: 5 | B17: Furniture > Lamps & Lighting > Desk Lamps | C17: =INDEX('Path Scorecard'!$Z$5:$Z$71,MATCH("CL167867",'Path Scorecard'!$H$5:$H$71,0)) -> 86 | D17: L3 | E17: =INDEX('Path Scorecard'!$Q$5:$Q$71,MATCH("CL167867",'Path Scorecard'!$H$5:$H$71,0))&" · "&INDEX('Path Scorecard'!$AC$5:$AC$71,MATCH("CL167867",'Path Scorecard'!$H$5:$H$71,0)) -> Probable Hero · BUILD | F17: =INDEX('Path Scorecard'!$AE$5:$AE$71,MATCH("CL167867",'Path Scorecard'!$H$5:$H$71,0)) -> Wayfair | G17: =INDEX('Path Scorecard'!$AF$5:$AF$71,MATCH("CL167867",'Path Scorecard'!$H$5:$H$71,0)) -> Amazon | H17: 2026 home-office trend reports all name better lighting and warm materials. | I17: Q1-2027 home-office refresh; BTS dorm. | J17: =INDEX('Path Scorecard'!$AD$5:$AD$71,MATCH("CL167867",'Path Scorecard'!$H$5:$H$71,0)) -> Yes
A18: 6 | B18: Office Supplies > Writing Supplies & Instruments > Pencil Accessories > Pencil Cases & Pouches | C18: =INDEX('Path Scorecard'!$Z$5:$Z$71,MATCH("CL141253",'Path Scorecard'!$H$5:$H$71,0)) -> 86 | D18: L4 | E18: =INDEX('Path Scorecard'!$Q$5:$Q$71,MATCH("CL141253",'Path Scorecard'!$H$5:$H$71,0))&" · "&INDEX('Path Scorecard'!$AC$5:$AC$71,MATCH("CL141253",'Path Scorecard'!$H$5:$H$71,0)) -> Probable Hero · BUILD | F18: =INDEX('Path Scorecard'!$AE$5:$AE$71,MATCH("CL141253",'Path Scorecard'!$H$5:$H$71,0)) -> Amazon | G18: =INDEX('Path Scorecard'!$AF$5:$AF$71,MATCH("CL141253",'Path Scorecard'!$H$5:$H$71,0)) -> Target | H18: Staples' Recess Club / Jellygram exclusives (BTS 2026) already prove the demand. | I18: BTS-2027 (Jul-Sep). | J18: =INDEX('Path Scorecard'!$AD$5:$AD$71,MATCH("CL141253",'Path Scorecard'!$H$5:$H$71,0))
A19: 7 | B19: Bags, Backpacks & Luggage > Backpacks & Laptop Bags > Backpacks | C19: =INDEX('Path Scorecard'!$Z$5:$Z$71,MATCH("CL142745",'Path Scorecard'!$H$5:$H$71,0)) -> 86 | D19: L3 | E19: =INDEX('Path Scorecard'!$Q$5:$Q$71,MATCH("CL142745",'Path Scorecard'!$H$5:$H$71,0))&" · "&INDEX('Path Scorecard'!$AC$5:$AC$71,MATCH("CL142745",'Path Scorecard'!$H$5:$H$71,0)) -> Hero · EXTEND | F19: =INDEX('Path Scorecard'!$AE$5:$AE$71,MATCH("CL142745",'Path Scorecard'!$H$5:$H$71,0)) -> Amazon | G19: =INDEX('Path Scorecard'!$AF$5:$AF$71,MATCH("CL142745",'Path Scorecard'!$H$5:$H$71,0)) -> Target | H19: JanSport now sells on Target Plus, the curated-marketplace peer Pat can point to. | I19: BTS-2027. | J19: =INDEX('Path Scorecard'!$AD$5:$AD$71,MATCH("CL142745",'Path Scorecard'!$H$5:$H$71,0)) -> Yes
A20: 8 | B20: Bags, Backpacks & Luggage > Totes & Handbags > Lunch Bags & Boxes | C20: =INDEX('Path Scorecard'!$Z$5:$Z$71,MATCH("CL165124",'Path Scorecard'!$H$5:$H$71,0)) -> 86 | D20: L3 | E20: =INDEX('Path Scorecard'!$Q$5:$Q$71,MATCH("CL165124",'Path Scorecard'!$H$5:$H$71,0))&" · "&INDEX('Path Scorecard'!$AC$5:$AC$71,MATCH("CL165124",'Path Scorecard'!$H$5:$H$71,0)) -> Probable Hero · BUILD | F20: =INDEX('Path Scorecard'!$AE$5:$AE$71,MATCH("CL165124",'Path Scorecard'!$H$5:$H$71,0)) -> Amazon | G20: =INDEX('Path Scorecard'!$AF$5:$AF$71,MATCH("CL165124",'Path Scorecard'!$H$5:$H$71,0)) -> Target | H20: BTS is Pat's named seasonal anchor and lunch is on every parent's list. | I20: BTS-2027; January 'bring lunch to the office' resolutions. | J20: =INDEX('Path Scorecard'!$AD$5:$AD$71,MATCH("CL165124",'Path Scorecard'!$H$5:$H$71,0)) -> Yes
A21: 9 | B21: School Supplies > Teacher Supplies > Classroom Decorations > Decorative Accents & Board Sets | C21: =INDEX('Path Scorecard'!$Z$5:$Z$71,MATCH("CL219245",'Path Scorecard'!$H$5:$H$71,0)) -> 86 | D21: L4 | E21: =INDEX('Path Scorecard'!$Q$5:$Q$71,MATCH("CL219245",'Path Scorecard'!$H$5:$H$71,0))&" · "&INDEX('Path Scorecard'!$AC$5:$AC$71,MATCH("CL219245",'Path Scorecard'!$H$5:$H$71,0)) -> Hero · EXTEND | F21: =INDEX('Path Scorecard'!$AE$5:$AE$71,MATCH("CL219245",'Path Scorecard'!$H$5:$H$71,0)) -> Amazon | G21: =INDEX('Path Scorecard'!$AF$5:$AF$71,MATCH("CL219245",'Path Scorecard'!$H$5:$H$71,0)) -> Oriental Trading | H21: Teachers are a Staples loyalty segment (teacher coupon, teacher lists). | I21: BTS-2027 classroom set-up (Jul-Aug); Teacher Appreciation Week (May). | J21: =INDEX('Path Scorecard'!$AD$5:$AD$71,MATCH("CL219245",'Path Scorecard'!$H$5:$H$71,0))
A22: 10 | B22: Office Supplies > Storage & Organization > Storage Baskets | C22: =INDEX('Path Scorecard'!$Z$5:$Z$71,MATCH("CL354705",'Path Scorecard'!$H$5:$H$71,0)) -> 85 | D22: L3 | E22: =INDEX('Path Scorecard'!$Q$5:$Q$71,MATCH("CL354705",'Path Scorecard'!$H$5:$H$71,0))&" · "&INDEX('Path Scorecard'!$AC$5:$AC$71,MATCH("CL354705",'Path Scorecard'!$H$5:$H$71,0)) -> Probable Hero · BUILD | F22: =INDEX('Path Scorecard'!$AE$5:$AE$71,MATCH("CL354705",'Path Scorecard'!$H$5:$H$71,0)) -> Wayfair | G22: =INDEX('Path Scorecard'!$AF$5:$AF$71,MATCH("CL354705",'Path Scorecard'!$H$5:$H$71,0)) -> Target | H22: Organization is a January ritual every retailer promotes. | I22: January 'get organized' season. | J22: =INDEX('Path Scorecard'!$AD$5:$AD$71,MATCH("CL354705",'Path Scorecard'!$H$5:$H$71,0))
B23: Tier-1 mix (live) | C23: =COUNTIFS('Path Scorecard'!$AB$5:$AB$71,"Tier 1",'Path Scorecard'!$Q$5:$Q$71,"Hero")&" Hero · "&COUNTIFS('Path Scorecard'!$AB$5:$AB$71,"Tier 1",'Path Scorecard'!$Q$5:$Q$71,"Probable Hero")&" Probable Hero · "&COUNTIFS('Path Scorecard'!$AB$5:$AB$71,"Tier 1",'Path Scorecard'!$Q$5:$Q$71,"Non-Hero")&" Non-Hero" -> 4 Hero · 6 Probable Hero · 0 Non-Hero
A25: What changed versus the initial 9-item list
A26: • | B26: Kept and drilled down: Chairs & Seating, Desks, Lamps & Lighting (Wayfair stays primary), Hydration (now the exact L3 'Water Bottles, Tumblers & Travel Mugs') and Planning (Planners is the #1 shelf overall).
A27: • | B27: Hero segmentation moved from L2 to L3/L4. Most of the original L2s hold more than one segment: Chairs & Seating has a Hero to protect (Office Chairs), Probable Heroes to build (Accent, Bar Stools, Benches, Breakroom, Ottomans) and Non-Heroes (Kids, Gaming). See 'Your List Review' column I and the roll-up in 'Hero Segmentation'.
A28: • | B28: Competitor changed: Backpacks & Bags moves from Scheels to Amazon + Target (Scheels skews technical / outdoor, away from Staples' student and commuter shopper); Hydration moves to Dick's + Target (same brands as Scheels, national reach).
A29: • | B29: Parked: Rugs (no L3/L4 under 'Decor > Rugs') and Labels (an L2 leaf of commodity labels, and a Staples Hero to protect). Reframed: 'Labels & Packaging' becomes small-business packaging (Retail Boxes & Bags, Mailers, Label Makers vs Amazon + Uline); gift wrap and gift bags are gated out because of the Party City partnership.
A30: • | B30: Refocused: Fitness becomes an 'active workstation' idea (walking pads next to sit-stand desks); a Probable Hero, but Tier 3 on path score.
A31: • | B31: New shelves the list missed: Desk Organizers, Pencil Cases & Pouches, Classroom Decor, Storage Baskets (all Tier 1), plus desk-setup items and office decor in Tier 2.
A32: • | B32: v2 vs v1: added the Hero lens. Clocks and Desk Pads drop from Tier 2 to Tier 3 because they are Non-Hero; Tier 2 now holds 23 shelves.
A34: Suggested sequencing
A35: 1. | B35: Wave 1a (Staples data already in hand): Accent & Waiting Room Chairs, Desk Lamps, Planners, Water Bottles, Backpacks, Lunch Bags & Boxes: 2 Heroes (extend) and 4 Probable Heroes (build).
A36: 2. | B36: Wave 1b (needs a Staples leaf scrape first): Desk Organizers, Pencil Cases & Pouches, Classroom Decor, Storage Baskets.
A37: 3. | B37: Keep Office Chairs as a control shelf (Hero, PROTECT): it shows the safety gate correctly rejecting look-alikes of core 1P chairs.
A38: 4. | B38: Before the run: collect competitor listings per 'Competitor Fit' (primary first), confirm the depth scores, and ask Pat for a Staples sales / margin rank to replace the Hero proxies.
A40: How to read this workbook
B41: Segment Map | C41: One picture: every shelf placed as Hero, Probable Hero or Non-Hero.
B42: Your List Review | C42: Verdict on each of the 9 initial items, their segment mix, and exact L3/L4 drill-downs.
B43: Recommended Paths | C43: Tier 1 + Tier 2 shelves with segment, play, archetype hypotheses, 1P watch-outs, moments and where to look.
B44: Selection Criteria | C44: Gates, weights, segmentation proxies, cut-offs and plays (editable yellow cells).
B45: Path Scorecard | C45: All 67 candidate shelves with gates, segment, scores, rank, tier and play (formulas).
B46: Hero Segmentation | C46: The two indices behind each segment, plus an L2 roll-up.
B47: Competitor Fit / Competitor Profiles | C47: Why each primary and secondary competitor was chosen.
B48: Parked & Excluded | C48: What was considered and dropped, and why.
B49: Evidence & Sources | C49: Every fact with its source, date and reliability.
B50: Staples Tree Extract | C50: All terminal Staples nodes, for checking any path.
B52: Legend | C52: Blue text on yellow = editable input. Tiers: green Tier 1, amber Tier 2, grey Tier 3, red Parked. Segments: blue Hero, orange Probable Hero, grey Non-Hero.

Sheet Segment Map
A1: Segment map: Staples strength vs market attractiveness
A2: Picture = snapshot at default inputs (labelled). The Excel chart further down is live: it moves when you edit inputs or cut-offs.
B47: How to read it: right of the dashed line = Hero (Staples is already strong); top-left = Probable Hero (the market loves it, Staples is not yet a destination); bottom-left = Non-Hero.
B48: Plays: Hero shelves get EXTEND (add style extensions only) or PROTECT (keep the marketplace out, e.g. Office Chairs, Pens); Probable Heroes get BUILD (fill the gap with marketplace sellers); Non-Heroes are held.
B49: Tier 1 mixes both growth stories: Heroes to extend (Planners, Desk Organizers, Backpacks, Classroom Decor) and Probable Heroes to build (Water Bottles, Accent Chairs, Desk Lamps, Pencil Cases, Lunch, Storage Baskets).

Sheet Your List Review
A1: Review of the initial 9-item list, with exact L3/L4 drill-downs and their Hero segments
A2: Table 1 = verdict per item; column I shows that most L2s mix Hero, Probable Hero and Non-Hero shelves, which is why segmenting at L2 misleads. Table 2 = the drill-down paths.
A4: # | B4: Your item | C4: Your competitor | D4: Exact Staples node(s) | E4: Verdict | F4: What the research says | G4: Competitor view | H4: Recommended primary / secondary | I4: Segment mix of its L3/L4 paths (live)
A5: 1 | B5: Chairs & Seating | C5: Wayfair | D5: Furniture > Chairs & Seating | E5: KEEP: strongest item on the list | F5: Core-adjacent furniture with 14 leaves. The pilot already proved the method here (Accent & Waiting Room, Benches, Bar Stools). The 2026 'resimercial' return-to-office trend supports design-led seating. | G5: Wayfair is the right primary (depth + aesthetic, already scraped). Add Amazon as secondary for the recruitable seller pool and the value tier. | H5: Wayfair / Amazon | I5: ="Hero "&COUNTIFS('Hero Segmentation'!$C$5:$C$71,"1. Chairs & Seating",'Hero Segmentation'!$Q$5:$Q$71,"Hero",'Hero Segmentation'!$S$5:$S$71,"<>Parked (gate)")&CHAR(10)&"Probable Hero "&COUNTIFS('Hero Segmentation'!$C$5:$C$71,"1. Chairs & Seating",'Hero Segmentation'!$Q$5:$Q$71,"Probable Hero",'Hero Segmentation'!$S$5:$S$71,"<>Parked (gate)")&CHAR(10)&"Non-Hero "&COUNTIFS('Hero Segmentation'!$C$5:$C$71,"1. Chairs & Seating",'Hero Segmentation'!$Q$5:$Q$71,"Non-Hero",'Hero Segmentation'!$S$5:$S$71,"<>Parked (gate)")&CHAR(10)&"Parked "&COUNTIFS('Hero Segmentation'!$C$5:$C$71,"1. Chairs & Seating",'Hero Segmentation'!$S$5:$S$71,"Parked (gate)") -> Hero 1 Probable Hero 5 Non-Hero 2 Parked 0
A6: 2 | B6: Desks | C6: Wayfair | D6: Furniture > Desks | E6: KEEP, narrow to Office Desks | F6: Office Desks is the real shelf (1,501 items) and splits cleanly by Staples' own type facet. Sit & Stand is spec-led (motors, frames), so design gaps are smaller and cannibalisation risk is higher. | G6: Wayfair primary for Office Desks. If Sit & Stand is kept, Amazon should lead it (FlexiSpot / VIVO-type sellers). | H6: Wayfair / Amazon | I6: ="Hero "&COUNTIFS('Hero Segmentation'!$C$5:$C$71,"2. Desks",'Hero Segmentation'!$Q$5:$Q$71,"Hero",'Hero Segmentation'!$S$5:$S$71,"<>Parked (gate)")&CHAR(10)&"Probable Hero "&COUNTIFS('Hero Segmentation'!$C$5:$C$71,"2. Desks",'Hero Segmentation'!$Q$5:$Q$71,"Probable Hero",'Hero Segmentation'!$S$5:$S$71,"<>Parked (gate)")&CHAR(10)&"Non-Hero "&COUNTIFS('Hero Segmentation'!$C$5:$C$71,"2. Desks",'Hero Segmentation'!$Q$5:$Q$71,"Non-Hero",'Hero Segmentation'!$S$5:$S$71,"<>Parked (gate)")&CHAR(10)&"Parked "&COUNTIFS('Hero Segmentation'!$C$5:$C$71,"2. Desks",'Hero Segmentation'!$S$5:$S$71,"Parked (gate)") -> Hero 2 Probable Hero 0 Non-Hero 1 Parked 0
A7: 3 | B7: Lamps & Lighting | C7: Wayfair | D7: Furniture > Lamps & Lighting | E7: KEEP | F7: The purest aesthetic category in the core catalogue, and Staples SKUs are already in hand for desk, table and floor lamps. | G7: Wayfair is right. Amazon as secondary for Desk Lamps; Target for Table and Floor Lamps. | H7: Wayfair / Amazon or Target | I7: ="Hero "&COUNTIFS('Hero Segmentation'!$C$5:$C$71,"3. Lamps & Lighting",'Hero Segmentation'!$Q$5:$Q$71,"Hero",'Hero Segmentation'!$S$5:$S$71,"<>Parked (gate)")&CHAR(10)&"Probable Hero "&COUNTIFS('Hero Segmentation'!$C$5:$C$71,"3. Lamps & Lighting",'Hero Segmentation'!$Q$5:$Q$71,"Probable Hero",'Hero Segmentation'!$S$5:$S$71,"<>Parked (gate)")&CHAR(10)&"Non-Hero "&COUNTIFS('Hero Segmentation'!$C$5:$C$71,"3. Lamps & Lighting",'Hero Segmentation'!$Q$5:$Q$71,"Non-Hero",'Hero Segmentation'!$S$5:$S$71,"<>Parked (gate)")&CHAR(10)&"Parked "&COUNTIFS('Hero Segmentation'!$C$5:$C$71,"3. Lamps & Lighting",'Hero Segmentation'!$S$5:$S$71,"Parked (gate)") -> Hero 0 Probable Hero 3 Non-Hero 0 Parked 0
A8: 4 | B8: Rugs | C8: Wayfair | D8: Decor > Rugs (L2 leaf, no L3/L4 under it) | E8: PARK: fails the granularity gate | F8: There is nothing to drill into: 'Decor > Rugs' is a single L2 leaf of 804 items. Rugs are also residential decor, the weakest link to Staples' work and school mission. | G8: Wayfair would be the right competitor if a rug story is ever needed. For a decor story at L3/L4, use Storage Baskets (Tier 1) or Faux Plants / Frames (Tier 2). | H8: n/a | I8: ="Hero "&COUNTIFS('Hero Segmentation'!$C$5:$C$71,"4. Rugs",'Hero Segmentation'!$Q$5:$Q$71,"Hero",'Hero Segmentation'!$S$5:$S$71,"<>Parked (gate)")&CHAR(10)&"Probable Hero "&COUNTIFS('Hero Segmentation'!$C$5:$C$71,"4. Rugs",'Hero Segmentation'!$Q$5:$Q$71,"Probable Hero",'Hero Segmentation'!$S$5:$S$71,"<>Parked (gate)")&CHAR(10)&"Non-Hero "&COUNTIFS('Hero Segmentation'!$C$5:$C$71,"4. Rugs",'Hero Segmentation'!$Q$5:$Q$71,"Non-Hero",'Hero Segmentation'!$S$5:$S$71,"<>Parked (gate)")&CHAR(10)&"Parked "&COUNTIFS('Hero Segmentation'!$C$5:$C$71,"4. Rugs",'Hero Segmentation'!$S$5:$S$71,"Parked (gate)") -> Hero 0 Probable Hero 0 Non-Hero 0 Parked 1
A9: 5 | B9: Fitness Equipment | C9: Amazon | D9: Fitness > Fitness Equipment > Fitness Machines > Fitness Machines (the only leaf) | E9: REFOCUS as 'active workstation': Tier 3 | F9: Fitness is not a Staples destination: one leaf, 43 items, and not in the header nav. The only defensible angle is under-desk walking pads and desk bikes sold next to sit-stand desks. Bulky, low attach. | G9: Amazon is the right primary; Dick's Sporting Goods as secondary. | H9: Amazon / Dick's | I9: ="Hero "&COUNTIFS('Hero Segmentation'!$C$5:$C$71,"5. Fitness Equipment",'Hero Segmentation'!$Q$5:$Q$71,"Hero",'Hero Segmentation'!$S$5:$S$71,"<>Parked (gate)")&CHAR(10)&"Probable Hero "&COUNTIFS('Hero Segmentation'!$C$5:$C$71,"5. Fitness Equipment",'Hero Segmentation'!$Q$5:$Q$71,"Probable Hero",'Hero Segmentation'!$S$5:$S$71,"<>Parked (gate)")&CHAR(10)&"Non-Hero "&COUNTIFS('Hero Segmentation'!$C$5:$C$71,"5. Fitness Equipment",'Hero Segmentation'!$Q$5:$Q$71,"Non-Hero",'Hero Segmentation'!$S$5:$S$71,"<>Parked (gate)")&CHAR(10)&"Parked "&COUNTIFS('Hero Segmentation'!$C$5:$C$71,"5. Fitness Equipment",'Hero Segmentation'!$S$5:$S$71,"Parked (gate)") -> Hero 0 Probable Hero 1 Non-Hero 0 Parked 0
A10: 6 | B10: Backpacks & Bags | C10: Scheels | D10: Bags, Backpacks & Luggage > Backpacks & Laptop Bags (+ Totes & Handbags, Briefcases & Padfolios) | E10: KEEP the category, CHANGE the competitor | F10: A strong BTS anchor (85% of parents buy a backpack, Circana). But Scheels' depth is technical, hunting and outdoor packs, far from Staples' student and commuter shopper, so the method would mostly return OFF-BRAND archetypes. Scheels is also regional and blocks scraping. | G10: Amazon primary (breadth, recruitable sellers), Target secondary (lifestyle styles; JanSport sells via Target Plus). Keep Scheels only as an outdoor style reference. | H10: Amazon / Target | I10: ="Hero "&COUNTIFS('Hero Segmentation'!$C$5:$C$71,"6. Backpacks & Bags",'Hero Segmentation'!$Q$5:$Q$71,"Hero",'Hero Segmentation'!$S$5:$S$71,"<>Parked (gate)")&CHAR(10)&"Probable Hero "&COUNTIFS('Hero Segmentation'!$C$5:$C$71,"6. Backpacks & Bags",'Hero Segmentation'!$Q$5:$Q$71,"Probable Hero",'Hero Segmentation'!$S$5:$S$71,"<>Parked (gate)")&CHAR(10)&"Non-Hero "&COUNTIFS('Hero Segmentation'!$C$5:$C$71,"6. Backpacks & Bags",'Hero Segmentation'!$Q$5:$Q$71,"Non-Hero",'Hero Segmentation'!$S$5:$S$71,"<>Parked (gate)")&CHAR(10)&"Parked "&COUNTIFS('Hero Segmentation'!$C$5:$C$71,"6. Backpacks & Bags",'Hero Segmentation'!$S$5:$S$71,"Parked (gate)") -> Hero 1 Probable Hero 3 Non-Hero 0 Parked 1
A11: 7 | B11: Hydration & Drinkware | C11: Scheels | D11: Coffee, Water & Snacks > Water & Beverages > Water Bottles, Tumblers & Travel Mugs | E11: KEEP: a top-3 path | F11: The Staples node is an L3 under Coffee, Water & Snacks (there is no 'Hydration' node). 463 items, already in the sample. The kitchen 'Drinkware & Glassware' leaf has only 15 items and fails the baseline gate. | G11: Dick's primary (same brand depth as Scheels, but national); Target secondary (exclusive colourways, closest shopper). Scheels is an acceptable alternate. | H11: Dick's / Target | I11: ="Hero "&COUNTIFS('Hero Segmentation'!$C$5:$C$71,"7. Hydration & Drinkware",'Hero Segmentation'!$Q$5:$Q$71,"Hero",'Hero Segmentation'!$S$5:$S$71,"<>Parked (gate)")&CHAR(10)&"Probable Hero "&COUNTIFS('Hero Segmentation'!$C$5:$C$71,"7. Hydration & Drinkware",'Hero Segmentation'!$Q$5:$Q$71,"Probable Hero",'Hero Segmentation'!$S$5:$S$71,"<>Parked (gate)")&CHAR(10)&"Non-Hero "&COUNTIFS('Hero Segmentation'!$C$5:$C$71,"7. Hydration & Drinkware",'Hero Segmentation'!$Q$5:$Q$71,"Non-Hero",'Hero Segmentation'!$S$5:$S$71,"<>Parked (gate)")&CHAR(10)&"Parked "&COUNTIFS('Hero Segmentation'!$C$5:$C$71,"7. Hydration & Drinkware",'Hero Segmentation'!$S$5:$S$71,"Parked (gate)") -> Hero 0 Probable Hero 1 Non-Hero 0 Parked 1
A12: 8 | B12: Labels & Packaging Accessories | C12: Michaels | D12: Office Supplies > Labels (L2 leaf) · Party Supplies > Wrapping Supplies · Retail Store Supplies > Retail Packaging | E12: REFRAME | F12: 'Labels' is an L2 leaf of 11,493 Avery-type labels: no L3/L4, commodity, core 1P. Gift wrap and gift bags now overlap the Party City partner assortment on Staples.com (Apr-2026). Michaels has little depth in business labels or small-business packaging. | G12: Reframe as small-business packaging & labelling: Amazon primary, Uline secondary. For Label Makers: Amazon + Michaels (Cricut). | H12: Amazon / Uline | I12: ="Hero "&COUNTIFS('Hero Segmentation'!$C$5:$C$71,"8. Labels & Packaging Accessories",'Hero Segmentation'!$Q$5:$Q$71,"Hero",'Hero Segmentation'!$S$5:$S$71,"<>Parked (gate)")&CHAR(10)&"Probable Hero "&COUNTIFS('Hero Segmentation'!$C$5:$C$71,"8. Labels & Packaging Accessories",'Hero Segmentation'!$Q$5:$Q$71,"Probable Hero",'Hero Segmentation'!$S$5:$S$71,"<>Parked (gate)")&CHAR(10)&"Non-Hero "&COUNTIFS('Hero Segmentation'!$C$5:$C$71,"8. Labels & Packaging Accessories",'Hero Segmentation'!$Q$5:$Q$71,"Non-Hero",'Hero Segmentation'!$S$5:$S$71,"<>Parked (gate)")&CHAR(10)&"Parked "&COUNTIFS('Hero Segmentation'!$C$5:$C$71,"8. Labels & Packaging Accessories",'Hero Segmentation'!$S$5:$S$71,"Parked (gate)") -> Hero 2 Probable Hero 1 Non-Hero 0 Parked 3
A13: 9 | B13: Planning & Craft Organization | C13: Michaels | D13: Office Supplies > Calendars & Planners · Arts & Crafts > Scrapbooking / Crafting · Office Supplies > Storage & Organization | E13: KEEP, split in two | F13: Two different shopper missions in one bucket. Planning is the #1 path overall (Michaels' Happy Planner ecosystem vs Staples' dated planners). Craft organization is thin at Staples (66 items) and works better as general organization. | G13: Planning: Amazon and Michaels are a near-tie (Amazon edges it on seller recruitability): run both, with Michaels as the enthusiast-format benchmark. Organization: Target + Amazon, with Container Store as the style benchmark. | H13: Amazon / Michaels; Target / Amazon | I13: ="Hero "&COUNTIFS('Hero Segmentation'!$C$5:$C$71,"9. Planning & Craft Organization",'Hero Segmentation'!$Q$5:$Q$71,"Hero",'Hero Segmentation'!$S$5:$S$71,"<>Parked (gate)")&CHAR(10)&"Probable Hero "&COUNTIFS('Hero Segmentation'!$C$5:$C$71,"9. Planning & Craft Organization",'Hero Segmentation'!$Q$5:$Q$71,"Probable Hero",'Hero Segmentation'!$S$5:$S$71,"<>Parked (gate)")&CHAR(10)&"Non-Hero "&COUNTIFS('Hero Segmentation'!$C$5:$C$71,"9. Planning & Craft Organization",'Hero Segmentation'!$Q$5:$Q$71,"Non-Hero",'Hero Segmentation'!$S$5:$S$71,"<>Parked (gate)")&CHAR(10)&"Parked "&COUNTIFS('Hero Segmentation'!$C$5:$C$71,"9. Planning & Craft Organization",'Hero Segmentation'!$S$5:$S$71,"Parked (gate)") -> Hero 3 Probable Hero 3 Non-Hero 1 Parked 0
A15: Table 2. Drill-down L3/L4 paths for each item (exact nav-tree paths; tier, score and competitors are live)
A16: # | B16: Path ID | C16: Staples path (exact) | D16: Level | E16: Category ID | F16: Staples items | G16: Hero segment | H16: Marketplace play | I16: Tier | J16: Score | K16: Primary / Secondary competitor | L16: Role in PoC
A17: 1 | B17: P04 | C17: Furniture > Chairs & Seating > Accent & Waiting Room Chairs | D17: 3 | E17: CL70203 | F17: 229 | G17: =INDEX('Path Scorecard'!$Q$5:$Q$71,MATCH($E17,'Path Scorecard'!$H$5:$H$71,0)) -> Probable Hero | H17: =INDEX('Path Scorecard'!$AC$5:$AC$71,MATCH($E17,'Path Scorecard'!$H$5:$H$71,0)) -> BUILD | I17: =INDEX('Path Scorecard'!$AB$5:$AB$71,MATCH($E17,'Path Scorecard'!$H$5:$H$71,0)) -> Tier 1 | J17: =INDEX('Path Scorecard'!$Z$5:$Z$71,MATCH($E17,'Path Scorecard'!$H$5:$H$71,0)) -> 89 | K17: =INDEX('Path Scorecard'!$AE$5:$AE$71,MATCH($E17,'Path Scorecard'!$H$5:$H$71,0))&" / "&INDEX('Path Scorecard'!$AF$5:$AF$71,MATCH($E17,'Path Scorecard'!$H$5:$H$71,0)) -> Wayfair / Amazon | L17: PoC wave 1
A18: 1 | B18: P25 | C18: Furniture > Chairs & Seating > Sofas & Benches > Benches & Beam Seating | D18: 4 | E18: CL163750 | F18: 49 | G18: =INDEX('Path Scorecard'!$Q$5:$Q$71,MATCH($E18,'Path Scorecard'!$H$5:$H$71,0)) -> Probable Hero | H18: =INDEX('Path Scorecard'!$AC$5:$AC$71,MATCH($E18,'Path Scorecard'!$H$5:$H$71,0)) -> BUILD | I18: =INDEX('Path Scorecard'!$AB$5:$AB$71,MATCH($E18,'Path Scorecard'!$H$5:$H$71,0)) -> Tier 2 | J18: =INDEX('Path Scorecard'!$Z$5:$Z$71,MATCH($E18,'Path Scorecard'!$H$5:$H$71,0)) -> 75 | K18: =INDEX('Path Scorecard'!$AE$5:$AE$71,MATCH($E18,'Path Scorecard'!$H$5:$H$71,0))&" / "&INDEX('Path Scorecard'!$AF$5:$AF$71,MATCH($E18,'Path Scorecard'!$H$5:$H$71,0)) -> Wayfair / Amazon | L18: Wave 2 / swap-in
A19: 1 | B19: P30 | C19: Furniture > Chairs & Seating > Stools & Ottomans > Counter & Bar Stools | D19: 4 | E19: CL166182 | F19: 617 | G19: =INDEX('Path Scorecard'!$Q$5:$Q$71,MATCH($E19,'Path Scorecard'!$H$5:$H$71,0)) -> Probable Hero | H19: =INDEX('Path Scorecard'!$AC$5:$AC$71,MATCH($E19,'Path Scorecard'!$H$5:$H$71,0)) -> BUILD | I19: =INDEX('Path Scorecard'!$AB$5:$AB$71,MATCH($E19,'Path Scorecard'!$H$5:$H$71,0)) -> Tier 2 | J19: =INDEX('Path Scorecard'!$Z$5:$Z$71,MATCH($E19,'Path Scorecard'!$H$5:$H$71,0)) -> 73 | K19: =INDEX('Path Scorecard'!$AE$5:$AE$71,MATCH($E19,'Path Scorecard'!$H$5:$H$71,0))&" / "&INDEX('Path Scorecard'!$AF$5:$AF$71,MATCH($E19,'Path Scorecard'!$H$5:$H$71,0)) -> Wayfair / Amazon | L19: Wave 2 / swap-in
A20: 1 | B20: P28 | C20: Furniture > Chairs & Seating > Breakroom & Dining Chairs | D20: 3 | E20: CL166181 | F20: 75 | G20: =INDEX('Path Scorecard'!$Q$5:$Q$71,MATCH($E20,'Path Scorecard'!$H$5:$H$71,0)) -> Probable Hero | H20: =INDEX('Path Scorecard'!$AC$5:$AC$71,MATCH($E20,'Path Scorecard'!$H$5:$H$71,0)) -> BUILD | I20: =INDEX('Path Scorecard'!$AB$5:$AB$71,MATCH($E20,'Path Scorecard'!$H$5:$H$71,0)) -> Tier 2 | J20: =INDEX('Path Scorecard'!$Z$5:$Z$71,MATCH($E20,'Path Scorecard'!$H$5:$H$71,0)) -> 74 | K20: =INDEX('Path Scorecard'!$AE$5:$AE$71,MATCH($E20,'Path Scorecard'!$H$5:$H$71,0))&" / "&INDEX('Path Scorecard'!$AF$5:$AF$71,MATCH($E20,'Path Scorecard'!$H$5:$H$71,0)) -> Wayfair / Amazon | L20: Wave 2 / swap-in
A21: 1 | B21: P36 | C21: Furniture > Chairs & Seating > Stools & Ottomans > Ottomans | D21: 4 | E21: CL161807 | F21: 64 | G21: =INDEX('Path Scorecard'!$Q$5:$Q$71,MATCH($E21,'Path Scorecard'!$H$5:$H$71,0)) -> Probable Hero | H21: =INDEX('Path Scorecard'!$AC$5:$AC$71,MATCH($E21,'Path Scorecard'!$H$5:$H$71,0)) -> BUILD | I21: =INDEX('Path Scorecard'!$AB$5:$AB$71,MATCH($E21,'Path Scorecard'!$H$5:$H$71,0)) -> Tier 3 | J21: =INDEX('Path Scorecard'!$Z$5:$Z$71,MATCH($E21,'Path Scorecard'!$H$5:$H$71,0)) -> 69 | K21: =INDEX('Path Scorecard'!$AE$5:$AE$71,MATCH($E21,'Path Scorecard'!$H$5:$H$71,0))&" / "&INDEX('Path Scorecard'!$AF$5:$AF$71,MATCH($E21,'Path Scorecard'!$H$5:$H$71,0)) -> Wayfair / Amazon | L21: Backlog
A22: 1 | B22: P48 | C22: Furniture > Chairs & Seating > Office Chairs | D22: 3 | E22: CL166253 | F22: 1008 | G22: =INDEX('Path Scorecard'!$Q$5:$Q$71,MATCH($E22,'Path Scorecard'!$H$5:$H$71,0)) -> Hero | H22: =INDEX('Path Scorecard'!$AC$5:$AC$71,MATCH($E22,'Path Scorecard'!$H$5:$H$71,0)) -> PROTECT | I22: =INDEX('Path Scorecard'!$AB$5:$AB$71,MATCH($E22,'Path Scorecard'!$H$5:$H$71,0)) -> Tier 3 | J22: =INDEX('Path Scorecard'!$Z$5:$Z$71,MATCH($E22,'Path Scorecard'!$H$5:$H$71,0)) -> 65 | K22: =INDEX('Path Scorecard'!$AE$5:$AE$71,MATCH($E22,'Path Scorecard'!$H$5:$H$71,0))&" / "&INDEX('Path Scorecard'!$AF$5:$AF$71,MATCH($E22,'Path Scorecard'!$H$5:$H$71,0)) -> Wayfair / Amazon (control shelf) | L22: Control shelf (Hero, PROTECT): shows the safety gate rejecting core-1P look-alikes
A23: 1 | B23: P55 | C23: Furniture > Chairs & Seating > Kids Seating | D23: 3 | E23: CL210316 | F23: 147 | G23: =INDEX('Path Scorecard'!$Q$5:$Q$71,MATCH($E23,'Path Scorecard'!$H$5:$H$71,0)) -> Non-Hero | H23: =INDEX('Path Scorecard'!$AC$5:$AC$71,MATCH($E23,'Path Scorecard'!$H$5:$H$71,0)) -> HOLD | I23: =INDEX('Path Scorecard'!$AB$5:$AB$71,MATCH($E23,'Path Scorecard'!$H$5:$H$71,0)) -> Tier 3 | J23: =INDEX('Path Scorecard'!$Z$5:$Z$71,MATCH($E23,'Path Scorecard'!$H$5:$H$71,0)) -> 59 | K23: =INDEX('Path Scorecard'!$AE$5:$AE$71,MATCH($E23,'Path Scorecard'!$H$5:$H$71,0))&" / "&INDEX('Path Scorecard'!$AF$5:$AF$71,MATCH($E23,'Path Scorecard'!$H$5:$H$71,0)) -> Wayfair / Target | L23: Backlog
A24: 1 | B24: P58 | C24: Furniture > Chairs & Seating > Gaming Chairs | D24: 3 | E24: CL210317 | F24: 87 | G24: =INDEX('Path Scorecard'!$Q$5:$Q$71,MATCH($E24,'Path Scorecard'!$H$5:$H$71,0)) -> Non-Hero | H24: =INDEX('Path Scorecard'!$AC$5:$AC$71,MATCH($E24,'Path Scorecard'!$H$5:$H$71,0)) -> HOLD | I24: =INDEX('Path Scorecard'!$AB$5:$AB$71,MATCH($E24,'Path Scorecard'!$H$5:$H$71,0)) -> Tier 3 | J24: =INDEX('Path Scorecard'!$Z$5:$Z$71,MATCH($E24,'Path Scorecard'!$H$5:$H$71,0)) -> 50 | K24: =INDEX('Path Scorecard'!$AE$5:$AE$71,MATCH($E24,'Path Scorecard'!$H$5:$H$71,0))&" / "&INDEX('Path Scorecard'!$AF$5:$AF$71,MATCH($E24,'Path Scorecard'!$H$5:$H$71,0)) -> Best Buy / Amazon | L24: Backlog
A25: 2 | B25: P13 | C25: Furniture > Desks > Office Desks | D25: 3 | E25: CL210795 | F25: 1501 | G25: =INDEX('Path Scorecard'!$Q$5:$Q$71,MATCH($E25,'Path Scorecard'!$H$5:$H$71,0)) -> Hero | H25: =INDEX('Path Scorecard'!$AC$5:$AC$71,MATCH($E25,'Path Scorecard'!$H$5:$H$71,0)) -> EXTEND | I25: =INDEX('Path Scorecard'!$AB$5:$AB$71,MATCH($E25,'Path Scorecard'!$H$5:$H$71,0)) -> Tier 2 | J25: =INDEX('Path Scorecard'!$Z$5:$Z$71,MATCH($E25,'Path Scorecard'!$H$5:$H$71,0)) -> 81 | K25: =INDEX('Path Scorecard'!$AE$5:$AE$71,MATCH($E25,'Path Scorecard'!$H$5:$H$71,0))&" / "&INDEX('Path Scorecard'!$AF$5:$AF$71,MATCH($E25,'Path Scorecard'!$H$5:$H$71,0)) -> Wayfair / Amazon | L25: Wave 2 / swap-in
A26: 2 | B26: P47 | C26: Furniture > Desks > Sit & Stand Desks | D26: 3 | E26: CL215523 | F26: 576 | G26: =INDEX('Path Scorecard'!$Q$5:$Q$71,MATCH($E26,'Path Scorecard'!$H$5:$H$71,0)) -> Hero | H26: =INDEX('Path Scorecard'!$AC$5:$AC$71,MATCH($E26,'Path Scorecard'!$H$5:$H$71,0)) -> PROTECT | I26: =INDEX('Path Scorecard'!$AB$5:$AB$71,MATCH($E26,'Path Scorecard'!$H$5:$H$71,0)) -> Tier 3 | J26: =INDEX('Path Scorecard'!$Z$5:$Z$71,MATCH($E26,'Path Scorecard'!$H$5:$H$71,0)) -> 66 | K26: =INDEX('Path Scorecard'!$AE$5:$AE$71,MATCH($E26,'Path Scorecard'!$H$5:$H$71,0))&" / "&INDEX('Path Scorecard'!$AF$5:$AF$71,MATCH($E26,'Path Scorecard'!$H$5:$H$71,0)) -> Amazon / Wayfair | L26: Backlog
A27: 2 | B27: P57 | C27: Furniture > Desks > Desk Components & Hutches > Hutches | D27: 4 | E27: CL353865 | F27: 77 | G27: =INDEX('Path Scorecard'!$Q$5:$Q$71,MATCH($E27,'Path Scorecard'!$H$5:$H$71,0)) -> Non-Hero | H27: =INDEX('Path Scorecard'!$AC$5:$AC$71,MATCH($E27,'Path Scorecard'!$H$5:$H$71,0)) -> HOLD | I27: =INDEX('Path Scorecard'!$AB$5:$AB$71,MATCH($E27,'Path Scorecard'!$H$5:$H$71,0)) -> Tier 3 | J27: =INDEX('Path Scorecard'!$Z$5:$Z$71,MATCH($E27,'Path Scorecard'!$H$5:$H$71,0)) -> 52 | K27: =INDEX('Path Scorecard'!$AE$5:$AE$71,MATCH($E27,'Path Scorecard'!$H$5:$H$71,0))&" / "&INDEX('Path Scorecard'!$AF$5:$AF$71,MATCH($E27,'Path Scorecard'!$H$5:$H$71,0)) -> Wayfair / Amazon | L27: Backlog
A28: 3 | B28: P05 | C28: Furniture > Lamps & Lighting > Desk Lamps | D28: 3 | E28: CL167867 | F28: 210 | G28: =INDEX('Path Scorecard'!$Q$5:$Q$71,MATCH($E28,'Path Scorecard'!$H$5:$H$71,0)) -> Probable Hero | H28: =INDEX('Path Scorecard'!$AC$5:$AC$71,MATCH($E28,'Path Scorecard'!$H$5:$H$71,0)) -> BUILD | I28: =INDEX('Path Scorecard'!$AB$5:$AB$71,MATCH($E28,'Path Scorecard'!$H$5:$H$71,0)) -> Tier 1 | J28: =INDEX('Path Scorecard'!$Z$5:$Z$71,MATCH($E28,'Path Scorecard'!$H$5:$H$71,0)) -> 86 | K28: =INDEX('Path Scorecard'!$AE$5:$AE$71,MATCH($E28,'Path Scorecard'!$H$5:$H$71,0))&" / "&INDEX('Path Scorecard'!$AF$5:$AF$71,MATCH($E28,'Path Scorecard'!$H$5:$H$71,0)) -> Wayfair / Amazon | L28: PoC wave 1
... A53: 9 | B53: P34 | C53: Office Supplies > Storage & Organization > Storage Bins | D53: 3 | E53: CL354710 | F53: 660 | G53: =INDEX('Path Scorecard'!$Q$5:$Q$71,MATCH($E53,'Path Scorecard'!$H$5:$H$71,0)) -> Hero | H53: =INDEX('Path Scorecard'!$AC$5:$AC$71,MATCH($E53,'Path Scorecard'!$H$5:$H$71,0)) -> EXTEND | I53: =INDEX('Path Scorecard'!$AB$5:$AB$71,MATCH($E53,'Path Scorecard'!$H$5:$H$71,0)) -> Tier 2 | J53: =INDEX('Path Scorecard'!$Z$5:$Z$71,MATCH($E53,'Path Scorecard'!$H$5:$H$71,0)) -> 72 | K53: =INDEX('Path Scorecard'!$AE$5:$AE$71,MATCH($E53,'Path Scorecard'!$H$5:$H$71,0))&" / "&INDEX('Path Scorecard'!$AF$5:$AF$71,MATCH($E53,'Path Scorecard'!$H$5:$H$71,0)) -> Target / Amazon | L53: Wave 2 / swap-in

Sheet Recommended Paths
A1: Recommended L3/L4 paths: Tier 1 (PoC wave 1) and Tier 2 (wave 2 / swap-ins)
A2: Rows are in default-score order. Segment, play, score, tier, rank and competitors are live lookups; the narrative reflects the research at default inputs.
A4: Rank | B4: Tier | C4: Hero segment | D4: Marketplace play | E4: Score | F4: Staples path (exact) | G4: Level | H4: Category ID | I4: Staples items | J4: SKUs in hand | K4: Fast-start | L4: Primary competitor | M4: Secondary competitor | N4: Why this path | O4: Archetypes we expect to find (hypotheses) | P4: 1P watch-out (cannibalisation) | Q4: Commercial moment | R4: Why the room will relate | S4: Where to look on the competitors | T4: Staples URL
A5: =INDEX('Path Scorecard'!$AA$5:$AA$71,MATCH($H5,'Path Scorecard'!$H$5:$H$71,0)) -> 1 | B5: =INDEX('Path Scorecard'!$AB$5:$AB$71,MATCH($H5,'Path Scorecard'!$H$5:$H$71,0)) -> Tier 1 | C5: =INDEX('Path Scorecard'!$Q$5:$Q$71,MATCH($H5,'Path Scorecard'!$H$5:$H$71,0)) -> Hero | D5: =INDEX('Path Scorecard'!$AC$5:$AC$71,MATCH($H5,'Path Scorecard'!$H$5:$H$71,0)) -> EXTEND | E5: =INDEX('Path Scorecard'!$Z$5:$Z$71,MATCH($H5,'Path Scorecard'!$H$5:$H$71,0)) -> 95 | F5: Office Supplies > Calendars & Planners > Planners & Personal Organizers | G5: 3 | H5: CL166388 | I5: 1037 | J5: 1016 | K5: =INDEX('Path Scorecard'!$AD$5:$AD$71,MATCH($H5,'Path Scorecard'!$H$5:$H$71,0)) -> Yes | L5: =INDEX('Path Scorecard'!$AE$5:$AE$71,MATCH($H5,'Path Scorecard'!$H$5:$H$71,0)) -> Amazon | M5: =INDEX('Path Scorecard'!$AF$5:$AF$71,MATCH($H5,'Path Scorecard'!$H$5:$H$71,0)) -> Michaels | N5: Staples' deepest stationery shelf (1,037 items) is dated-planner led (Blue Sky, At-A-Glance). Enthusiast formats (disc-bound, undated, sticker-ready, wellness) live at Michaels and Amazon. | O5: Disc-bound customisable planners; undated goal & wellness planners; pastel/floral teacher & student planners; vegan-leather premium planners ($30-60). | P5: Dated 12-month planners incl. the Sincerely Jules exclusive: add other formats, not look-alikes. | Q5: Jan-2027 New Year planning; Jul-Aug 2027 academic planners. | R5: Staples launched Sincerely Jules for Blue Sky in Jun-2026. This shows the next step beyond one influencer line. | S5: Amazon: Planners, Refills & Covers (breadth + recruitable sellers). Michaels: Papercraft > Planners (The Happy Planner + companion accessories); near-tie with Amazon. | T5: https://www.staples.com/Planners-Personal-Organizers/cat_CL166388
A6: =INDEX('Path Scorecard'!$AA$5:$AA$71,MATCH($H6,'Path Scorecard'!$H$5:$H$71,0)) -> 2 | B6: =INDEX('Path Scorecard'!$AB$5:$AB$71,MATCH($H6,'Path Scorecard'!$H$5:$H$71,0)) -> Tier 1 | C6: =INDEX('Path Scorecard'!$Q$5:$Q$71,MATCH($H6,'Path Scorecard'!$H$5:$H$71,0)) -> Hero | D6: =INDEX('Path Scorecard'!$AC$5:$AC$71,MATCH($H6,'Path Scorecard'!$H$5:$H$71,0)) -> EXTEND | E6: =INDEX('Path Scorecard'!$Z$5:$Z$71,MATCH($H6,'Path Scorecard'!$H$5:$H$71,0)) -> 91 | F6: Office Supplies > Desk Organizers & Accessories > Desk Organizers | G6: 3 | H6: CL140991 | I6: 342 | J6: 0 | K6: =INDEX('Path Scorecard'!$AD$5:$AD$71,MATCH($H6,'Path Scorecard'!$H$5:$H$71,0)) | L6: =INDEX('Path Scorecard'!$AE$5:$AE$71,MATCH($H6,'Path Scorecard'!$H$5:$H$71,0)) -> Target | M6: =INDEX('Path Scorecard'!$AF$5:$AF$71,MATCH($H6,'Path Scorecard'!$H$5:$H$71,0)) -> Amazon | N6: Staples' 342 organizers are mostly black mesh and utility. Target (Brightroom) and Container Store sell coordinated desk collections in acrylic, bamboo, marble, linen and pastel. | O6: Clear acrylic modular sets; warm-wood / bamboo sets; pastel & neutral 'aesthetic desk' collections; turntable caddies. | P6: Black mesh sets (Staples brand, Officemate). | Q6: January 'get organized' season; BTS desk & dorm refresh. | R6: Desk organization is a header-nav Staples staple and a low-ticket attach to every paper and pen basket. | S6: Target: Brightroom desk organization + Target Plus brands. Amazon: Desk Organizers. Container Store: Office > Desktop Collections (style benchmark). | T6: https://www.staples.com/Desk-Organizers/cat_CL140991
A7: =INDEX('Path Scorecard'!$AA$5:$AA$71,MATCH($H7,'Path Scorecard'!$H$5:$H$71,0)) -> 2 | B7: =INDEX('Path Scorecard'!$AB$5:$AB$71,MATCH($H7,'Path Scorecard'!$H$5:$H$71,0)) -> Tier 1 | C7: =INDEX('Path Scorecard'!$Q$5:$Q$71,MATCH($H7,'Path Scorecard'!$H$5:$H$71,0)) -> Probable Hero | D7: =INDEX('Path Scorecard'!$AC$5:$AC$71,MATCH($H7,'Path Scorecard'!$H$5:$H$71,0)) -> BUILD | E7: =INDEX('Path Scorecard'!$Z$5:$Z$71,MATCH($H7,'Path Scorecard'!$H$5:$H$71,0)) -> 91 | F7: Coffee, Water & Snacks > Water & Beverages > Water Bottles, Tumblers & Travel Mugs | G7: 3 | H7: CL354650 | I7: 463 | J7: 462 | K7: =INDEX('Path Scorecard'!$AD$5:$AD$71,MATCH($H7,'Path Scorecard'!$H$5:$H$71,0)) -> Yes | L7: =INDEX('Path Scorecard'!$AE$5:$AE$71,MATCH($H7,'Path Scorecard'!$H$5:$H$71,0)) -> Dick's Sporting Goods | M7: =INDEX('Path Scorecard'!$AF$5:$AF$71,MATCH($H7,'Path Scorecard'!$H$5:$H$71,0)) -> Target | N7: Staples carries 463 desk-use items. Specialists sell full colourways, lids, sizes and accessories from Owala, Stanley, YETI, HydroJug and BruMate. | O7: Sip/chug hybrid bottles; 40 oz handle tumblers in seasonal colourways; kids' 12-16 oz school bottles; lids, boots & straw accessories. | P7: Stanley / Hydro Flask SKUs Staples already sells: gap is colourway & size, not the same SKU. | Q7: BTS-2027 (Jul-Sep); Q4 gifting; January hydration resolutions. | R7: Everyone in the room knows the Stanley / Owala craze. | S7: Dick's: Drinkware / Sport Water Bottles. Target: water bottles & tumblers incl. exclusive colourways. | T7: https://www.staples.com/Water-Bottles-Tumblers-Travel-Mugs/cat_CL354650
A8: =INDEX('Path Scorecard'!$AA$5:$AA$71,MATCH($H8,'Path Scorecard'!$H$5:$H$71,0)) -> 4 | B8: =INDEX('Path Scorecard'!$AB$5:$AB$71,MATCH($H8,'Path Scorecard'!$H$5:$H$71,0)) -> Tier 1 | C8: =INDEX('Path Scorecard'!$Q$5:$Q$71,MATCH($H8,'Path Scorecard'!$H$5:$H$71,0)) -> Probable Hero | D8: =INDEX('Path Scorecard'!$AC$5:$AC$71,MATCH($H8,'Path Scorecard'!$H$5:$H$71,0)) -> BUILD | E8: =INDEX('Path Scorecard'!$Z$5:$Z$71,MATCH($H8,'Path Scorecard'!$H$5:$H$71,0)) -> 89 | F8: Furniture > Chairs & Seating > Accent & Waiting Room Chairs | G8: 3 | H8: CL70203 | I8: 229 | J8: 199 | K8: =INDEX('Path Scorecard'!$AD$5:$AD$71,MATCH($H8,'Path Scorecard'!$H$5:$H$71,0)) -> Yes | L8: =INDEX('Path Scorecard'!$AE$5:$AE$71,MATCH($H8,'Path Scorecard'!$H$5:$H$71,0)) -> Wayfair | M8: =INDEX('Path Scorecard'!$AF$5:$AF$71,MATCH($H8,'Path Scorecard'!$H$5:$H$71,0)) -> Amazon | N8: The original 'White Chair' shelf. Pilot (Sep-2026): 5 recommended archetypes, 2 Strong; 94% high-confidence mapping. | O8: Boucle / curved barrel chairs; cream & sage upholstered side chairs with wood legs; rattan & cane lounge chairs; $150-350 design tier. | P8: Black vinyl / fabric guest & reception chairs (Flash, Boss, HON). | Q8: Q1-2027 office refresh and return-to-office budgets. | R8: Pat's own example: the thesis in one picture. | S8: Wayfair: Living Room > Accent Chairs and Professional > Office Seating > Accent Chairs. Amazon: Accent Chairs. | T8: https://www.staples.com/Accent-Waiting-Room-Chairs/cat_CL70203
A9: =INDEX('Path Scorecard'!$AA$5:$AA$71,MATCH($H9,'Path Scorecard'!$H$5:$H$71,0)) -> 5 | B9: =INDEX('Path Scorecard'!$AB$5:$AB$71,MATCH($H9,'Path Scorecard'!$H$5:$H$71,0)) -> Tier 1 | C9: =INDEX('Path Scorecard'!$Q$5:$Q$71,MATCH($H9,'Path Scorecard'!$H$5:$H$71,0)) -> Probable Hero | D9: =INDEX('Path Scorecard'!$AC$5:$AC$71,MATCH($H9,'Path Scorecard'!$H$5:$H$71,0)) -> BUILD | E9: =INDEX('Path Scorecard'!$Z$5:$Z$71,MATCH($H9,'Path Scorecard'!$H$5:$H$71,0)) -> 86 | F9: Furniture > Lamps & Lighting > Desk Lamps | G9: 3 | H9: CL167867 | I9: 210 | J9: 195 | K9: =INDEX('Path Scorecard'!$AD$5:$AD$71,MATCH($H9,'Path Scorecard'!$H$5:$H$71,0)) -> Yes | L9: =INDEX('Path Scorecard'!$AE$5:$AE$71,MATCH($H9,'Path Scorecard'!$H$5:$H$71,0)) -> Wayfair | M9: =INDEX('Path Scorecard'!$AF$5:$AF$71,MATCH($H9,'Path Scorecard'!$H$5:$H$71,0)) -> Amazon | N9: 210 Staples items, mostly LED task lamps. Wayfair sells mushroom, pleated, rechargeable and sculptural lamps that sit between task light and decor. | O9: Mushroom / dome lamps; pleated-shade & ceramic-base lamps; rechargeable cordless lamps; brass & warm-wood architect lamps. | P9: LED task lamps with USB ports: Staples' core. | Q9: Q1-2027 home-office refresh; BTS dorm. | R9: 2026 home-office trend reports all name better lighting and warm materials. | S9: Wayfair: Lighting > Table & Floor Lamps > Desk Lamps (+ Teen Desk Lamps). Amazon: Desk Lamps. | T9: https://www.staples.com/Desk-Lamps/cat_CL167867
A10: =INDEX('Path Scorecard'!$AA$5:$AA$71,MATCH($H10,'Path Scorecard'!$H$5:$H$71,0)) -> 5 | B10: =INDEX('Path Scorecard'!$AB$5:$AB$71,MATCH($H10,'Path Scorecard'!$H$5:$H$71,0)) -> Tier 1 | C10: =INDEX('Path Scorecard'!$Q$5:$Q$71,MATCH($H10,'Path Scorecard'!$H$5:$H$71,0)) -> Probable Hero | D10: =INDEX('Path Scorecard'!$AC$5:$AC$71,MATCH($H10,'Path Scorecard'!$H$5:$H$71,0)) -> BUILD | E10: =INDEX('Path Scorecard'!$Z$5:$Z$71,MATCH($H10,'Path Scorecard'!$H$5:$H$71,0)) -> 86 | F10: Office Supplies > Writing Supplies & Instruments > Pencil Accessories > Pencil Cases & Pouches | G10: 4 | H10: CL141253 | I10: 107 | J10: 0 | K10: =INDEX('Path Scorecard'!$AD$5:$AD$71,MATCH($H10,'Path Scorecard'!$H$5:$H$71,0)) | L10: =INDEX('Path Scorecard'!$AE$5:$AE$71,MATCH($H10,'Path Scorecard'!$H$5:$H$71,0)) -> Amazon | M10: =INDEX('Path Scorecard'!$AF$5:$AF$71,MATCH($H10,'Path Scorecard'!$H$5:$H$71,0)) -> Target | N10: 107 Staples items. The pencil pouch is the first 'aesthetic' purchase in the BTS basket, at under $20. | O10: Large-capacity multi-layer pouches (Japanese style); clear / jelly pouches; corduroy & quilted pouches; kawaii & character cases. | P10: Staples' own Recess Club pouches: extend beyond them, don't duplicate. | Q10: BTS-2027 (Jul-Sep). | R10: Staples' Recess Club / Jellygram exclusives (BTS 2026) already prove the demand. | S10: Amazon: Pencil Cases. Target: pencil cases & pouches. JetPens: Pencil Cases (style benchmark). | T10: https://www.staples.com/Pencil-Cases-Pouches/cat_CL141253
A11: =INDEX('Path Scorecard'!$AA$5:$AA$71,MATCH($H11,'Path Scorecard'!$H$5:$H$71,0)) -> 5 | B11: =INDEX('Path Scorecard'!$AB$5:$AB$71,MATCH($H11,'Path Scorecard'!$H$5:$H$71,0)) -> Tier 1 | C11: =INDEX('Path Scorecard'!$Q$5:$Q$71,MATCH($H11,'Path Scorecard'!$H$5:$H$71,0)) -> Hero | D11: =INDEX('Path Scorecard'!$AC$5:$AC$71,MATCH($H11,'Path Scorecard'!$H$5:$H$71,0)) -> EXTEND | E11: =INDEX('Path Scorecard'!$Z$5:$Z$71,MATCH($H11,'Path Scorecard'!$H$5:$H$71,0)) -> 86 | F11: Bags, Backpacks & Luggage > Backpacks & Laptop Bags > Backpacks | G11: 3 | H11: CL142745 | I11: 585 | J11: 542 | K11: =INDEX('Path Scorecard'!$AD$5:$AD$71,MATCH($H11,'Path Scorecard'!$H$5:$H$71,0)) -> Yes | L11: =INDEX('Path Scorecard'!$AE$5:$AE$71,MATCH($H11,'Path Scorecard'!$H$5:$H$71,0)) -> Amazon | M11: =INDEX('Path Scorecard'!$AF$5:$AF$71,MATCH($H11,'Path Scorecard'!$H$5:$H$71,0)) -> Target | N11: 585 Staples items, laptop & commuter led. 85% of parents bought a backpack for BTS; lifestyle backpacks grew 3% in 2025 (Circana). | O11: Corduroy / soft-aesthetic backpacks; Scandinavian-minimal daypacks; mini backpacks; personalisable patch & pin packs. | P11: Laptop backpacks (SwissGear, Targus): watch cannibalisation here. | Q11: BTS-2027. | R11: JanSport now sells on Target Plus, the curated-marketplace peer Pat can point to. | S11: Amazon: Backpacks. Target: Backpacks (incl. JanSport on Target Plus). | T11: https://www.staples.com/Backpacks/cat_CL142745
A12: =INDEX('Path Scorecard'!$AA$5:$AA$71,MATCH($H12,'Path Scorecard'!$H$5:$H$71,0)) -> 5 | B12: =INDEX('Path Scorecard'!$AB$5:$AB$71,MATCH($H12,'Path Scorecard'!$H$5:$H$71,0)) -> Tier 1 | C12: =INDEX('Path Scorecard'!$Q$5:$Q$71,MATCH($H12,'Path Scorecard'!$H$5:$H$71,0)) -> Probable Hero | D12: =INDEX('Path Scorecard'!$AC$5:$AC$71,MATCH($H12,'Path Scorecard'!$H$5:$H$71,0)) -> BUILD | E12: =INDEX('Path Scorecard'!$Z$5:$Z$71,MATCH($H12,'Path Scorecard'!$H$5:$H$71,0)) -> 86 | F12: Bags, Backpacks & Luggage > Totes & Handbags > Lunch Bags & Boxes | G12: 3 | H12: CL165124 | I12: 404 | J12: 406 | K12: =INDEX('Path Scorecard'!$AD$5:$AD$71,MATCH($H12,'Path Scorecard'!$H$5:$H$71,0)) -> Yes | L12: =INDEX('Path Scorecard'!$AE$5:$AE$71,MATCH($H12,'Path Scorecard'!$H$5:$H$71,0)) -> Amazon | M12: =INDEX('Path Scorecard'!$AF$5:$AF$71,MATCH($H12,'Path Scorecard'!$H$5:$H$71,0)) -> Target | N12: 404 Staples items. Bento compartments, stainless and leak-proof designs lead BTS and work-lunch search. | O12: Bento compartment boxes (kids & adult); neutral / vegan-leather insulated lunch totes; stainless & glass meal-prep sets. | P12: Basic insulated lunch bags Staples already stocks. | Q12: BTS-2027; January 'bring lunch to the office' resolutions. | R12: BTS is Pat's named seasonal anchor and lunch is on every parent's list. | S12: Amazon: Lunch Boxes & Bags. Target: lunch boxes & bags (Bentgo, Stasher, owned brands). | T12: https://www.staples.com/Lunch-Bags-Boxes/cat_CL165124
A13: =INDEX('Path Scorecard'!$AA$5:$AA$71,MATCH($H13,'Path Scorecard'!$H$5:$H$71,0)) -> 5 | B13: =INDEX('Path Scorecard'!$AB$5:$AB$71,MATCH($H13,'Path Scorecard'!$H$5:$H$71,0)) -> Tier 1 | C13: =INDEX('Path Scorecard'!$Q$5:$Q$71,MATCH($H13,'Path Scorecard'!$H$5:$H$71,0)) -> Hero | D13: =INDEX('Path Scorecard'!$AC$5:$AC$71,MATCH($H13,'Path Scorecard'!$H$5:$H$71,0)) -> EXTEND | E13: =INDEX('Path Scorecard'!$Z$5:$Z$71,MATCH($H13,'Path Scorecard'!$H$5:$H$71,0)) -> 86 | F13: School Supplies > Teacher Supplies > Classroom Decorations > Decorative Accents & Board Sets | G13: 4 | H13: CL219245 | I13: 607 | J13: 0 | K13: =INDEX('Path Scorecard'!$AD$5:$AD$71,MATCH($H13,'Path Scorecard'!$H$5:$H$71,0)) | L13: =INDEX('Path Scorecard'!$AE$5:$AE$71,MATCH($H13,'Path Scorecard'!$H$5:$H$71,0)) -> Amazon | M13: =INDEX('Path Scorecard'!$AF$5:$AF$71,MATCH($H13,'Path Scorecard'!$H$5:$H$71,0)) -> Oriental Trading | N13: 607 Staples items. Teachers self-fund about $895 a year and buy decor as coordinated themes (boho, calm, pastel). | O13: Boho / neutral theme sets; calm-corner & SEL decor; pastel bulletin-board kits; plant & nature themes. | P13: Existing bulletin-board sets: compare theme coverage, not SKU swaps. | Q13: BTS-2027 classroom set-up (Jul-Aug); Teacher Appreciation Week (May). | R13: Teachers are a Staples loyalty segment (teacher coupon, teacher lists). | S13: Amazon: Classroom Decorations. Oriental Trading: Teaching Supplies > Classroom Decorations. Michaels: Teacher Supplies. | T13: https://www.staples.com/Decorative-Accents-Board-Sets/cat_CL219245
A14: =INDEX('Path Scorecard'!$AA$5:$AA$71,MATCH($H14,'Path Scorecard'!$H$5:$H$71,0)) -> 10 | B14: =INDEX('Path Scorecard'!$AB$5:$AB$71,MATCH($H14,'Path Scorecard'!$H$5:$H$71,0)) -> Tier 1 | C14: =INDEX('Path Scorecard'!$Q$5:$Q$71,MATCH($H14,'Path Scorecard'!$H$5:$H$71,0)) -> Probable Hero | D14: =INDEX('Path Scorecard'!$AC$5:$AC$71,MATCH($H14,'Path Scorecard'!$H$5:$H$71,0)) -> BUILD | E14: =INDEX('Path Scorecard'!$Z$5:$Z$71,MATCH($H14,'Path Scorecard'!$H$5:$H$71,0)) -> 85 | F14: Office Supplies > Storage & Organization > Storage Baskets | G14: 3 | H14: CL354705 | I14: 95 | J14: 0 | K14: =INDEX('Path Scorecard'!$AD$5:$AD$71,MATCH($H14,'Path Scorecard'!$H$5:$H$71,0)) | L14: =INDEX('Path Scorecard'!$AE$5:$AE$71,MATCH($H14,'Path Scorecard'!$H$5:$H$71,0)) -> Wayfair | M14: =INDEX('Path Scorecard'!$AF$5:$AF$71,MATCH($H14,'Path Scorecard'!$H$5:$H$71,0)) -> Target | N14: Only 95 Staples items, while Wayfair has dedicated Woven Baskets, Decorative Bins and Fabric Baskets nodes. Pure style-led storage. | O14: Seagrass / water-hyacinth woven baskets; felt & linen fabric bins; lined wire baskets; lidded decorative boxes. | P14: Plastic bins sit in the sister node: keep baskets style-led. | Q14: January 'get organized' season. | R14: Organization is a January ritual every retailer promotes. | S14: Wayfair: Organization > Storage Containers & Drawers (Woven Baskets, Decorative Bins, Fabric Baskets). Target: Brightroom baskets. | T14: https://www.staples.com/Storage-Baskets/cat_CL354705
A15: =INDEX('Path Scorecard'!$AA$5:$AA$71,MATCH($H15,'Path Scorecard'!$H$5:$H$71,0)) -> 11 | B15: =INDEX('Path Scorecard'!$AB$5:$AB$71,MATCH($H15,'Path Scorecard'!$H$5:$H$71,0)) -> Tier 2 | C15: =INDEX('Path Scorecard'!$Q$5:$Q$71,MATCH($H15,'Path Scorecard'!$H$5:$H$71,0)) -> Probable Hero | D15: =INDEX('Path Scorecard'!$AC$5:$AC$71,MATCH($H15,'Path Scorecard'!$H$5:$H$71,0)) -> BUILD | E15: =INDEX('Path Scorecard'!$Z$5:$Z$71,MATCH($H15,'Path Scorecard'!$H$5:$H$71,0)) -> 83 | F15: Bags, Backpacks & Luggage > Backpacks & Laptop Bags > Laptop Sleeves & Cases | G15: 3 | H15: CL219256 | I15: 300 | J15: 265 | K15: =INDEX('Path Scorecard'!$AD$5:$AD$71,MATCH($H15,'Path Scorecard'!$H$5:$H$71,0)) | L15: =INDEX('Path Scorecard'!$AE$5:$AE$71,MATCH($H15,'Path Scorecard'!$H$5:$H$71,0)) -> Amazon | M15: =INDEX('Path Scorecard'!$AF$5:$AF$71,MATCH($H15,'Path Scorecard'!$H$5:$H$71,0)) -> Target | N15: 300 Staples items. A sleeve is a low-ticket attach to every laptop sale. | O15: Felt & vegan-leather sleeves; pastel / pattern sleeves with pouch; puffer sleeves. | P15: Black Targus / Case Logic sleeves. | Q15: BTS; laptop-attach all year. | R15: Directly serves Pat's '1-2 extra items per checkout'. | S15: Amazon: Laptop Sleeves. Target: laptop sleeves. | T15: https://www.staples.com/Laptop-Sleeves-Cases/cat_CL219256
A16: =INDEX('Path Scorecard'!$AA$5:$AA$71,MATCH($H16,'Path Scorecard'!$H$5:$H$71,0)) -> 12 | B16: =INDEX('Path Scorecard'!$AB$5:$AB$71,MATCH($H16,'Path Scorecard'!$H$5:$H$71,0)) -> Tier 2 | C16: =INDEX('Path Scorecard'!$Q$5:$Q$71,MATCH($H16,'Path Scorecard'!$H$5:$H$71,0)) -> Probable Hero | D16: =INDEX('Path Scorecard'!$AC$5:$AC$71,MATCH($H16,'Path Scorecard'!$H$5:$H$71,0)) -> BUILD | E16: =INDEX('Path Scorecard'!$Z$5:$Z$71,MATCH($H16,'Path Scorecard'!$H$5:$H$71,0)) -> 82 | F16: Bags, Backpacks & Luggage > Briefcases & Padfolios > Totes & Handbags | G16: 3 | H16: CL160451 | I16: 173 | J16: 166 | K16: =INDEX('Path Scorecard'!$AD$5:$AD$71,MATCH($H16,'Path Scorecard'!$H$5:$H$71,0)) | L16: =INDEX('Path Scorecard'!$AE$5:$AE$71,MATCH($H16,'Path Scorecard'!$H$5:$H$71,0)) -> Amazon | M16: =INDEX('Path Scorecard'!$AF$5:$AF$71,MATCH($H16,'Path Scorecard'!$H$5:$H$71,0)) -> Target | N16: 173 Staples items. The work tote is the lifestyle version of the briefcase. | O16: Structured work totes with laptop sleeve; neoprene totes; vegan-leather commuter totes. | P16: Briefcases & padfolios (Samsonite, Solo). | Q16: Q1 return-to-office; graduation gifting. | R16: The 'White Chair' of bags. | S16: Amazon: work totes. Target: tote bags. | T16: https://www.staples.com/Totes-Handbags/cat_CL160451
... A37: =INDEX('Path Scorecard'!$AA$5:$AA$71,MATCH($H37,'Path Scorecard'!$H$5:$H$71,0)) -> 34 | B37: =INDEX('Path Scorecard'!$AB$5:$AB$71,MATCH($H37,'Path Scorecard'!$H$5:$H$71,0)) -> Tier 2 | C37: =INDEX('Path Scorecard'!$Q$5:$Q$71,MATCH($H37,'Path Scorecard'!$H$5:$H$71,0)) -> Probable Hero | D37: =INDEX('Path Scorecard'!$AC$5:$AC$71,MATCH($H37,'Path Scorecard'!$H$5:$H$71,0)) -> BUILD | E37: =INDEX('Path Scorecard'!$Z$5:$Z$71,MATCH($H37,'Path Scorecard'!$H$5:$H$71,0)) -> 72 | F37: Furniture > Boards & Easels > Calendar & In-Out Boards | G37: 3 | H37: CL142105 | I37: 63 | J37: 0 | K37: =INDEX('Path Scorecard'!$AD$5:$AD$71,MATCH($H37,'Path Scorecard'!$H$5:$H$71,0)) | L37: =INDEX('Path Scorecard'!$AE$5:$AE$71,MATCH($H37,'Path Scorecard'!$H$5:$H$71,0)) -> Amazon | M37: =INDEX('Path Scorecard'!$AF$5:$AF$71,MATCH($H37,'Path Scorecard'!$H$5:$H$71,0)) -> Wayfair | N37: 63 Staples items. | O37: Acrylic dry-erase wall calendars; glass monthly planners; felt calendar boards. | P37: In/out boards. | Q37: January. | R37: Pairs with planners & calendars. | S37: Amazon: acrylic calendars. Wayfair: Memo Boards. | T37: https://www.staples.com/Calendar-In-Out-Boards/cat_CL142105

Sheet Selection Criteria
A1: Selection criteria, weights and thresholds
A2: Yellow cells with blue text are editable. Every score, rank, tier and competitor role in the workbook recalculates from them.
A4: A. Hard gates: a path must pass all four to be scored
A5: Code | B5: Gate | C5: Rule | D5: Why it matters
A6: G1 | B6: Granularity | C6: The node is an L3 or L4 in the Staples navigation tree (Level 3 or 4). | D6: Your feedback: L2 is too coarse. The gap must be readable on one shelf.
A7: G2 | B7: Brand authority | C7: The node sits on a Staples work / school / small-business mission (not mis-shelved or leisure). | D7: Pat: build momentum 'without straying too far from Staples' brand authority'.
A8: G3 | B8: Staples baseline | C8: Staples lists at least the minimum item count (threshold in section C). | D8: Needs a nearest-Staples-family comparison and a share baseline.
A9: G4 | B9: No partner conflict | C9: No Staples strategic partner already owns the assortment on Staples.com. | D9: Party City (Apr-2026) now supplies party décor, gift bags & wrap: marketplace adds would compete with a partner.
A11: B. Weighted path criteria: each scored 1-5, weighted score scaled to 0-100
A12: Code | B12: Criterion | C12: What it measures | D12: Scores 5 when | E12: Scores 1 when | F12: Weight
A13: C1 | B13: Design & lifestyle variance ('White Chair' test) | C13: Do shoppers choose on colour, material, style or 'vibe' rather than spec? | D13: Style drives the choice; many aesthetic archetypes exist | E13: Pure spec / commodity | F13: 20
A14: C2 | B14: Competitor depth advantage | C14: How much wider the best competitor's assortment is on this shelf | D14: Best competitor is several times wider, with archetypes Staples lacks | E14: Parity with Staples | F14: 15
A15: C3 | B15: 1P protection (low cannibalisation) | C15: Can design variants be added without substituting Staples' core best-sellers? | D15: Design variants clearly distinct from the 1P core | E15: Direct substitute of core 1P | F15: 15
A16: C4 | B16: Core-adjacency & shopper mission | C16: Same work, school or small-business mission as Staples' core | D16: Sits on the core Staples mission | E16: Residential or leisure mission | F16: 15
A17: C5 | B17: Basket attach & quick-win economics | C17: Parcel-shippable, lower ticket, attaches to core baskets (Pat: +1-2 items per checkout) | D17: Under ~$50, parcel, frequent attach | E17: Oversize freight, considered purchase | F17: 10
A18: C6 | B18: Business familiarity & story | C18: Would the Staples room recognise it instantly (header nav, Staples' own recent moves, visible trend)? | D18: Header-nav shelf + Staples' own recent move or a famous trend | E18: Obscure shelf | F18: 10
A19: C7 | B19: Commercial moment | C19: Peaks in the Q1-2027 window or BTS-2027 (Pat's seasonal anchor) | D19: Peaks in Jan-Mar or Jul-Sep 2027 | E19: No clear moment | F19: 5
A20: C8 | B20: Data readiness | C20: Staples SKUs already in hand + competitor already scraped or reachable | D20: Both sides in hand / reachable | E20: Neither side available | F20: 10
E21: Total weight | F21: =SUM(F13:F20) -> 100
A23: C. Thresholds
A24: Code | B24: Parameter | C24: Value | D24: Note
A25: T1 | B25: Tier 1 cut-off (score >=) | C25: 84 | D25: Tier 1 = PoC wave 1 (10 paths at default weights).
A26: T2 | B26: Tier 2 cut-off (score >=) | C26: 72 | D26: Tier 2 = wave 2 / swap-ins (25 paths at default weights).
A27: G3 | B27: Minimum Staples items on the leaf | C27: 20 | D27: Feeds gate G3.
A28: FS | B28: Fast-start: min Staples SKUs already in the sample | C28: 100 | D28: Tier 1 paths above this can start without a new Staples scrape.
A30: D. Competitor selection criteria: each competitor scored 1-5 per path
A31: Code | B31: Criterion | C31: What it measures | D31: Scores 5 when | E31: Scores 1 when | F31: Weight
A32: K1 | B32: Assortment depth on this shelf | C32: Breadth of the competitor's range on the mapped node | D32: Several times Staples' range, many sub-types | E32: Similar or smaller than Staples | F32: 30
A33: K2 | B33: Aesthetic & lifestyle range | C33: Variety of styles, colourways, materials and price tiers | D33: Destination for design-led choice | E33: Utility only | F33: 25
A34: K3 | B34: Shopper overlap with Staples | C34: Same home-office, student, teacher or small-business shopper | D34: Same shopper and mission | E34: Different shopper (e.g. hunters, hobby pros) | F34: 15
A35: K4 | B35: Seller recruitability | C35: Can the brands / suppliers behind the range be invited onto Staples Marketplace? | D35: Multi-brand 3P or drop-ship suppliers | E35: Mostly own / private label | F35: 15
A36: K5 | B36: Data accessibility | C36: Can the team collect listing-level data at PoC speed? (tested 29-Sep-2026) | D36: Already scraped or official API | E36: Bot-blocked, needs a paid proxy | F36: 15
E37: Total weight | F37: =SUM(F32:F36) -> 100
A39: E. How primary and secondary competitors are picked
A40: 1. | B40: For each Tier 1 / Tier 2 path, 2-4 plausible competitors are scored K1-K5 in 'Competitor Fit'. Rank 1 = Primary, rank 2 = Secondary; ties are broken by K1 (depth).
A41: 2. | B41: K4 and K5 are competitor-level (see 'Competitor Profiles'); K1-K3 are path-specific.
A42: 3. | B42: Office Depot is deliberately NOT used as a primary: its assortment mirrors Staples' utility range, so it produces little gap signal. Use it only as a sanity check.
A43: 4. | B43: All scores are analyst judgement from the desk research in 'Evidence & Sources'. Live SKU counts could not be pulled (retailer sites bot-protected); confirm depth with the S0 scrape before the analysis run.
A46: F. Hero segmentation: the second lens (Hero / Probable Hero / Non-Hero)
A47: Hero = Staples' own top categories. Probable Hero = the market's top categories where Staples is not (yet) a destination: room for improvement. Non-Hero = neither. There is no internal sales or margin data, so both axes use external proxies; when Staples shares sales / margin rank, replace S1-S4 with it and everything recalculates.
A48: Code | B48: Staples Strength Index (SSI): is it a Staples hero? | C48: What it measures | D48: Scores 5 when | E48: Scores 1 when | F48: Weight
A49: S1 | B49: Assortment depth | C49: Staples items on the leaf, banded (computed from the tree) | D49: >= 1,000 items | E49: < 75 items | F49: 30
A50: S2 | B50: Shelf visibility | C50: Is the L1 in Staples' header navigation? (computed from the tree) | D50: In the header nav | E50: Not in the header nav | F50: 15
A51: S3 | B51: Merchandising investment | C51: Exclusives, collaborations, own brands, BTS / seasonal feature slots | D51: Staples exclusives or own brand + feature slots | E51: No visible investment | F51: 25
A52: S4 | B52: Shopper association | C52: Would a shopper think of Staples first for this? | D52: Staples is a go-to destination | E52: Nobody thinks of Staples for this | F52: 30
E53: Total weight | F53: =SUM(F49:F52) -> 100
A54: Code | B54: Market Attractiveness Index (MAI): is it a market hero? | C54: What it measures | D54: Scores 5 when | E54: Scores 1 when | F54: Weight
A55: M1 | B55: Demand momentum | C55: Growth and trend signals (Circana, trade press, social) | D55: Clear growth or a viral trend | E55: Flat or declining | F55: 35
A56: M2 | B56: Competitor destination strength | C56: Do competitors run it as a department with specialist depth? | D56: Several retailers treat it as a destination | E56: Few competitors care | F56: 25
A57: M3 | B57: Category size & purchase frequency | C57: How big the category is and how often it is bought | D57: Large and frequently bought | E57: Small, rare purchase | F57: 25
A58: M4 | B58: Occasion strength | C58: Reuses C7 (Q1-2027 / BTS-2027 moment) from the scorecard | D58: Strong Q1 or BTS peak | E58: No moment | F58: 15
E59: Total weight | F59: =SUM(F55:F58) -> 100
A61: Code | B61: Segmentation parameter | C61: Value | D61: Note
A62: H | B62: Hero cut-off (SSI >=) | C62: 65 | D62: Checked first: a strong Staples shelf is a Hero whatever the market does.
A63: P | B63: Probable Hero cut-off (MAI >=) | C63: 65 | D63: Applied to shelves that are not Heroes.
A64: PR | B64: Protect cut-off (Hero with C3 1P-protection <=) | C64: 2 | D64: Hero shelves where design variants would substitute 1P: keep the marketplace out.
A65: NC | B65: Cap Non-Hero shelves at Tier 3? (Yes / No) | C65: Yes | D65: PoC time goes to Heroes and Probable Heroes.
A66: B5 | B66: S1 band: items >= this scores 5 | C66: 1000
A67: B4 | B67: S1 band: scores 4 | C67: 500
A68: B3 | B68: S1 band: scores 3 | C68: 200
A69: B2 | B69: S1 band: scores 2 (else 1) | C69: 75
A70: NY | B70: S2 score if the L1 is in the header nav | C70: 5
A71: NN | B71: S2 score if not | C71: 2
A73: G. Segments and marketplace plays
A74: Segment | B74: Play | C74: When | D74: What Staples Marketplace does
A75: Hero | B75: EXTEND | C75: Staples is strong and 1P risk is manageable (C3 above the Protect cut-off). | D75: Add style / lifestyle extensions of the hero only (the 'White Chair' move); strict cannibalisation gate; invite brands Staples already buys first.
A76: Hero | B76: PROTECT | C76: Staples is strong and design variants would substitute 1P (C3 at or below the Protect cut-off). | D76: Keep the marketplace out; use as a control shelf that shows the safety gate working.
A77: Probable Hero | B77: BUILD | C77: The market treats it as a top category but Staples is not (yet) a destination. | D77: Fill the depth gap quickly with marketplace sellers recruited from the primary competitor's brands: the biggest commission upside.
A78: Non-Hero | B78: HOLD | C78: Neither a Staples strength nor a market favourite. | D78: Backlog, capped at Tier 3. Revisit only if strategy or data changes.

Sheet Path Scorecard
A1: Path scorecard: every candidate Staples L3/L4 path
A2: Blue cells are analyst inputs. Gates, segment, score, rank, tier, play and competitors are formulas. Sort or filter freely; IDs are stable.
A4: Path ID | B4: Staples path (exact, from nav tree) | C4: L1 | D4: L2 | E4: L3 | F4: L4 | G4: Level | H4: Category ID | I4: Staples items (site) | J4: Staples SKUs in hand (sample) | K4: Link to your list | L4: G1 Granularity | M4: G2 Brand authority | N4: G3 Baseline | O4: G4 No partner conflict | P4: All gates | Q4: Hero segment | R4: C1 Design variance | S4: C2 Comp. depth | T4: C3 1P protection | U4: C4 Core-adjacency | V4: C5 Basket attach | W4: C6 Familiarity | X4: C7 Moment | Y4: C8 Data readiness | Z4: Score (0-100) | AA4: Rank | AB4: Tier | AC4: Marketplace play | AD4: Fast-start | AE4: Primary competitor | AF4: Secondary competitor | AG4: Rationale / gate note
A5: P01 | B5: Office Supplies > Calendars & Planners > Planners & Personal Organizers | C5: Office Supplies | D5: Calendars & Planners | E5: Planners & Personal Organizers | G5: 3 | H5: CL166388 | I5: 1037 | J5: 1016 | K5: 9. Planning & Craft Organization | L5: =IF(OR(G5=3,G5=4),"Pass","Fail") -> Pass | M5: Pass | N5: =IF(I5>='Selection Criteria'!$C$27,"Pass","Fail") -> Pass | O5: Pass | P5: =IF(AND(L5="Pass",M5="Pass",N5="Pass",O5="Pass"),"Pass","Fail") -> Pass | Q5: =INDEX('Hero Segmentation'!$Q$5:$Q$71,MATCH($A5,'Hero Segmentation'!$A$5:$A$71,0)) -> Hero | R5: 5 | S5: 5 | T5: 4 | U5: 5 | V5: 5 | W5: 5 | X5: 5 | Y5: 4 | Z5: =IF(P5="Pass",(R5*'Selection Criteria'!$F$13+S5*'Selection Criteria'!$F$14+T5*'Selection Criteria'!$F$15+U5*'Selection Criteria'!$F$16+V5*'Selection Criteria'!$F$17+W5*'Selection Criteria'!$F$18+X5*'Selection Criteria'!$F$19+Y5*'Selection Criteria'!$F$20)/(5*'Selection Criteria'!$F$21)*100,"-") -> 95 | AA5: =IF(P5="Pass",COUNTIFS($P$5:$P$71,"Pass",$Z$5:$Z$71,">"&Z5)+1,"-") -> 1 | AB5: =IF(P5<>"Pass","Parked (gate)",IF(AND('Selection Criteria'!$C$65="Yes",Q5="Non-Hero"),"Tier 3",IF(Z5>='Selection Criteria'!$C$25,"Tier 1",IF(Z5>='Selection Criteria'!$C$26,"Tier 2","Tier 3")))) -> Tier 1 | AC5: =INDEX('Hero Segmentation'!$R$5:$R$71,MATCH($A5,'Hero Segmentation'!$A$5:$A$71,0)) -> EXTEND | AD5: =IF(AND(AB5="Tier 1",J5>='Selection Criteria'!$C$28),"Yes","") -> Yes | AE5: =IFERROR(INDEX('Competitor Fit'!$C$5:$C$103,MATCH($A5&"|Primary",'Competitor Fit'!$L$5:$L$103,0)),"-") -> Amazon | AF5: =IFERROR(INDEX('Competitor Fit'!$C$5:$C$103,MATCH($A5&"|Secondary",'Competitor Fit'!$L$5:$L$103,0)),"-") -> Michaels | AG5: Deep Staples shelf (1,037) and Staples' own Sincerely Jules move; enthusiast formats missing.
A6: P02 | B6: Office Supplies > Desk Organizers & Accessories > Desk Organizers | C6: Office Supplies | D6: Desk Organizers & Accessories | E6: Desk Organizers | G6: 3 | H6: CL140991 | I6: 342 | J6: 0 | K6: New | L6: =IF(OR(G6=3,G6=4),"Pass","Fail") -> Pass | M6: Pass | N6: =IF(I6>='Selection Criteria'!$C$27,"Pass","Fail") -> Pass | O6: Pass | P6: =IF(AND(L6="Pass",M6="Pass",N6="Pass",O6="Pass"),"Pass","Fail") -> Pass | Q6: =INDEX('Hero Segmentation'!$Q$5:$Q$71,MATCH($A6,'Hero Segmentation'!$A$5:$A$71,0)) -> Hero | R6: 5 | S6: 5 | T6: 4 | U6: 5 | V6: 5 | W6: 5 | X6: 5 | Y6: 2 | Z6: =IF(P6="Pass",(R6*'Selection Criteria'!$F$13+S6*'Selection Criteria'!$F$14+T6*'Selection Criteria'!$F$15+U6*'Selection Criteria'!$F$16+V6*'Selection Criteria'!$F$17+W6*'Selection Criteria'!$F$18+X6*'Selection Criteria'!$F$19+Y6*'Selection Criteria'!$F$20)/(5*'Selection Criteria'!$F$21)*100,"-") -> 91 | AA6: =IF(P6="Pass",COUNTIFS($P$5:$P$71,"Pass",$Z$5:$Z$71,">"&Z6)+1,"-") -> 2 | AB6: =IF(P6<>"Pass","Parked (gate)",IF(AND('Selection Criteria'!$C$65="Yes",Q6="Non-Hero"),"Tier 3",IF(Z6>='Selection Criteria'!$C$25,"Tier 1",IF(Z6>='Selection Criteria'!$C$26,"Tier 2","Tier 3")))) -> Tier 1 | AC6: =INDEX('Hero Segmentation'!$R$5:$R$71,MATCH($A6,'Hero Segmentation'!$A$5:$A$71,0)) -> EXTEND | AD6: =IF(AND(AB6="Tier 1",J6>='Selection Criteria'!$C$28),"Yes","") | AE6: =IFERROR(INDEX('Competitor Fit'!$C$5:$C$103,MATCH($A6&"|Primary",'Competitor Fit'!$L$5:$L$103,0)),"-") -> Target | AF6: =IFERROR(INDEX('Competitor Fit'!$C$5:$C$103,MATCH($A6&"|Secondary",'Competitor Fit'!$L$5:$L$103,0)),"-") -> Amazon | AG6: Header-nav core, low ticket, coordinated design collections at Target/Container Store.
A7: P03 | B7: Coffee, Water & Snacks > Water & Beverages > Water Bottles, Tumblers & Travel Mugs | C7: Coffee, Water & Snacks | D7: Water & Beverages | E7: Water Bottles, Tumblers & Travel Mugs | G7: 3 | H7: CL354650 | I7: 463 | J7: 462 | K7: 7. Hydration & Drinkware | L7: =IF(OR(G7=3,G7=4),"Pass","Fail") -> Pass | M7: Pass | N7: =IF(I7>='Selection Criteria'!$C$27,"Pass","Fail") -> Pass | O7: Pass | P7: =IF(AND(L7="Pass",M7="Pass",N7="Pass",O7="Pass"),"Pass","Fail") -> Pass | Q7: =INDEX('Hero Segmentation'!$Q$5:$Q$71,MATCH($A7,'Hero Segmentation'!$A$5:$A$71,0)) -> Probable Hero | R7: 5 | S7: 5 | T7: 4 | U7: 4 | V7: 5 | W7: 5 | X7: 4 | Y7: 4 | Z7: =IF(P7="Pass",(R7*'Selection Criteria'!$F$13+S7*'Selection Criteria'!$F$14+T7*'Selection Criteria'!$F$15+U7*'Selection Criteria'!$F$16+V7*'Selection Criteria'!$F$17+W7*'Selection Criteria'!$F$18+X7*'Selection Criteria'!$F$19+Y7*'Selection Criteria'!$F$20)/(5*'Selection Criteria'!$F$21)*100,"-") -> 91 | AA7: =IF(P7="Pass",COUNTIFS($P$5:$P$71,"Pass",$Z$5:$Z$71,">"&Z7)+1,"-") -> 2 | AB7: =IF(P7<>"Pass","Parked (gate)",IF(AND('Selection Criteria'!$C$65="Yes",Q7="Non-Hero"),"Tier 3",IF(Z7>='Selection Criteria'!$C$25,"Tier 1",IF(Z7>='Selection Criteria'!$C$26,"Tier 2","Tier 3")))) -> Tier 1 | AC7: =INDEX('Hero Segmentation'!$R$5:$R$71,MATCH($A7,'Hero Segmentation'!$A$5:$A$71,0)) -> BUILD | AD7: =IF(AND(AB7="Tier 1",J7>='Selection Criteria'!$C$28),"Yes","") -> Yes | AE7: =IFERROR(INDEX('Competitor Fit'!$C$5:$C$103,MATCH($A7&"|Primary",'Competitor Fit'!$L$5:$L$103,0)),"-") -> Dick's Sporting Goods | AF7: =IFERROR(INDEX('Competitor Fit'!$C$5:$C$103,MATCH($A7&"|Secondary",'Competitor Fit'!$L$5:$L$103,0)),"-") -> Target | AG7: Owala/Stanley colourway gap; data in hand; everyone relates.
A8: P04 | B8: Furniture > Chairs & Seating > Accent & Waiting Room Chairs | C8: Furniture | D8: Chairs & Seating | E8: Accent & Waiting Room Chairs | G8: 3 | H8: CL70203 | I8: 229 | J8: 199 | K8: 1. Chairs & Seating | L8: =IF(OR(G8=3,G8=4),"Pass","Fail") -> Pass | M8: Pass | N8: =IF(I8>='Selection Criteria'!$C$27,"Pass","Fail") -> Pass | O8: Pass | P8: =IF(AND(L8="Pass",M8="Pass",N8="Pass",O8="Pass"),"Pass","Fail") -> Pass | Q8: =INDEX('Hero Segmentation'!$Q$5:$Q$71,MATCH($A8,'Hero Segmentation'!$A$5:$A$71,0)) -> Probable Hero | R8: 5 | S8: 5 | T8: 5 | U8: 4 | V8: 2 | W8: 5 | X8: 3 | Y8: 5 | Z8: =IF(P8="Pass",(R8*'Selection Criteria'!$F$13+S8*'Selection Criteria'!$F$14+T8*'Selection Criteria'!$F$15+U8*'Selection Criteria'!$F$16+V8*'Selection Criteria'!$F$17+W8*'Selection Criteria'!$F$18+X8*'Selection Criteria'!$F$19+Y8*'Selection Criteria'!$F$20)/(5*'Selection Criteria'!$F$21)*100,"-") -> 89 | AA8: =IF(P8="Pass",COUNTIFS($P$5:$P$71,"Pass",$Z$5:$Z$71,">"&Z8)+1,"-") -> 4 | AB8: =IF(P8<>"Pass","Parked (gate)",IF(AND('Selection Criteria'!$C$65="Yes",Q8="Non-Hero"),"Tier 3",IF(Z8>='Selection Criteria'!$C$25,"Tier 1",IF(Z8>='Selection Criteria'!$C$26,"Tier 2","Tier 3")))) -> Tier 1 | AC8: =INDEX('Hero Segmentation'!$R$5:$R$71,MATCH($A8,'Hero Segmentation'!$A$5:$A$71,0)) -> BUILD | AD8: =IF(AND(AB8="Tier 1",J8>='Selection Criteria'!$C$28),"Yes","") -> Yes | AE8: =IFERROR(INDEX('Competitor Fit'!$C$5:$C$103,MATCH($A8&"|Primary",'Competitor Fit'!$L$5:$L$103,0)),"-") -> Wayfair | AF8: =IFERROR(INDEX('Competitor Fit'!$C$5:$C$103,MATCH($A8&"|Secondary",'Competitor Fit'!$L$5:$L$103,0)),"-") -> Amazon | AG8: Pat's own 'White Chair' shelf; pilot: 5 recs, 2 Strong, 94% confident mapping.
A9: P05 | B9: Furniture > Lamps & Lighting > Desk Lamps | C9: Furniture | D9: Lamps & Lighting | E9: Desk Lamps | G9: 3 | H9: CL167867 | I9: 210 | J9: 195 | K9: 3. Lamps & Lighting | L9: =IF(OR(G9=3,G9=4),"Pass","Fail") -> Pass | M9: Pass | N9: =IF(I9>='Selection Criteria'!$C$27,"Pass","Fail") -> Pass | O9: Pass | P9: =IF(AND(L9="Pass",M9="Pass",N9="Pass",O9="Pass"),"Pass","Fail") -> Pass | Q9: =INDEX('Hero Segmentation'!$Q$5:$Q$71,MATCH($A9,'Hero Segmentation'!$A$5:$A$71,0)) -> Probable Hero | R9: 5 | S9: 4 | T9: 4 | U9: 5 | V9: 4 | W9: 4 | X9: 3 | Y9: 4 | Z9: =IF(P9="Pass",(R9*'Selection Criteria'!$F$13+S9*'Selection Criteria'!$F$14+T9*'Selection Criteria'!$F$15+U9*'Selection Criteria'!$F$16+V9*'Selection Criteria'!$F$17+W9*'Selection Criteria'!$F$18+X9*'Selection Criteria'!$F$19+Y9*'Selection Criteria'!$F$20)/(5*'Selection Criteria'!$F$21)*100,"-") -> 86 | AA9: =IF(P9="Pass",COUNTIFS($P$5:$P$71,"Pass",$Z$5:$Z$71,">"&Z9)+1,"-") -> 5 | AB9: =IF(P9<>"Pass","Parked (gate)",IF(AND('Selection Criteria'!$C$65="Yes",Q9="Non-Hero"),"Tier 3",IF(Z9>='Selection Criteria'!$C$25,"Tier 1",IF(Z9>='Selection Criteria'!$C$26,"Tier 2","Tier 3")))) -> Tier 1 | AC9: =INDEX('Hero Segmentation'!$R$5:$R$71,MATCH($A9,'Hero Segmentation'!$A$5:$A$71,0)) -> BUILD | AD9: =IF(AND(AB9="Tier 1",J9>='Selection Criteria'!$C$28),"Yes","") -> Yes | AE9: =IFERROR(INDEX('Competitor Fit'!$C$5:$C$103,MATCH($A9&"|Primary",'Competitor Fit'!$L$5:$L$103,0)),"-") -> Wayfair | AF9: =IFERROR(INDEX('Competitor Fit'!$C$5:$C$103,MATCH($A9&"|Secondary",'Competitor Fit'!$L$5:$L$103,0)),"-") -> Amazon | AG9: Aesthetic lighting on the work desk; Staples SKUs in hand.
A10: P06 | B10: Office Supplies > Writing Supplies & Instruments > Pencil Accessories > Pencil Cases & Pouches | C10: Office Supplies | D10: Writing Supplies & Instruments | E10: Pencil Accessories | F10: Pencil Cases & Pouches | G10: 4 | H10: CL141253 | I10: 107 | J10: 0 | K10: New | L10: =IF(OR(G10=3,G10=4),"Pass","Fail") -> Pass | M10: Pass | N10: =IF(I10>='Selection Criteria'!$C$27,"Pass","Fail") -> Pass | O10: Pass | P10: =IF(AND(L10="Pass",M10="Pass",N10="Pass",O10="Pass"),"Pass","Fail") -> Pass | Q10: =INDEX('Hero Segmentation'!$Q$5:$Q$71,MATCH($A10,'Hero Segmentation'!$A$5:$A$71,0)) -> Probable Hero | R10: 5 | S10: 4 | T10: 5 | U10: 4 | V10: 5 | W10: 4 | X10: 5 | Y10: 2 | Z10: =IF(P10="Pass",(R10*'Selection Criteria'!$F$13+S10*'Selection Criteria'!$F$14+T10*'Selection Criteria'!$F$15+U10*'Selection Criteria'!$F$16+V10*'Selection Criteria'!$F$17+W10*'Selection Criteria'!$F$18+X10*'Selection Criteria'!$F$19+Y10*'Selection Criteria'!$F$20)/(5*'Selection Criteria'!$F$21)*100,"-") -> 86 | AA10: =IF(P10="Pass",COUNTIFS($P$5:$P$71,"Pass",$Z$5:$Z$71,">"&Z10)+1,"-") -> 5 | AB10: =IF(P10<>"Pass","Parked (gate)",IF(AND('Selection Criteria'!$C$65="Yes",Q10="Non-Hero"),"Tier 3",IF(Z10>='Selection Criteria'!$C$25,"Tier 1",IF(Z10>='Selection Criteria'!$C$26,"Tier 2","Tier 3")))) -> Tier 1 | AC10: =INDEX('Hero Segmentation'!$R$5:$R$71,MATCH($A10,'Hero Segmentation'!$A$5:$A$71,0)) -> BUILD | AD10: =IF(AND(AB10="Tier 1",J10>='Selection Criteria'!$C$28),"Yes","") | AE10: =IFERROR(INDEX('Competitor Fit'!$C$5:$C$103,MATCH($A10&"|Primary",'Competitor Fit'!$L$5:$L$103,0)),"-") -> Amazon | AF10: =IFERROR(INDEX('Competitor Fit'!$C$5:$C$103,MATCH($A10&"|Secondary",'Competitor Fit'!$L$5:$L$103,0)),"-") -> Target | AG10: First 'aesthetic' item in the BTS basket; Staples' Recess Club proves demand.
A11: P07 | B11: Bags, Backpacks & Luggage > Backpacks & Laptop Bags > Backpacks | C11: Bags, Backpacks & Luggage | D11: Backpacks & Laptop Bags | E11: Backpacks | G11: 3 | H11: CL142745 | I11: 585 | J11: 542 | K11: 6. Backpacks & Bags | L11: =IF(OR(G11=3,G11=4),"Pass","Fail") -> Pass | M11: Pass | N11: =IF(I11>='Selection Criteria'!$C$27,"Pass","Fail") -> Pass | O11: Pass | P11: =IF(AND(L11="Pass",M11="Pass",N11="Pass",O11="Pass"),"Pass","Fail") -> Pass | Q11: =INDEX('Hero Segmentation'!$Q$5:$Q$71,MATCH($A11,'Hero Segmentation'!$A$5:$A$71,0)) -> Hero | R11: 4 | S11: 5 | T11: 3 | U11: 5 | V11: 4 | W11: 5 | X11: 5 | Y11: 4 | Z11: =IF(P11="Pass",(R11*'Selection Criteria'!$F$13+S11*'Selection Criteria'!$F$14+T11*'Selection Criteria'!$F$15+U11*'Selection Criteria'!$F$16+V11*'Selection Criteria'!$F$17+W11*'Selection Criteria'!$F$18+X11*'Selection Criteria'!$F$19+Y11*'Selection Criteria'!$F$20)/(5*'Selection Criteria'!$F$21)*100,"-") -> 86 | AA11: =IF(P11="Pass",COUNTIFS($P$5:$P$71,"Pass",$Z$5:$Z$71,">"&Z11)+1,"-") -> 5 | AB11: =IF(P11<>"Pass","Parked (gate)",IF(AND('Selection Criteria'!$C$65="Yes",Q11="Non-Hero"),"Tier 3",IF(Z11>='Selection Criteria'!$C$25,"Tier 1",IF(Z11>='Selection Criteria'!$C$26,"Tier 2","Tier 3")))) -> Tier 1 | AC11: =INDEX('Hero Segmentation'!$R$5:$R$71,MATCH($A11,'Hero Segmentation'!$A$5:$A$71,0)) -> EXTEND | AD11: =IF(AND(AB11="Tier 1",J11>='Selection Criteria'!$C$28),"Yes","") -> Yes | AE11: =IFERROR(INDEX('Competitor Fit'!$C$5:$C$103,MATCH($A11&"|Primary",'Competitor Fit'!$L$5:$L$103,0)),"-") -> Amazon | AF11: =IFERROR(INDEX('Competitor Fit'!$C$5:$C$103,MATCH($A11&"|Secondary",'Competitor Fit'!$L$5:$L$103,0)),"-") -> Target | AG11: BTS anchor (85% of parents buy one); laptop packs are core 1P.
A12: P08 | B12: Bags, Backpacks & Luggage > Totes & Handbags > Lunch Bags & Boxes | C12: Bags, Backpacks & Luggage | D12: Totes & Handbags | E12: Lunch Bags & Boxes | G12: 3 | H12: CL165124 | I12: 404 | J12: 406 | K12: 6. Backpacks & Bags | L12: =IF(OR(G12=3,G12=4),"Pass","Fail") -> Pass | M12: Pass | N12: =IF(I12>='Selection Criteria'!$C$27,"Pass","Fail") -> Pass | O12: Pass | P12: =IF(AND(L12="Pass",M12="Pass",N12="Pass",O12="Pass"),"Pass","Fail") -> Pass | Q12: =INDEX('Hero Segmentation'!$Q$5:$Q$71,MATCH($A12,'Hero Segmentation'!$A$5:$A$71,0)) -> Probable Hero | R12: 4 | S12: 5 | T12: 4 | U12: 4 | V12: 5 | W12: 4 | X12: 5 | Y12: 4 | Z12: =IF(P12="Pass",(R12*'Selection Criteria'!$F$13+S12*'Selection Criteria'!$F$14+T12*'Selection Criteria'!$F$15+U12*'Selection Criteria'!$F$16+V12*'Selection Criteria'!$F$17+W12*'Selection Criteria'!$F$18+X12*'Selection Criteria'!$F$19+Y12*'Selection Criteria'!$F$20)/(5*'Selection Criteria'!$F$21)*100,"-") -> 86 | AA12: =IF(P12="Pass",COUNTIFS($P$5:$P$71,"Pass",$Z$5:$Z$71,">"&Z12)+1,"-") -> 5 | AB12: =IF(P12<>"Pass","Parked (gate)",IF(AND('Selection Criteria'!$C$65="Yes",Q12="Non-Hero"),"Tier 3",IF(Z12>='Selection Criteria'!$C$25,"Tier 1",IF(Z12>='Selection Criteria'!$C$26,"Tier 2","Tier 3")))) -> Tier 1 | AC12: =INDEX('Hero Segmentation'!$R$5:$R$71,MATCH($A12,'Hero Segmentation'!$A$5:$A$71,0)) -> BUILD | AD12: =IF(AND(AB12="Tier 1",J12>='Selection Criteria'!$C$28),"Yes","") -> Yes | AE12: =IFERROR(INDEX('Competitor Fit'!$C$5:$C$103,MATCH($A12&"|Primary",'Competitor Fit'!$L$5:$L$103,0)),"-") -> Amazon | AF12: =IFERROR(INDEX('Competitor Fit'!$C$5:$C$103,MATCH($A12&"|Secondary",'Competitor Fit'!$L$5:$L$103,0)),"-") -> Target | AG12: Bento/leak-proof designs lead BTS & work-lunch; data in hand.
A13: P09 | B13: School Supplies > Teacher Supplies > Classroom Decorations > Decorative Accents & Board Sets | C13: School Supplies | D13: Teacher Supplies | E13: Classroom Decorations | F13: Decorative Accents & Board Sets | G13: 4 | H13: CL219245 | I13: 607 | J13: 0 | K13: New | L13: =IF(OR(G13=3,G13=4),"Pass","Fail") -> Pass | M13: Pass | N13: =IF(I13>='Selection Criteria'!$C$27,"Pass","Fail") -> Pass | O13: Pass | P13: =IF(AND(L13="Pass",M13="Pass",N13="Pass",O13="Pass"),"Pass","Fail") -> Pass | Q13: =INDEX('Hero Segmentation'!$Q$5:$Q$71,MATCH($A13,'Hero Segmentation'!$A$5:$A$71,0)) -> Hero | R13: 5 | S13: 4 | T13: 4 | U13: 5 | V13: 5 | W13: 4 | X13: 5 | Y13: 2 | Z13: =IF(P13="Pass",(R13*'Selection Criteria'!$F$13+S13*'Selection Criteria'!$F$14+T13*'Selection Criteria'!$F$15+U13*'Selection Criteria'!$F$16+V13*'Selection Criteria'!$F$17+W13*'Selection Criteria'!$F$18+X13*'Selection Criteria'!$F$19+Y13*'Selection Criteria'!$F$20)/(5*'Selection Criteria'!$F$21)*100,"-") -> 86 | AA13: =IF(P13="Pass",COUNTIFS($P$5:$P$71,"Pass",$Z$5:$Z$71,">"&Z13)+1,"-") -> 5 | AB13: =IF(P13<>"Pass","Parked (gate)",IF(AND('Selection Criteria'!$C$65="Yes",Q13="Non-Hero"),"Tier 3",IF(Z13>='Selection Criteria'!$C$25,"Tier 1",IF(Z13>='Selection Criteria'!$C$26,"Tier 2","Tier 3")))) -> Tier 1 | AC13: =INDEX('Hero Segmentation'!$R$5:$R$71,MATCH($A13,'Hero Segmentation'!$A$5:$A$71,0)) -> EXTEND | AD13: =IF(AND(AB13="Tier 1",J13>='Selection Criteria'!$C$28),"Yes","") | AE13: =IFERROR(INDEX('Competitor Fit'!$C$5:$C$103,MATCH($A13&"|Primary",'Competitor Fit'!$L$5:$L$103,0)),"-") -> Amazon | AF13: =IFERROR(INDEX('Competitor Fit'!$C$5:$C$103,MATCH($A13&"|Secondary",'Competitor Fit'!$L$5:$L$103,0)),"-") -> Oriental Trading | AG13: Teachers self-fund ~$895/yr and buy themed sets: Pat's BTS anchor.
A14: P10 | B14: Office Supplies > Storage & Organization > Storage Baskets | C14: Office Supplies | D14: Storage & Organization | E14: Storage Baskets | G14: 3 | H14: CL354705 | I14: 95 | J14: 0 | K14: New | L14: =IF(OR(G14=3,G14=4),"Pass","Fail") -> Pass | M14: Pass | N14: =IF(I14>='Selection Criteria'!$C$27,"Pass","Fail") -> Pass | O14: Pass | P14: =IF(AND(L14="Pass",M14="Pass",N14="Pass",O14="Pass"),"Pass","Fail") -> Pass | Q14: =INDEX('Hero Segmentation'!$Q$5:$Q$71,MATCH($A14,'Hero Segmentation'!$A$5:$A$71,0)) -> Probable Hero | R14: 5 | S14: 5 | T14: 5 | U14: 4 | V14: 4 | W14: 3 | X14: 5 | Y14: 2 | Z14: =IF(P14="Pass",(R14*'Selection Criteria'!$F$13+S14*'Selection Criteria'!$F$14+T14*'Selection Criteria'!$F$15+U14*'Selection Criteria'!$F$16+V14*'Selection Criteria'!$F$17+W14*'Selection Criteria'!$F$18+X14*'Selection Criteria'!$F$19+Y14*'Selection Criteria'!$F$20)/(5*'Selection Criteria'!$F$21)*100,"-") -> 85 | AA14: =IF(P14="Pass",COUNTIFS($P$5:$P$71,"Pass",$Z$5:$Z$71,">"&Z14)+1,"-") -> 10 | AB14: =IF(P14<>"Pass","Parked (gate)",IF(AND('Selection Criteria'!$C$65="Yes",Q14="Non-Hero"),"Tier 3",IF(Z14>='Selection Criteria'!$C$25,"Tier 1",IF(Z14>='Selection Criteria'!$C$26,"Tier 2","Tier 3")))) -> Tier 1 | AC14: =INDEX('Hero Segmentation'!$R$5:$R$71,MATCH($A14,'Hero Segmentation'!$A$5:$A$71,0)) -> BUILD | AD14: =IF(AND(AB14="Tier 1",J14>='Selection Criteria'!$C$28),"Yes","") | AE14: =IFERROR(INDEX('Competitor Fit'!$C$5:$C$103,MATCH($A14&"|Primary",'Competitor Fit'!$L$5:$L$103,0)),"-") -> Wayfair | AF14: =IFERROR(INDEX('Competitor Fit'!$C$5:$C$103,MATCH($A14&"|Secondary",'Competitor Fit'!$L$5:$L$103,0)),"-") -> Target | AG14: 95 items vs Wayfair's Woven/Decorative/Fabric basket nodes; style-led storage.
A15: P11 | B15: Bags, Backpacks & Luggage > Backpacks & Laptop Bags > Laptop Sleeves & Cases | C15: Bags, Backpacks & Luggage | D15: Backpacks & Laptop Bags | E15: Laptop Sleeves & Cases | G15: 3 | H15: CL219256 | I15: 300 | J15: 265 | K15: 6. Backpacks & Bags | L15: =IF(OR(G15=3,G15=4),"Pass","Fail") -> Pass | M15: Pass | N15: =IF(I15>='Selection Criteria'!$C$27,"Pass","Fail") -> Pass | O15: Pass | P15: =IF(AND(L15="Pass",M15="Pass",N15="Pass",O15="Pass"),"Pass","Fail") -> Pass | Q15: =INDEX('Hero Segmentation'!$Q$5:$Q$71,MATCH($A15,'Hero Segmentation'!$A$5:$A$71,0)) -> Probable Hero | R15: 4 | S15: 4 | T15: 4 | U15: 5 | V15: 5 | W15: 3 | X15: 4 | Y15: 4 | Z15: =IF(P15="Pass",(R15*'Selection Criteria'!$F$13+S15*'Selection Criteria'!$F$14+T15*'Selection Criteria'!$F$15+U15*'Selection Criteria'!$F$16+V15*'Selection Criteria'!$F$17+W15*'Selection Criteria'!$F$18+X15*'Selection Criteria'!$F$19+Y15*'Selection Criteria'!$F$20)/(5*'Selection Criteria'!$F$21)*100,"-") -> 83 | AA15: =IF(P15="Pass",COUNTIFS($P$5:$P$71,"Pass",$Z$5:$Z$71,">"&Z15)+1,"-") -> 11 | AB15: =IF(P15<>"Pass","Parked (gate)",IF(AND('Selection Criteria'!$C$65="Yes",Q15="Non-Hero"),"Tier 3",IF(Z15>='Selection Criteria'!$C$25,"Tier 1",IF(Z15>='Selection Criteria'!$C$26,"Tier 2","Tier 3")))) -> Tier 2 | AC15: =INDEX('Hero Segmentation'!$R$5:$R$71,MATCH($A15,'Hero Segmentation'!$A$5:$A$71,0)) -> BUILD | AD15: =IF(AND(AB15="Tier 1",J15>='Selection Criteria'!$C$28),"Yes","") | AE15: =IFERROR(INDEX('Competitor Fit'!$C$5:$C$103,MATCH($A15&"|Primary",'Competitor Fit'!$L$5:$L$103,0)),"-") -> Amazon | AF15: =IFERROR(INDEX('Competitor Fit'!$C$5:$C$103,MATCH($A15&"|Secondary",'Competitor Fit'!$L$5:$L$103,0)),"-") -> Target | AG15: Low-ticket attach to every laptop sale.
A16: P12 | B16: Bags, Backpacks & Luggage > Briefcases & Padfolios > Totes & Handbags | C16: Bags, Backpacks & Luggage | D16: Briefcases & Padfolios | E16: Totes & Handbags | G16: 3 | H16: CL160451 | I16: 173 | J16: 166 | K16: 6. Backpacks & Bags | L16: =IF(OR(G16=3,G16=4),"Pass","Fail") -> Pass | M16: Pass | N16: =IF(I16>='Selection Criteria'!$C$27,"Pass","Fail") -> Pass | O16: Pass | P16: =IF(AND(L16="Pass",M16="Pass",N16="Pass",O16="Pass"),"Pass","Fail") -> Pass | Q16: =INDEX('Hero Segmentation'!$Q$5:$Q$71,MATCH($A16,'Hero Segmentation'!$A$5:$A$71,0)) -> Probable Hero | R16: 5 | S16: 5 | T16: 4 | U16: 4 | V16: 3 | W16: 3 | X16: 3 | Y16: 4 | Z16: =IF(P16="Pass",(R16*'Selection Criteria'!$F$13+S16*'Selection Criteria'!$F$14+T16*'Selection Criteria'!$F$15+U16*'Selection Criteria'!$F$16+V16*'Selection Criteria'!$F$17+W16*'Selection Criteria'!$F$18+X16*'Selection Criteria'!$F$19+Y16*'Selection Criteria'!$F$20)/(5*'Selection Criteria'!$F$21)*100,"-") -> 82 | AA16: =IF(P16="Pass",COUNTIFS($P$5:$P$71,"Pass",$Z$5:$Z$71,">"&Z16)+1,"-") -> 12 | AB16: =IF(P16<>"Pass","Parked (gate)",IF(AND('Selection Criteria'!$C$65="Yes",Q16="Non-Hero"),"Tier 3",IF(Z16>='Selection Criteria'!$C$25,"Tier 1",IF(Z16>='Selection Criteria'!$C$26,"Tier 2","Tier 3")))) -> Tier 2 | AC16: =INDEX('Hero Segmentation'!$R$5:$R$71,MATCH($A16,'Hero Segmentation'!$A$5:$A$71,0)) -> BUILD | AD16: =IF(AND(AB16="Tier 1",J16>='Selection Criteria'!$C$28),"Yes","") | AE16: =IFERROR(INDEX('Competitor Fit'!$C$5:$C$103,MATCH($A16&"|Primary",'Competitor Fit'!$L$5:$L$103,0)),"-") -> Amazon | AF16: =IFERROR(INDEX('Competitor Fit'!$C$5:$C$103,MATCH($A16&"|Secondary",'Competitor Fit'!$L$5:$L$103,0)),"-") -> Target | AG16: Lifestyle version of the briefcase.
A17: P13 | B17: Furniture > Desks > Office Desks | C17: Furniture | D17: Desks | E17: Office Desks | G17: 3 | H17: CL210795 | I17: 1501 | J17: 1265 | K17: 2. Desks | L17: =IF(OR(G17=3,G17=4),"Pass","Fail") -> Pass | M17: Pass | N17: =IF(I17>='Selection Criteria'!$C$27,"Pass","Fail") -> Pass | O17: Pass | P17: =IF(AND(L17="Pass",M17="Pass",N17="Pass",O17="Pass"),"Pass","Fail") -> Pass | Q17: =INDEX('Hero Segmentation'!$Q$5:$Q$71,MATCH($A17,'Hero Segmentation'!$A$5:$A$71,0)) -> Hero | R17: 4 | S17: 5 | T17: 3 | U17: 5 | V17: 1 | W17: 5 | X17: 4 | Y17: 5 | Z17: =IF(P17="Pass",(R17*'Selection Criteria'!$F$13+S17*'Selection Criteria'!$F$14+T17*'Selection Criteria'!$F$15+U17*'Selection Criteria'!$F$16+V17*'Selection Criteria'!$F$17+W17*'Selection Criteria'!$F$18+X17*'Selection Criteria'!$F$19+Y17*'Selection Criteria'!$F$20)/(5*'Selection Criteria'!$F$21)*100,"-") -> 81 | AA17: =IF(P17="Pass",COUNTIFS($P$5:$P$71,"Pass",$Z$5:$Z$71,">"&Z17)+1,"-") -> 13 | AB17: =IF(P17<>"Pass","Parked (gate)",IF(AND('Selection Criteria'!$C$65="Yes",Q17="Non-Hero"),"Tier 3",IF(Z17>='Selection Criteria'!$C$25,"Tier 1",IF(Z17>='Selection Criteria'!$C$26,"Tier 2","Tier 3")))) -> Tier 2 | AC17: =INDEX('Hero Segmentation'!$R$5:$R$71,MATCH($A17,'Hero Segmentation'!$A$5:$A$71,0)) -> EXTEND | AD17: =IF(AND(AB17="Tier 1",J17>='Selection Criteria'!$C$28),"Yes","") | AE17: =IFERROR(INDEX('Competitor Fit'!$C$5:$C$103,MATCH($A17&"|Primary",'Competitor Fit'!$L$5:$L$103,0)),"-") -> Wayfair | AF17: =IFERROR(INDEX('Competitor Fit'!$C$5:$C$103,MATCH($A17&"|Secondary",'Competitor Fit'!$L$5:$L$103,0)),"-") -> Amazon | AG17: 1,501 items; pilot Computer split: 3 recs (1 Strong). Split by Staples' own type facet.
A18: P14 | B18: Office Supplies > Notebooks & Notepads > Journals & Diaries | C18: Office Supplies | D18: Notebooks & Notepads | E18: Journals & Diaries | G18: 3 | H18: CL166390 | I18: 253 | J18: 0 | K18: 9. Planning & Craft Organization | L18: =IF(OR(G18=3,G18=4),"Pass","Fail") -> Pass | M18: Pass | N18: =IF(I18>='Selection Criteria'!$C$27,"Pass","Fail") -> Pass | O18: Pass | P18: =IF(AND(L18="Pass",M18="Pass",N18="Pass",O18="Pass"),"Pass","Fail") -> Pass | Q18: =INDEX('Hero Segmentation'!$Q$5:$Q$71,MATCH($A18,'Hero Segmentation'!$A$5:$A$71,0)) -> Probable Hero | R18: 5 | S18: 4 | T18: 4 | U18: 4 | V18: 5 | W18: 3 | X18: 4 | Y18: 2 | Z18: =IF(P18="Pass",(R18*'Selection Criteria'!$F$13+S18*'Selection Criteria'!$F$14+T18*'Selection Criteria'!$F$15+U18*'Selection Criteria'!$F$16+V18*'Selection Criteria'!$F$17+W18*'Selection Criteria'!$F$18+X18*'Selection Criteria'!$F$19+Y18*'Selection Criteria'!$F$20)/(5*'Selection Criteria'!$F$21)*100,"-") -> 80 | AA18: =IF(P18="Pass",COUNTIFS($P$5:$P$71,"Pass",$Z$5:$Z$71,">"&Z18)+1,"-") -> 14 | AB18: =IF(P18<>"Pass","Parked (gate)",IF(AND('Selection Criteria'!$C$65="Yes",Q18="Non-Hero"),"Tier 3",IF(Z18>='Selection Criteria'!$C$25,"Tier 1",IF(Z18>='Selection Criteria'!$C$26,"Tier 2","Tier 3")))) -> Tier 2 | AC18: =INDEX('Hero Segmentation'!$R$5:$R$71,MATCH($A18,'Hero Segmentation'!$A$5:$A$71,0)) -> BUILD | AD18: =IF(AND(AB18="Tier 1",J18>='Selection Criteria'!$C$28),"Yes","") | AE18: =IFERROR(INDEX('Competitor Fit'!$C$5:$C$103,MATCH($A18&"|Primary",'Competitor Fit'!$L$5:$L$103,0)),"-") -> Amazon | AF18: =IFERROR(INDEX('Competitor Fit'!$C$5:$C$103,MATCH($A18&"|Secondary",'Competitor Fit'!$L$5:$L$103,0)),"-") -> Michaels | AG18: Gen-Z journaling habit; pairs with planners.
A19: P15 | B19: Furniture > Decor > Artificial Plants & Flowers > Artificial Plants | C19: Furniture | D19: Decor | E19: Artificial Plants & Flowers | F19: Artificial Plants | G19: 4 | H19: CL355087 | I19: 203 | J19: 0 | K19: New | L19: =IF(OR(G19=3,G19=4),"Pass","Fail") -> Pass | M19: Pass | N19: =IF(I19>='Selection Criteria'!$C$27,"Pass","Fail") -> Pass | O19: Pass | P19: =IF(AND(L19="Pass",M19="Pass",N19="Pass",O19="Pass"),"Pass","Fail") -> Pass | Q19: =INDEX('Hero Segmentation'!$Q$5:$Q$71,MATCH($A19,'Hero Segmentation'!$A$5:$A$71,0)) -> Probable Hero | R19: 5 | S19: 5 | T19: 5 | U19: 3 | V19: 4 | W19: 3 | X19: 3 | Y19: 2 | Z19: =IF(P19="Pass",(R19*'Selection Criteria'!$F$13+S19*'Selection Criteria'!$F$14+T19*'Selection Criteria'!$F$15+U19*'Selection Criteria'!$F$16+V19*'Selection Criteria'!$F$17+W19*'Selection Criteria'!$F$18+X19*'Selection Criteria'!$F$19+Y19*'Selection Criteria'!$F$20)/(5*'Selection Criteria'!$F$21)*100,"-") -> 80 | AA19: =IF(P19="Pass",COUNTIFS($P$5:$P$71,"Pass",$Z$5:$Z$71,">"&Z19)+1,"-") -> 14 | AB19: =IF(P19<>"Pass","Parked (gate)",IF(AND('Selection Criteria'!$C$65="Yes",Q19="Non-Hero"),"Tier 3",IF(Z19>='Selection Criteria'!$C$25,"Tier 1",IF(Z19>='Selection Criteria'!$C$26,"Tier 2","Tier 3")))) -> Tier 2 | AC19: =INDEX('Hero Segmentation'!$R$5:$R$71,MATCH($A19,'Hero Segmentation'!$A$5:$A$71,0)) -> BUILD | AD19: =IF(AND(AB19="Tier 1",J19>='Selection Criteria'!$C$28),"Yes","") | AE19: =IFERROR(INDEX('Competitor Fit'!$C$5:$C$103,MATCH($A19&"|Primary",'Competitor Fit'!$L$5:$L$103,0)),"-") -> Wayfair | AF19: =IFERROR(INDEX('Competitor Fit'!$C$5:$C$103,MATCH($A19&"|Secondary",'Competitor Fit'!$L$5:$L$103,0)),"-") -> Michaels | AG19: Biophilic / resimercial office default.
A20: P16 | B20: Office Supplies > Tape, Fasteners & Adhesives > Tape > Arts & Crafts Tape | C20: Office Supplies | D20: Tape, Fasteners & Adhesives | E20: Tape | F20: Arts & Crafts Tape | G20: 4 | H20: CL215702 | I20: 32 | J20: 0 | K20: 9. Planning & Craft Organization | L20: =IF(OR(G20=3,G20=4),"Pass","Fail") -> Pass | M20: Pass | N20: =IF(I20>='Selection Criteria'!$C$27,"Pass","Fail") -> Pass | O20: Pass | P20: =IF(AND(L20="Pass",M20="Pass",N20="Pass",O20="Pass"),"Pass","Fail") -> Pass | Q20: =INDEX('Hero Segmentation'!$Q$5:$Q$71,MATCH($A20,'Hero Segmentation'!$A$5:$A$71,0)) -> Probable Hero | R20: 5 | S20: 5 | T20: 5 | U20: 3 | V20: 5 | W20: 2 | X20: 3 | Y20: 1 | Z20: =IF(P20="Pass",(R20*'Selection Criteria'!$F$13+S20*'Selection Criteria'!$F$14+T20*'Selection Criteria'!$F$15+U20*'Selection Criteria'!$F$16+V20*'Selection Criteria'!$F$17+W20*'Selection Criteria'!$F$18+X20*'Selection Criteria'!$F$19+Y20*'Selection Criteria'!$F$20)/(5*'Selection Criteria'!$F$21)*100,"-") -> 78 | AA20: =IF(P20="Pass",COUNTIFS($P$5:$P$71,"Pass",$Z$5:$Z$71,">"&Z20)+1,"-") -> 16 | AB20: =IF(P20<>"Pass","Parked (gate)",IF(AND('Selection Criteria'!$C$65="Yes",Q20="Non-Hero"),"Tier 3",IF(Z20>='Selection Criteria'!$C$25,"Tier 1",IF(Z20>='Selection Criteria'!$C$26,"Tier 2","Tier 3")))) -> Tier 2 | AC20: =INDEX('Hero Segmentation'!$R$5:$R$71,MATCH($A20,'Hero Segmentation'!$A$5:$A$71,0)) -> BUILD | AD20: =IF(AND(AB20="Tier 1",J20>='Selection Criteria'!$C$28),"Yes","") | AE20: =IFERROR(INDEX('Competitor Fit'!$C$5:$C$103,MATCH($A20&"|Primary",'Competitor Fit'!$L$5:$L$103,0)),"-") -> Michaels | AF20: =IFERROR(INDEX('Competitor Fit'!$C$5:$C$103,MATCH($A20&"|Secondary",'Competitor Fit'!$L$5:$L$103,0)),"-") -> Amazon | AG20: Only 32 Staples items: near-pure whitespace, tiny ticket.
A21: P17 | B21: Arts & Crafts > Scrapbooking > Stickers & Embellishments | C21: Arts & Crafts | D21: Scrapbooking | E21: Stickers & Embellishments | G21: 3 | H21: CL167442 | I21: 166 | J21: 0 | K21: 9. Planning & Craft Organization | L21: =IF(OR(G21=3,G21=4),"Pass","Fail") -> Pass | M21: Pass | N21: =IF(I21>='Selection Criteria'!$C$27,"Pass","Fail") -> Pass | O21: Pass | P21: =IF(AND(L21="Pass",M21="Pass",N21="Pass",O21="Pass"),"Pass","Fail") -> Pass | Q21: =INDEX('Hero Segmentation'!$Q$5:$Q$71,MATCH($A21,'Hero Segmentation'!$A$5:$A$71,0)) -> Probable Hero | R21: 5 | S21: 5 | T21: 5 | U21: 3 | V21: 5 | W21: 2 | X21: 3 | Y21: 1 | Z21: =IF(P21="Pass",(R21*'Selection Criteria'!$F$13+S21*'Selection Criteria'!$F$14+T21*'Selection Criteria'!$F$15+U21*'Selection Criteria'!$F$16+V21*'Selection Criteria'!$F$17+W21*'Selection Criteria'!$F$18+X21*'Selection Criteria'!$F$19+Y21*'Selection Criteria'!$F$20)/(5*'Selection Criteria'!$F$21)*100,"-") -> 78 | AA21: =IF(P21="Pass",COUNTIFS($P$5:$P$71,"Pass",$Z$5:$Z$71,">"&Z21)+1,"-") -> 16 | AB21: =IF(P21<>"Pass","Parked (gate)",IF(AND('Selection Criteria'!$C$65="Yes",Q21="Non-Hero"),"Tier 3",IF(Z21>='Selection Criteria'!$C$25,"Tier 1",IF(Z21>='Selection Criteria'!$C$26,"Tier 2","Tier 3")))) -> Tier 2 | AC21: =INDEX('Hero Segmentation'!$R$5:$R$71,MATCH($A21,'Hero Segmentation'!$A$5:$A$71,0)) -> BUILD | AD21: =IF(AND(AB21="Tier 1",J21>='Selection Criteria'!$C$28),"Yes","") | AE21: =IFERROR(INDEX('Competitor Fit'!$C$5:$C$103,MATCH($A21&"|Primary",'Competitor Fit'!$L$5:$L$103,0)),"-") -> Michaels | AF21: =IFERROR(INDEX('Competitor Fit'!$C$5:$C$103,MATCH($A21&"|Secondary",'Competitor Fit'!$L$5:$L$103,0)),"-") -> Amazon | AG21: Planner-companion consumable = repeat commission.
A22: P18 | B22: Computers & Accessories > Computer Accessories & Peripherals > Mouse Pads & Wrist Rests | C22: Computers & Accessories | D22: Computer Accessories & Peripherals | E22: Mouse Pads & Wrist Rests | G22: 3 | H22: CL141474 | I22: 318 | J22: 0 | K22: New | L22: =IF(OR(G22=3,G22=4),"Pass","Fail") -> Pass | M22: Pass | N22: =IF(I22>='Selection Criteria'!$C$27,"Pass","Fail") -> Pass | O22: Pass | P22: =IF(AND(L22="Pass",M22="Pass",N22="Pass",O22="Pass"),"Pass","Fail") -> Pass | Q22: =INDEX('Hero Segmentation'!$Q$5:$Q$71,MATCH($A22,'Hero Segmentation'!$A$5:$A$71,0)) -> Probable Hero | R22: 4 | S22: 4 | T22: 4 | U22: 5 | V22: 5 | W22: 3 | X22: 3 | Y22: 2 | Z22: =IF(P22="Pass",(R22*'Selection Criteria'!$F$13+S22*'Selection Criteria'!$F$14+T22*'Selection Criteria'!$F$15+U22*'Selection Criteria'!$F$16+V22*'Selection Criteria'!$F$17+W22*'Selection Criteria'!$F$18+X22*'Selection Criteria'!$F$19+Y22*'Selection Criteria'!$F$20)/(5*'Selection Criteria'!$F$21)*100,"-") -> 78 | AA22: =IF(P22="Pass",COUNTIFS($P$5:$P$71,"Pass",$Z$5:$Z$71,">"&Z22)+1,"-") -> 16 | AB22: =IF(P22<>"Pass","Parked (gate)",IF(AND('Selection Criteria'!$C$65="Yes",Q22="Non-Hero"),"Tier 3",IF(Z22>='Selection Criteria'!$C$25,"Tier 1",IF(Z22>='Selection Criteria'!$C$26,"Tier 2","Tier 3")))) -> Tier 2 | AC22: =INDEX('Hero Segmentation'!$R$5:$R$71,MATCH($A22,'Hero Segmentation'!$A$5:$A$71,0)) -> BUILD | AD22: =IF(AND(AB22="Tier 1",J22>='Selection Criteria'!$C$28),"Yes","") | AE22: =IFERROR(INDEX('Competitor Fit'!$C$5:$C$103,MATCH($A22&"|Primary",'Competitor Fit'!$L$5:$L$103,0)),"-") -> Amazon | AF22: =IFERROR(INDEX('Competitor Fit'!$C$5:$C$103,MATCH($A22&"|Secondary",'Competitor Fit'!$L$5:$L$103,0)),"-") -> Wayfair | AG22: Desk mat is now a decor object; gel wrist rests are core.
A23: P19 | B23: Furniture > Boards & Easels > Bulletin Boards | C23: Furniture | D23: Boards & Easels | E23: Bulletin Boards | G23: 3 | H23: CL142403 | I23: 284 | J23: 0 | K23: New | L23: =IF(OR(G23=3,G23=4),"Pass","Fail") -> Pass | M23: Pass | N23: =IF(I23>='Selection Criteria'!$C$27,"Pass","Fail") -> Pass | O23: Pass | P23: =IF(AND(L23="Pass",M23="Pass",N23="Pass",O23="Pass"),"Pass","Fail") -> Pass | Q23: =INDEX('Hero Segmentation'!$Q$5:$Q$71,MATCH($A23,'Hero Segmentation'!$A$5:$A$71,0)) -> Hero | R23: 4 | S23: 4 | T23: 4 | U23: 5 | V23: 4 | W23: 3 | X23: 4 | Y23: 2 | Z23: =IF(P23="Pass",(R23*'Selection Criteria'!$F$13+S23*'Selection Criteria'!$F$14+T23*'Selection Criteria'!$F$15+U23*'Selection Criteria'!$F$16+V23*'Selection Criteria'!$F$17+W23*'Selection Criteria'!$F$18+X23*'Selection Criteria'!$F$19+Y23*'Selection Criteria'!$F$20)/(5*'Selection Criteria'!$F$21)*100,"-") -> 77 | AA23: =IF(P23="Pass",COUNTIFS($P$5:$P$71,"Pass",$Z$5:$Z$71,">"&Z23)+1,"-") -> 19 | AB23: =IF(P23<>"Pass","Parked (gate)",IF(AND('Selection Criteria'!$C$65="Yes",Q23="Non-Hero"),"Tier 3",IF(Z23>='Selection Criteria'!$C$25,"Tier 1",IF(Z23>='Selection Criteria'!$C$26,"Tier 2","Tier 3")))) -> Tier 2 | AC23: =INDEX('Hero Segmentation'!$R$5:$R$71,MATCH($A23,'Hero Segmentation'!$A$5:$A$71,0)) -> EXTEND | AD23: =IF(AND(AB23="Tier 1",J23>='Selection Criteria'!$C$28),"Yes","") | AE23: =IFERROR(INDEX('Competitor Fit'!$C$5:$C$103,MATCH($A23&"|Primary",'Competitor Fit'!$L$5:$L$103,0)),"-") -> Amazon | AF23: =IFERROR(INDEX('Competitor Fit'!$C$5:$C$103,MATCH($A23&"|Secondary",'Competitor Fit'!$L$5:$L$103,0)),"-") -> Wayfair | AG23: Letter/felt/fabric memo boards vs cork utility.
A24: P20 | B24: Furniture > Decor > Clocks & Timers | C24: Furniture | D24: Decor | E24: Clocks & Timers | G24: 3 | H24: CL161533 | I24: 229 | J24: 0 | K24: New | L24: =IF(OR(G24=3,G24=4),"Pass","Fail") -> Pass | M24: Pass | N24: =IF(I24>='Selection Criteria'!$C$27,"Pass","Fail") -> Pass | O24: Pass | P24: =IF(AND(L24="Pass",M24="Pass",N24="Pass",O24="Pass"),"Pass","Fail") -> Pass | Q24: =INDEX('Hero Segmentation'!$Q$5:$Q$71,MATCH($A24,'Hero Segmentation'!$A$5:$A$71,0)) -> Non-Hero | R24: 5 | S24: 5 | T24: 4 | U24: 4 | V24: 4 | W24: 2 | X24: 2 | Y24: 2 | Z24: =IF(P24="Pass",(R24*'Selection Criteria'!$F$13+S24*'Selection Criteria'!$F$14+T24*'Selection Criteria'!$F$15+U24*'Selection Criteria'!$F$16+V24*'Selection Criteria'!$F$17+W24*'Selection Criteria'!$F$18+X24*'Selection Criteria'!$F$19+Y24*'Selection Criteria'!$F$20)/(5*'Selection Criteria'!$F$21)*100,"-") -> 77 | AA24: =IF(P24="Pass",COUNTIFS($P$5:$P$71,"Pass",$Z$5:$Z$71,">"&Z24)+1,"-") -> 19 | AB24: =IF(P24<>"Pass","Parked (gate)",IF(AND('Selection Criteria'!$C$65="Yes",Q24="Non-Hero"),"Tier 3",IF(Z24>='Selection Criteria'!$C$25,"Tier 1",IF(Z24>='Selection Criteria'!$C$26,"Tier 2","Tier 3")))) -> Tier 3 | AC24: =INDEX('Hero Segmentation'!$R$5:$R$71,MATCH($A24,'Hero Segmentation'!$A$5:$A$71,0)) -> HOLD | AD24: =IF(AND(AB24="Tier 1",J24>='Selection Criteria'!$C$28),"Yes","") | AE24: =IFERROR(INDEX('Competitor Fit'!$C$5:$C$103,MATCH($A24&"|Primary",'Competitor Fit'!$L$5:$L$103,0)),"-") -> Wayfair | AF24: =IFERROR(INDEX('Competitor Fit'!$C$5:$C$103,MATCH($A24&"|Secondary",'Competitor Fit'!$L$5:$L$103,0)),"-") -> Amazon | AG24: Wayfair runs a whole Clocks department. Capped at Tier 3 because it is Non-Hero.
A25: P21 | B25: Furniture > Decor > Picture Frames & Photo Albums | C25: Furniture | D25: Decor | E25: Picture Frames & Photo Albums | G25: 3 | H25: CL161523 | I25: 435 | J25: 0 | K25: New | L25: =IF(OR(G25=3,G25=4),"Pass","Fail") -> Pass | M25: Pass | N25: =IF(I25>='Selection Criteria'!$C$27,"Pass","Fail") -> Pass | O25: Pass | P25: =IF(AND(L25="Pass",M25="Pass",N25="Pass",O25="Pass"),"Pass","Fail") -> Pass | Q25: =INDEX('Hero Segmentation'!$Q$5:$Q$71,MATCH($A25,'Hero Segmentation'!$A$5:$A$71,0)) -> Probable Hero | R25: 5 | S25: 5 | T25: 4 | U25: 3 | V25: 4 | W25: 3 | X25: 3 | Y25: 2 | Z25: =IF(P25="Pass",(R25*'Selection Criteria'!$F$13+S25*'Selection Criteria'!$F$14+T25*'Selection Criteria'!$F$15+U25*'Selection Criteria'!$F$16+V25*'Selection Criteria'!$F$17+W25*'Selection Criteria'!$F$18+X25*'Selection Criteria'!$F$19+Y25*'Selection Criteria'!$F$20)/(5*'Selection Criteria'!$F$21)*100,"-") -> 77 | AA25: =IF(P25="Pass",COUNTIFS($P$5:$P$71,"Pass",$Z$5:$Z$71,">"&Z25)+1,"-") -> 19 | AB25: =IF(P25<>"Pass","Parked (gate)",IF(AND('Selection Criteria'!$C$65="Yes",Q25="Non-Hero"),"Tier 3",IF(Z25>='Selection Criteria'!$C$25,"Tier 1",IF(Z25>='Selection Criteria'!$C$26,"Tier 2","Tier 3")))) -> Tier 2 | AC25: =INDEX('Hero Segmentation'!$R$5:$R$71,MATCH($A25,'Hero Segmentation'!$A$5:$A$71,0)) -> BUILD | AD25: =IF(AND(AB25="Tier 1",J25>='Selection Criteria'!$C$28),"Yes","") | AE25: =IFERROR(INDEX('Competitor Fit'!$C$5:$C$103,MATCH($A25&"|Primary",'Competitor Fit'!$L$5:$L$103,0)),"-") -> Michaels | AF25: =IFERROR(INDEX('Competitor Fit'!$C$5:$C$103,MATCH($A25&"|Secondary",'Competitor Fit'!$L$5:$L$103,0)),"-") -> Wayfair | AG25: Examples doc already names Michaels on framing.
A26: P22 | B26: Retail Store Supplies > Retail Packaging > Retail Boxes & Bags | C26: Retail Store Supplies | D26: Retail Packaging | E26: Retail Boxes & Bags | G26: 3 | H26: CL167951 | I26: 99 | J26: 98 | K26: 8. Labels & Packaging Accessories | L26: =IF(OR(G26=3,G26=4),"Pass","Fail") -> Pass | M26: Pass | N26: =IF(I26>='Selection Criteria'!$C$27,"Pass","Fail") -> Pass | O26: Pass | P26: =IF(AND(L26="Pass",M26="Pass",N26="Pass",O26="Pass"),"Pass","Fail") -> Pass | Q26: =INDEX('Hero Segmentation'!$Q$5:$Q$71,MATCH($A26,'Hero Segmentation'!$A$5:$A$71,0)) -> Probable Hero | R26: 4 | S26: 4 | T26: 4 | U26: 4 | V26: 4 | W26: 3 | X26: 3 | Y26: 4 | Z26: =IF(P26="Pass",(R26*'Selection Criteria'!$F$13+S26*'Selection Criteria'!$F$14+T26*'Selection Criteria'!$F$15+U26*'Selection Criteria'!$F$16+V26*'Selection Criteria'!$F$17+W26*'Selection Criteria'!$F$18+X26*'Selection Criteria'!$F$19+Y26*'Selection Criteria'!$F$20)/(5*'Selection Criteria'!$F$21)*100,"-") -> 77 | AA26: =IF(P26="Pass",COUNTIFS($P$5:$P$71,"Pass",$Z$5:$Z$71,">"&Z26)+1,"-") -> 19 | AB26: =IF(P26<>"Pass","Parked (gate)",IF(AND('Selection Criteria'!$C$65="Yes",Q26="Non-Hero"),"Tier 3",IF(Z26>='Selection Criteria'!$C$25,"Tier 1",IF(Z26>='Selection Criteria'!$C$26,"Tier 2","Tier 3")))) -> Tier 2 | AC26: =INDEX('Hero Segmentation'!$R$5:$R$71,MATCH($A26,'Hero Segmentation'!$A$5:$A$71,0)) -> BUILD | AD26: =IF(AND(AB26="Tier 1",J26>='Selection Criteria'!$C$28),"Yes","") | AE26: =IFERROR(INDEX('Competitor Fit'!$C$5:$C$103,MATCH($A26&"|Primary",'Competitor Fit'!$L$5:$L$103,0)),"-") -> Amazon | AF26: =IFERROR(INDEX('Competitor Fit'!$C$5:$C$103,MATCH($A26&"|Secondary",'Competitor Fit'!$L$5:$L$103,0)),"-") -> Uline | AG26: Boutique packaging for small sellers: Staples' core SMB customer.
A27: P23 | B27: Office Supplies > Desk Organizers & Accessories > Desk Pads | C27: Office Supplies | D27: Desk Organizers & Accessories | E27: Desk Pads | G27: 3 | H27: CL140589 | I27: 82 | J27: 0 | K27: New | L27: =IF(OR(G27=3,G27=4),"Pass","Fail") -> Pass | M27: Pass | N27: =IF(I27>='Selection Criteria'!$C$27,"Pass","Fail") -> Pass | O27: Pass | P27: =IF(AND(L27="Pass",M27="Pass",N27="Pass",O27="Pass"),"Pass","Fail") -> Pass | Q27: =INDEX('Hero Segmentation'!$Q$5:$Q$71,MATCH($A27,'Hero Segmentation'!$A$5:$A$71,0)) -> Non-Hero | R27: 4 | S27: 4 | T27: 4 | U27: 5 | V27: 4 | W27: 3 | X27: 3 | Y27: 2 | Z27: =IF(P27="Pass",(R27*'Selection Criteria'!$F$13+S27*'Selection Criteria'!$F$14+T27*'Selection Criteria'!$F$15+U27*'Selection Criteria'!$F$16+V27*'Selection Criteria'!$F$17+W27*'Selection Criteria'!$F$18+X27*'Selection Criteria'!$F$19+Y27*'Selection Criteria'!$F$20)/(5*'Selection Criteria'!$F$21)*100,"-") -> 76 | AA27: =IF(P27="Pass",COUNTIFS($P$5:$P$71,"Pass",$Z$5:$Z$71,">"&Z27)+1,"-") -> 23 | AB27: =IF(P27<>"Pass","Parked (gate)",IF(AND('Selection Criteria'!$C$65="Yes",Q27="Non-Hero"),"Tier 3",IF(Z27>='Selection Criteria'!$C$25,"Tier 1",IF(Z27>='Selection Criteria'!$C$26,"Tier 2","Tier 3")))) -> Tier 3 | AC27: =INDEX('Hero Segmentation'!$R$5:$R$71,MATCH($A27,'Hero Segmentation'!$A$5:$A$71,0)) -> HOLD | AD27: =IF(AND(AB27="Tier 1",J27>='Selection Criteria'!$C$28),"Yes","") | AE27: =IFERROR(INDEX('Competitor Fit'!$C$5:$C$103,MATCH($A27&"|Primary",'Competitor Fit'!$L$5:$L$103,0)),"-") -> Amazon | AF27: =IFERROR(INDEX('Competitor Fit'!$C$5:$C$103,MATCH($A27&"|Secondary",'Competitor Fit'!$L$5:$L$103,0)),"-") -> Wayfair | AG27: Leather/felt desk pads; Wayfair has a Desk Pads node. Capped at Tier 3 because it is Non-Hero.
A28: P24 | B28: Computers & Accessories > Computer Accessories & Peripherals > Laptop Accessories > Laptop Stands & Lap Desks | C28: Computers & Accessories | D28: Computer Accessories & Peripherals | E28: Laptop Accessories | F28: Laptop Stands & Lap Desks | G28: 4 | H28: CL165071 | I28: 205 | J28: 0 | K28: New | L28: =IF(OR(G28=3,G28=4),"Pass","Fail") -> Pass | M28: Pass | N28: =IF(I28>='Selection Criteria'!$C$27,"Pass","Fail") -> Pass | O28: Pass | P28: =IF(AND(L28="Pass",M28="Pass",N28="Pass",O28="Pass"),"Pass","Fail") -> Pass | Q28: =INDEX('Hero Segmentation'!$Q$5:$Q$71,MATCH($A28,'Hero Segmentation'!$A$5:$A$71,0)) -> Probable Hero | R28: 4 | S28: 4 | T28: 4 | U28: 5 | V28: 4 | W28: 3 | X28: 3 | Y28: 2 | Z28: =IF(P28="Pass",(R28*'Selection Criteria'!$F$13+S28*'Selection Criteria'!$F$14+T28*'Selection Criteria'!$F$15+U28*'Selection Criteria'!$F$16+V28*'Selection Criteria'!$F$17+W28*'Selection Criteria'!$F$18+X28*'Selection Criteria'!$F$19+Y28*'Selection Criteria'!$F$20)/(5*'Selection Criteria'!$F$21)*100,"-") -> 76 | AA28: =IF(P28="Pass",COUNTIFS($P$5:$P$71,"Pass",$Z$5:$Z$71,">"&Z28)+1,"-") -> 23 | AB28: =IF(P28<>"Pass","Parked (gate)",IF(AND('Selection Criteria'!$C$65="Yes",Q28="Non-Hero"),"Tier 3",IF(Z28>='Selection Criteria'!$C$25,"Tier 1",IF(Z28>='Selection Criteria'!$C$26,"Tier 2","Tier 3")))) -> Tier 2 | AC28: =INDEX('Hero Segmentation'!$R$5:$R$71,MATCH($A28,'Hero Segmentation'!$A$5:$A$71,0)) -> BUILD | AD28: =IF(AND(AB28="Tier 1",J28>='Selection Criteria'!$C$28),"Yes","") | AE28: =IFERROR(INDEX('Competitor Fit'!$C$5:$C$103,MATCH($A28&"|Primary",'Competitor Fit'!$L$5:$L$103,0)),"-") -> Amazon | AF28: =IFERROR(INDEX('Competitor Fit'!$C$5:$C$103,MATCH($A28&"|Secondary",'Competitor Fit'!$L$5:$L$103,0)),"-") -> Best Buy | AG28: Wood/aluminium stands are desk-setup objects.
A29: P25 | B29: Furniture > Chairs & Seating > Sofas & Benches > Benches & Beam Seating | C29: Furniture | D29: Chairs & Seating | E29: Sofas & Benches | F29: Benches & Beam Seating | G29: 4 | H29: CL163750 | I29: 49 | J29: 40 | K29: 1. Chairs & Seating | L29: =IF(OR(G29=3,G29=4),"Pass","Fail") -> Pass | M29: Pass | N29: =IF(I29>='Selection Criteria'!$C$27,"Pass","Fail") -> Pass | O29: Pass | P29: =IF(AND(L29="Pass",M29="Pass",N29="Pass",O29="Pass"),"Pass","Fail") -> Pass | Q29: =INDEX('Hero Segmentation'!$Q$5:$Q$71,MATCH($A29,'Hero Segmentation'!$A$5:$A$71,0)) -> Probable Hero | R29: 4 | S29: 5 | T29: 4 | U29: 4 | V29: 1 | W29: 3 | X29: 2 | Y29: 5 | Z29: =IF(P29="Pass",(R29*'Selection Criteria'!$F$13+S29*'Selection Criteria'!$F$14+T29*'Selection Criteria'!$F$15+U29*'Selection Criteria'!$F$16+V29*'Selection Criteria'!$F$17+W29*'Selection Criteria'!$F$18+X29*'Selection Criteria'!$F$19+Y29*'Selection Criteria'!$F$20)/(5*'Selection Criteria'!$F$21)*100,"-") -> 75 | AA29: =IF(P29="Pass",COUNTIFS($P$5:$P$71,"Pass",$Z$5:$Z$71,">"&Z29)+1,"-") -> 25 | AB29: =IF(P29<>"Pass","Parked (gate)",IF(AND('Selection Criteria'!$C$65="Yes",Q29="Non-Hero"),"Tier 3",IF(Z29>='Selection Criteria'!$C$25,"Tier 1",IF(Z29>='Selection Criteria'!$C$26,"Tier 2","Tier 3")))) -> Tier 2 | AC29: =INDEX('Hero Segmentation'!$R$5:$R$71,MATCH($A29,'Hero Segmentation'!$A$5:$A$71,0)) -> BUILD | AD29: =IF(AND(AB29="Tier 1",J29>='Selection Criteria'!$C$28),"Yes","") | AE29: =IFERROR(INDEX('Competitor Fit'!$C$5:$C$103,MATCH($A29&"|Primary",'Competitor Fit'!$L$5:$L$103,0)),"-") -> Wayfair | AF29: =IFERROR(INDEX('Competitor Fit'!$C$5:$C$103,MATCH($A29&"|Secondary",'Competitor Fit'!$L$5:$L$103,0)),"-") -> Amazon | AG29: Pilot: 2 Strong recs; thin Staples baseline (49); oversize freight.
A30: P26 | B30: Furniture > Lamps & Lighting > Table Lamps | C30: Furniture | D30: Lamps & Lighting | E30: Table Lamps | G30: 3 | H30: CL216712 | I30: 211 | J30: 129 | K30: 3. Lamps & Lighting | L30: =IF(OR(G30=3,G30=4),"Pass","Fail") -> Pass | M30: Pass | N30: =IF(I30>='Selection Criteria'!$C$27,"Pass","Fail") -> Pass | O30: Pass | P30: =IF(AND(L30="Pass",M30="Pass",N30="Pass",O30="Pass"),"Pass","Fail") -> Pass | Q30: =INDEX('Hero Segmentation'!$Q$5:$Q$71,MATCH($A30,'Hero Segmentation'!$A$5:$A$71,0)) -> Probable Hero | R30: 5 | S30: 4 | T30: 4 | U30: 3 | V30: 3 | W30: 3 | X30: 2 | Y30: 4 | Z30: =IF(P30="Pass",(R30*'Selection Criteria'!$F$13+S30*'Selection Criteria'!$F$14+T30*'Selection Criteria'!$F$15+U30*'Selection Criteria'!$F$16+V30*'Selection Criteria'!$F$17+W30*'Selection Criteria'!$F$18+X30*'Selection Criteria'!$F$19+Y30*'Selection Criteria'!$F$20)/(5*'Selection Criteria'!$F$21)*100,"-") -> 75 | AA30: =IF(P30="Pass",COUNTIFS($P$5:$P$71,"Pass",$Z$5:$Z$71,">"&Z30)+1,"-") -> 25 | AB30: =IF(P30<>"Pass","Parked (gate)",IF(AND('Selection Criteria'!$C$65="Yes",Q30="Non-Hero"),"Tier 3",IF(Z30>='Selection Criteria'!$C$25,"Tier 1",IF(Z30>='Selection Criteria'!$C$26,"Tier 2","Tier 3")))) -> Tier 2 | AC30: =INDEX('Hero Segmentation'!$R$5:$R$71,MATCH($A30,'Hero Segmentation'!$A$5:$A$71,0)) -> BUILD | AD30: =IF(AND(AB30="Tier 1",J30>='Selection Criteria'!$C$28),"Yes","") | AE30: =IFERROR(INDEX('Competitor Fit'!$C$5:$C$103,MATCH($A30&"|Primary",'Competitor Fit'!$L$5:$L$103,0)),"-") -> Wayfair | AF30: =IFERROR(INDEX('Competitor Fit'!$C$5:$C$103,MATCH($A30&"|Secondary",'Competitor Fit'!$L$5:$L$103,0)),"-") -> Target | AG30: Reception / home-office decor lighting.
A31: P27 | B31: Computers & Accessories > Computer Accessories & Peripherals > Computer Keyboards | C31: Computers & Accessories | D31: Computer Accessories & Peripherals | E31: Computer Keyboards | G31: 3 | H31: CL215783 | I31: 374 | J31: 0 | K31: New | L31: =IF(OR(G31=3,G31=4),"Pass","Fail") -> Pass | M31: Pass | N31: =IF(I31>='Selection Criteria'!$C$27,"Pass","Fail") -> Pass | O31: Pass | P31: =IF(AND(L31="Pass",M31="Pass",N31="Pass",O31="Pass"),"Pass","Fail") -> Pass | Q31: =INDEX('Hero Segmentation'!$Q$5:$Q$71,MATCH($A31,'Hero Segmentation'!$A$5:$A$71,0)) -> Hero | R31: 4 | S31: 4 | T31: 3 | U31: 5 | V31: 4 | W31: 4 | X31: 3 | Y31: 2 | Z31: =IF(P31="Pass",(R31*'Selection Criteria'!$F$13+S31*'Selection Criteria'!$F$14+T31*'Selection Criteria'!$F$15+U31*'Selection Criteria'!$F$16+V31*'Selection Criteria'!$F$17+W31*'Selection Criteria'!$F$18+X31*'Selection Criteria'!$F$19+Y31*'Selection Criteria'!$F$20)/(5*'Selection Criteria'!$F$21)*100,"-") -> 75 | AA31: =IF(P31="Pass",COUNTIFS($P$5:$P$71,"Pass",$Z$5:$Z$71,">"&Z31)+1,"-") -> 25 | AB31: =IF(P31<>"Pass","Parked (gate)",IF(AND('Selection Criteria'!$C$65="Yes",Q31="Non-Hero"),"Tier 3",IF(Z31>='Selection Criteria'!$C$25,"Tier 1",IF(Z31>='Selection Criteria'!$C$26,"Tier 2","Tier 3")))) -> Tier 2 | AC31: =INDEX('Hero Segmentation'!$R$5:$R$71,MATCH($A31,'Hero Segmentation'!$A$5:$A$71,0)) -> EXTEND | AD31: =IF(AND(AB31="Tier 1",J31>='Selection Criteria'!$C$28),"Yes","") | AE31: =IFERROR(INDEX('Competitor Fit'!$C$5:$C$103,MATCH($A31&"|Primary",'Competitor Fit'!$L$5:$L$103,0)),"-") -> Amazon | AF31: =IFERROR(INDEX('Competitor Fit'!$C$5:$C$103,MATCH($A31&"|Secondary",'Competitor Fit'!$L$5:$L$103,0)),"-") -> Best Buy | AG31: Typewriter/pastel keyboards mainstream (Logitech POP); business keyboards are core.
A32: P28 | B32: Furniture > Chairs & Seating > Breakroom & Dining Chairs | C32: Furniture | D32: Chairs & Seating | E32: Breakroom & Dining Chairs | G32: 3 | H32: CL166181 | I32: 75 | J32: 40 | K32: 1. Chairs & Seating | L32: =IF(OR(G32=3,G32=4),"Pass","Fail") -> Pass | M32: Pass | N32: =IF(I32>='Selection Criteria'!$C$27,"Pass","Fail") -> Pass | O32: Pass | P32: =IF(AND(L32="Pass",M32="Pass",N32="Pass",O32="Pass"),"Pass","Fail") -> Pass | Q32: =INDEX('Hero Segmentation'!$Q$5:$Q$71,MATCH($A32,'Hero Segmentation'!$A$5:$A$71,0)) -> Probable Hero | R32: 4 | S32: 5 | T32: 3 | U32: 4 | V32: 2 | W32: 3 | X32: 2 | Y32: 5 | Z32: =IF(P32="Pass",(R32*'Selection Criteria'!$F$13+S32*'Selection Criteria'!$F$14+T32*'Selection Criteria'!$F$15+U32*'Selection Criteria'!$F$16+V32*'Selection Criteria'!$F$17+W32*'Selection Criteria'!$F$18+X32*'Selection Criteria'!$F$19+Y32*'Selection Criteria'!$F$20)/(5*'Selection Criteria'!$F$21)*100,"-") -> 74 | AA32: =IF(P32="Pass",COUNTIFS($P$5:$P$71,"Pass",$Z$5:$Z$71,">"&Z32)+1,"-") -> 28 | AB32: =IF(P32<>"Pass","Parked (gate)",IF(AND('Selection Criteria'!$C$65="Yes",Q32="Non-Hero"),"Tier 3",IF(Z32>='Selection Criteria'!$C$25,"Tier 1",IF(Z32>='Selection Criteria'!$C$26,"Tier 2","Tier 3")))) -> Tier 2 | AC32: =INDEX('Hero Segmentation'!$R$5:$R$71,MATCH($A32,'Hero Segmentation'!$A$5:$A$71,0)) -> BUILD | AD32: =IF(AND(AB32="Tier 1",J32>='Selection Criteria'!$C$28),"Yes","") | AE32: =IFERROR(INDEX('Competitor Fit'!$C$5:$C$103,MATCH($A32&"|Primary",'Competitor Fit'!$L$5:$L$103,0)),"-") -> Wayfair | AF32: =IFERROR(INDEX('Competitor Fit'!$C$5:$C$103,MATCH($A32&"|Secondary",'Competitor Fit'!$L$5:$L$103,0)),"-") -> Amazon | AG32: Pilot: 5 recs but methods disagree (rho 0.08); RTO breakroom story.
A33: P29 | B33: Office Supplies > Calendars & Planners > Calendars | C33: Office Supplies | D33: Calendars & Planners | E33: Calendars | G33: 3 | H33: CL166389 | I33: 1234 | J33: 0 | K33: 9. Planning & Craft Organization | L33: =IF(OR(G33=3,G33=4),"Pass","Fail") -> Pass | M33: Pass | N33: =IF(I33>='Selection Criteria'!$C$27,"Pass","Fail") -> Pass | O33: Pass | P33: =IF(AND(L33="Pass",M33="Pass",N33="Pass",O33="Pass"),"Pass","Fail") -> Pass | Q33: =INDEX('Hero Segmentation'!$Q$5:$Q$71,MATCH($A33,'Hero Segmentation'!$A$5:$A$71,0)) -> Hero | R33: 4 | S33: 3 | T33: 3 | U33: 5 | V33: 5 | W33: 3 | X33: 5 | Y33: 2 | Z33: =IF(P33="Pass",(R33*'Selection Criteria'!$F$13+S33*'Selection Criteria'!$F$14+T33*'Selection Criteria'!$F$15+U33*'Selection Criteria'!$F$16+V33*'Selection Criteria'!$F$17+W33*'Selection Criteria'!$F$18+X33*'Selection Criteria'!$F$19+Y33*'Selection Criteria'!$F$20)/(5*'Selection Criteria'!$F$21)*100,"-") -> 74 | AA33: =IF(P33="Pass",COUNTIFS($P$5:$P$71,"Pass",$Z$5:$Z$71,">"&Z33)+1,"-") -> 28 | AB33: =IF(P33<>"Pass","Parked (gate)",IF(AND('Selection Criteria'!$C$65="Yes",Q33="Non-Hero"),"Tier 3",IF(Z33>='Selection Criteria'!$C$25,"Tier 1",IF(Z33>='Selection Criteria'!$C$26,"Tier 2","Tier 3")))) -> Tier 2 | AC33: =INDEX('Hero Segmentation'!$R$5:$R$71,MATCH($A33,'Hero Segmentation'!$A$5:$A$71,0)) -> EXTEND | AD33: =IF(AND(AB33="Tier 1",J33>='Selection Criteria'!$C$28),"Yes","") | AE33: =IFERROR(INDEX('Competitor Fit'!$C$5:$C$103,MATCH($A33&"|Primary",'Competitor Fit'!$L$5:$L$103,0)),"-") -> Amazon | AF33: =IFERROR(INDEX('Competitor Fit'!$C$5:$C$103,MATCH($A33&"|Secondary",'Competitor Fit'!$L$5:$L$103,0)),"-") -> Target | AG33: Dated goods are core 1P; design calendars are the adjacency.
A34: P30 | B34: Furniture > Chairs & Seating > Stools & Ottomans > Counter & Bar Stools | C34: Furniture | D34: Chairs & Seating | E34: Stools & Ottomans | F34: Counter & Bar Stools | G34: 4 | H34: CL166182 | I34: 617 | J34: 601 | K34: 1. Chairs & Seating | L34: =IF(OR(G34=3,G34=4),"Pass","Fail") -> Pass | M34: Pass | N34: =IF(I34>='Selection Criteria'!$C$27,"Pass","Fail") -> Pass | O34: Pass | P34: =IF(AND(L34="Pass",M34="Pass",N34="Pass",O34="Pass"),"Pass","Fail") -> Pass | Q34: =INDEX('Hero Segmentation'!$Q$5:$Q$71,MATCH($A34,'Hero Segmentation'!$A$5:$A$71,0)) -> Probable Hero | R34: 4 | S34: 4 | T34: 4 | U34: 3 | V34: 2 | W34: 4 | X34: 2 | Y34: 5 | Z34: =IF(P34="Pass",(R34*'Selection Criteria'!$F$13+S34*'Selection Criteria'!$F$14+T34*'Selection Criteria'!$F$15+U34*'Selection Criteria'!$F$16+V34*'Selection Criteria'!$F$17+W34*'Selection Criteria'!$F$18+X34*'Selection Criteria'!$F$19+Y34*'Selection Criteria'!$F$20)/(5*'Selection Criteria'!$F$21)*100,"-") -> 73 | AA34: =IF(P34="Pass",COUNTIFS($P$5:$P$71,"Pass",$Z$5:$Z$71,">"&Z34)+1,"-") -> 30 | AB34: =IF(P34<>"Pass","Parked (gate)",IF(AND('Selection Criteria'!$C$65="Yes",Q34="Non-Hero"),"Tier 3",IF(Z34>='Selection Criteria'!$C$25,"Tier 1",IF(Z34>='Selection Criteria'!$C$26,"Tier 2","Tier 3")))) -> Tier 2 | AC34: =INDEX('Hero Segmentation'!$R$5:$R$71,MATCH($A34,'Hero Segmentation'!$A$5:$A$71,0)) -> BUILD | AD34: =IF(AND(AB34="Tier 1",J34>='Selection Criteria'!$C$28),"Yes","") | AE34: =IFERROR(INDEX('Competitor Fit'!$C$5:$C$103,MATCH($A34&"|Primary",'Competitor Fit'!$L$5:$L$103,0)),"-") -> Wayfair | AF34: =IFERROR(INDEX('Competitor Fit'!$C$5:$C$103,MATCH($A34&"|Secondary",'Competitor Fit'!$L$5:$L$103,0)),"-") -> Amazon | AG34: Pilot: best method agreement (rho 0.73 on bar-height split); café/breakroom, not the core work mission.
A35: P31 | B35: Furniture > Lamps & Lighting > Floor Lamps | C35: Furniture | D35: Lamps & Lighting | E35: Floor Lamps | G35: 3 | H35: CL216710 | I35: 132 | J35: 120 | K35: 3. Lamps & Lighting | L35: =IF(OR(G35=3,G35=4),"Pass","Fail") -> Pass | M35: Pass | N35: =IF(I35>='Selection Criteria'!$C$27,"Pass","Fail") -> Pass | O35: Pass | P35: =IF(AND(L35="Pass",M35="Pass",N35="Pass",O35="Pass"),"Pass","Fail") -> Pass | Q35: =INDEX('Hero Segmentation'!$Q$5:$Q$71,MATCH($A35,'Hero Segmentation'!$A$5:$A$71,0)) -> Probable Hero | R35: 5 | S35: 4 | T35: 4 | U35: 3 | V35: 2 | W35: 3 | X35: 2 | Y35: 4 | Z35: =IF(P35="Pass",(R35*'Selection Criteria'!$F$13+S35*'Selection Criteria'!$F$14+T35*'Selection Criteria'!$F$15+U35*'Selection Criteria'!$F$16+V35*'Selection Criteria'!$F$17+W35*'Selection Criteria'!$F$18+X35*'Selection Criteria'!$F$19+Y35*'Selection Criteria'!$F$20)/(5*'Selection Criteria'!$F$21)*100,"-") -> 73 | AA35: =IF(P35="Pass",COUNTIFS($P$5:$P$71,"Pass",$Z$5:$Z$71,">"&Z35)+1,"-") -> 30 | AB35: =IF(P35<>"Pass","Parked (gate)",IF(AND('Selection Criteria'!$C$65="Yes",Q35="Non-Hero"),"Tier 3",IF(Z35>='Selection Criteria'!$C$25,"Tier 1",IF(Z35>='Selection Criteria'!$C$26,"Tier 2","Tier 3")))) -> Tier 2 | AC35: =INDEX('Hero Segmentation'!$R$5:$R$71,MATCH($A35,'Hero Segmentation'!$A$5:$A$71,0)) -> BUILD | AD35: =IF(AND(AB35="Tier 1",J35>='Selection Criteria'!$C$28),"Yes","") | AE35: =IFERROR(INDEX('Competitor Fit'!$C$5:$C$103,MATCH($A35&"|Primary",'Competitor Fit'!$L$5:$L$103,0)),"-") -> Wayfair | AF35: =IFERROR(INDEX('Competitor Fit'!$C$5:$C$103,MATCH($A35&"|Secondary",'Competitor Fit'!$L$5:$L$103,0)),"-") -> Target | AG35: Strong design variance; living-room leaning.
A36: P32 | B36: Office Supplies > Label Makers & Tapes > Label Makers | C36: Office Supplies | D36: Label Makers & Tapes | E36: Label Makers | G36: 3 | H36: CL90400 | I36: 148 | J36: 103 | K36: 8. Labels & Packaging Accessories | L36: =IF(OR(G36=3,G36=4),"Pass","Fail") -> Pass | M36: Pass | N36: =IF(I36>='Selection Criteria'!$C$27,"Pass","Fail") -> Pass | O36: Pass | P36: =IF(AND(L36="Pass",M36="Pass",N36="Pass",O36="Pass"),"Pass","Fail") -> Pass | Q36: =INDEX('Hero Segmentation'!$Q$5:$Q$71,MATCH($A36,'Hero Segmentation'!$A$5:$A$71,0)) -> Hero | R36: 3 | S36: 4 | T36: 3 | U36: 5 | V36: 4 | W36: 3 | X36: 3 | Y36: 4 | Z36: =IF(P36="Pass",(R36*'Selection Criteria'!$F$13+S36*'Selection Criteria'!$F$14+T36*'Selection Criteria'!$F$15+U36*'Selection Criteria'!$F$16+V36*'Selection Criteria'!$F$17+W36*'Selection Criteria'!$F$18+X36*'Selection Criteria'!$F$19+Y36*'Selection Criteria'!$F$20)/(5*'Selection Criteria'!$F$21)*100,"-") -> 73 | AA36: =IF(P36="Pass",COUNTIFS($P$5:$P$71,"Pass",$Z$5:$Z$71,">"&Z36)+1,"-") -> 30 | AB36: =IF(P36<>"Pass","Parked (gate)",IF(AND('Selection Criteria'!$C$65="Yes",Q36="Non-Hero"),"Tier 3",IF(Z36>='Selection Criteria'!$C$25,"Tier 1",IF(Z36>='Selection Criteria'!$C$26,"Tier 2","Tier 3")))) -> Tier 2 | AC36: =INDEX('Hero Segmentation'!$R$5:$R$71,MATCH($A36,'Hero Segmentation'!$A$5:$A$71,0)) -> EXTEND | AD36: =IF(AND(AB36="Tier 1",J36>='Selection Criteria'!$C$28),"Yes","") | AE36: =IFERROR(INDEX('Competitor Fit'!$C$5:$C$103,MATCH($A36&"|Primary",'Competitor Fit'!$L$5:$L$103,0)),"-") -> Amazon | AF36: =IFERROR(INDEX('Competitor Fit'!$C$5:$C$103,MATCH($A36&"|Secondary",'Competitor Fit'!$L$5:$L$103,0)),"-") -> Michaels | AG36: Mini thermal label printers went viral; Brother/DYMO are core 1P.
A37: P33 | B37: Shipping, Packing & Mailing Supplies > Mailing Supplies > Mailers | C37: Shipping, Packing & Mailing Supplies | D37: Mailing Supplies | E37: Mailers | G37: 3 | H37: CL142648 | I37: 396 | J37: 387 | K37: 8. Labels & Packaging Accessories | L37: =IF(OR(G37=3,G37=4),"Pass","Fail") -> Pass | M37: Pass | N37: =IF(I37>='Selection Criteria'!$C$27,"Pass","Fail") -> Pass | O37: Pass | P37: =IF(AND(L37="Pass",M37="Pass",N37="Pass",O37="Pass"),"Pass","Fail") -> Pass | Q37: =INDEX('Hero Segmentation'!$Q$5:$Q$71,MATCH($A37,'Hero Segmentation'!$A$5:$A$71,0)) -> Hero | R37: 3 | S37: 4 | T37: 3 | U37: 5 | V37: 4 | W37: 3 | X37: 3 | Y37: 4 | Z37: =IF(P37="Pass",(R37*'Selection Criteria'!$F$13+S37*'Selection Criteria'!$F$14+T37*'Selection Criteria'!$F$15+U37*'Selection Criteria'!$F$16+V37*'Selection Criteria'!$F$17+W37*'Selection Criteria'!$F$18+X37*'Selection Criteria'!$F$19+Y37*'Selection Criteria'!$F$20)/(5*'Selection Criteria'!$F$21)*100,"-") -> 73 | AA37: =IF(P37="Pass",COUNTIFS($P$5:$P$71,"Pass",$Z$5:$Z$71,">"&Z37)+1,"-") -> 30 | AB37: =IF(P37<>"Pass","Parked (gate)",IF(AND('Selection Criteria'!$C$65="Yes",Q37="Non-Hero"),"Tier 3",IF(Z37>='Selection Criteria'!$C$25,"Tier 1",IF(Z37>='Selection Criteria'!$C$26,"Tier 2","Tier 3")))) -> Tier 2 | AC37: =INDEX('Hero Segmentation'!$R$5:$R$71,MATCH($A37,'Hero Segmentation'!$A$5:$A$71,0)) -> EXTEND | AD37: =IF(AND(AB37="Tier 1",J37>='Selection Criteria'!$C$28),"Yes","") | AE37: =IFERROR(INDEX('Competitor Fit'!$C$5:$C$103,MATCH($A37&"|Primary",'Competitor Fit'!$L$5:$L$103,0)),"-") -> Amazon | AF37: =IFERROR(INDEX('Competitor Fit'!$C$5:$C$103,MATCH($A37&"|Secondary",'Competitor Fit'!$L$5:$L$103,0)),"-") -> Uline | AG37: Coloured/printed/recycled mailers; utility mailers are core 1P.
A38: P34 | B38: Office Supplies > Storage & Organization > Storage Bins | C38: Office Supplies | D38: Storage & Organization | E38: Storage Bins | G38: 3 | H38: CL354710 | I38: 660 | J38: 0 | K38: 9. Planning & Craft Organization | L38: =IF(OR(G38=3,G38=4),"Pass","Fail") -> Pass | M38: Pass | N38: =IF(I38>='Selection Criteria'!$C$27,"Pass","Fail") -> Pass | O38: Pass | P38: =IF(AND(L38="Pass",M38="Pass",N38="Pass",O38="Pass"),"Pass","Fail") -> Pass | Q38: =INDEX('Hero Segmentation'!$Q$5:$Q$71,MATCH($A38,'Hero Segmentation'!$A$5:$A$71,0)) -> Hero | R38: 4 | S38: 4 | T38: 3 | U38: 4 | V38: 4 | W38: 3 | X38: 5 | Y38: 2 | Z38: =IF(P38="Pass",(R38*'Selection Criteria'!$F$13+S38*'Selection Criteria'!$F$14+T38*'Selection Criteria'!$F$15+U38*'Selection Criteria'!$F$16+V38*'Selection Criteria'!$F$17+W38*'Selection Criteria'!$F$18+X38*'Selection Criteria'!$F$19+Y38*'Selection Criteria'!$F$20)/(5*'Selection Criteria'!$F$21)*100,"-") -> 72 | AA38: =IF(P38="Pass",COUNTIFS($P$5:$P$71,"Pass",$Z$5:$Z$71,">"&Z38)+1,"-") -> 34 | AB38: =IF(P38<>"Pass","Parked (gate)",IF(AND('Selection Criteria'!$C$65="Yes",Q38="Non-Hero"),"Tier 3",IF(Z38>='Selection Criteria'!$C$25,"Tier 1",IF(Z38>='Selection Criteria'!$C$26,"Tier 2","Tier 3")))) -> Tier 2 | AC38: =INDEX('Hero Segmentation'!$R$5:$R$71,MATCH($A38,'Hero Segmentation'!$A$5:$A$71,0)) -> EXTEND | AD38: =IF(AND(AB38="Tier 1",J38>='Selection Criteria'!$C$28),"Yes","") | AE38: =IFERROR(INDEX('Competitor Fit'!$C$5:$C$103,MATCH($A38&"|Primary",'Competitor Fit'!$L$5:$L$103,0)),"-") -> Target | AF38: =IFERROR(INDEX('Competitor Fit'!$C$5:$C$103,MATCH($A38&"|Secondary",'Competitor Fit'!$L$5:$L$103,0)),"-") -> Amazon | AG38: Plastic utility bins are core; fabric/acrylic are the adjacency.
A39: P35 | B39: Furniture > Boards & Easels > Calendar & In-Out Boards | C39: Furniture | D39: Boards & Easels | E39: Calendar & In-Out Boards | G39: 3 | H39: CL142105 | I39: 63 | J39: 0 | K39: New | L39: =IF(OR(G39=3,G39=4),"Pass","Fail") -> Pass | M39: Pass | N39: =IF(I39>='Selection Criteria'!$C$27,"Pass","Fail") -> Pass | O39: Pass | P39: =IF(AND(L39="Pass",M39="Pass",N39="Pass",O39="Pass"),"Pass","Fail") -> Pass | Q39: =INDEX('Hero Segmentation'!$Q$5:$Q$71,MATCH($A39,'Hero Segmentation'!$A$5:$A$71,0)) -> Probable Hero | R39: 4 | S39: 3 | T39: 4 | U39: 5 | V39: 4 | W39: 2 | X39: 4 | Y39: 2 | Z39: =IF(P39="Pass",(R39*'Selection Criteria'!$F$13+S39*'Selection Criteria'!$F$14+T39*'Selection Criteria'!$F$15+U39*'Selection Criteria'!$F$16+V39*'Selection Criteria'!$F$17+W39*'Selection Criteria'!$F$18+X39*'Selection Criteria'!$F$19+Y39*'Selection Criteria'!$F$20)/(5*'Selection Criteria'!$F$21)*100,"-") -> 72 | AA39: =IF(P39="Pass",COUNTIFS($P$5:$P$71,"Pass",$Z$5:$Z$71,">"&Z39)+1,"-") -> 34 | AB39: =IF(P39<>"Pass","Parked (gate)",IF(AND('Selection Criteria'!$C$65="Yes",Q39="Non-Hero"),"Tier 3",IF(Z39>='Selection Criteria'!$C$25,"Tier 1",IF(Z39>='Selection Criteria'!$C$26,"Tier 2","Tier 3")))) -> Tier 2 | AC39: =INDEX('Hero Segmentation'!$R$5:$R$71,MATCH($A39,'Hero Segmentation'!$A$5:$A$71,0)) -> BUILD | AD39: =IF(AND(AB39="Tier 1",J39>='Selection Criteria'!$C$28),"Yes","") | AE39: =IFERROR(INDEX('Competitor Fit'!$C$5:$C$103,MATCH($A39&"|Primary",'Competitor Fit'!$L$5:$L$103,0)),"-") -> Amazon | AF39: =IFERROR(INDEX('Competitor Fit'!$C$5:$C$103,MATCH($A39&"|Secondary",'Competitor Fit'!$L$5:$L$103,0)),"-") -> Wayfair | AG39: Acrylic/glass calendars; pairs with planners.
A40: P36 | B40: Furniture > Chairs & Seating > Stools & Ottomans > Ottomans | C40: Furniture | D40: Chairs & Seating | E40: Stools & Ottomans | F40: Ottomans | G40: 4 | H40: CL161807 | I40: 64 | J40: 39 | K40: 1. Chairs & Seating | L40: =IF(OR(G40=3,G40=4),"Pass","Fail") -> Pass | M40: Pass | N40: =IF(I40>='Selection Criteria'!$C$27,"Pass","Fail") -> Pass | O40: Pass | P40: =IF(AND(L40="Pass",M40="Pass",N40="Pass",O40="Pass"),"Pass","Fail") -> Pass | Q40: =INDEX('Hero Segmentation'!$Q$5:$Q$71,MATCH($A40,'Hero Segmentation'!$A$5:$A$71,0)) -> Probable Hero | R40: 4 | S40: 5 | T40: 4 | U40: 2 | V40: 3 | W40: 2 | X40: 2 | Y40: 4 | Z40: =IF(P40="Pass",(R40*'Selection Criteria'!$F$13+S40*'Selection Criteria'!$F$14+T40*'Selection Criteria'!$F$15+U40*'Selection Criteria'!$F$16+V40*'Selection Criteria'!$F$17+W40*'Selection Criteria'!$F$18+X40*'Selection Criteria'!$F$19+Y40*'Selection Criteria'!$F$20)/(5*'Selection Criteria'!$F$21)*100,"-") -> 69 | AA40: =IF(P40="Pass",COUNTIFS($P$5:$P$71,"Pass",$Z$5:$Z$71,">"&Z40)+1,"-") -> 36 | AB40: =IF(P40<>"Pass","Parked (gate)",IF(AND('Selection Criteria'!$C$65="Yes",Q40="Non-Hero"),"Tier 3",IF(Z40>='Selection Criteria'!$C$25,"Tier 1",IF(Z40>='Selection Criteria'!$C$26,"Tier 2","Tier 3")))) -> Tier 3 | AC40: =INDEX('Hero Segmentation'!$R$5:$R$71,MATCH($A40,'Hero Segmentation'!$A$5:$A$71,0)) -> BUILD | AD40: =IF(AND(AB40="Tier 1",J40>='Selection Criteria'!$C$28),"Yes","") | AE40: =IFERROR(INDEX('Competitor Fit'!$C$5:$C$103,MATCH($A40&"|Primary",'Competitor Fit'!$L$5:$L$103,0)),"Wayfair") -> Wayfair | AF40: =IFERROR(INDEX('Competitor Fit'!$C$5:$C$103,MATCH($A40&"|Secondary",'Competitor Fit'!$L$5:$L$103,0)),"Amazon") -> Amazon | AG40: Wayfair 1,069 vs Staples 29 in pilot; residential, weak work mission.
A41: P37 | B41: Furniture > Cubicle & Panel Systems > Desktop Privacy Panels | C41: Furniture | D41: Cubicle & Panel Systems | E41: Desktop Privacy Panels | G41: 3 | H41: CL166381 | I41: 136 | J41: 0 | K41: New | L41: =IF(OR(G41=3,G41=4),"Pass","Fail") -> Pass | M41: Pass | N41: =IF(I41>='Selection Criteria'!$C$27,"Pass","Fail") -> Pass | O41: Pass | P41: =IF(AND(L41="Pass",M41="Pass",N41="Pass",O41="Pass"),"Pass","Fail") -> Pass | Q41: =INDEX('Hero Segmentation'!$Q$5:$Q$71,MATCH($A41,'Hero Segmentation'!$A$5:$A$71,0)) -> Non-Hero | R41: 4 | S41: 3 | T41: 4 | U41: 5 | V41: 3 | W41: 2 | X41: 3 | Y41: 2 | Z41: =IF(P41="Pass",(R41*'Selection Criteria'!$F$13+S41*'Selection Criteria'!$F$14+T41*'Selection Criteria'!$F$15+U41*'Selection Criteria'!$F$16+V41*'Selection Criteria'!$F$17+W41*'Selection Criteria'!$F$18+X41*'Selection Criteria'!$F$19+Y41*'Selection Criteria'!$F$20)/(5*'Selection Criteria'!$F$21)*100,"-") -> 69 | AA41: =IF(P41="Pass",COUNTIFS($P$5:$P$71,"Pass",$Z$5:$Z$71,">"&Z41)+1,"-") -> 36 | AB41: =IF(P41<>"Pass","Parked (gate)",IF(AND('Selection Criteria'!$C$65="Yes",Q41="Non-Hero"),"Tier 3",IF(Z41>='Selection Criteria'!$C$25,"Tier 1",IF(Z41>='Selection Criteria'!$C$26,"Tier 2","Tier 3")))) -> Tier 3 | AC41: =INDEX('Hero Segmentation'!$R$5:$R$71,MATCH($A41,'Hero Segmentation'!$A$5:$A$71,0)) -> HOLD | AD41: =IF(AND(AB41="Tier 1",J41>='Selection Criteria'!$C$28),"Yes","") | AE41: =IFERROR(INDEX('Competitor Fit'!$C$5:$C$103,MATCH($A41&"|Primary",'Competitor Fit'!$L$5:$L$103,0)),"Amazon") -> Amazon | AF41: =IFERROR(INDEX('Competitor Fit'!$C$5:$C$103,MATCH($A41&"|Secondary",'Competitor Fit'!$L$5:$L$103,0)),"Wayfair") -> Wayfair | AG41: Acoustic felt desk dividers.
A42: P38 | B42: Office Supplies > Writing Supplies & Instruments > Pens | C42: Office Supplies | D42: Writing Supplies & Instruments | E42: Pens | G42: 3 | H42: CL110001 | I42: 1504 | J42: 0 | K42: New | L42: =IF(OR(G42=3,G42=4),"Pass","Fail") -> Pass | M42: Pass | N42: =IF(I42>='Selection Criteria'!$C$27,"Pass","Fail") -> Pass | O42: Pass | P42: =IF(AND(L42="Pass",M42="Pass",N42="Pass",O42="Pass"),"Pass","Fail") -> Pass | Q42: =INDEX('Hero Segmentation'!$Q$5:$Q$71,MATCH($A42,'Hero Segmentation'!$A$5:$A$71,0)) -> Hero | R42: 3 | S42: 4 | T42: 1 | U42: 5 | V42: 5 | W42: 4 | X42: 4 | Y42: 2 | Z42: =IF(P42="Pass",(R42*'Selection Criteria'!$F$13+S42*'Selection Criteria'!$F$14+T42*'Selection Criteria'!$F$15+U42*'Selection Criteria'!$F$16+V42*'Selection Criteria'!$F$17+W42*'Selection Criteria'!$F$18+X42*'Selection Criteria'!$F$19+Y42*'Selection Criteria'!$F$20)/(5*'Selection Criteria'!$F$21)*100,"-") -> 68 | AA42: =IF(P42="Pass",COUNTIFS($P$5:$P$71,"Pass",$Z$5:$Z$71,">"&Z42)+1,"-") -> 38 | AB42: =IF(P42<>"Pass","Parked (gate)",IF(AND('Selection Criteria'!$C$65="Yes",Q42="Non-Hero"),"Tier 3",IF(Z42>='Selection Criteria'!$C$25,"Tier 1",IF(Z42>='Selection Criteria'!$C$26,"Tier 2","Tier 3")))) -> Tier 3 | AC42: =INDEX('Hero Segmentation'!$R$5:$R$71,MATCH($A42,'Hero Segmentation'!$A$5:$A$71,0)) -> PROTECT | AD42: =IF(AND(AB42="Tier 1",J42>='Selection Criteria'!$C$28),"Yes","") | AE42: =IFERROR(INDEX('Competitor Fit'!$C$5:$C$103,MATCH($A42&"|Primary",'Competitor Fit'!$L$5:$L$103,0)),"JetPens") -> JetPens | AF42: =IFERROR(INDEX('Competitor Fit'!$C$5:$C$103,MATCH($A42&"|Secondary",'Competitor Fit'!$L$5:$L$103,0)),"Amazon") -> Amazon | AG42: Core 1P writing instruments: design pens would substitute best-sellers.
A43: P39 | B43: Audio > Headphones > Headphones | C43: Audio | D43: Headphones | E43: Headphones | G43: 3 | H43: CL210844 | I43: 782 | J43: 0 | K43: New | L43: =IF(OR(G43=3,G43=4),"Pass","Fail") -> Pass | M43: Pass | N43: =IF(I43>='Selection Criteria'!$C$27,"Pass","Fail") -> Pass | O43: Pass | P43: =IF(AND(L43="Pass",M43="Pass",N43="Pass",O43="Pass"),"Pass","Fail") -> Pass | Q43: =INDEX('Hero Segmentation'!$Q$5:$Q$71,MATCH($A43,'Hero Segmentation'!$A$5:$A$71,0)) -> Probable Hero | R43: 4 | S43: 4 | T43: 2 | U43: 4 | V43: 4 | W43: 3 | X43: 4 | Y43: 2 | Z43: =IF(P43="Pass",(R43*'Selection Criteria'!$F$13+S43*'Selection Criteria'!$F$14+T43*'Selection Criteria'!$F$15+U43*'Selection Criteria'!$F$16+V43*'Selection Criteria'!$F$17+W43*'Selection Criteria'!$F$18+X43*'Selection Criteria'!$F$19+Y43*'Selection Criteria'!$F$20)/(5*'Selection Criteria'!$F$21)*100,"-") -> 68 | AA43: =IF(P43="Pass",COUNTIFS($P$5:$P$71,"Pass",$Z$5:$Z$71,">"&Z43)+1,"-") -> 38 | AB43: =IF(P43<>"Pass","Parked (gate)",IF(AND('Selection Criteria'!$C$65="Yes",Q43="Non-Hero"),"Tier 3",IF(Z43>='Selection Criteria'!$C$25,"Tier 1",IF(Z43>='Selection Criteria'!$C$26,"Tier 2","Tier 3")))) -> Tier 3 | AC43: =INDEX('Hero Segmentation'!$R$5:$R$71,MATCH($A43,'Hero Segmentation'!$A$5:$A$71,0)) -> BUILD | AD43: =IF(AND(AB43="Tier 1",J43>='Selection Criteria'!$C$28),"Yes","") | AE43: =IFERROR(INDEX('Competitor Fit'!$C$5:$C$103,MATCH($A43&"|Primary",'Competitor Fit'!$L$5:$L$103,0)),"Best Buy") -> Best Buy | AF43: =IFERROR(INDEX('Competitor Fit'!$C$5:$C$103,MATCH($A43&"|Secondary",'Competitor Fit'!$L$5:$L$103,0)),"Target") -> Target | AG43: BTS growth category but Staples already carries 782 items: substitution risk.
A44: P40 | B44: Computers & Accessories > Computer Monitors & Stands > Monitor Stands & Mounts | C44: Computers & Accessories | D44: Computer Monitors & Stands | E44: Monitor Stands & Mounts | G44: 3 | H44: CL141470 | I44: 661 | J44: 0 | K44: New | L44: =IF(OR(G44=3,G44=4),"Pass","Fail") -> Pass | M44: Pass | N44: =IF(I44>='Selection Criteria'!$C$27,"Pass","Fail") -> Pass | O44: Pass | P44: =IF(AND(L44="Pass",M44="Pass",N44="Pass",O44="Pass"),"Pass","Fail") -> Pass | Q44: =INDEX('Hero Segmentation'!$Q$5:$Q$71,MATCH($A44,'Hero Segmentation'!$A$5:$A$71,0)) -> Hero | R44: 3 | S44: 4 | T44: 3 | U44: 5 | V44: 3 | W44: 3 | X44: 3 | Y44: 2 | Z44: =IF(P44="Pass",(R44*'Selection Criteria'!$F$13+S44*'Selection Criteria'!$F$14+T44*'Selection Criteria'!$F$15+U44*'Selection Criteria'!$F$16+V44*'Selection Criteria'!$F$17+W44*'Selection Criteria'!$F$18+X44*'Selection Criteria'!$F$19+Y44*'Selection Criteria'!$F$20)/(5*'Selection Criteria'!$F$21)*100,"-") -> 67 | AA44: =IF(P44="Pass",COUNTIFS($P$5:$P$71,"Pass",$Z$5:$Z$71,">"&Z44)+1,"-") -> 40 | AB44: =IF(P44<>"Pass","Parked (gate)",IF(AND('Selection Criteria'!$C$65="Yes",Q44="Non-Hero"),"Tier 3",IF(Z44>='Selection Criteria'!$C$25,"Tier 1",IF(Z44>='Selection Criteria'!$C$26,"Tier 2","Tier 3")))) -> Tier 3 | AC44: =INDEX('Hero Segmentation'!$R$5:$R$71,MATCH($A44,'Hero Segmentation'!$A$5:$A$71,0)) -> EXTEND | AD44: =IF(AND(AB44="Tier 1",J44>='Selection Criteria'!$C$28),"Yes","") | AE44: =IFERROR(INDEX('Competitor Fit'!$C$5:$C$103,MATCH($A44&"|Primary",'Competitor Fit'!$L$5:$L$103,0)),"Amazon") -> Amazon | AF44: =IFERROR(INDEX('Competitor Fit'!$C$5:$C$103,MATCH($A44&"|Secondary",'Competitor Fit'!$L$5:$L$103,0)),"Wayfair") -> Wayfair | AG44: Mounts/arms are spec-led; only risers are style-led.
A45: P41 | B45: Furniture > Cubicle & Panel Systems > Office Partitions & Dividers | C45: Furniture | D45: Cubicle & Panel Systems | E45: Office Partitions & Dividers | G45: 3 | H45: CL70600 | I45: 152 | J45: 0 | K45: New | L45: =IF(OR(G45=3,G45=4),"Pass","Fail") -> Pass | M45: Pass | N45: =IF(I45>='Selection Criteria'!$C$27,"Pass","Fail") -> Pass | O45: Pass | P45: =IF(AND(L45="Pass",M45="Pass",N45="Pass",O45="Pass"),"Pass","Fail") -> Pass | Q45: =INDEX('Hero Segmentation'!$Q$5:$Q$71,MATCH($A45,'Hero Segmentation'!$A$5:$A$71,0)) -> Non-Hero | R45: 4 | S45: 4 | T45: 4 | U45: 4 | V45: 1 | W45: 3 | X45: 3 | Y45: 2 | Z45: =IF(P45="Pass",(R45*'Selection Criteria'!$F$13+S45*'Selection Criteria'!$F$14+T45*'Selection Criteria'!$F$15+U45*'Selection Criteria'!$F$16+V45*'Selection Criteria'!$F$17+W45*'Selection Criteria'!$F$18+X45*'Selection Criteria'!$F$19+Y45*'Selection Criteria'!$F$20)/(5*'Selection Criteria'!$F$21)*100,"-") -> 67 | AA45: =IF(P45="Pass",COUNTIFS($P$5:$P$71,"Pass",$Z$5:$Z$71,">"&Z45)+1,"-") -> 40 | AB45: =IF(P45<>"Pass","Parked (gate)",IF(AND('Selection Criteria'!$C$65="Yes",Q45="Non-Hero"),"Tier 3",IF(Z45>='Selection Criteria'!$C$25,"Tier 1",IF(Z45>='Selection Criteria'!$C$26,"Tier 2","Tier 3")))) -> Tier 3 | AC45: =INDEX('Hero Segmentation'!$R$5:$R$71,MATCH($A45,'Hero Segmentation'!$A$5:$A$71,0)) -> HOLD | AD45: =IF(AND(AB45="Tier 1",J45>='Selection Criteria'!$C$28),"Yes","") | AE45: =IFERROR(INDEX('Competitor Fit'!$C$5:$C$103,MATCH($A45&"|Primary",'Competitor Fit'!$L$5:$L$103,0)),"Wayfair") -> Wayfair | AF45: =IFERROR(INDEX('Competitor Fit'!$C$5:$C$103,MATCH($A45&"|Secondary",'Competitor Fit'!$L$5:$L$103,0)),"Amazon") -> Amazon | AG45: Decorative dividers & acoustic panels (RTO); freight.
A46: P42 | B46: Cleaning Supplies > Waste & Recycling > Trash Cans & Recycling Bins | C46: Cleaning Supplies | D46: Waste & Recycling | E46: Trash Cans & Recycling Bins | G46: 3 | H46: CL141928 | I46: 798 | J46: 0 | K46: New | L46: =IF(OR(G46=3,G46=4),"Pass","Fail") -> Pass | M46: Pass | N46: =IF(I46>='Selection Criteria'!$C$27,"Pass","Fail") -> Pass | O46: Pass | P46: =IF(AND(L46="Pass",M46="Pass",N46="Pass",O46="Pass"),"Pass","Fail") -> Pass | Q46: =INDEX('Hero Segmentation'!$Q$5:$Q$71,MATCH($A46,'Hero Segmentation'!$A$5:$A$71,0)) -> Hero | R46: 4 | S46: 4 | T46: 3 | U46: 4 | V46: 3 | W46: 3 | X46: 2 | Y46: 2 | Z46: =IF(P46="Pass",(R46*'Selection Criteria'!$F$13+S46*'Selection Criteria'!$F$14+T46*'Selection Criteria'!$F$15+U46*'Selection Criteria'!$F$16+V46*'Selection Criteria'!$F$17+W46*'Selection Criteria'!$F$18+X46*'Selection Criteria'!$F$19+Y46*'Selection Criteria'!$F$20)/(5*'Selection Criteria'!$F$21)*100,"-") -> 67 | AA46: =IF(P46="Pass",COUNTIFS($P$5:$P$71,"Pass",$Z$5:$Z$71,">"&Z46)+1,"-") -> 40 | AB46: =IF(P46<>"Pass","Parked (gate)",IF(AND('Selection Criteria'!$C$65="Yes",Q46="Non-Hero"),"Tier 3",IF(Z46>='Selection Criteria'!$C$25,"Tier 1",IF(Z46>='Selection Criteria'!$C$26,"Tier 2","Tier 3")))) -> Tier 3 | AC46: =INDEX('Hero Segmentation'!$R$5:$R$71,MATCH($A46,'Hero Segmentation'!$A$5:$A$71,0)) -> EXTEND | AD46: =IF(AND(AB46="Tier 1",J46>='Selection Criteria'!$C$28),"Yes","") | AE46: =IFERROR(INDEX('Competitor Fit'!$C$5:$C$103,MATCH($A46&"|Primary",'Competitor Fit'!$L$5:$L$103,0)),"Wayfair") -> Wayfair | AF46: =IFERROR(INDEX('Competitor Fit'!$C$5:$C$103,MATCH($A46&"|Secondary",'Competitor Fit'!$L$5:$L$103,0)),"Target") -> Target | AG46: Facilities whitespace (Pat's doc); design bins for lobbies.
A47: P43 | B47: School Supplies > Teacher Supplies > Classroom Storage & Organization | C47: School Supplies | D47: Teacher Supplies | E47: Classroom Storage & Organization | G47: 3 | H47: CL207294 | I47: 284 | J47: 0 | K47: New | L47: =IF(OR(G47=3,G47=4),"Pass","Fail") -> Pass | M47: Pass | N47: =IF(I47>='Selection Criteria'!$C$27,"Pass","Fail") -> Pass | O47: Pass | P47: =IF(AND(L47="Pass",M47="Pass",N47="Pass",O47="Pass"),"Pass","Fail") -> Pass | Q47: =INDEX('Hero Segmentation'!$Q$5:$Q$71,MATCH($A47,'Hero Segmentation'!$A$5:$A$71,0)) -> Hero | R47: 3 | S47: 3 | T47: 3 | U47: 5 | V47: 4 | W47: 3 | X47: 4 | Y47: 2 | Z47: =IF(P47="Pass",(R47*'Selection Criteria'!$F$13+S47*'Selection Criteria'!$F$14+T47*'Selection Criteria'!$F$15+U47*'Selection Criteria'!$F$16+V47*'Selection Criteria'!$F$17+W47*'Selection Criteria'!$F$18+X47*'Selection Criteria'!$F$19+Y47*'Selection Criteria'!$F$20)/(5*'Selection Criteria'!$F$21)*100,"-") -> 67 | AA47: =IF(P47="Pass",COUNTIFS($P$5:$P$71,"Pass",$Z$5:$Z$71,">"&Z47)+1,"-") -> 40 | AB47: =IF(P47<>"Pass","Parked (gate)",IF(AND('Selection Criteria'!$C$65="Yes",Q47="Non-Hero"),"Tier 3",IF(Z47>='Selection Criteria'!$C$25,"Tier 1",IF(Z47>='Selection Criteria'!$C$26,"Tier 2","Tier 3")))) -> Tier 3 | AC47: =INDEX('Hero Segmentation'!$R$5:$R$71,MATCH($A47,'Hero Segmentation'!$A$5:$A$71,0)) -> EXTEND | AD47: =IF(AND(AB47="Tier 1",J47>='Selection Criteria'!$C$28),"Yes","") | AE47: =IFERROR(INDEX('Competitor Fit'!$C$5:$C$103,MATCH($A47&"|Primary",'Competitor Fit'!$L$5:$L$103,0)),"Amazon") -> Amazon | AF47: =IFERROR(INDEX('Competitor Fit'!$C$5:$C$103,MATCH($A47&"|Secondary",'Competitor Fit'!$L$5:$L$103,0)),"Oriental Trading") -> Oriental Trading | AG47: Functional; weaker design variance.
A48: P44 | B48: Fitness > Fitness Equipment > Fitness Machines > Fitness Machines | C48: Fitness | D48: Fitness Equipment | E48: Fitness Machines | F48: Fitness Machines | G48: 4 | H48: CL205616 | I48: 43 | J48: 40 | K48: 5. Fitness Equipment | L48: =IF(OR(G48=3,G48=4),"Pass","Fail") -> Pass | M48: Pass | N48: =IF(I48>='Selection Criteria'!$C$27,"Pass","Fail") -> Pass | O48: Pass | P48: =IF(AND(L48="Pass",M48="Pass",N48="Pass",O48="Pass"),"Pass","Fail") -> Pass | Q48: =INDEX('Hero Segmentation'!$Q$5:$Q$71,MATCH($A48,'Hero Segmentation'!$A$5:$A$71,0)) -> Probable Hero | R48: 3 | S48: 5 | T48: 5 | U48: 3 | V48: 1 | W48: 3 | X48: 4 | Y48: 2 | Z48: =IF(P48="Pass",(R48*'Selection Criteria'!$F$13+S48*'Selection Criteria'!$F$14+T48*'Selection Criteria'!$F$15+U48*'Selection Criteria'!$F$16+V48*'Selection Criteria'!$F$17+W48*'Selection Criteria'!$F$18+X48*'Selection Criteria'!$F$19+Y48*'Selection Criteria'!$F$20)/(5*'Selection Criteria'!$F$21)*100,"-") -> 67 | AA48: =IF(P48="Pass",COUNTIFS($P$5:$P$71,"Pass",$Z$5:$Z$71,">"&Z48)+1,"-") -> 40 | AB48: =IF(P48<>"Pass","Parked (gate)",IF(AND('Selection Criteria'!$C$65="Yes",Q48="Non-Hero"),"Tier 3",IF(Z48>='Selection Criteria'!$C$25,"Tier 1",IF(Z48>='Selection Criteria'!$C$26,"Tier 2","Tier 3")))) -> Tier 3 | AC48: =INDEX('Hero Segmentation'!$R$5:$R$71,MATCH($A48,'Hero Segmentation'!$A$5:$A$71,0)) -> BUILD | AD48: =IF(AND(AB48="Tier 1",J48>='Selection Criteria'!$C$28),"Yes","") | AE48: =IFERROR(INDEX('Competitor Fit'!$C$5:$C$103,MATCH($A48&"|Primary",'Competitor Fit'!$L$5:$L$103,0)),"Amazon") -> Amazon | AF48: =IFERROR(INDEX('Competitor Fit'!$C$5:$C$103,MATCH($A48&"|Secondary",'Competitor Fit'!$L$5:$L$103,0)),"Dick's Sporting Goods") -> Dick's Sporting Goods | AG48: Only as 'active workstation' (walking pads, desk bikes); bulky, thin baseline.
A49: P45 | B49: Coffee, Water & Snacks > Coffee, Coffee Makers & Supplies > Carafes, Kettles & Decanters | C49: Coffee, Water & Snacks | D49: Coffee, Coffee Makers & Supplies | E49: Carafes, Kettles & Decanters | G49: 3 | H49: CL142180 | I49: 55 | J49: 0 | K49: New | L49: =IF(OR(G49=3,G49=4),"Pass","Fail") -> Pass | M49: Pass | N49: =IF(I49>='Selection Criteria'!$C$27,"Pass","Fail") -> Pass | O49: Pass | P49: =IF(AND(L49="Pass",M49="Pass",N49="Pass",O49="Pass"),"Pass","Fail") -> Pass | Q49: =INDEX('Hero Segmentation'!$Q$5:$Q$71,MATCH($A49,'Hero Segmentation'!$A$5:$A$71,0)) -> Non-Hero | R49: 4 | S49: 4 | T49: 4 | U49: 3 | V49: 4 | W49: 2 | X49: 2 | Y49: 2 | Z49: =IF(P49="Pass",(R49*'Selection Criteria'!$F$13+S49*'Selection Criteria'!$F$14+T49*'Selection Criteria'!$F$15+U49*'Selection Criteria'!$F$16+V49*'Selection Criteria'!$F$17+W49*'Selection Criteria'!$F$18+X49*'Selection Criteria'!$F$19+Y49*'Selection Criteria'!$F$20)/(5*'Selection Criteria'!$F$21)*100,"-") -> 67 | AA49: =IF(P49="Pass",COUNTIFS($P$5:$P$71,"Pass",$Z$5:$Z$71,">"&Z49)+1,"-") -> 40 | AB49: =IF(P49<>"Pass","Parked (gate)",IF(AND('Selection Criteria'!$C$65="Yes",Q49="Non-Hero"),"Tier 3",IF(Z49>='Selection Criteria'!$C$25,"Tier 1",IF(Z49>='Selection Criteria'!$C$26,"Tier 2","Tier 3")))) -> Tier 3 | AC49: =INDEX('Hero Segmentation'!$R$5:$R$71,MATCH($A49,'Hero Segmentation'!$A$5:$A$71,0)) -> HOLD | AD49: =IF(AND(AB49="Tier 1",J49>='Selection Criteria'!$C$28),"Yes","") | AE49: =IFERROR(INDEX('Competitor Fit'!$C$5:$C$103,MATCH($A49&"|Primary",'Competitor Fit'!$L$5:$L$103,0)),"Target") -> Target | AF49: =IFERROR(INDEX('Competitor Fit'!$C$5:$C$103,MATCH($A49&"|Secondary",'Competitor Fit'!$L$5:$L$103,0)),"Amazon") -> Amazon | AG49: Design electric kettles for breakrooms.
A50: P46 | B50: Furniture > Decor > Essential Oils & Diffusers | C50: Furniture | D50: Decor | E50: Essential Oils & Diffusers | G50: 3 | H50: CL354884 | I50: 46 | J50: 0 | K50: New | L50: =IF(OR(G50=3,G50=4),"Pass","Fail") -> Pass | M50: Pass | N50: =IF(I50>='Selection Criteria'!$C$27,"Pass","Fail") -> Pass | O50: Pass | P50: =IF(AND(L50="Pass",M50="Pass",N50="Pass",O50="Pass"),"Pass","Fail") -> Pass | Q50: =INDEX('Hero Segmentation'!$Q$5:$Q$71,MATCH($A50,'Hero Segmentation'!$A$5:$A$71,0)) -> Non-Hero | R50: 4 | S50: 4 | T50: 5 | U50: 2 | V50: 5 | W50: 1 | X50: 2 | Y50: 2 | Z50: =IF(P50="Pass",(R50*'Selection Criteria'!$F$13+S50*'Selection Criteria'!$F$14+T50*'Selection Criteria'!$F$15+U50*'Selection Criteria'!$F$16+V50*'Selection Criteria'!$F$17+W50*'Selection Criteria'!$F$18+X50*'Selection Criteria'!$F$19+Y50*'Selection Criteria'!$F$20)/(5*'Selection Criteria'!$F$21)*100,"-") -> 67 | AA50: =IF(P50="Pass",COUNTIFS($P$5:$P$71,"Pass",$Z$5:$Z$71,">"&Z50)+1,"-") -> 40 | AB50: =IF(P50<>"Pass","Parked (gate)",IF(AND('Selection Criteria'!$C$65="Yes",Q50="Non-Hero"),"Tier 3",IF(Z50>='Selection Criteria'!$C$25,"Tier 1",IF(Z50>='Selection Criteria'!$C$26,"Tier 2","Tier 3")))) -> Tier 3 | AC50: =INDEX('Hero Segmentation'!$R$5:$R$71,MATCH($A50,'Hero Segmentation'!$A$5:$A$71,0)) -> HOLD | AD50: =IF(AND(AB50="Tier 1",J50>='Selection Criteria'!$C$28),"Yes","") | AE50: =IFERROR(INDEX('Competitor Fit'!$C$5:$C$103,MATCH($A50&"|Primary",'Competitor Fit'!$L$5:$L$103,0)),"Target") -> Target | AF50: =IFERROR(INDEX('Competitor Fit'!$C$5:$C$103,MATCH($A50&"|Secondary",'Competitor Fit'!$L$5:$L$103,0)),"Amazon") -> Amazon | AG50: Wellness decor; weak Staples authority.
A51: P47 | B51: Furniture > Desks > Sit & Stand Desks | C51: Furniture | D51: Desks | E51: Sit & Stand Desks | G51: 3 | H51: CL215523 | I51: 576 | J51: 395 | K51: 2. Desks | L51: =IF(OR(G51=3,G51=4),"Pass","Fail") -> Pass | M51: Pass | N51: =IF(I51>='Selection Criteria'!$C$27,"Pass","Fail") -> Pass | O51: Pass | P51: =IF(AND(L51="Pass",M51="Pass",N51="Pass",O51="Pass"),"Pass","Fail") -> Pass | Q51: =INDEX('Hero Segmentation'!$Q$5:$Q$71,MATCH($A51,'Hero Segmentation'!$A$5:$A$71,0)) -> Hero | R51: 3 | S51: 4 | T51: 2 | U51: 5 | V51: 1 | W51: 4 | X51: 3 | Y51: 4 | Z51: =IF(P51="Pass",(R51*'Selection Criteria'!$F$13+S51*'Selection Criteria'!$F$14+T51*'Selection Criteria'!$F$15+U51*'Selection Criteria'!$F$16+V51*'Selection Criteria'!$F$17+W51*'Selection Criteria'!$F$18+X51*'Selection Criteria'!$F$19+Y51*'Selection Criteria'!$F$20)/(5*'Selection Criteria'!$F$21)*100,"-") -> 66 | AA51: =IF(P51="Pass",COUNTIFS($P$5:$P$71,"Pass",$Z$5:$Z$71,">"&Z51)+1,"-") -> 47 | AB51: =IF(P51<>"Pass","Parked (gate)",IF(AND('Selection Criteria'!$C$65="Yes",Q51="Non-Hero"),"Tier 3",IF(Z51>='Selection Criteria'!$C$25,"Tier 1",IF(Z51>='Selection Criteria'!$C$26,"Tier 2","Tier 3")))) -> Tier 3 | AC51: =INDEX('Hero Segmentation'!$R$5:$R$71,MATCH($A51,'Hero Segmentation'!$A$5:$A$71,0)) -> PROTECT | AD51: =IF(AND(AB51="Tier 1",J51>='Selection Criteria'!$C$28),"Yes","") | AE51: =IFERROR(INDEX('Competitor Fit'!$C$5:$C$103,MATCH($A51&"|Primary",'Competitor Fit'!$L$5:$L$103,0)),"Amazon") -> Amazon | AF51: =IFERROR(INDEX('Competitor Fit'!$C$5:$C$103,MATCH($A51&"|Secondary",'Competitor Fit'!$L$5:$L$103,0)),"Wayfair") -> Wayfair | AG51: Spec-led (motor/frame); design gaps small, CRS high.
A52: P48 | B52: Furniture > Chairs & Seating > Office Chairs | C52: Furniture | D52: Chairs & Seating | E52: Office Chairs | G52: 3 | H52: CL166253 | I52: 1008 | J52: 897 | K52: 1. Chairs & Seating | L52: =IF(OR(G52=3,G52=4),"Pass","Fail") -> Pass | M52: Pass | N52: =IF(I52>='Selection Criteria'!$C$27,"Pass","Fail") -> Pass | O52: Pass | P52: =IF(AND(L52="Pass",M52="Pass",N52="Pass",O52="Pass"),"Pass","Fail") -> Pass | Q52: =INDEX('Hero Segmentation'!$Q$5:$Q$71,MATCH($A52,'Hero Segmentation'!$A$5:$A$71,0)) -> Hero | R52: 3 | S52: 3 | T52: 1 | U52: 5 | V52: 1 | W52: 5 | X52: 4 | Y52: 5 | Z52: =IF(P52="Pass",(R52*'Selection Criteria'!$F$13+S52*'Selection Criteria'!$F$14+T52*'Selection Criteria'!$F$15+U52*'Selection Criteria'!$F$16+V52*'Selection Criteria'!$F$17+W52*'Selection Criteria'!$F$18+X52*'Selection Criteria'!$F$19+Y52*'Selection Criteria'!$F$20)/(5*'Selection Criteria'!$F$21)*100,"-") -> 65 | AA52: =IF(P52="Pass",COUNTIFS($P$5:$P$71,"Pass",$Z$5:$Z$71,">"&Z52)+1,"-") -> 48 | AB52: =IF(P52<>"Pass","Parked (gate)",IF(AND('Selection Criteria'!$C$65="Yes",Q52="Non-Hero"),"Tier 3",IF(Z52>='Selection Criteria'!$C$25,"Tier 1",IF(Z52>='Selection Criteria'!$C$26,"Tier 2","Tier 3")))) -> Tier 3 | AC52: =INDEX('Hero Segmentation'!$R$5:$R$71,MATCH($A52,'Hero Segmentation'!$A$5:$A$71,0)) -> PROTECT | AD52: =IF(AND(AB52="Tier 1",J52>='Selection Criteria'!$C$28),"Yes","") | AE52: =IFERROR(INDEX('Competitor Fit'!$C$5:$C$103,MATCH($A52&"|Primary",'Competitor Fit'!$L$5:$L$103,0)),"Wayfair") -> Wayfair | AF52: =IFERROR(INDEX('Competitor Fit'!$C$5:$C$103,MATCH($A52&"|Secondary",'Competitor Fit'!$L$5:$L$103,0)),"Amazon (control shelf)") -> Amazon (control shelf) | AG52: Core 1P, highest cannibalisation risk. Keep as the CONTROL shelf that shows the gate working.
A53: P49 | B53: Furniture > Home & Office Tables > Accent & Coffee Tables | C53: Furniture | D53: Home & Office Tables | E53: Accent & Coffee Tables | G53: 3 | H53: CL161009 | I53: 203 | J53: 0 | K53: New | L53: =IF(OR(G53=3,G53=4),"Pass","Fail") -> Pass | M53: Pass | N53: =IF(I53>='Selection Criteria'!$C$27,"Pass","Fail") -> Pass | O53: Pass | P53: =IF(AND(L53="Pass",M53="Pass",N53="Pass",O53="Pass"),"Pass","Fail") -> Pass | Q53: =INDEX('Hero Segmentation'!$Q$5:$Q$71,MATCH($A53,'Hero Segmentation'!$A$5:$A$71,0)) -> Non-Hero | R53: 4 | S53: 5 | T53: 4 | U53: 3 | V53: 1 | W53: 2 | X53: 2 | Y53: 2 | Z53: =IF(P53="Pass",(R53*'Selection Criteria'!$F$13+S53*'Selection Criteria'!$F$14+T53*'Selection Criteria'!$F$15+U53*'Selection Criteria'!$F$16+V53*'Selection Criteria'!$F$17+W53*'Selection Criteria'!$F$18+X53*'Selection Criteria'!$F$19+Y53*'Selection Criteria'!$F$20)/(5*'Selection Criteria'!$F$21)*100,"-") -> 64 | AA53: =IF(P53="Pass",COUNTIFS($P$5:$P$71,"Pass",$Z$5:$Z$71,">"&Z53)+1,"-") -> 49 | AB53: =IF(P53<>"Pass","Parked (gate)",IF(AND('Selection Criteria'!$C$65="Yes",Q53="Non-Hero"),"Tier 3",IF(Z53>='Selection Criteria'!$C$25,"Tier 1",IF(Z53>='Selection Criteria'!$C$26,"Tier 2","Tier 3")))) -> Tier 3 | AC53: =INDEX('Hero Segmentation'!$R$5:$R$71,MATCH($A53,'Hero Segmentation'!$A$5:$A$71,0)) -> HOLD | AD53: =IF(AND(AB53="Tier 1",J53>='Selection Criteria'!$C$28),"Yes","") | AE53: =IFERROR(INDEX('Competitor Fit'!$C$5:$C$103,MATCH($A53&"|Primary",'Competitor Fit'!$L$5:$L$103,0)),"Wayfair") -> Wayfair | AF53: =IFERROR(INDEX('Competitor Fit'!$C$5:$C$103,MATCH($A53&"|Secondary",'Competitor Fit'!$L$5:$L$103,0)),"Target") -> Target | AG53: Reception-area furniture; oversize.
A54: P50 | B54: Arts & Crafts > Crafting > Art Portfolios & Craft Storage | C54: Arts & Crafts | D54: Crafting | E54: Art Portfolios & Craft Storage | G54: 3 | H54: CL166121 | I54: 66 | J54: 63 | K54: 9. Planning & Craft Organization | L54: =IF(OR(G54=3,G54=4),"Pass","Fail") -> Pass | M54: Pass | N54: =IF(I54>='Selection Criteria'!$C$27,"Pass","Fail") -> Pass | O54: Pass | P54: =IF(AND(L54="Pass",M54="Pass",N54="Pass",O54="Pass"),"Pass","Fail") -> Pass | Q54: =INDEX('Hero Segmentation'!$Q$5:$Q$71,MATCH($A54,'Hero Segmentation'!$A$5:$A$71,0)) -> Non-Hero | R54: 3 | S54: 4 | T54: 4 | U54: 3 | V54: 3 | W54: 2 | X54: 2 | Y54: 3 | Z54: =IF(P54="Pass",(R54*'Selection Criteria'!$F$13+S54*'Selection Criteria'!$F$14+T54*'Selection Criteria'!$F$15+U54*'Selection Criteria'!$F$16+V54*'Selection Criteria'!$F$17+W54*'Selection Criteria'!$F$18+X54*'Selection Criteria'!$F$19+Y54*'Selection Criteria'!$F$20)/(5*'Selection Criteria'!$F$21)*100,"-") -> 63 | AA54: =IF(P54="Pass",COUNTIFS($P$5:$P$71,"Pass",$Z$5:$Z$71,">"&Z54)+1,"-") -> 50 | AB54: =IF(P54<>"Pass","Parked (gate)",IF(AND('Selection Criteria'!$C$65="Yes",Q54="Non-Hero"),"Tier 3",IF(Z54>='Selection Criteria'!$C$25,"Tier 1",IF(Z54>='Selection Criteria'!$C$26,"Tier 2","Tier 3")))) -> Tier 3 | AC54: =INDEX('Hero Segmentation'!$R$5:$R$71,MATCH($A54,'Hero Segmentation'!$A$5:$A$71,0)) -> HOLD | AD54: =IF(AND(AB54="Tier 1",J54>='Selection Criteria'!$C$28),"Yes","") | AE54: =IFERROR(INDEX('Competitor Fit'!$C$5:$C$103,MATCH($A54&"|Primary",'Competitor Fit'!$L$5:$L$103,0)),"Michaels") -> Michaels | AF54: =IFERROR(INDEX('Competitor Fit'!$C$5:$C$103,MATCH($A54&"|Secondary",'Competitor Fit'!$L$5:$L$103,0)),"Container Store") -> Container Store | AG54: Thin (66) and a hobbyist mission.
A55: P51 | B55: Furniture > Storage Furniture > Coat Trees, Stands & Hooks | C55: Furniture | D55: Storage Furniture | E55: Coat Trees, Stands & Hooks | G55: 3 | H55: CL167079 | I55: 126 | J55: 0 | K55: New | L55: =IF(OR(G55=3,G55=4),"Pass","Fail") -> Pass | M55: Pass | N55: =IF(I55>='Selection Criteria'!$C$27,"Pass","Fail") -> Pass | O55: Pass | P55: =IF(AND(L55="Pass",M55="Pass",N55="Pass",O55="Pass"),"Pass","Fail") -> Pass | Q55: =INDEX('Hero Segmentation'!$Q$5:$Q$71,MATCH($A55,'Hero Segmentation'!$A$5:$A$71,0)) -> Non-Hero | R55: 4 | S55: 4 | T55: 4 | U55: 3 | V55: 2 | W55: 2 | X55: 2 | Y55: 2 | Z55: =IF(P55="Pass",(R55*'Selection Criteria'!$F$13+S55*'Selection Criteria'!$F$14+T55*'Selection Criteria'!$F$15+U55*'Selection Criteria'!$F$16+V55*'Selection Criteria'!$F$17+W55*'Selection Criteria'!$F$18+X55*'Selection Criteria'!$F$19+Y55*'Selection Criteria'!$F$20)/(5*'Selection Criteria'!$F$21)*100,"-") -> 63 | AA55: =IF(P55="Pass",COUNTIFS($P$5:$P$71,"Pass",$Z$5:$Z$71,">"&Z55)+1,"-") -> 50 | AB55: =IF(P55<>"Pass","Parked (gate)",IF(AND('Selection Criteria'!$C$65="Yes",Q55="Non-Hero"),"Tier 3",IF(Z55>='Selection Criteria'!$C$25,"Tier 1",IF(Z55>='Selection Criteria'!$C$26,"Tier 2","Tier 3")))) -> Tier 3 | AC55: =INDEX('Hero Segmentation'!$R$5:$R$71,MATCH($A55,'Hero Segmentation'!$A$5:$A$71,0)) -> HOLD | AD55: =IF(AND(AB55="Tier 1",J55>='Selection Criteria'!$C$28),"Yes","") | AE55: =IFERROR(INDEX('Competitor Fit'!$C$5:$C$103,MATCH($A55&"|Primary",'Competitor Fit'!$L$5:$L$103,0)),"Wayfair") -> Wayfair | AF55: =IFERROR(INDEX('Competitor Fit'!$C$5:$C$103,MATCH($A55&"|Secondary",'Competitor Fit'!$L$5:$L$103,0)),"Amazon") -> Amazon | AG55: Entry/office coat racks; niche.
A56: P52 | B56: Facilities > Floor Mats & Flooring > Commercial Floor Mats | C56: Facilities | D56: Floor Mats & Flooring | E56: Commercial Floor Mats | G56: 3 | H56: CL214671 | I56: 639 | J56: 0 | K56: New | L56: =IF(OR(G56=3,G56=4),"Pass","Fail") -> Pass | M56: Pass | N56: =IF(I56>='Selection Criteria'!$C$27,"Pass","Fail") -> Pass | O56: Pass | P56: =IF(AND(L56="Pass",M56="Pass",N56="Pass",O56="Pass"),"Pass","Fail") -> Pass | Q56: =INDEX('Hero Segmentation'!$Q$5:$Q$71,MATCH($A56,'Hero Segmentation'!$A$5:$A$71,0)) -> Hero | R56: 3 | S56: 4 | T56: 3 | U56: 4 | V56: 3 | W56: 2 | X56: 2 | Y56: 3 | Z56: =IF(P56="Pass",(R56*'Selection Criteria'!$F$13+S56*'Selection Criteria'!$F$14+T56*'Selection Criteria'!$F$15+U56*'Selection Criteria'!$F$16+V56*'Selection Criteria'!$F$17+W56*'Selection Criteria'!$F$18+X56*'Selection Criteria'!$F$19+Y56*'Selection Criteria'!$F$20)/(5*'Selection Criteria'!$F$21)*100,"-") -> 63 | AA56: =IF(P56="Pass",COUNTIFS($P$5:$P$71,"Pass",$Z$5:$Z$71,">"&Z56)+1,"-") -> 50 | AB56: =IF(P56<>"Pass","Parked (gate)",IF(AND('Selection Criteria'!$C$65="Yes",Q56="Non-Hero"),"Tier 3",IF(Z56>='Selection Criteria'!$C$25,"Tier 1",IF(Z56>='Selection Criteria'!$C$26,"Tier 2","Tier 3")))) -> Tier 3 | AC56: =INDEX('Hero Segmentation'!$R$5:$R$71,MATCH($A56,'Hero Segmentation'!$A$5:$A$71,0)) -> EXTEND | AD56: =IF(AND(AB56="Tier 1",J56>='Selection Criteria'!$C$28),"Yes","") | AE56: =IFERROR(INDEX('Competitor Fit'!$C$5:$C$103,MATCH($A56&"|Primary",'Competitor Fit'!$L$5:$L$103,0)),"Wayfair") -> Wayfair | AF56: =IFERROR(INDEX('Competitor Fit'!$C$5:$C$103,MATCH($A56&"|Secondary",'Competitor Fit'!$L$5:$L$103,0)),"Amazon") -> Amazon | AG56: Wayfair doormat pages already scraped; commercial mats are core.
A57: P53 | B57: Coffee, Water & Snacks > Coffee, Coffee Makers & Supplies > Coffee Makers & Espresso Machines | C57: Coffee, Water & Snacks | D57: Coffee, Coffee Makers & Supplies | E57: Coffee Makers & Espresso Machines | G57: 3 | H57: CL140860 | I57: 139 | J57: 0 | K57: New | L57: =IF(OR(G57=3,G57=4),"Pass","Fail") -> Pass | M57: Pass | N57: =IF(I57>='Selection Criteria'!$C$27,"Pass","Fail") -> Pass | O57: Pass | P57: =IF(AND(L57="Pass",M57="Pass",N57="Pass",O57="Pass"),"Pass","Fail") -> Pass | Q57: =INDEX('Hero Segmentation'!$Q$5:$Q$71,MATCH($A57,'Hero Segmentation'!$A$5:$A$71,0)) -> Probable Hero | R57: 4 | S57: 4 | T57: 3 | U57: 3 | V57: 3 | W57: 2 | X57: 2 | Y57: 2 | Z57: =IF(P57="Pass",(R57*'Selection Criteria'!$F$13+S57*'Selection Criteria'!$F$14+T57*'Selection Criteria'!$F$15+U57*'Selection Criteria'!$F$16+V57*'Selection Criteria'!$F$17+W57*'Selection Criteria'!$F$18+X57*'Selection Criteria'!$F$19+Y57*'Selection Criteria'!$F$20)/(5*'Selection Criteria'!$F$21)*100,"-") -> 62 | AA57: =IF(P57="Pass",COUNTIFS($P$5:$P$71,"Pass",$Z$5:$Z$71,">"&Z57)+1,"-") -> 53 | AB57: =IF(P57<>"Pass","Parked (gate)",IF(AND('Selection Criteria'!$C$65="Yes",Q57="Non-Hero"),"Tier 3",IF(Z57>='Selection Criteria'!$C$25,"Tier 1",IF(Z57>='Selection Criteria'!$C$26,"Tier 2","Tier 3")))) -> Tier 3 | AC57: =INDEX('Hero Segmentation'!$R$5:$R$71,MATCH($A57,'Hero Segmentation'!$A$5:$A$71,0)) -> BUILD | AD57: =IF(AND(AB57="Tier 1",J57>='Selection Criteria'!$C$28),"Yes","") | AE57: =IFERROR(INDEX('Competitor Fit'!$C$5:$C$103,MATCH($A57&"|Primary",'Competitor Fit'!$L$5:$L$103,0)),"Target") -> Target | AF57: =IFERROR(INDEX('Competitor Fit'!$C$5:$C$103,MATCH($A57&"|Secondary",'Competitor Fit'!$L$5:$L$103,0)),"Best Buy") -> Best Buy | AG57: Breakroom design appliances; moderate fit.
A58: P54 | B58: Furniture > Boards & Easels > Dry Erase Whiteboards | C58: Furniture | D58: Boards & Easels | E58: Dry Erase Whiteboards | G58: 3 | H58: CL166382 | I58: 745 | J58: 0 | K58: New | L58: =IF(OR(G58=3,G58=4),"Pass","Fail") -> Pass | M58: Pass | N58: =IF(I58>='Selection Criteria'!$C$27,"Pass","Fail") -> Pass | O58: Pass | P58: =IF(AND(L58="Pass",M58="Pass",N58="Pass",O58="Pass"),"Pass","Fail") -> Pass | Q58: =INDEX('Hero Segmentation'!$Q$5:$Q$71,MATCH($A58,'Hero Segmentation'!$A$5:$A$71,0)) -> Hero | R58: 3 | S58: 3 | T58: 2 | U58: 5 | V58: 3 | W58: 3 | X58: 3 | Y58: 2 | Z58: =IF(P58="Pass",(R58*'Selection Criteria'!$F$13+S58*'Selection Criteria'!$F$14+T58*'Selection Criteria'!$F$15+U58*'Selection Criteria'!$F$16+V58*'Selection Criteria'!$F$17+W58*'Selection Criteria'!$F$18+X58*'Selection Criteria'!$F$19+Y58*'Selection Criteria'!$F$20)/(5*'Selection Criteria'!$F$21)*100,"-") -> 61 | AA58: =IF(P58="Pass",COUNTIFS($P$5:$P$71,"Pass",$Z$5:$Z$71,">"&Z58)+1,"-") -> 54 | AB58: =IF(P58<>"Pass","Parked (gate)",IF(AND('Selection Criteria'!$C$65="Yes",Q58="Non-Hero"),"Tier 3",IF(Z58>='Selection Criteria'!$C$25,"Tier 1",IF(Z58>='Selection Criteria'!$C$26,"Tier 2","Tier 3")))) -> Tier 3 | AC58: =INDEX('Hero Segmentation'!$R$5:$R$71,MATCH($A58,'Hero Segmentation'!$A$5:$A$71,0)) -> PROTECT | AD58: =IF(AND(AB58="Tier 1",J58>='Selection Criteria'!$C$28),"Yes","") | AE58: =IFERROR(INDEX('Competitor Fit'!$C$5:$C$103,MATCH($A58&"|Primary",'Competitor Fit'!$L$5:$L$103,0)),"Amazon") -> Amazon | AF58: =IFERROR(INDEX('Competitor Fit'!$C$5:$C$103,MATCH($A58&"|Secondary",'Competitor Fit'!$L$5:$L$103,0)),"Wayfair") -> Wayfair | AG58: Quartet-led core 1P; glass boards the only adjacency.
A59: P55 | B59: Furniture > Chairs & Seating > Kids Seating | C59: Furniture | D59: Chairs & Seating | E59: Kids Seating | G59: 3 | H59: CL210316 | I59: 147 | J59: 120 | K59: 1. Chairs & Seating | L59: =IF(OR(G59=3,G59=4),"Pass","Fail") -> Pass | M59: Pass | N59: =IF(I59>='Selection Criteria'!$C$27,"Pass","Fail") -> Pass | O59: Pass | P59: =IF(AND(L59="Pass",M59="Pass",N59="Pass",O59="Pass"),"Pass","Fail") -> Pass | Q59: =INDEX('Hero Segmentation'!$Q$5:$Q$71,MATCH($A59,'Hero Segmentation'!$A$5:$A$71,0)) -> Non-Hero | R59: 3 | S59: 3 | T59: 3 | U59: 3 | V59: 2 | W59: 2 | X59: 4 | Y59: 4 | Z59: =IF(P59="Pass",(R59*'Selection Criteria'!$F$13+S59*'Selection Criteria'!$F$14+T59*'Selection Criteria'!$F$15+U59*'Selection Criteria'!$F$16+V59*'Selection Criteria'!$F$17+W59*'Selection Criteria'!$F$18+X59*'Selection Criteria'!$F$19+Y59*'Selection Criteria'!$F$20)/(5*'Selection Criteria'!$F$21)*100,"-") -> 59 | AA59: =IF(P59="Pass",COUNTIFS($P$5:$P$71,"Pass",$Z$5:$Z$71,">"&Z59)+1,"-") -> 55 | AB59: =IF(P59<>"Pass","Parked (gate)",IF(AND('Selection Criteria'!$C$65="Yes",Q59="Non-Hero"),"Tier 3",IF(Z59>='Selection Criteria'!$C$25,"Tier 1",IF(Z59>='Selection Criteria'!$C$26,"Tier 2","Tier 3")))) -> Tier 3 | AC59: =INDEX('Hero Segmentation'!$R$5:$R$71,MATCH($A59,'Hero Segmentation'!$A$5:$A$71,0)) -> HOLD | AD59: =IF(AND(AB59="Tier 1",J59>='Selection Criteria'!$C$28),"Yes","") | AE59: =IFERROR(INDEX('Competitor Fit'!$C$5:$C$103,MATCH($A59&"|Primary",'Competitor Fit'!$L$5:$L$103,0)),"Wayfair") -> Wayfair | AF59: =IFERROR(INDEX('Competitor Fit'!$C$5:$C$103,MATCH($A59&"|Secondary",'Competitor Fit'!$L$5:$L$103,0)),"Target") -> Target | AG59: Pilot: no recommended archetypes.
A60: P56 | B60: Facilities > Air Quality > Air Purifiers | C60: Facilities | D60: Air Quality | E60: Air Purifiers | G60: 3 | H60: CL140858 | I60: 91 | J60: 0 | K60: New | L60: =IF(OR(G60=3,G60=4),"Pass","Fail") -> Pass | M60: Pass | N60: =IF(I60>='Selection Criteria'!$C$27,"Pass","Fail") -> Pass | O60: Pass | P60: =IF(AND(L60="Pass",M60="Pass",N60="Pass",O60="Pass"),"Pass","Fail") -> Pass | Q60: =INDEX('Hero Segmentation'!$Q$5:$Q$71,MATCH($A60,'Hero Segmentation'!$A$5:$A$71,0)) -> Non-Hero | R60: 3 | S60: 3 | T60: 3 | U60: 3 | V60: 2 | W60: 2 | X60: 2 | Y60: 2 | Z60: =IF(P60="Pass",(R60*'Selection Criteria'!$F$13+S60*'Selection Criteria'!$F$14+T60*'Selection Criteria'!$F$15+U60*'Selection Criteria'!$F$16+V60*'Selection Criteria'!$F$17+W60*'Selection Criteria'!$F$18+X60*'Selection Criteria'!$F$19+Y60*'Selection Criteria'!$F$20)/(5*'Selection Criteria'!$F$21)*100,"-") -> 53 | AA60: =IF(P60="Pass",COUNTIFS($P$5:$P$71,"Pass",$Z$5:$Z$71,">"&Z60)+1,"-") -> 56 | AB60: =IF(P60<>"Pass","Parked (gate)",IF(AND('Selection Criteria'!$C$65="Yes",Q60="Non-Hero"),"Tier 3",IF(Z60>='Selection Criteria'!$C$25,"Tier 1",IF(Z60>='Selection Criteria'!$C$26,"Tier 2","Tier 3")))) -> Tier 3 | AC60: =INDEX('Hero Segmentation'!$R$5:$R$71,MATCH($A60,'Hero Segmentation'!$A$5:$A$71,0)) -> HOLD | AD60: =IF(AND(AB60="Tier 1",J60>='Selection Criteria'!$C$28),"Yes","") | AE60: =IFERROR(INDEX('Competitor Fit'!$C$5:$C$103,MATCH($A60&"|Primary",'Competitor Fit'!$L$5:$L$103,0)),"Best Buy") -> Best Buy | AF60: =IFERROR(INDEX('Competitor Fit'!$C$5:$C$103,MATCH($A60&"|Secondary",'Competitor Fit'!$L$5:$L$103,0)),"Target") -> Target | AG60: Spec-led wellness appliance.
A61: P57 | B61: Furniture > Desks > Desk Components & Hutches > Hutches | C61: Furniture | D61: Desks | E61: Desk Components & Hutches | F61: Hutches | G61: 4 | H61: CL353865 | I61: 77 | J61: 40 | K61: 2. Desks | L61: =IF(OR(G61=3,G61=4),"Pass","Fail") -> Pass | M61: Pass | N61: =IF(I61>='Selection Criteria'!$C$27,"Pass","Fail") -> Pass | O61: Pass | P61: =IF(AND(L61="Pass",M61="Pass",N61="Pass",O61="Pass"),"Pass","Fail") -> Pass | Q61: =INDEX('Hero Segmentation'!$Q$5:$Q$71,MATCH($A61,'Hero Segmentation'!$A$5:$A$71,0)) -> Non-Hero | R61: 2 | S61: 3 | T61: 3 | U61: 4 | V61: 1 | W61: 2 | X61: 2 | Y61: 3 | Z61: =IF(P61="Pass",(R61*'Selection Criteria'!$F$13+S61*'Selection Criteria'!$F$14+T61*'Selection Criteria'!$F$15+U61*'Selection Criteria'!$F$16+V61*'Selection Criteria'!$F$17+W61*'Selection Criteria'!$F$18+X61*'Selection Criteria'!$F$19+Y61*'Selection Criteria'!$F$20)/(5*'Selection Criteria'!$F$21)*100,"-") -> 52 | AA61: =IF(P61="Pass",COUNTIFS($P$5:$P$71,"Pass",$Z$5:$Z$71,">"&Z61)+1,"-") -> 57 | AB61: =IF(P61<>"Pass","Parked (gate)",IF(AND('Selection Criteria'!$C$65="Yes",Q61="Non-Hero"),"Tier 3",IF(Z61>='Selection Criteria'!$C$25,"Tier 1",IF(Z61>='Selection Criteria'!$C$26,"Tier 2","Tier 3")))) -> Tier 3 | AC61: =INDEX('Hero Segmentation'!$R$5:$R$71,MATCH($A61,'Hero Segmentation'!$A$5:$A$71,0)) -> HOLD | AD61: =IF(AND(AB61="Tier 1",J61>='Selection Criteria'!$C$28),"Yes","") | AE61: =IFERROR(INDEX('Competitor Fit'!$C$5:$C$103,MATCH($A61&"|Primary",'Competitor Fit'!$L$5:$L$103,0)),"Wayfair") -> Wayfair | AF61: =IFERROR(INDEX('Competitor Fit'!$C$5:$C$103,MATCH($A61&"|Secondary",'Competitor Fit'!$L$5:$L$103,0)),"Amazon") -> Amazon | AG61: Component shelf, little design variance.
A62: P58 | B62: Furniture > Chairs & Seating > Gaming Chairs | C62: Furniture | D62: Chairs & Seating | E62: Gaming Chairs | G62: 3 | H62: CL210317 | I62: 87 | J62: 40 | K62: 1. Chairs & Seating | L62: =IF(OR(G62=3,G62=4),"Pass","Fail") -> Pass | M62: Pass | N62: =IF(I62>='Selection Criteria'!$C$27,"Pass","Fail") -> Pass | O62: Pass | P62: =IF(AND(L62="Pass",M62="Pass",N62="Pass",O62="Pass"),"Pass","Fail") -> Pass | Q62: =INDEX('Hero Segmentation'!$Q$5:$Q$71,MATCH($A62,'Hero Segmentation'!$A$5:$A$71,0)) -> Non-Hero | R62: 3 | S62: 3 | T62: 2 | U62: 3 | V62: 1 | W62: 2 | X62: 2 | Y62: 3 | Z62: =IF(P62="Pass",(R62*'Selection Criteria'!$F$13+S62*'Selection Criteria'!$F$14+T62*'Selection Criteria'!$F$15+U62*'Selection Criteria'!$F$16+V62*'Selection Criteria'!$F$17+W62*'Selection Criteria'!$F$18+X62*'Selection Criteria'!$F$19+Y62*'Selection Criteria'!$F$20)/(5*'Selection Criteria'!$F$21)*100,"-") -> 50 | AA62: =IF(P62="Pass",COUNTIFS($P$5:$P$71,"Pass",$Z$5:$Z$71,">"&Z62)+1,"-") -> 58 | AB62: =IF(P62<>"Pass","Parked (gate)",IF(AND('Selection Criteria'!$C$65="Yes",Q62="Non-Hero"),"Tier 3",IF(Z62>='Selection Criteria'!$C$25,"Tier 1",IF(Z62>='Selection Criteria'!$C$26,"Tier 2","Tier 3")))) -> Tier 3 | AC62: =INDEX('Hero Segmentation'!$R$5:$R$71,MATCH($A62,'Hero Segmentation'!$A$5:$A$71,0)) -> HOLD | AD62: =IF(AND(AB62="Tier 1",J62>='Selection Criteria'!$C$28),"Yes","") | AE62: =IFERROR(INDEX('Competitor Fit'!$C$5:$C$103,MATCH($A62&"|Primary",'Competitor Fit'!$L$5:$L$103,0)),"Best Buy") -> Best Buy | AF62: =IFERROR(INDEX('Competitor Fit'!$C$5:$C$103,MATCH($A62&"|Secondary",'Competitor Fit'!$L$5:$L$103,0)),"Amazon") -> Amazon | AG62: Pilot thin (22 families); spec-led.
A63: X01 | B63: Decor > Rugs | C63: Decor | D63: Rugs | G63: 2 | H63: CL167008 | I63: 804 | J63: 746 | K63: 4. Rugs | L63: =IF(OR(G63=3,G63=4),"Pass","Fail") -> Fail | M63: Pass | N63: =IF(I63>='Selection Criteria'!$C$27,"Pass","Fail") -> Pass | O63: Pass | P63: =IF(AND(L63="Pass",M63="Pass",N63="Pass",O63="Pass"),"Pass","Fail") -> Fail | Q63: =INDEX('Hero Segmentation'!$Q$5:$Q$71,MATCH($A63,'Hero Segmentation'!$A$5:$A$71,0)) -> Probable Hero | Z63: =IF(P63="Pass",(R63*'Selection Criteria'!$F$13+S63*'Selection Criteria'!$F$14+T63*'Selection Criteria'!$F$15+U63*'Selection Criteria'!$F$16+V63*'Selection Criteria'!$F$17+W63*'Selection Criteria'!$F$18+X63*'Selection Criteria'!$F$19+Y63*'Selection Criteria'!$F$20)/(5*'Selection Criteria'!$F$21)*100,"-") -> - | AA63: =IF(P63="Pass",COUNTIFS($P$5:$P$71,"Pass",$Z$5:$Z$71,">"&Z63)+1,"-") -> - | AB63: =IF(P63<>"Pass","Parked (gate)",IF(AND('Selection Criteria'!$C$65="Yes",Q63="Non-Hero"),"Tier 3",IF(Z63>='Selection Criteria'!$C$25,"Tier 1",IF(Z63>='Selection Criteria'!$C$26,"Tier 2","Tier 3")))) -> Parked (gate) | AC63: =INDEX('Hero Segmentation'!$R$5:$R$71,MATCH($A63,'Hero Segmentation'!$A$5:$A$71,0)) -> BUILD | AD63: =IF(AND(AB63="Tier 1",J63>='Selection Criteria'!$C$28),"Yes","") | AE63: =IFERROR(INDEX('Competitor Fit'!$C$5:$C$103,MATCH($A63&"|Primary",'Competitor Fit'!$L$5:$L$103,0)),"-") -> - | AF63: =IFERROR(INDEX('Competitor Fit'!$C$5:$C$103,MATCH($A63&"|Secondary",'Competitor Fit'!$L$5:$L$103,0)),"-") -> - | AG63: No L3/L4 exists under Rugs (L2 leaf).
A64: X02 | B64: Furniture > Chair Mats | C64: Furniture | D64: Chair Mats | G64: 2 | H64: CL70205 | I64: 308 | J64: 0 | K64: New | L64: =IF(OR(G64=3,G64=4),"Pass","Fail") -> Fail | M64: Pass | N64: =IF(I64>='Selection Criteria'!$C$27,"Pass","Fail") -> Pass | O64: Pass | P64: =IF(AND(L64="Pass",M64="Pass",N64="Pass",O64="Pass"),"Pass","Fail") -> Fail | Q64: =INDEX('Hero Segmentation'!$Q$5:$Q$71,MATCH($A64,'Hero Segmentation'!$A$5:$A$71,0)) -> Hero | Z64: =IF(P64="Pass",(R64*'Selection Criteria'!$F$13+S64*'Selection Criteria'!$F$14+T64*'Selection Criteria'!$F$15+U64*'Selection Criteria'!$F$16+V64*'Selection Criteria'!$F$17+W64*'Selection Criteria'!$F$18+X64*'Selection Criteria'!$F$19+Y64*'Selection Criteria'!$F$20)/(5*'Selection Criteria'!$F$21)*100,"-") -> - | AA64: =IF(P64="Pass",COUNTIFS($P$5:$P$71,"Pass",$Z$5:$Z$71,">"&Z64)+1,"-") -> - | AB64: =IF(P64<>"Pass","Parked (gate)",IF(AND('Selection Criteria'!$C$65="Yes",Q64="Non-Hero"),"Tier 3",IF(Z64>='Selection Criteria'!$C$25,"Tier 1",IF(Z64>='Selection Criteria'!$C$26,"Tier 2","Tier 3")))) -> Parked (gate) | AC64: =INDEX('Hero Segmentation'!$R$5:$R$71,MATCH($A64,'Hero Segmentation'!$A$5:$A$71,0)) -> PROTECT | AD64: =IF(AND(AB64="Tier 1",J64>='Selection Criteria'!$C$28),"Yes","") | AE64: =IFERROR(INDEX('Competitor Fit'!$C$5:$C$103,MATCH($A64&"|Primary",'Competitor Fit'!$L$5:$L$103,0)),"-") -> - | AF64: =IFERROR(INDEX('Competitor Fit'!$C$5:$C$103,MATCH($A64&"|Secondary",'Competitor Fit'!$L$5:$L$103,0)),"-") -> - | AG64: L2 leaf: no L3/L4 to drill into.
A65: X03 | B65: Office Supplies > Labels | C65: Office Supplies | D65: Labels | G65: 2 | H65: CL142725 | I65: 11493 | J65: 9862 | K65: 8. Labels & Packaging Accessories | L65: =IF(OR(G65=3,G65=4),"Pass","Fail") -> Fail | M65: Pass | N65: =IF(I65>='Selection Criteria'!$C$27,"Pass","Fail") -> Pass | O65: Pass | P65: =IF(AND(L65="Pass",M65="Pass",N65="Pass",O65="Pass"),"Pass","Fail") -> Fail | Q65: =INDEX('Hero Segmentation'!$Q$5:$Q$71,MATCH($A65,'Hero Segmentation'!$A$5:$A$71,0)) -> Hero | Z65: =IF(P65="Pass",(R65*'Selection Criteria'!$F$13+S65*'Selection Criteria'!$F$14+T65*'Selection Criteria'!$F$15+U65*'Selection Criteria'!$F$16+V65*'Selection Criteria'!$F$17+W65*'Selection Criteria'!$F$18+X65*'Selection Criteria'!$F$19+Y65*'Selection Criteria'!$F$20)/(5*'Selection Criteria'!$F$21)*100,"-") -> - | AA65: =IF(P65="Pass",COUNTIFS($P$5:$P$71,"Pass",$Z$5:$Z$71,">"&Z65)+1,"-") -> - | AB65: =IF(P65<>"Pass","Parked (gate)",IF(AND('Selection Criteria'!$C$65="Yes",Q65="Non-Hero"),"Tier 3",IF(Z65>='Selection Criteria'!$C$25,"Tier 1",IF(Z65>='Selection Criteria'!$C$26,"Tier 2","Tier 3")))) -> Parked (gate) | AC65: =INDEX('Hero Segmentation'!$R$5:$R$71,MATCH($A65,'Hero Segmentation'!$A$5:$A$71,0)) -> PROTECT | AD65: =IF(AND(AB65="Tier 1",J65>='Selection Criteria'!$C$28),"Yes","") | AE65: =IFERROR(INDEX('Competitor Fit'!$C$5:$C$103,MATCH($A65&"|Primary",'Competitor Fit'!$L$5:$L$103,0)),"-") -> - | AF65: =IFERROR(INDEX('Competitor Fit'!$C$5:$C$103,MATCH($A65&"|Secondary",'Competitor Fit'!$L$5:$L$103,0)),"-") -> - | AG65: L2 leaf of 11,493 commodity labels.
A66: X04 | B66: Party Supplies > Wrapping Supplies > Gift Boxes & Bags | C66: Party Supplies | D66: Wrapping Supplies | E66: Gift Boxes & Bags | G66: 3 | H66: CL215556 | I66: 123 | J66: 0 | K66: 8. Labels & Packaging Accessories | L66: =IF(OR(G66=3,G66=4),"Pass","Fail") -> Pass | M66: Pass | N66: =IF(I66>='Selection Criteria'!$C$27,"Pass","Fail") -> Pass | O66: Fail | P66: =IF(AND(L66="Pass",M66="Pass",N66="Pass",O66="Pass"),"Pass","Fail") -> Fail | Q66: =INDEX('Hero Segmentation'!$Q$5:$Q$71,MATCH($A66,'Hero Segmentation'!$A$5:$A$71,0)) -> Hero | Z66: =IF(P66="Pass",(R66*'Selection Criteria'!$F$13+S66*'Selection Criteria'!$F$14+T66*'Selection Criteria'!$F$15+U66*'Selection Criteria'!$F$16+V66*'Selection Criteria'!$F$17+W66*'Selection Criteria'!$F$18+X66*'Selection Criteria'!$F$19+Y66*'Selection Criteria'!$F$20)/(5*'Selection Criteria'!$F$21)*100,"-") -> - | AA66: =IF(P66="Pass",COUNTIFS($P$5:$P$71,"Pass",$Z$5:$Z$71,">"&Z66)+1,"-") -> - | AB66: =IF(P66<>"Pass","Parked (gate)",IF(AND('Selection Criteria'!$C$65="Yes",Q66="Non-Hero"),"Tier 3",IF(Z66>='Selection Criteria'!$C$25,"Tier 1",IF(Z66>='Selection Criteria'!$C$26,"Tier 2","Tier 3")))) -> Parked (gate) | AC66: =INDEX('Hero Segmentation'!$R$5:$R$71,MATCH($A66,'Hero Segmentation'!$A$5:$A$71,0)) -> PROTECT | AD66: =IF(AND(AB66="Tier 1",J66>='Selection Criteria'!$C$28),"Yes","") | AE66: =IFERROR(INDEX('Competitor Fit'!$C$5:$C$103,MATCH($A66&"|Primary",'Competitor Fit'!$L$5:$L$103,0)),"-") -> - | AF66: =IFERROR(INDEX('Competitor Fit'!$C$5:$C$103,MATCH($A66&"|Secondary",'Competitor Fit'!$L$5:$L$103,0)),"-") -> - | AG66: Overlaps the Party City partner assortment on Staples.com (Apr-2026).
A67: X05 | B67: Party Supplies > Wrapping Supplies > Gift Wrap & Wrapping Paper | C67: Party Supplies | D67: Wrapping Supplies | E67: Gift Wrap & Wrapping Paper | G67: 3 | H67: CL215563 | I67: 149 | J67: 0 | K67: 8. Labels & Packaging Accessories | L67: =IF(OR(G67=3,G67=4),"Pass","Fail") -> Pass | M67: Pass | N67: =IF(I67>='Selection Criteria'!$C$27,"Pass","Fail") -> Pass | O67: Fail | P67: =IF(AND(L67="Pass",M67="Pass",N67="Pass",O67="Pass"),"Pass","Fail") -> Fail | Q67: =INDEX('Hero Segmentation'!$Q$5:$Q$71,MATCH($A67,'Hero Segmentation'!$A$5:$A$71,0)) -> Hero | Z67: =IF(P67="Pass",(R67*'Selection Criteria'!$F$13+S67*'Selection Criteria'!$F$14+T67*'Selection Criteria'!$F$15+U67*'Selection Criteria'!$F$16+V67*'Selection Criteria'!$F$17+W67*'Selection Criteria'!$F$18+X67*'Selection Criteria'!$F$19+Y67*'Selection Criteria'!$F$20)/(5*'Selection Criteria'!$F$21)*100,"-") -> - | AA67: =IF(P67="Pass",COUNTIFS($P$5:$P$71,"Pass",$Z$5:$Z$71,">"&Z67)+1,"-") -> - | AB67: =IF(P67<>"Pass","Parked (gate)",IF(AND('Selection Criteria'!$C$65="Yes",Q67="Non-Hero"),"Tier 3",IF(Z67>='Selection Criteria'!$C$25,"Tier 1",IF(Z67>='Selection Criteria'!$C$26,"Tier 2","Tier 3")))) -> Parked (gate) | AC67: =INDEX('Hero Segmentation'!$R$5:$R$71,MATCH($A67,'Hero Segmentation'!$A$5:$A$71,0)) -> PROTECT | AD67: =IF(AND(AB67="Tier 1",J67>='Selection Criteria'!$C$28),"Yes","") | AE67: =IFERROR(INDEX('Competitor Fit'!$C$5:$C$103,MATCH($A67&"|Primary",'Competitor Fit'!$L$5:$L$103,0)),"-") -> - | AF67: =IFERROR(INDEX('Competitor Fit'!$C$5:$C$103,MATCH($A67&"|Secondary",'Competitor Fit'!$L$5:$L$103,0)),"-") -> - | AG67: Overlaps the Party City partner assortment on Staples.com (Apr-2026).
A68: X06 | B68: Appliances & Kitchenware > Kitchenware > Dining & Tableware > Drinkware & Glassware | C68: Appliances & Kitchenware | D68: Kitchenware | E68: Dining & Tableware | F68: Drinkware & Glassware | G68: 4 | H68: CL212425 | I68: 15 | J68: 15 | K68: 7. Hydration & Drinkware | L68: =IF(OR(G68=3,G68=4),"Pass","Fail") -> Pass | M68: Pass | N68: =IF(I68>='Selection Criteria'!$C$27,"Pass","Fail") -> Fail | O68: Pass | P68: =IF(AND(L68="Pass",M68="Pass",N68="Pass",O68="Pass"),"Pass","Fail") -> Fail | Q68: =INDEX('Hero Segmentation'!$Q$5:$Q$71,MATCH($A68,'Hero Segmentation'!$A$5:$A$71,0)) -> Probable Hero | Z68: =IF(P68="Pass",(R68*'Selection Criteria'!$F$13+S68*'Selection Criteria'!$F$14+T68*'Selection Criteria'!$F$15+U68*'Selection Criteria'!$F$16+V68*'Selection Criteria'!$F$17+W68*'Selection Criteria'!$F$18+X68*'Selection Criteria'!$F$19+Y68*'Selection Criteria'!$F$20)/(5*'Selection Criteria'!$F$21)*100,"-") -> - | AA68: =IF(P68="Pass",COUNTIFS($P$5:$P$71,"Pass",$Z$5:$Z$71,">"&Z68)+1,"-") -> - | AB68: =IF(P68<>"Pass","Parked (gate)",IF(AND('Selection Criteria'!$C$65="Yes",Q68="Non-Hero"),"Tier 3",IF(Z68>='Selection Criteria'!$C$25,"Tier 1",IF(Z68>='Selection Criteria'!$C$26,"Tier 2","Tier 3")))) -> Parked (gate) | AC68: =INDEX('Hero Segmentation'!$R$5:$R$71,MATCH($A68,'Hero Segmentation'!$A$5:$A$71,0)) -> BUILD | AD68: =IF(AND(AB68="Tier 1",J68>='Selection Criteria'!$C$28),"Yes","") | AE68: =IFERROR(INDEX('Competitor Fit'!$C$5:$C$103,MATCH($A68&"|Primary",'Competitor Fit'!$L$5:$L$103,0)),"-") -> - | AF68: =IFERROR(INDEX('Competitor Fit'!$C$5:$C$103,MATCH($A68&"|Secondary",'Competitor Fit'!$L$5:$L$103,0)),"-") -> - | AG68: Only 15 Staples items: no baseline.
A69: X07 | B69: Gift Shop > Stationery | C69: Gift Shop | D69: Stationery | G69: 2 | H69: CL164333 | I69: 437 | J69: 0 | K69: New | L69: =IF(OR(G69=3,G69=4),"Pass","Fail") -> Fail | M69: Pass | N69: =IF(I69>='Selection Criteria'!$C$27,"Pass","Fail") -> Pass | O69: Pass | P69: =IF(AND(L69="Pass",M69="Pass",N69="Pass",O69="Pass"),"Pass","Fail") -> Fail | Q69: =INDEX('Hero Segmentation'!$Q$5:$Q$71,MATCH($A69,'Hero Segmentation'!$A$5:$A$71,0)) -> Non-Hero | Z69: =IF(P69="Pass",(R69*'Selection Criteria'!$F$13+S69*'Selection Criteria'!$F$14+T69*'Selection Criteria'!$F$15+U69*'Selection Criteria'!$F$16+V69*'Selection Criteria'!$F$17+W69*'Selection Criteria'!$F$18+X69*'Selection Criteria'!$F$19+Y69*'Selection Criteria'!$F$20)/(5*'Selection Criteria'!$F$21)*100,"-") -> - | AA69: =IF(P69="Pass",COUNTIFS($P$5:$P$71,"Pass",$Z$5:$Z$71,">"&Z69)+1,"-") -> - | AB69: =IF(P69<>"Pass","Parked (gate)",IF(AND('Selection Criteria'!$C$65="Yes",Q69="Non-Hero"),"Tier 3",IF(Z69>='Selection Criteria'!$C$25,"Tier 1",IF(Z69>='Selection Criteria'!$C$26,"Tier 2","Tier 3")))) -> Parked (gate) | AC69: =INDEX('Hero Segmentation'!$R$5:$R$71,MATCH($A69,'Hero Segmentation'!$A$5:$A$71,0)) -> HOLD | AD69: =IF(AND(AB69="Tier 1",J69>='Selection Criteria'!$C$28),"Yes","") | AE69: =IFERROR(INDEX('Competitor Fit'!$C$5:$C$103,MATCH($A69&"|Primary",'Competitor Fit'!$L$5:$L$103,0)),"-") -> - | AF69: =IFERROR(INDEX('Competitor Fit'!$C$5:$C$103,MATCH($A69&"|Secondary",'Competitor Fit'!$L$5:$L$103,0)),"-") -> - | AG69: L2 leaf.
A70: X08 | B70: Gift Shop > Professional Gifts > Compasses > Patio Furniture | C70: Gift Shop | D70: Professional Gifts | E70: Compasses | F70: Patio Furniture | G70: 4 | H70: CL213655 | I70: 1116 | J70: 0 | K70: New | L70: =IF(OR(G70=3,G70=4),"Pass","Fail") -> Pass | M70: Fail | N70: =IF(I70>='Selection Criteria'!$C$27,"Pass","Fail") -> Pass | O70: Pass | P70: =IF(AND(L70="Pass",M70="Pass",N70="Pass",O70="Pass"),"Pass","Fail") -> Fail | Q70: =INDEX('Hero Segmentation'!$Q$5:$Q$71,MATCH($A70,'Hero Segmentation'!$A$5:$A$71,0)) -> Probable Hero | Z70: =IF(P70="Pass",(R70*'Selection Criteria'!$F$13+S70*'Selection Criteria'!$F$14+T70*'Selection Criteria'!$F$15+U70*'Selection Criteria'!$F$16+V70*'Selection Criteria'!$F$17+W70*'Selection Criteria'!$F$18+X70*'Selection Criteria'!$F$19+Y70*'Selection Criteria'!$F$20)/(5*'Selection Criteria'!$F$21)*100,"-") -> - | AA70: =IF(P70="Pass",COUNTIFS($P$5:$P$71,"Pass",$Z$5:$Z$71,">"&Z70)+1,"-") -> - | AB70: =IF(P70<>"Pass","Parked (gate)",IF(AND('Selection Criteria'!$C$65="Yes",Q70="Non-Hero"),"Tier 3",IF(Z70>='Selection Criteria'!$C$25,"Tier 1",IF(Z70>='Selection Criteria'!$C$26,"Tier 2","Tier 3")))) -> Parked (gate) | AC70: =INDEX('Hero Segmentation'!$R$5:$R$71,MATCH($A70,'Hero Segmentation'!$A$5:$A$71,0)) -> BUILD | AD70: =IF(AND(AB70="Tier 1",J70>='Selection Criteria'!$C$28),"Yes","") | AE70: =IFERROR(INDEX('Competitor Fit'!$C$5:$C$103,MATCH($A70&"|Primary",'Competitor Fit'!$L$5:$L$103,0)),"-") -> - | AF70: =IFERROR(INDEX('Competitor Fit'!$C$5:$C$103,MATCH($A70&"|Secondary",'Competitor Fit'!$L$5:$L$103,0)),"-") -> - | AG70: Mis-shelved under Gift Shop > Compasses; leisure, off-mission.
A71: X09 | B71: Bags, Backpacks & Luggage > Luggage & Travel Accessories > Luggage & Duffel Bags > Suitcases & Luggage Sets | C71: Bags, Backpacks & Luggage | D71: Luggage & Travel Accessories | E71: Luggage & Duffel Bags | F71: Suitcases & Luggage Sets | G71: 4 | H71: CL140613 | I71: 881 | J71: 872 | K71: 6. Backpacks & Bags | L71: =IF(OR(G71=3,G71=4),"Pass","Fail") -> Pass | M71: Fail | N71: =IF(I71>='Selection Criteria'!$C$27,"Pass","Fail") -> Pass | O71: Pass | P71: =IF(AND(L71="Pass",M71="Pass",N71="Pass",O71="Pass"),"Pass","Fail") -> Fail | Q71: =INDEX('Hero Segmentation'!$Q$5:$Q$71,MATCH($A71,'Hero Segmentation'!$A$5:$A$71,0)) -> Probable Hero | Z71: =IF(P71="Pass",(R71*'Selection Criteria'!$F$13+S71*'Selection Criteria'!$F$14+T71*'Selection Criteria'!$F$15+U71*'Selection Criteria'!$F$16+V71*'Selection Criteria'!$F$17+W71*'Selection Criteria'!$F$18+X71*'Selection Criteria'!$F$19+Y71*'Selection Criteria'!$F$20)/(5*'Selection Criteria'!$F$21)*100,"-") -> - | AA71: =IF(P71="Pass",COUNTIFS($P$5:$P$71,"Pass",$Z$5:$Z$71,">"&Z71)+1,"-") -> - | AB71: =IF(P71<>"Pass","Parked (gate)",IF(AND('Selection Criteria'!$C$65="Yes",Q71="Non-Hero"),"Tier 3",IF(Z71>='Selection Criteria'!$C$25,"Tier 1",IF(Z71>='Selection Criteria'!$C$26,"Tier 2","Tier 3")))) -> Parked (gate) | AC71: =INDEX('Hero Segmentation'!$R$5:$R$71,MATCH($A71,'Hero Segmentation'!$A$5:$A$71,0)) -> BUILD | AD71: =IF(AND(AB71="Tier 1",J71>='Selection Criteria'!$C$28),"Yes","") | AE71: =IFERROR(INDEX('Competitor Fit'!$C$5:$C$103,MATCH($A71&"|Primary",'Competitor Fit'!$L$5:$L$103,0)),"-") -> - | AF71: =IFERROR(INDEX('Competitor Fit'!$C$5:$C$103,MATCH($A71&"|Secondary",'Competitor Fit'!$L$5:$L$103,0)),"-") -> - | AG71: Leisure travel; off Staples' work/school mission.

Sheet Hero Segmentation
A1: Hero segmentation: Staples strength vs market attractiveness, per L3/L4 path
A2: S1-S2 and M4 are computed; S3, S4, M1-M3 are analyst inputs (blue). Segment: Hero if SSI >= cut-off, else Probable Hero if MAI >= cut-off, else Non-Hero.
A4: Path ID | B4: Staples path (exact) | C4: Link to your list | D4: L1 > L2 | E4: Staples items | F4: L1 in header nav | G4: S1 Depth | H4: S2 Visibility | I4: S3 Merch. investment | J4: S4 Shopper association | K4: SSI Staples strength (0-100) | L4: M1 Demand momentum | M4: M2 Competitor destination | N4: M3 Size & frequency | O4: M4 Occasion (=C7) | P4: MAI Market attractiveness (0-100) | Q4: Segment | R4: Marketplace play | S4: Tier | T4: Evidence / note | U4: Chart helpers (#N/A = point hidden on purpose) | V4: chart: SSI Hero | W4: chart: MAI Hero | X4: chart: SSI Prob. Hero | Y4: chart: MAI Prob. Hero | Z4: chart: SSI Non-Hero | AA4: chart: MAI Non-Hero
A5: P01 | B5: Office Supplies > Calendars & Planners > Planners & Personal Organizers | C5: 9. Planning & Craft Organization | D5: Office Supplies > Calendars & Planners | E5: 1037 | F5: Yes | G5: =IF(E5>='Selection Criteria'!$C$66,5,IF(E5>='Selection Criteria'!$C$67,4,IF(E5>='Selection Criteria'!$C$68,3,IF(E5>='Selection Criteria'!$C$69,2,1)))) -> 5 | H5: =IF(F5="Yes",'Selection Criteria'!$C$70,'Selection Criteria'!$C$71) -> 5 | I5: 5 | J5: 5 | K5: =(G5*'Selection Criteria'!$F$49+H5*'Selection Criteria'!$F$50+I5*'Selection Criteria'!$F$51+J5*'Selection Criteria'!$F$52)/(5*'Selection Criteria'!$F$53)*100 -> 100 | L5: 5 | M5: 5 | N5: 4 | O5: =IF(INDEX('Path Scorecard'!$X$5:$X$71,MATCH($A5,'Path Scorecard'!$A$5:$A$71,0))="",3,INDEX('Path Scorecard'!$X$5:$X$71,MATCH($A5,'Path Scorecard'!$A$5:$A$71,0))) -> 5 | P5: =(L5*'Selection Criteria'!$F$55+M5*'Selection Criteria'!$F$56+N5*'Selection Criteria'!$F$57+O5*'Selection Criteria'!$F$58)/(5*'Selection Criteria'!$F$59)*100 -> 95 | Q5: =IF(K5>='Selection Criteria'!$C$62,"Hero",IF(P5>='Selection Criteria'!$C$63,"Probable Hero","Non-Hero")) -> Hero | R5: =IF(Q5="Hero",IF(INDEX('Path Scorecard'!$T$5:$T$71,MATCH($A5,'Path Scorecard'!$A$5:$A$71,0))<='Selection Criteria'!$C$64,"PROTECT","EXTEND"),IF(Q5="Probable Hero","BUILD","HOLD")) -> EXTEND | S5: =INDEX('Path Scorecard'!$AB$5:$AB$71,MATCH($A5,'Path Scorecard'!$A$5:$A$71,0)) -> Tier 1 | T5: Staples: Sincerely Jules for Blue Sky exclusive (Jun-2026), Vera Bradley; deepest dated-goods shelf. Market: planning / journaling habit. | V5: =IF(AND($Q5="Hero",$S5<>"Parked (gate)"),K5,NA()) -> 100 | W5: =IF(AND($Q5="Hero",$S5<>"Parked (gate)"),P5,NA()) -> 95 | X5: =IF(AND($Q5="Probable Hero",$S5<>"Parked (gate)"),K5,NA()) -> #N/A | Y5: =IF(AND($Q5="Probable Hero",$S5<>"Parked (gate)"),P5,NA()) -> #N/A | Z5: =IF(AND($Q5="Non-Hero",$S5<>"Parked (gate)"),K5,NA()) -> #N/A | AA5: =IF(AND($Q5="Non-Hero",$S5<>"Parked (gate)"),P5,NA()) -> #N/A
A6: P02 | B6: Office Supplies > Desk Organizers & Accessories > Desk Organizers | C6: New | D6: Office Supplies > Desk Organizers & Accessories | E6: 342 | F6: Yes | G6: =IF(E6>='Selection Criteria'!$C$66,5,IF(E6>='Selection Criteria'!$C$67,4,IF(E6>='Selection Criteria'!$C$68,3,IF(E6>='Selection Criteria'!$C$69,2,1)))) -> 3 | H6: =IF(F6="Yes",'Selection Criteria'!$C$70,'Selection Criteria'!$C$71) -> 5 | I6: 4 | J6: 5 | K6: =(G6*'Selection Criteria'!$F$49+H6*'Selection Criteria'!$F$50+I6*'Selection Criteria'!$F$51+J6*'Selection Criteria'!$F$52)/(5*'Selection Criteria'!$F$53)*100 -> 83 | L6: 4 | M6: 5 | N6: 4 | O6: =IF(INDEX('Path Scorecard'!$X$5:$X$71,MATCH($A6,'Path Scorecard'!$A$5:$A$71,0))="",3,INDEX('Path Scorecard'!$X$5:$X$71,MATCH($A6,'Path Scorecard'!$A$5:$A$71,0))) -> 5 | P6: =(L6*'Selection Criteria'!$F$55+M6*'Selection Criteria'!$F$56+N6*'Selection Criteria'!$F$57+O6*'Selection Criteria'!$F$58)/(5*'Selection Criteria'!$F$59)*100 -> 88 | Q6: =IF(K6>='Selection Criteria'!$C$62,"Hero",IF(P6>='Selection Criteria'!$C$63,"Probable Hero","Non-Hero")) -> Hero | R6: =IF(Q6="Hero",IF(INDEX('Path Scorecard'!$T$5:$T$71,MATCH($A6,'Path Scorecard'!$A$5:$A$71,0))<='Selection Criteria'!$C$64,"PROTECT","EXTEND"),IF(Q6="Probable Hero","BUILD","HOLD")) -> EXTEND | S6: =INDEX('Path Scorecard'!$AB$5:$AB$71,MATCH($A6,'Path Scorecard'!$A$5:$A$71,0)) -> Tier 1 | T6: Staples: header-nav Office Supplies staple with Staples-brand ranges. Market: 'desk setup' trend, Target Brightroom. | V6: =IF(AND($Q6="Hero",$S6<>"Parked (gate)"),K6,NA()) -> 83 | W6: =IF(AND($Q6="Hero",$S6<>"Parked (gate)"),P6,NA()) -> 88 | X6: =IF(AND($Q6="Probable Hero",$S6<>"Parked (gate)"),K6,NA()) -> #N/A | Y6: =IF(AND($Q6="Probable Hero",$S6<>"Parked (gate)"),P6,NA()) -> #N/A | Z6: =IF(AND($Q6="Non-Hero",$S6<>"Parked (gate)"),K6,NA()) -> #N/A | AA6: =IF(AND($Q6="Non-Hero",$S6<>"Parked (gate)"),P6,NA()) -> #N/A
A7: P03 | B7: Coffee, Water & Snacks > Water & Beverages > Water Bottles, Tumblers & Travel Mugs | C7: 7. Hydration & Drinkware | D7: Coffee, Water & Snacks > Water & Beverages | E7: 463 | F7: Yes | G7: =IF(E7>='Selection Criteria'!$C$66,5,IF(E7>='Selection Criteria'!$C$67,4,IF(E7>='Selection Criteria'!$C$68,3,IF(E7>='Selection Criteria'!$C$69,2,1)))) -> 3 | H7: =IF(F7="Yes",'Selection Criteria'!$C$70,'Selection Criteria'!$C$71) -> 5 | I7: 3 | J7: 2 | K7: =(G7*'Selection Criteria'!$F$49+H7*'Selection Criteria'!$F$50+I7*'Selection Criteria'!$F$51+J7*'Selection Criteria'!$F$52)/(5*'Selection Criteria'!$F$53)*100 -> 60 | L7: 5 | M7: 5 | N7: 5 | O7: =IF(INDEX('Path Scorecard'!$X$5:$X$71,MATCH($A7,'Path Scorecard'!$A$5:$A$71,0))="",3,INDEX('Path Scorecard'!$X$5:$X$71,MATCH($A7,'Path Scorecard'!$A$5:$A$71,0))) -> 4 | P7: =(L7*'Selection Criteria'!$F$55+M7*'Selection Criteria'!$F$56+N7*'Selection Criteria'!$F$57+O7*'Selection Criteria'!$F$58)/(5*'Selection Criteria'!$F$59)*100 -> 97 | Q7: =IF(K7>='Selection Criteria'!$C$62,"Hero",IF(P7>='Selection Criteria'!$C$63,"Probable Hero","Non-Hero")) -> Probable Hero | R7: =IF(Q7="Hero",IF(INDEX('Path Scorecard'!$T$5:$T$71,MATCH($A7,'Path Scorecard'!$A$5:$A$71,0))<='Selection Criteria'!$C$64,"PROTECT","EXTEND"),IF(Q7="Probable Hero","BUILD","HOLD")) -> BUILD | S7: =INDEX('Path Scorecard'!$AB$5:$AB$71,MATCH($A7,'Path Scorecard'!$A$5:$A$71,0)) -> Tier 1 | T7: Staples: carries Stanley / Hydro Flask but no exclusives; not a drinkware destination. Market: Owala / Stanley / HydroJug craze. | V7: =IF(AND($Q7="Hero",$S7<>"Parked (gate)"),K7,NA()) -> #N/A | W7: =IF(AND($Q7="Hero",$S7<>"Parked (gate)"),P7,NA()) -> #N/A | X7: =IF(AND($Q7="Probable Hero",$S7<>"Parked (gate)"),K7,NA()) -> 60 | Y7: =IF(AND($Q7="Probable Hero",$S7<>"Parked (gate)"),P7,NA()) -> 97 | Z7: =IF(AND($Q7="Non-Hero",$S7<>"Parked (gate)"),K7,NA()) -> #N/A | AA7: =IF(AND($Q7="Non-Hero",$S7<>"Parked (gate)"),P7,NA()) -> #N/A
A8: P04 | B8: Furniture > Chairs & Seating > Accent & Waiting Room Chairs | C8: 1. Chairs & Seating | D8: Furniture > Chairs & Seating | E8: 229 | F8: Yes | G8: =IF(E8>='Selection Criteria'!$C$66,5,IF(E8>='Selection Criteria'!$C$67,4,IF(E8>='Selection Criteria'!$C$68,3,IF(E8>='Selection Criteria'!$C$69,2,1)))) -> 3 | H8: =IF(F8="Yes",'Selection Criteria'!$C$70,'Selection Criteria'!$C$71) -> 5 | I8: 2 | J8: 2 | K8: =(G8*'Selection Criteria'!$F$49+H8*'Selection Criteria'!$F$50+I8*'Selection Criteria'!$F$51+J8*'Selection Criteria'!$F$52)/(5*'Selection Criteria'!$F$53)*100 -> 55 | L8: 4 | M8: 5 | N8: 4 | O8: =IF(INDEX('Path Scorecard'!$X$5:$X$71,MATCH($A8,'Path Scorecard'!$A$5:$A$71,0))="",3,INDEX('Path Scorecard'!$X$5:$X$71,MATCH($A8,'Path Scorecard'!$A$5:$A$71,0))) -> 3 | P8: =(L8*'Selection Criteria'!$F$55+M8*'Selection Criteria'!$F$56+N8*'Selection Criteria'!$F$57+O8*'Selection Criteria'!$F$58)/(5*'Selection Criteria'!$F$59)*100 -> 82 | Q8: =IF(K8>='Selection Criteria'!$C$62,"Hero",IF(P8>='Selection Criteria'!$C$63,"Probable Hero","Non-Hero")) -> Probable Hero | R8: =IF(Q8="Hero",IF(INDEX('Path Scorecard'!$T$5:$T$71,MATCH($A8,'Path Scorecard'!$A$5:$A$71,0))<='Selection Criteria'!$C$64,"PROTECT","EXTEND"),IF(Q8="Probable Hero","BUILD","HOLD")) -> BUILD | S8: =INDEX('Path Scorecard'!$AB$5:$AB$71,MATCH($A8,'Path Scorecard'!$A$5:$A$71,0)) -> Tier 1 | T8: Staples: 229 items of utilitarian guest chairs. Market: Wayfair's core design category. | V8: =IF(AND($Q8="Hero",$S8<>"Parked (gate)"),K8,NA()) -> #N/A | W8: =IF(AND($Q8="Hero",$S8<>"Parked (gate)"),P8,NA()) -> #N/A | X8: =IF(AND($Q8="Probable Hero",$S8<>"Parked (gate)"),K8,NA()) -> 55 | Y8: =IF(AND($Q8="Probable Hero",$S8<>"Parked (gate)"),P8,NA()) -> 82 | Z8: =IF(AND($Q8="Non-Hero",$S8<>"Parked (gate)"),K8,NA()) -> #N/A | AA8: =IF(AND($Q8="Non-Hero",$S8<>"Parked (gate)"),P8,NA()) -> #N/A
A9: P05 | B9: Furniture > Lamps & Lighting > Desk Lamps | C9: 3. Lamps & Lighting | D9: Furniture > Lamps & Lighting | E9: 210 | F9: Yes | G9: =IF(E9>='Selection Criteria'!$C$66,5,IF(E9>='Selection Criteria'!$C$67,4,IF(E9>='Selection Criteria'!$C$68,3,IF(E9>='Selection Criteria'!$C$69,2,1)))) -> 3 | H9: =IF(F9="Yes",'Selection Criteria'!$C$70,'Selection Criteria'!$C$71) -> 5 | I9: 2 | J9: 3 | K9: =(G9*'Selection Criteria'!$F$49+H9*'Selection Criteria'!$F$50+I9*'Selection Criteria'!$F$51+J9*'Selection Criteria'!$F$52)/(5*'Selection Criteria'!$F$53)*100 -> 61 | L9: 4 | M9: 5 | N9: 4 | O9: =IF(INDEX('Path Scorecard'!$X$5:$X$71,MATCH($A9,'Path Scorecard'!$A$5:$A$71,0))="",3,INDEX('Path Scorecard'!$X$5:$X$71,MATCH($A9,'Path Scorecard'!$A$5:$A$71,0))) -> 3 | P9: =(L9*'Selection Criteria'!$F$55+M9*'Selection Criteria'!$F$56+N9*'Selection Criteria'!$F$57+O9*'Selection Criteria'!$F$58)/(5*'Selection Criteria'!$F$59)*100 -> 82 | Q9: =IF(K9>='Selection Criteria'!$C$62,"Hero",IF(P9>='Selection Criteria'!$C$63,"Probable Hero","Non-Hero")) -> Probable Hero | R9: =IF(Q9="Hero",IF(INDEX('Path Scorecard'!$T$5:$T$71,MATCH($A9,'Path Scorecard'!$A$5:$A$71,0))<='Selection Criteria'!$C$64,"PROTECT","EXTEND"),IF(Q9="Probable Hero","BUILD","HOLD")) -> BUILD | S9: =INDEX('Path Scorecard'!$AB$5:$AB$71,MATCH($A9,'Path Scorecard'!$A$5:$A$71,0)) -> Tier 1 | T9: Staples: task-lamp led. Market: decor-led lighting is a Wayfair department. | V9: =IF(AND($Q9="Hero",$S9<>"Parked (gate)"),K9,NA()) -> #N/A | W9: =IF(AND($Q9="Hero",$S9<>"Parked (gate)"),P9,NA()) -> #N/A | X9: =IF(AND($Q9="Probable Hero",$S9<>"Parked (gate)"),K9,NA()) -> 61 | Y9: =IF(AND($Q9="Probable Hero",$S9<>"Parked (gate)"),P9,NA()) -> 82 | Z9: =IF(AND($Q9="Non-Hero",$S9<>"Parked (gate)"),K9,NA()) -> #N/A | AA9: =IF(AND($Q9="Non-Hero",$S9<>"Parked (gate)"),P9,NA()) -> #N/A
A10: P06 | B10: Office Supplies > Writing Supplies & Instruments > Pencil Accessories > Pencil Cases & Pouches | C10: New | D10: Office Supplies > Writing Supplies & Instruments | E10: 107 | F10: Yes | G10: =IF(E10>='Selection Criteria'!$C$66,5,IF(E10>='Selection Criteria'!$C$67,4,IF(E10>='Selection Criteria'!$C$68,3,IF(E10>='Selection Criteria'!$C$69,2,1)))) -> 2 | H10: =IF(F10="Yes",'Selection Criteria'!$C$70,'Selection Criteria'!$C$71) -> 5 | I10: 3 | J10: 3 | K10: =(G10*'Selection Criteria'!$F$49+H10*'Selection Criteria'!$F$50+I10*'Selection Criteria'!$F$51+J10*'Selection Criteria'!$F$52)/(5*'Selection Criteria'!$F$53)*100 -> 60 | L10: 5 | M10: 4 | N10: 4 | O10: =IF(INDEX('Path Scorecard'!$X$5:$X$71,MATCH($A10,'Path Scorecard'!$A$5:$A$71,0))="",3,INDEX('Path Scorecard'!$X$5:$X$71,MATCH($A10,'Path Scorecard'!$A$5:$A$71,0))) -> 5 | P10: =(L10*'Selection Criteria'!$F$55+M10*'Selection Criteria'!$F$56+N10*'Selection Criteria'!$F$57+O10*'Selection Criteria'!$F$58)/(5*'Selection Criteria'!$F$59)*100 -> 90 | Q10: =IF(K10>='Selection Criteria'!$C$62,"Hero",IF(P10>='Selection Criteria'!$C$63,"Probable Hero","Non-Hero")) -> Probable Hero | R10: =IF(Q10="Hero",IF(INDEX('Path Scorecard'!$T$5:$T$71,MATCH($A10,'Path Scorecard'!$A$5:$A$71,0))<='Selection Criteria'!$C$64,"PROTECT","EXTEND"),IF(Q10="Probable Hero","BUILD","HOLD")) -> BUILD | S10: =INDEX('Path Scorecard'!$AB$5:$AB$71,MATCH($A10,'Path Scorecard'!$A$5:$A$71,0)) -> Tier 1 | T10: Staples: Recess Club exclusive, but only 107 items. Market: the BTS aesthetic essential. | V10: =IF(AND($Q10="Hero",$S10<>"Parked (gate)"),K10,NA()) -> #N/A | W10: =IF(AND($Q10="Hero",$S10<>"Parked (gate)"),P10,NA()) -> #N/A | X10: =IF(AND($Q10="Probable Hero",$S10<>"Parked (gate)"),K10,NA()) -> 60 | Y10: =IF(AND($Q10="Probable Hero",$S10<>"Parked (gate)"),P10,NA()) -> 90 | Z10: =IF(AND($Q10="Non-Hero",$S10<>"Parked (gate)"),K10,NA()) -> #N/A | AA10: =IF(AND($Q10="Non-Hero",$S10<>"Parked (gate)"),P10,NA()) -> #N/A
A11: P07 | B11: Bags, Backpacks & Luggage > Backpacks & Laptop Bags > Backpacks | C11: 6. Backpacks & Bags | D11: Bags, Backpacks & Luggage > Backpacks & Laptop Bags | E11: 585 | F11: No | G11: =IF(E11>='Selection Criteria'!$C$66,5,IF(E11>='Selection Criteria'!$C$67,4,IF(E11>='Selection Criteria'!$C$68,3,IF(E11>='Selection Criteria'!$C$69,2,1)))) -> 4 | H11: =IF(F11="Yes",'Selection Criteria'!$C$70,'Selection Criteria'!$C$71) -> 2 | I11: 4 | J11: 4 | K11: =(G11*'Selection Criteria'!$F$49+H11*'Selection Criteria'!$F$50+I11*'Selection Criteria'!$F$51+J11*'Selection Criteria'!$F$52)/(5*'Selection Criteria'!$F$53)*100 -> 74 | L11: 4 | M11: 5 | N11: 5 | O11: =IF(INDEX('Path Scorecard'!$X$5:$X$71,MATCH($A11,'Path Scorecard'!$A$5:$A$71,0))="",3,INDEX('Path Scorecard'!$X$5:$X$71,MATCH($A11,'Path Scorecard'!$A$5:$A$71,0))) -> 5 | P11: =(L11*'Selection Criteria'!$F$55+M11*'Selection Criteria'!$F$56+N11*'Selection Criteria'!$F$57+O11*'Selection Criteria'!$F$58)/(5*'Selection Criteria'!$F$59)*100 -> 93 | Q11: =IF(K11>='Selection Criteria'!$C$62,"Hero",IF(P11>='Selection Criteria'!$C$63,"Probable Hero","Non-Hero")) -> Hero | R11: =IF(Q11="Hero",IF(INDEX('Path Scorecard'!$T$5:$T$71,MATCH($A11,'Path Scorecard'!$A$5:$A$71,0))<='Selection Criteria'!$C$64,"PROTECT","EXTEND"),IF(Q11="Probable Hero","BUILD","HOLD")) -> EXTEND | S11: =INDEX('Path Scorecard'!$AB$5:$AB$71,MATCH($A11,'Path Scorecard'!$A$5:$A$71,0)) -> Tier 1 | T11: Staples: BTS feature category. Market: 85% of parents buy one (Circana). | V11: =IF(AND($Q11="Hero",$S11<>"Parked (gate)"),K11,NA()) -> 74 | W11: =IF(AND($Q11="Hero",$S11<>"Parked (gate)"),P11,NA()) -> 93 | X11: =IF(AND($Q11="Probable Hero",$S11<>"Parked (gate)"),K11,NA()) -> #N/A | Y11: =IF(AND($Q11="Probable Hero",$S11<>"Parked (gate)"),P11,NA()) -> #N/A | Z11: =IF(AND($Q11="Non-Hero",$S11<>"Parked (gate)"),K11,NA()) -> #N/A | AA11: =IF(AND($Q11="Non-Hero",$S11<>"Parked (gate)"),P11,NA()) -> #N/A
A12: P08 | B12: Bags, Backpacks & Luggage > Totes & Handbags > Lunch Bags & Boxes | C12: 6. Backpacks & Bags | D12: Bags, Backpacks & Luggage > Totes & Handbags | E12: 404 | F12: No | G12: =IF(E12>='Selection Criteria'!$C$66,5,IF(E12>='Selection Criteria'!$C$67,4,IF(E12>='Selection Criteria'!$C$68,3,IF(E12>='Selection Criteria'!$C$69,2,1)))) -> 3 | H12: =IF(F12="Yes",'Selection Criteria'!$C$70,'Selection Criteria'!$C$71) -> 2 | I12: 3 | J12: 3 | K12: =(G12*'Selection Criteria'!$F$49+H12*'Selection Criteria'!$F$50+I12*'Selection Criteria'!$F$51+J12*'Selection Criteria'!$F$52)/(5*'Selection Criteria'!$F$53)*100 -> 57 | L12: 5 | M12: 5 | N12: 4 | O12: =IF(INDEX('Path Scorecard'!$X$5:$X$71,MATCH($A12,'Path Scorecard'!$A$5:$A$71,0))="",3,INDEX('Path Scorecard'!$X$5:$X$71,MATCH($A12,'Path Scorecard'!$A$5:$A$71,0))) -> 5 | P12: =(L12*'Selection Criteria'!$F$55+M12*'Selection Criteria'!$F$56+N12*'Selection Criteria'!$F$57+O12*'Selection Criteria'!$F$58)/(5*'Selection Criteria'!$F$59)*100 -> 95 | Q12: =IF(K12>='Selection Criteria'!$C$62,"Hero",IF(P12>='Selection Criteria'!$C$63,"Probable Hero","Non-Hero")) -> Probable Hero | R12: =IF(Q12="Hero",IF(INDEX('Path Scorecard'!$T$5:$T$71,MATCH($A12,'Path Scorecard'!$A$5:$A$71,0))<='Selection Criteria'!$C$64,"PROTECT","EXTEND"),IF(Q12="Probable Hero","BUILD","HOLD")) -> BUILD | S12: =INDEX('Path Scorecard'!$AB$5:$AB$71,MATCH($A12,'Path Scorecard'!$A$5:$A$71,0)) -> Tier 1 | T12: Staples: 404 items, basic insulated bags. Market: bento / leak-proof BTS and work-lunch trend. | V12: =IF(AND($Q12="Hero",$S12<>"Parked (gate)"),K12,NA()) -> #N/A | W12: =IF(AND($Q12="Hero",$S12<>"Parked (gate)"),P12,NA()) -> #N/A | X12: =IF(AND($Q12="Probable Hero",$S12<>"Parked (gate)"),K12,NA()) -> 57 | Y12: =IF(AND($Q12="Probable Hero",$S12<>"Parked (gate)"),P12,NA()) -> 95 | Z12: =IF(AND($Q12="Non-Hero",$S12<>"Parked (gate)"),K12,NA()) -> #N/A | AA12: =IF(AND($Q12="Non-Hero",$S12<>"Parked (gate)"),P12,NA()) -> #N/A
